Workbook
Name estimate: '[1]01 收入底稿'!$B$4
Name YM: '[2]01 收入底稿(計價收入)'!$I$6:$T$6

Sheet 調整說明
A1: 調整說明
A3: 1. | B3: 依KL意見(詳圖一)
B4: 1) 增加2023年底Underbill,(即2023年底調整C/TO_Adj. $400m),2023年底與2023.8.31差異請詳"Over Under Bill 1"工作表
B5: 2) B0 2264工作表_考量物調,專案先行投入及權重因素,調整業主計價百分比,比例詳line 2, 以利underbill or overbill 金額表達較合理之趨勢
A6: 2. | B6: B1 ZSD060扣保工作表_包括CF重分配金額
A7: 3. | B7: 調整2028年底Underbill
B14: 圖一

Sheet BS2_WIP
A1: CEC 2026 Budget- Balance Sheets | C1: 3 | D1: 4 | E1: 5 | F1: 6 | G1: 7 | H1: 8 | I1: 9 | J1: 10 | K1: 11 | L1: 12 | M1: 13 | N1: 14 | O1: 15 | P1: 16 | Q1: 17 | R1: 18 | S1: 19 | T1: 20 | U1: 21 | V1: 22 | W1: 23 | X1: 24 | Z1: CEC 2020 Budget- Balance Sheets (for HQ Consolidation)
A2: Business Office : Taiwan Office | Z2: Business Office : Taiwan Office
A3: Currency : NTD | H3: =+H128-'A0 BS 1240在建'!#REF! -> #N/A | Z3: Currency : NTD
A4: BY Monthly _ for A0 BS 1240 | E4: =+E139-E79 -> -27724110 | H4: =+H139-H79 -> #N/A | I4: =+I139-I79 -> #N/A | J4: =+J139-J79 -> #N/A | K4: =+K139-K79 -> #N/A | L4: =+L139-L79 -> #N/A | M4: =+M139-M79 -> #N/A | N4: =+N139-N79 -> #N/A | O4: =+O139-O79 -> #N/A | ... X4: =+X139-X79 -> #N/A
A5: BS_WIP
A6: 2025.10.18 | D6: Actaul | E6: FCST | F6: 46022 | G6: 46387
A7: 月份 | D7: 45900 | E7: 9/1-12/31 | F7: Forecast | G7: Budget | H7: Year 2026 | I7: 46053 | J7: 46081 | K7: 46112 | L7: 46142 | M7: 46173 | N7: 46203 | O7: 46234 | P7: 46265 | Q7: 46295 | R7: 46326 | S7: 46356 | T7: 46387 | U7: Year 2027 | V7: Year 2028 | W7: Year 2029 | X7: Year 2030
A9: 流動資產: | Z9: Current Assets:
A10: 1100 現金及約當現金 | B10: 銀行存款 | E10: =SUMIF('A0 BS 1240在建'!$A$226:$A$245,$A10,'A0 BS 1240在建'!G$226:G$245) -> 0 | F10: =SUM(D10:E10) -> 0 | G10: =+F10+H10 -> 0 | I10: =SUMIF('A0 BS 1240在建'!$A$226:$A$245,$A10,'A0 BS 1240在建'!O$226:O$245) -> 0 | Z10: 1100 Cash and cash equivalents
A11: 1139 避險之金融資產-流動 | E11: =SUM(E12:E13) -> 0 | F11: =SUM(F12:F13) -> 0 | G11: =SUM(G12:G13) -> 0 | H11: =SUM(H12:H13) -> 0 | I11: =SUM(I12:I13) -> 0 | J11: =SUM(J12:J13) -> 0 | K11: =SUM(K12:K13) -> 0 | L11: =SUM(L12:L13) -> 0 | ... X11: =SUM(X12:X13) -> 0 | Z11: 1130 Current financial assets for hedging
A12: 1103外幣存款-避險 | B12: 銀行存款 | E12: =SUMIF('A0 BS 1240在建'!$A$226:$A$245, $A12,'A0 BS 1240在建'!G$226:G$245) -> 0 | F12: =SUM(D12:E12) -> 0 | G12: =+F12+H12 -> 0 | H12: =SUM(I12:T12) -> 0 | I12: =SUMIF('A0 BS 1240在建'!$A$226:$A$245,$A12,'A0 BS 1240在建'!O$226:O$245) -> 0 | J12: =SUMIF('A0 BS 1240在建'!$A$226:$A$245,$A12,'A0 BS 1240在建'!S$226:S$245) -> 0 | K12: =SUMIF('A0 BS 1240在建'!$A$226:$A$245,$A12,'A0 BS 1240在建'!W$226:W$245) -> 0 | L12: =SUMIF('A0 BS 1240在建'!$A$226:$A$245,$A12,'A0 BS 1240在建'!AA$226:AA$245) -> 0 | M12: =SUMIF('A0 BS 1240在建'!$A$226:$A$245,$A12,'A0 BS 1240在建'!AE$226:AE$245) -> 0 | N12: =SUMIF('A0 BS 1240在建'!$A$226:$A$245,$A12,'A0 BS 1240在建'!AI$226:AI$245) -> 0 | O12: =SUMIF('A0 BS 1240在建'!$A$226:$A$245,$A12,'A0 BS 1240在建'!AM$226:AM$245) -> 0 | P12: =SUMIF('A0 BS 1240在建'!$A$226:$A$245,$A12,'A0 BS 1240在建'!AQ$226:AQ$245) -> 0 | Q12: =SUMIF('A0 BS 1240在建'!$A$226:$A$245,$A12,'A0 BS 1240在建'!AU$226:AU$245) -> 0 | R12: =SUMIF('A0 BS 1240在建'!$A$226:$A$245,$A12,'A0 BS 1240在建'!AY$226:AY$245) -> 0 | S12: =SUMIF('A0 BS 1240在建'!$A$226:$A$245,$A12,'A0 BS 1240在建'!BC$226:BC$245) -> 0 | T12: =SUMIF('A0 BS 1240在建'!$A$226:$A$245,$A12,'A0 BS 1240在建'!BG$226:BG$245) -> 0 | U12: =SUMIF('A0 BS 1240在建'!$A$226:$A$245,$A12,'A0 BS 1240在建'!BS$226:BS$245) -> 0 | V12: =SUMIF('A0 BS 1240在建'!$A$226:$A$245,$A12,'A0 BS 1240在建'!CA$226:CA$245) -> 0 | W12: =SUMIF('A0 BS 1240在建'!$A$226:$A$245,$A12,'A0 BS 1240在建'!CB$226:CB$245) -> 0 | X12: =SUMIF('A0 BS 1240在建'!$A$226:$A$245,$A12,'A0 BS 1240在建'!CC$226:CC$245) -> 0
A13: 1139避險之金融資產-流動. | B13: 其他流動資產 | E13: =SUMIF('A0 BS 1240在建'!$A$226:$A$245, $A13,'A0 BS 1240在建'!G$226:G$245) -> 0 | F13: =SUM(D13:E13) -> 0 | G13: =+F13+H13 -> 0 | H13: =SUM(I13:T13) -> 0 | I13: =SUMIF('A0 BS 1240在建'!$A$226:$A$245,$A13,'A0 BS 1240在建'!O$226:O$245) -> 0 | J13: =SUMIF('A0 BS 1240在建'!$A$226:$A$245,$A13,'A0 BS 1240在建'!S$226:S$245) -> 0 | K13: =SUMIF('A0 BS 1240在建'!$A$226:$A$245,$A13,'A0 BS 1240在建'!W$226:W$245) -> 0 | L13: =SUMIF('A0 BS 1240在建'!$A$226:$A$245,$A13,'A0 BS 1240在建'!AA$226:AA$245) -> 0 | M13: =SUMIF('A0 BS 1240在建'!$A$226:$A$245,$A13,'A0 BS 1240在建'!AE$226:AE$245) -> 0 | N13: =SUMIF('A0 BS 1240在建'!$A$226:$A$245,$A13,'A0 BS 1240在建'!AI$226:AI$245) -> 0 | O13: =SUMIF('A0 BS 1240在建'!$A$226:$A$245,$A13,'A0 BS 1240在建'!AM$226:AM$245) -> 0 | P13: =SUMIF('A0 BS 1240在建'!$A$226:$A$245,$A13,'A0 BS 1240在建'!AQ$226:AQ$245) -> 0 | Q13: =SUMIF('A0 BS 1240在建'!$A$226:$A$245,$A13,'A0 BS 1240在建'!AU$226:AU$245) -> 0 | R13: =SUMIF('A0 BS 1240在建'!$A$226:$A$245,$A13,'A0 BS 1240在建'!AY$226:AY$245) -> 0 | S13: =SUMIF('A0 BS 1240在建'!$A$226:$A$245,$A13,'A0 BS 1240在建'!BC$226:BC$245) -> 0 | T13: =SUMIF('A0 BS 1240在建'!$A$226:$A$245,$A13,'A0 BS 1240在建'!BG$226:BG$245) -> 0 | U13: =SUMIF('A0 BS 1240在建'!$A$226:$A$245,$A13,'A0 BS 1240在建'!BS$226:BS$245) -> 0 | V13: =SUMIF('A0 BS 1240在建'!$A$226:$A$245,$A13,'A0 BS 1240在建'!CA$226:CA$245) -> 0 | W13: =SUMIF('A0 BS 1240在建'!$A$226:$A$245,$A13,'A0 BS 1240在建'!CB$226:CB$245) -> 0 | X13: =SUMIF('A0 BS 1240在建'!$A$226:$A$245,$A13,'A0 BS 1240在建'!CC$226:CC$245) -> 0
A14: 1190 應收建造合約款 | D14: =+#REF! -> #REF! | E14: =VLOOKUP($A14,'Over Under Bill 2'!$1:$1048576,4,0) -> 0 | F14: =+D14+E14 -> #REF! | G14: =+F14+H14 -> #REF! | H14: =SUM(I14:T14) -> 0 | I14: =VLOOKUP($A14,'Over Under Bill 2'!$1:$1048576,5,0) -> 0 | J14: =VLOOKUP($A14,'Over Under Bill 2'!$1:$1048576,6,0) -> 0 | K14: =VLOOKUP($A14,'Over Under Bill 2'!$1:$1048576,7,0) -> 0 | L14: =VLOOKUP($A14,'Over Under Bill 2'!$1:$1048576,8,0) -> 0 | M14: =VLOOKUP($A14,'Over Under Bill 2'!$1:$1048576,9,0) -> 0 | N14: =VLOOKUP($A14,'Over Under Bill 2'!$1:$1048576,10,0) -> 0 | O14: =VLOOKUP($A14,'Over Under Bill 2'!$1:$1048576,11,0) -> 0 | P14: =VLOOKUP($A14,'Over Under Bill 2'!$1:$1048576,12,0) -> 0 | Q14: =VLOOKUP($A14,'Over Under Bill 2'!$1:$1048576,13,0) -> 0 | R14: =VLOOKUP($A14,'Over Under Bill 2'!$1:$1048576,14,0) -> 0 | S14: =VLOOKUP($A14,'Over Under Bill 2'!$1:$1048576,15,0) -> 0 | T14: =VLOOKUP($A14,'Over Under Bill 2'!$1:$1048576,16,0) -> 0 | U14: =VLOOKUP($A14,'Over Under Bill 2'!$1:$1048576,17,0) -> 0 | V14: =VLOOKUP($A14,'Over Under Bill 2'!$1:$1048576,18,0) -> 0 | W14: =VLOOKUP($A14,'Over Under Bill 2'!$1:$1048576,19,0) -> 0 | X14: =VLOOKUP($A14,'Over Under Bill 2'!$1:$1048576,20,0) -> 0 | Z14: 1190 Construction contracts receivable
A15: 1240 X 在建工程_成本 | F15: =SUM(D15:E15) -> 0 | G15: =+F15+H15 -> 0 | H15: =SUM(I15:T15) -> 0 | Z15: 1240 X WIP -Cost Incurred
A16: 1247X 在建損益 | F16: =SUM(D16:E16) -> 0 | G16: =+F16+H16 -> 0 | H16: =SUM(I16:T16) -> 0 | Z16: 1247X WIP - P&L (by POC)
A17: 2264X 工程合約-其他預收工程款 | F17: =SUM(D17:E17) -> 0 | G17: =+F17+H17 -> 0 | H17: =SUM(I17:T17) -> 0 | Z17: 2264X Construction contracts - Progress billing
A18: 2264X 工程合約-業主預付款 | F18: =SUM(D18:E18) -> 0 | G18: =+F18+H18 -> 0 | H18: =SUM(I18:T18) -> 0 | Z18: 2264X Construction contracts -Client's Advance Payment
A19: 1141 合約資產-應收工程保留款 | B19: 應收款項 | E19: =SUMIF('A0 BS 1240在建'!$A$226:$A$245, $A19,'A0 BS 1240在建'!G$226:G$245) -> 0 | F19: =SUM(D19:E19) -> 0 | G19: =+F19+H19 -> 0 | H19: =SUM(I19:T19) -> 0 | I19: =SUMIF('A0 BS 1240在建'!$A$226:$A$245,$A19,'A0 BS 1240在建'!O$226:O$245) -> 0 | J19: =SUMIF('A0 BS 1240在建'!$A$226:$A$245,$A19,'A0 BS 1240在建'!S$226:S$245) -> 0 | K19: =SUMIF('A0 BS 1240在建'!$A$226:$A$245,$A19,'A0 BS 1240在建'!W$226:W$245) -> 0 | L19: =SUMIF('A0 BS 1240在建'!$A$226:$A$245,$A19,'A0 BS 1240在建'!AA$226:AA$245) -> 0 | M19: =SUMIF('A0 BS 1240在建'!$A$226:$A$245,$A19,'A0 BS 1240在建'!AE$226:AE$245) -> 0 | N19: =SUMIF('A0 BS 1240在建'!$A$226:$A$245,$A19,'A0 BS 1240在建'!AI$226:AI$245) -> 0 | O19: =SUMIF('A0 BS 1240在建'!$A$226:$A$245,$A19,'A0 BS 1240在建'!AM$226:AM$245) -> 0 | P19: =SUMIF('A0 BS 1240在建'!$A$226:$A$245,$A19,'A0 BS 1240在建'!AQ$226:AQ$245) -> 0 | Q19: =SUMIF('A0 BS 1240在建'!$A$226:$A$245,$A19,'A0 BS 1240在建'!AU$226:AU$245) -> 0 | R19: =SUMIF('A0 BS 1240在建'!$A$226:$A$245,$A19,'A0 BS 1240在建'!AY$226:AY$245) -> 0 | S19: =SUMIF('A0 BS 1240在建'!$A$226:$A$245,$A19,'A0 BS 1240在建'!BC$226:BC$245) -> 0 | T19: =SUMIF('A0 BS 1240在建'!$A$226:$A$245,$A19,'A0 BS 1240在建'!BG$226:BG$245) -> 0 | U19: =SUMIF('A0 BS 1240在建'!$A$226:$A$245,$A19,'A0 BS 1240在建'!BS$226:BS$245) -> 0 | V19: =SUMIF('A0 BS 1240在建'!$A$226:$A$245,$A19,'A0 BS 1240在建'!CA$226:CA$245) -> 0 | W19: =SUMIF('A0 BS 1240在建'!$A$226:$A$245,$A19,'A0 BS 1240在建'!CI$226:CI$245) -> 0 | X19: =SUMIF('A0 BS 1240在建'!$A$226:$A$245,$A19,'A0 BS 1240在建'!CQ$226:CQ$245) -> #REF! | Z19: 1141 Contract assets - Retention receivable
A20: 1142 合約資產-應收完工估列款 | B20: 應收款項 | E20: =SUMIF('A0 BS 1240在建'!$A$226:$A$245, $A20,'A0 BS 1240在建'!G$226:G$245) -> 0 | F20: =SUM(D20:E20) -> 0 | G20: =+F20+H20 -> 0 | H20: =SUM(I20:T20) -> 0 | I20: =SUMIF('A0 BS 1240在建'!$A$226:$A$245,$A20,'A0 BS 1240在建'!O$226:O$245) -> 0 | J20: =SUMIF('A0 BS 1240在建'!$A$226:$A$245,$A20,'A0 BS 1240在建'!S$226:S$245) -> 0 | K20: =SUMIF('A0 BS 1240在建'!$A$226:$A$245,$A20,'A0 BS 1240在建'!W$226:W$245) -> 0 | L20: =SUMIF('A0 BS 1240在建'!$A$226:$A$245,$A20,'A0 BS 1240在建'!AA$226:AA$245) -> 0 | M20: =SUMIF('A0 BS 1240在建'!$A$226:$A$245,$A20,'A0 BS 1240在建'!AE$226:AE$245) -> 0 | N20: =SUMIF('A0 BS 1240在建'!$A$226:$A$245,$A20,'A0 BS 1240在建'!AI$226:AI$245) -> 0 | O20: =SUMIF('A0 BS 1240在建'!$A$226:$A$245,$A20,'A0 BS 1240在建'!AM$226:AM$245) -> 0 | P20: =SUMIF('A0 BS 1240在建'!$A$226:$A$245,$A20,'A0 BS 1240在建'!AQ$226:AQ$245) -> 0 | Q20: =SUMIF('A0 BS 1240在建'!$A$226:$A$245,$A20,'A0 BS 1240在建'!AU$226:AU$245) -> 0 | R20: =SUMIF('A0 BS 1240在建'!$A$226:$A$245,$A20,'A0 BS 1240在建'!AY$226:AY$245) -> 0 | S20: =SUMIF('A0 BS 1240在建'!$A$226:$A$245,$A20,'A0 BS 1240在建'!BC$226:BC$245) -> 0 | T20: =SUMIF('A0 BS 1240在建'!$A$226:$A$245,$A20,'A0 BS 1240在建'!BG$226:BG$245) -> 0 | U20: =SUMIF('A0 BS 1240在建'!$A$226:$A$245,$A20,'A0 BS 1240在建'!BS$226:BS$245) -> 0 | V20: =SUMIF('A0 BS 1240在建'!$A$226:$A$245,$A20,'A0 BS 1240在建'!CA$226:CA$245) -> 0 | W20: =SUMIF('A0 BS 1240在建'!$A$226:$A$245,$A20,'A0 BS 1240在建'!CI$226:CI$245) -> 0 | X20: =SUMIF('A0 BS 1240在建'!$A$226:$A$245,$A20,'A0 BS 1240在建'!CQ$226:CQ$245) -> 0 | Z20: 1142 Contract assets - Accrual receivable
A21: 1150 應收票據淨額 | B21: 應收款項 | E21: =SUMIF('A0 BS 1240在建'!$A$226:$A$245, $A21,'A0 BS 1240在建'!G$226:G$245) -> 0 | F21: =SUM(D21:E21) -> 0 | G21: =+F21+H21 -> 0 | H21: =SUM(I21:T21) -> 0 | I21: =SUMIF('A0 BS 1240在建'!$A$226:$A$245,$A21,'A0 BS 1240在建'!O$226:O$245) -> 0 | J21: =SUMIF('A0 BS 1240在建'!$A$226:$A$245,$A21,'A0 BS 1240在建'!S$226:S$245) -> 0 | K21: =SUMIF('A0 BS 1240在建'!$A$226:$A$245,$A21,'A0 BS 1240在建'!W$226:W$245) -> 0 | L21: =SUMIF('A0 BS 1240在建'!$A$226:$A$245,$A21,'A0 BS 1240在建'!AA$226:AA$245) -> 0 | M21: =SUMIF('A0 BS 1240在建'!$A$226:$A$245,$A21,'A0 BS 1240在建'!AE$226:AE$245) -> 0 | N21: =SUMIF('A0 BS 1240在建'!$A$226:$A$245,$A21,'A0 BS 1240在建'!AI$226:AI$245) -> 0 | O21: =SUMIF('A0 BS 1240在建'!$A$226:$A$245,$A21,'A0 BS 1240在建'!AM$226:AM$245) -> 0 | P21: =SUMIF('A0 BS 1240在建'!$A$226:$A$245,$A21,'A0 BS 1240在建'!AQ$226:AQ$245) -> 0 | Q21: =SUMIF('A0 BS 1240在建'!$A$226:$A$245,$A21,'A0 BS 1240在建'!AU$226:AU$245) -> 0 | R21: =SUMIF('A0 BS 1240在建'!$A$226:$A$245,$A21,'A0 BS 1240在建'!AY$226:AY$245) -> 0 | S21: =SUMIF('A0 BS 1240在建'!$A$226:$A$245,$A21,'A0 BS 1240在建'!BC$226:BC$245) -> 0 | T21: =SUMIF('A0 BS 1240在建'!$A$226:$A$245,$A21,'A0 BS 1240在建'!BG$226:BG$245) -> 0 | U21: =SUMIF('A0 BS 1240在建'!$A$226:$A$245,$A21,'A0 BS 1240在建'!BS$226:BS$245) -> 0 | V21: =SUMIF('A0 BS 1240在建'!$A$226:$A$245,$A21,'A0 BS 1240在建'!CA$226:CA$245) -> 0 | W21: =SUMIF('A0 BS 1240在建'!$A$226:$A$245,$A21,'A0 BS 1240在建'!CI$226:CI$245) -> 0 | X21: =SUMIF('A0 BS 1240在建'!$A$226:$A$245,$A21,'A0 BS 1240在建'!CQ$226:CQ$245) -> 0 | Z21: 1150 Notes receivable, net
A22: 1170 應收帳款淨額 | B22: 應收款項 | E22: =SUMIF('A0 BS 1240在建'!$A$226:$A$245, $A22,'A0 BS 1240在建'!G$226:G$245) -> 21367000 | F22: =SUM(D22:E22) -> 21367000 | G22: =+F22+H22 -> #N/A | H22: =SUM(I22:T22) -> #N/A | I22: =SUMIF('A0 BS 1240在建'!$A$226:$A$245,$A22,'A0 BS 1240在建'!O$226:O$245) -> #N/A | J22: =SUMIF('A0 BS 1240在建'!$A$226:$A$245,$A22,'A0 BS 1240在建'!S$226:S$245) -> #N/A | K22: =SUMIF('A0 BS 1240在建'!$A$226:$A$245,$A22,'A0 BS 1240在建'!W$226:W$245) -> #N/A | L22: =SUMIF('A0 BS 1240在建'!$A$226:$A$245,$A22,'A0 BS 1240在建'!AA$226:AA$245) -> #N/A | M22: =SUMIF('A0 BS 1240在建'!$A$226:$A$245,$A22,'A0 BS 1240在建'!AE$226:AE$245) -> #N/A | N22: =SUMIF('A0 BS 1240在建'!$A$226:$A$245,$A22,'A0 BS 1240在建'!AI$226:AI$245) -> #N/A | O22: =SUMIF('A0 BS 1240在建'!$A$226:$A$245,$A22,'A0 BS 1240在建'!AM$226:AM$245) -> #N/A | P22: =SUMIF('A0 BS 1240在建'!$A$226:$A$245,$A22,'A0 BS 1240在建'!AQ$226:AQ$245) -> #N/A | Q22: =SUMIF('A0 BS 1240在建'!$A$226:$A$245,$A22,'A0 BS 1240在建'!AU$226:AU$245) -> #N/A | R22: =SUMIF('A0 BS 1240在建'!$A$226:$A$245,$A22,'A0 BS 1240在建'!AY$226:AY$245) -> #N/A | S22: =SUMIF('A0 BS 1240在建'!$A$226:$A$245,$A22,'A0 BS 1240在建'!BC$226:BC$245) -> #N/A | T22: =SUMIF('A0 BS 1240在建'!$A$226:$A$245,$A22,'A0 BS 1240在建'!BG$226:BG$245) -> #N/A | U22: =SUMIF('A0 BS 1240在建'!$A$226:$A$245,$A22,'A0 BS 1240在建'!BS$226:BS$245) -> #N/A | V22: =SUMIF('A0 BS 1240在建'!$A$226:$A$245,$A22,'A0 BS 1240在建'!CA$226:CA$245) -> #N/A | W22: =SUMIF('A0 BS 1240在建'!$A$226:$A$245,$A22,'A0 BS 1240在建'!CI$226:CI$245) -> #N/A | X22: =SUMIF('A0 BS 1240在建'!$A$226:$A$245,$A22,'A0 BS 1240在建'!CQ$226:CQ$245) -> #N/A | Z22: 1170 Accounts receivable, net
A23: 1180 應收帳款-關係人淨額 | E23: =SUMIF('A0 BS 1240在建'!$A$226:$A$245, $A23,'A0 BS 1240在建'!G$226:G$245) -> 0 | F23: =SUM(D23:E23) -> 0 | G23: =+F23+H23 -> 0 | H23: =SUM(I23:T23) -> 0 | I23: =SUMIF('A0 BS 1240在建'!$A$226:$A$245,$A23,'A0 BS 1240在建'!O$226:O$245) -> 0 | J23: =SUMIF('A0 BS 1240在建'!$A$226:$A$245,$A23,'A0 BS 1240在建'!S$226:S$245) -> 0 | K23: =SUMIF('A0 BS 1240在建'!$A$226:$A$245,$A23,'A0 BS 1240在建'!W$226:W$245) -> 0 | L23: =SUMIF('A0 BS 1240在建'!$A$226:$A$245,$A23,'A0 BS 1240在建'!AA$226:AA$245) -> 0 | M23: =SUMIF('A0 BS 1240在建'!$A$226:$A$245,$A23,'A0 BS 1240在建'!AE$226:AE$245) -> 0 | N23: =SUMIF('A0 BS 1240在建'!$A$226:$A$245,$A23,'A0 BS 1240在建'!AI$226:AI$245) -> 0 | O23: =SUMIF('A0 BS 1240在建'!$A$226:$A$245,$A23,'A0 BS 1240在建'!AM$226:AM$245) -> 0 | P23: =SUMIF('A0 BS 1240在建'!$A$226:$A$245,$A23,'A0 BS 1240在建'!AQ$226:AQ$245) -> 0 | Q23: =SUMIF('A0 BS 1240在建'!$A$226:$A$245,$A23,'A0 BS 1240在建'!AU$226:AU$245) -> 0 | R23: =SUMIF('A0 BS 1240在建'!$A$226:$A$245,$A23,'A0 BS 1240在建'!AY$226:AY$245) -> 0 | S23: =SUMIF('A0 BS 1240在建'!$A$226:$A$245,$A23,'A0 BS 1240在建'!BC$226:BC$245) -> 0 | T23: =SUMIF('A0 BS 1240在建'!$A$226:$A$245,$A23,'A0 BS 1240在建'!BG$226:BG$245) -> 0 | U23: =SUMIF('A0 BS 1240在建'!$A$226:$A$245,$A23,'A0 BS 1240在建'!BS$226:BS$245) -> 0 | V23: =SUMIF('A0 BS 1240在建'!$A$226:$A$245,$A23,'A0 BS 1240在建'!CA$226:CA$245) -> 0 | W23: =SUMIF('A0 BS 1240在建'!$A$226:$A$245,$A23,'A0 BS 1240在建'!CI$226:CI$245) -> 0 | X23: =SUMIF('A0 BS 1240在建'!$A$226:$A$245,$A23,'A0 BS 1240在建'!CQ$226:CQ$245) -> 0 | Z23: 1180 Accounts receivable-related parties, net
A24: 1200 其他應收款 | B24: 其他流動資產 | E24: =SUMIF('A0 BS 1240在建'!$A$226:$A$245, $A24,'A0 BS 1240在建'!G$226:G$245) -> 0 | F24: =SUM(D24:E24) -> 0 | G24: =+F24+H24 -> 0 | H24: =SUM(I24:T24) -> 0 | I24: =SUMIF('A0 BS 1240在建'!$A$226:$A$245,$A24,'A0 BS 1240在建'!O$226:O$245) -> 0 | J24: =SUMIF('A0 BS 1240在建'!$A$226:$A$245,$A24,'A0 BS 1240在建'!S$226:S$245) -> 0 | K24: =SUMIF('A0 BS 1240在建'!$A$226:$A$245,$A24,'A0 BS 1240在建'!W$226:W$245) -> 0 | L24: =SUMIF('A0 BS 1240在建'!$A$226:$A$245,$A24,'A0 BS 1240在建'!AA$226:AA$245) -> 0 | M24: =SUMIF('A0 BS 1240在建'!$A$226:$A$245,$A24,'A0 BS 1240在建'!AE$226:AE$245) -> 0 | N24: =SUMIF('A0 BS 1240在建'!$A$226:$A$245,$A24,'A0 BS 1240在建'!AI$226:AI$245) -> 0 | O24: =SUMIF('A0 BS 1240在建'!$A$226:$A$245,$A24,'A0 BS 1240在建'!AM$226:AM$245) -> 0 | P24: =SUMIF('A0 BS 1240在建'!$A$226:$A$245,$A24,'A0 BS 1240在建'!AQ$226:AQ$245) -> 0 | Q24: =SUMIF('A0 BS 1240在建'!$A$226:$A$245,$A24,'A0 BS 1240在建'!AU$226:AU$245) -> 0 | R24: =SUMIF('A0 BS 1240在建'!$A$226:$A$245,$A24,'A0 BS 1240在建'!AY$226:AY$245) -> 0 | S24: =SUMIF('A0 BS 1240在建'!$A$226:$A$245,$A24,'A0 BS 1240在建'!BC$226:BC$245) -> 0 | T24: =SUMIF('A0 BS 1240在建'!$A$226:$A$245,$A24,'A0 BS 1240在建'!BG$226:BG$245) -> 0 | U24: =SUMIF('A0 BS 1240在建'!$A$226:$A$245,$A24,'A0 BS 1240在建'!BS$226:BS$245) -> 0 | V24: =SUMIF('A0 BS 1240在建'!$A$226:$A$245,$A24,'A0 BS 1240在建'!CA$226:CA$245) -> 0 | W24: =SUMIF('A0 BS 1240在建'!$A$226:$A$245,$A24,'A0 BS 1240在建'!CI$226:CI$245) -> 0 | X24: =SUMIF('A0 BS 1240在建'!$A$226:$A$245,$A24,'A0 BS 1240在建'!CQ$226:CQ$245) -> 0 | Z24: 1200 Other receivable
A25: 1220 當期所得稅資產 | B25: 其他流動資產 | E25: =SUMIF('A0 BS 1240在建'!$A$226:$A$245, $A25,'A0 BS 1240在建'!G$226:G$245) -> 0 | F25: =SUM(D25:E25) -> 0 | G25: =+F25+H25 -> 0 | H25: =SUM(I25:T25) -> 0 | I25: =SUMIF('A0 BS 1240在建'!$A$226:$A$245,$A25,'A0 BS 1240在建'!O$226:O$245) -> 0 | J25: =SUMIF('A0 BS 1240在建'!$A$226:$A$245,$A25,'A0 BS 1240在建'!S$226:S$245) -> 0 | K25: =SUMIF('A0 BS 1240在建'!$A$226:$A$245,$A25,'A0 BS 1240在建'!W$226:W$245) -> 0 | L25: =SUMIF('A0 BS 1240在建'!$A$226:$A$245,$A25,'A0 BS 1240在建'!AA$226:AA$245) -> 0 | M25: =SUMIF('A0 BS 1240在建'!$A$226:$A$245,$A25,'A0 BS 1240在建'!AE$226:AE$245) -> 0 | N25: =SUMIF('A0 BS 1240在建'!$A$226:$A$245,$A25,'A0 BS 1240在建'!AI$226:AI$245) -> 0 | O25: =SUMIF('A0 BS 1240在建'!$A$226:$A$245,$A25,'A0 BS 1240在建'!AM$226:AM$245) -> 0 | P25: =SUMIF('A0 BS 1240在建'!$A$226:$A$245,$A25,'A0 BS 1240在建'!AQ$226:AQ$245) -> 0 | Q25: =SUMIF('A0 BS 1240在建'!$A$226:$A$245,$A25,'A0 BS 1240在建'!AU$226:AU$245) -> 0 | R25: =SUMIF('A0 BS 1240在建'!$A$226:$A$245,$A25,'A0 BS 1240在建'!AY$226:AY$245) -> 0 | S25: =SUMIF('A0 BS 1240在建'!$A$226:$A$245,$A25,'A0 BS 1240在建'!BC$226:BC$245) -> 0 | T25: =SUMIF('A0 BS 1240在建'!$A$226:$A$245,$A25,'A0 BS 1240在建'!BG$226:BG$245) -> 0 | U25: =SUMIF('A0 BS 1240在建'!$A$226:$A$245,$A25,'A0 BS 1240在建'!BS$226:BS$245) -> 0 | V25: =SUMIF('A0 BS 1240在建'!$A$226:$A$245,$A25,'A0 BS 1240在建'!CA$226:CA$245) -> 0 | W25: =SUMIF('A0 BS 1240在建'!$A$226:$A$245,$A25,'A0 BS 1240在建'!CI$226:CI$245) -> 0 | X25: =SUMIF('A0 BS 1240在建'!$A$226:$A$245,$A25,'A0 BS 1240在建'!CQ$226:CQ$245) -> 0 | Z25: 1220 Current tax assets
A26: 130X 存貨 | E26: =SUMIF('A0 BS 1240在建'!$A$226:$A$245, $A26,'A0 BS 1240在建'!G$226:G$245) -> 0 | F26: =SUM(D26:E26) -> 0 | G26: =+F26+H26 -> 0 | H26: =SUM(I26:T26) -> 0 | I26: =SUMIF('A0 BS 1240在建'!$A$226:$A$245,$A26,'A0 BS 1240在建'!O$226:O$245) -> 0 | J26: =SUMIF('A0 BS 1240在建'!$A$226:$A$245,$A26,'A0 BS 1240在建'!S$226:S$245) -> 0 | K26: =SUMIF('A0 BS 1240在建'!$A$226:$A$245,$A26,'A0 BS 1240在建'!W$226:W$245) -> 0 | L26: =SUMIF('A0 BS 1240在建'!$A$226:$A$245,$A26,'A0 BS 1240在建'!AA$226:AA$245) -> 0 | M26: =SUMIF('A0 BS 1240在建'!$A$226:$A$245,$A26,'A0 BS 1240在建'!AE$226:AE$245) -> 0 | N26: =SUMIF('A0 BS 1240在建'!$A$226:$A$245,$A26,'A0 BS 1240在建'!AI$226:AI$245) -> 0 | O26: =SUMIF('A0 BS 1240在建'!$A$226:$A$245,$A26,'A0 BS 1240在建'!AM$226:AM$245) -> 0 | P26: =SUMIF('A0 BS 1240在建'!$A$226:$A$245,$A26,'A0 BS 1240在建'!AQ$226:AQ$245) -> 0 | Q26: =SUMIF('A0 BS 1240在建'!$A$226:$A$245,$A26,'A0 BS 1240在建'!AU$226:AU$245) -> 0 | R26: =SUMIF('A0 BS 1240在建'!$A$226:$A$245,$A26,'A0 BS 1240在建'!AY$226:AY$245) -> 0 | S26: =SUMIF('A0 BS 1240在建'!$A$226:$A$245,$A26,'A0 BS 1240在建'!BC$226:BC$245) -> 0 | T26: =SUMIF('A0 BS 1240在建'!$A$226:$A$245,$A26,'A0 BS 1240在建'!BG$226:BG$245) -> 0 | U26: =SUMIF('A0 BS 1240在建'!$A$226:$A$245,$A26,'A0 BS 1240在建'!BS$226:BS$245) -> 0 | V26: =SUMIF('A0 BS 1240在建'!$A$226:$A$245,$A26,'A0 BS 1240在建'!CA$226:CA$245) -> 0 | W26: =SUMIF('A0 BS 1240在建'!$A$226:$A$245,$A26,'A0 BS 1240在建'!CI$226:CI$245) -> 0 | X26: =SUMIF('A0 BS 1240在建'!$A$226:$A$245,$A26,'A0 BS 1240在建'!CQ$226:CQ$245) -> 0 | Z26: 130X Inventories
A27: 1410 預付款項 | B27: 其他流動資產 | E27: =SUMIF('A0 BS 1240在建'!$A$226:$A$245, $A27,'A0 BS 1240在建'!G$226:G$245) -> 0 | F27: =SUM(D27:E27) -> 0 | G27: =+F27+H27 -> 0 | H27: =SUM(I27:T27) -> 0 | I27: =SUMIF('A0 BS 1240在建'!$A$226:$A$245,$A27,'A0 BS 1240在建'!O$226:O$245) -> 0 | J27: =SUMIF('A0 BS 1240在建'!$A$226:$A$245,$A27,'A0 BS 1240在建'!S$226:S$245) -> 0 | K27: =SUMIF('A0 BS 1240在建'!$A$226:$A$245,$A27,'A0 BS 1240在建'!W$226:W$245) -> 0 | L27: =SUMIF('A0 BS 1240在建'!$A$226:$A$245,$A27,'A0 BS 1240在建'!AA$226:AA$245) -> 0 | M27: =SUMIF('A0 BS 1240在建'!$A$226:$A$245,$A27,'A0 BS 1240在建'!AE$226:AE$245) -> 0 | N27: =SUMIF('A0 BS 1240在建'!$A$226:$A$245,$A27,'A0 BS 1240在建'!AI$226:AI$245) -> 0 | O27: =SUMIF('A0 BS 1240在建'!$A$226:$A$245,$A27,'A0 BS 1240在建'!AM$226:AM$245) -> 0 | P27: =SUMIF('A0 BS 1240在建'!$A$226:$A$245,$A27,'A0 BS 1240在建'!AQ$226:AQ$245) -> 0 | Q27: =SUMIF('A0 BS 1240在建'!$A$226:$A$245,$A27,'A0 BS 1240在建'!AU$226:AU$245) -> 0 | R27: =SUMIF('A0 BS 1240在建'!$A$226:$A$245,$A27,'A0 BS 1240在建'!AY$226:AY$245) -> 0 | S27: =SUMIF('A0 BS 1240在建'!$A$226:$A$245,$A27,'A0 BS 1240在建'!BC$226:BC$245) -> 0 | T27: =SUMIF('A0 BS 1240在建'!$A$226:$A$245,$A27,'A0 BS 1240在建'!BG$226:BG$245) -> 0 | U27: =SUMIF('A0 BS 1240在建'!$A$226:$A$245,$A27,'A0 BS 1240在建'!BS$226:BS$245) -> 0 | V27: =SUMIF('A0 BS 1240在建'!$A$226:$A$245,$A27,'A0 BS 1240在建'!CA$226:CA$245) -> 0 | W27: =SUMIF('A0 BS 1240在建'!$A$226:$A$245,$A27,'A0 BS 1240在建'!CI$226:CI$245) -> 0 | X27: =SUMIF('A0 BS 1240在建'!$A$226:$A$245,$A27,'A0 BS 1240在建'!CQ$226:CQ$245) -> 0 | Z27: 1410 Prepayments
A28: 1470 其他流動資產 | E28: =SUM(E29:E31) -> 0 | F28: =SUM(F29:F31) -> 0 | G28: =+F28+H28 -> 0 | H28: =SUM(I28:T28) -> 0 | I28: =SUM(I29:I31) -> 0 | J28: =SUM(J29:J31) -> 0 | K28: =SUM(K29:K31) -> 0 | L28: =SUM(L29:L31) -> 0 | M28: =SUM(M29:M31) -> 0 | N28: =SUM(N29:N31) -> 0 | O28: =SUM(O29:O31) -> 0 | P28: =SUM(P29:P31) -> 0 | ... V28: =SUM(V29:V31) -> 0 | W28: =SUMIF('A0 BS 1240在建'!$A$226:$A$245,$A28,'A0 BS 1240在建'!CI$226:CI$245) -> 0 | X28: =SUMIF('A0 BS 1240在建'!$A$226:$A$245,$A28,'A0 BS 1240在建'!CQ$226:CQ$245) -> 0 | Z28: 1470 Other current assets
A29: 質押定期存款 | B29: 銀行存款 | E29: =SUMIF('A0 BS 1240在建'!$A$226:$A$245, $A29,'A0 BS 1240在建'!G$226:G$245) -> 0 | F29: =SUM(D29:E29) -> 0 | G29: =+F29+H29 -> 0 | H29: =SUM(I29:T29) -> 0
A30: 銀行存款-備償 | B30: 銀行存款 | E30: =SUMIF('A0 BS 1240在建'!$A$226:$A$245, $A30,'A0 BS 1240在建'!G$226:G$245) -> 0 | F30: =SUM(D30:E30) -> 0 | G30: =+F30+H30 -> 0 | H30: =SUM(I30:T30) -> 0
A31: 其他流動資產 | B31: 其他流動資產 | E31: =SUMIF('A0 BS 1240在建'!$A$226:$A$245, $A31,'A0 BS 1240在建'!G$226:G$245) -> 0 | F31: =SUM(D31:E31) -> 0 | G31: =+F31+H31 -> 0 | H31: =SUM(I31:T31) -> 0
A32: 1471 公司內部往來: | E32: =SUM(E33:E40) -> 0 | F32: =SUM(F33:F40) -> 0 | G32: =SUM(G33:G40) -> 0 | H32: =SUM(H33:H40) -> 0 | I32: =SUM(I33:I40) -> 0 | J32: =SUM(J33:J40) -> 0 | K32: =SUM(K33:K40) -> 0 | L32: =SUM(L33:L40) -> 0 | ... X32: =SUM(X33:X40) -> 0 | Z32: 1471 Intercompany current account :
A33: 台灣事業處 | F33: =SUM(D33:E33) -> 0 | G33: =+F33+H33 -> 0 | H33: =SUM(I33:T33) -> 0 | Z33: Taiwan/HQ
A34: 台灣事業處-資金往來 | F34: =SUM(D34:E34) -> 0 | G34: =+F34+H34 -> 0 | H34: =SUM(I34:T34) -> 0 | Z34: Taiwan/HQ -Funding
A35: 香港分公司 | F35: =SUM(D35:E35) -> 0 | G35: =+F35+H35 -> 0 | H35: =SUM(I35:T35) -> 0 | Z35: HK branch /HQ
A36: 香港子公司 | F36: =SUM(D36:E36) -> 0 | G36: =+F36+H36 -> 0 | H36: =SUM(I36:T36) -> 0 | Z36: HK subsidiary/HQ
A37: 澳門分公司 | F37: =SUM(D37:E37) -> 0 | G37: =+F37+H37 -> 0 | H37: =SUM(I37:T37) -> 0 | Z37: Macau branch /HQ
A38: 印度專案辦公室 | F38: =SUM(D38:E38) -> 0 | G38: =+F38+H38 -> 0 | H38: =SUM(I38:T38) -> 0 | Z38: ICEC/HQ
A39: 印度子公司 | F39: =SUM(D39:E39) -> 0 | G39: =+F39+H39 -> 0 | H39: =SUM(I39:T39) -> 0 | Z39: CICI/HQ
A40: 馬來西亞子公司 | F40: =SUM(D40:E40) -> 0 | G40: =+F40+H40 -> 0 | H40: =SUM(I40:T40) -> 0 | Z40: CIMY/HQ
A41: 流動資產小計 | D41: =SUM(D10:D14,D19:D32)-SUM(D12:D13)-SUM(D29:D31) -> #REF! | E41: =SUM(E10:E14,E19:E32)-SUM(E12:E13)-SUM(E29:E31) -> 21367000 | F41: =SUM(F10:F14,F19:F32)-SUM(F12:F13)-SUM(F29:F31) -> #REF! | G41: =+F41+H41 -> #REF! | H41: =SUM(I41:T41) -> #N/A | I41: =SUM(I10:I14,I19:I32)-SUM(I12:I13)-SUM(I29:I31) -> #N/A | J41: =SUM(J10:J14,J19:J32)-SUM(J12:J13)-SUM(J29:J31) -> #N/A | K41: =SUM(K10:K14,K19:K32)-SUM(K12:K13)-SUM(K29:K31) -> #N/A | L41: =SUM(L10:L14,L19:L32)-SUM(L12:L13)-SUM(L29:L31) -> #N/A | M41: =SUM(M10:M14,M19:M32)-SUM(M12:M13)-SUM(M29:M31) -> #N/A | N41: =SUM(N10:N14,N19:N32)-SUM(N12:N13)-SUM(N29:N31) -> #N/A | O41: =SUM(O10:O14,O19:O32)-SUM(O12:O13)-SUM(O29:O31) -> #N/A | P41: =SUM(P10:P14,P19:P32)-SUM(P12:P13)-SUM(P29:P31) -> #N/A | ... X41: =SUM(X10:X14,X19:X32)-SUM(X12:X13)-SUM(X29:X31) -> #REF! | Z41: Subtotal Current assets
G42: =+F42+H42 -> 0 | H42: =SUM(I42:T42) -> 0
A43: 非流動資產: | G43: =+F43+H43 -> 0 | H43: =SUM(I43:T43) -> 0 | Z43: Non-current Assets:
A44: 1510 透過損益按公允價值衡量之金融資產-非流動 | G44: =+F44+H44 -> 0 | H44: =SUM(I44:T44) -> 0 | Z44: 1510 Non-current Financial Assets at FV through P&L
A45: 1517 透過OCI按FV衡量之金融資產-非流動 | G45: =+F45+H45 -> 0 | H45: =SUM(I45:T45) -> 0 | Z45: 1517 Non-current Financial Assets at FV through OCI
A46: 1550 採權益法之投資 | G46: =+F46+H46 -> 0 | H46: =SUM(I46:T46) -> 0 | Z46: 1550 Investment accounted for using equity method
A47: 1601 土地 | F47: =SUM(D47:E47) -> 0 | G47: =+F47+H47 -> 0 | H47: =SUM(I47:T47) -> 0 | Z47: 1601 Land
A48: 1611 房屋及建築 | F48: =SUM(D48:E48) -> 0 | G48: =+F48+H48 -> 0 | H48: =SUM(I48:T48) -> 0 | Z48: 1611 Buildings
A49: 1615 機器設備 | F49: =SUM(D49:E49) -> 0 | G49: =+F49+H49 -> 0 | H49: =SUM(I49:T49) -> 0 | Z49: 1615 Machinery and equipment
A50: 1655 電腦通訊設備 | F50: =SUM(D50:E50) -> 0 | G50: =+F50+H50 -> 0 | H50: =SUM(I50:T50) -> 0 | Z50: 1655 Computer equipment
A51: 1670 運輸設備 | F51: =SUM(D51:E51) -> 0 | G51: =+F51+H51 -> 0 | H51: =SUM(I51:T51) -> 0 | Z51: 1670 Transportation equipment
A52: 1690 辦公設備 | F52: =SUM(D52:E52) -> 0 | G52: =+F52+H52 -> 0 | H52: =SUM(I52:T52) -> 0 | Z52: 1690 Office equipment
A53: 1600 不動產、廠房及設備-成本 | E53: =SUM(E47:E52) -> 0 | F53: =SUM(D53:E53) -> 0 | G53: =+F53+H53 -> 0 | H53: =SUM(I53:T53) -> 0 | I53: =SUM(I47:I52) -> 0 | J53: =SUM(J47:J52) -> 0 | K53: =SUM(K47:K52) -> 0 | L53: =SUM(L47:L52) -> 0 | M53: =SUM(M47:M52) -> 0 | N53: =SUM(N47:N52) -> 0 | O53: =SUM(O47:O52) -> 0 | P53: =SUM(P47:P52) -> 0 | ... X53: =SUM(X47:X52) -> 0 | Z53: 1600 Property, plant and equipment -Cost
A54: 1613 累折-房屋及建築 | F54: =SUM(D54:E54) -> 0 | G54: =+F54+H54 -> 0 | H54: =SUM(I54:T54) -> 0 | Z54: 1613 AD-Buildings
A55: 1618 累折-機器設備 | F55: =SUM(D55:E55) -> 0 | G55: =+F55+H55 -> 0 | H55: =SUM(I55:T55) -> 0 | Z55: 1618 AD-Machinery and equipment
A56: 1658 累折-電腦通訊設備 | F56: =SUM(D56:E56) -> 0 | G56: =+F56+H56 -> 0 | H56: =SUM(I56:T56) -> 0 | Z56: 1658 Computer equipment
A57: 1673 累折-運輸設備 | F57: =SUM(D57:E57) -> 0 | G57: =+F57+H57 -> 0 | H57: =SUM(I57:T57) -> 0 | Z57: 1673 Transportation equipment
A58: 1693 累折-辦公設備 | F58: =SUM(D58:E58) -> 0 | G58: =+F58+H58 -> 0 | H58: =SUM(I58:T58) -> 0 | Z58: 1693 Office equipment
A59: 1619 累減-機器設備 | F59: =SUM(D59:E59) -> 0 | G59: =+F59+H59 -> 0 | H59: =SUM(I59:T59) -> 0 | Z59: 1619 Impairment-Machinery & Equipment
A60: 1600 不動產、廠房及設備-累折及減損 | E60: =SUM(E54:E59) -> 0 | F60: =SUM(F54:F59) -> 0 | G60: =+F60+H60 -> 0 | H60: =SUM(I60:T60) -> 0 | I60: =SUM(I54:I59) -> 0 | J60: =SUM(J54:J59) -> 0 | K60: =SUM(K54:K59) -> 0 | L60: =SUM(L54:L59) -> 0 | M60: =SUM(M54:M59) -> 0 | N60: =SUM(N54:N59) -> 0 | O60: =SUM(O54:O59) -> 0 | P60: =SUM(P54:P59) -> 0 | ... X60: =SUM(X54:X59) -> 0 | Z60: 1600 Property, plant and equipment -AD & impairment
A61: 1600 不動產、廠房及設備淨額 | E61: =E53+E60 -> 0 | F61: =F53+F60 -> 0 | G61: =+F61+H61 -> 0 | H61: =SUM(I61:T61) -> 0 | I61: =I53+I60 -> 0 | J61: =J53+J60 -> 0 | K61: =K53+K60 -> 0 | L61: =L53+L60 -> 0 | M61: =M53+M60 -> 0 | N61: =N53+N60 -> 0 | O61: =O53+O60 -> 0 | P61: =P53+P60 -> 0 | ... X61: =X53+X60 -> 0 | Z61: 1600 Property, plant and equipment -net
A63: 1751 使用權資產-土地 | F63: =SUM(D63:E63) -> 0 | G63: =+F63+H63 -> 0 | H63: =SUM(I63:T63) -> 0 | Z63: 1751 Right-of-use property-land
A64: 1752 使用權資產-房屋及建築 | F64: =SUM(D64:E64) -> 0 | G64: =+F64+H64 -> 0 | H64: =SUM(I64:T64) -> 0 | Z64: 1752 Right-of-use property-buildings
A65: 1754 使用權資產-運輸設備 | F65: =SUM(D65:E65) -> 0 | G65: =+F65+H65 -> 0 | H65: =SUM(I65:T65) -> 0 | Z65: 1754 Right-of-use property-transportation equip.
A66: 1750 使用權資產小計 | E66: =SUM(E63:E65) -> 0 | F66: =SUM(F63:F65) -> 0 | G66: =+F66+H66 -> 0 | H66: =SUM(I66:T66) -> 0 | I66: =SUM(I63:I65) -> 0 | J66: =SUM(J63:J65) -> 0 | K66: =SUM(K63:K65) -> 0 | L66: =SUM(L63:L65) -> 0 | M66: =SUM(M63:M65) -> 0 | N66: =SUM(N63:N65) -> 0 | O66: =SUM(O63:O65) -> 0 | P66: =SUM(P63:P65) -> 0 | ... X66: =SUM(X63:X65) -> 0 | Z66: 1750 Subtotal Right-of-use property
A67: 1756 累折-使用權資產-土地 | F67: =SUM(D67:E67) -> 0 | G67: =+F67+H67 -> 0 | H67: =SUM(I67:T67) -> 0 | Z67: 1756 AD_Right-of-use property-land
A68: 1757 累折-使用權資產-房屋及建築 | F68: =SUM(D68:E68) -> 0 | G68: =+F68+H68 -> 0 | H68: =SUM(I68:T68) -> 0 | Z68: 1757 AD_Right-of-use property-buildings
A69: 1759 累折-使用權資產-運輸設備 | F69: =SUM(D69:E69) -> 0 | G69: =+F69+H69 -> 0 | H69: =SUM(I69:T69) -> 0 | Z69: 1759 AD_Right-of-use property-transportation equip.
A70: 1750 使用權資產淨額 | E70: =SUM(E66:E69) -> 0 | F70: =SUM(F66:F69) -> 0 | G70: =+F70+H70 -> 0 | H70: =SUM(I70:T70) -> 0 | I70: =SUM(I66:I69) -> 0 | J70: =SUM(J66:J69) -> 0 | K70: =SUM(K66:K69) -> 0 | L70: =SUM(L66:L69) -> 0 | M70: =SUM(M66:M69) -> 0 | N70: =SUM(N66:N69) -> 0 | O70: =SUM(O66:O69) -> 0 | P70: =SUM(P66:P69) -> 0 | ... X70: =SUM(X66:X69) -> 0 | Z70: 1750 Right-of-use property - net (IFRS 16)
A71: 1761 投資性不動產-土地 | F71: =SUM(D71:E71) -> 0 | G71: =+F71+H71 -> 0 | H71: =SUM(I71:T71) -> 0 | Z71: 1761 Investment property-land
A72: 1765 投資性不動產-建築物 | F72: =SUM(D72:E72) -> 0 | G72: =+F72+H72 -> 0 | H72: =SUM(I72:T72) -> 0 | Z72: 1765 Investment property-buildings
A73: 1760 投資性不動產小計 | E73: =SUM(E71:E72) -> 0 | F73: =SUM(F71:F72) -> 0 | G73: =+F73+H73 -> 0 | H73: =SUM(I73:T73) -> 0 | I73: =SUM(I71:I72) -> 0 | J73: =SUM(J71:J72) -> 0 | K73: =SUM(K71:K72) -> 0 | L73: =SUM(L71:L72) -> 0 | M73: =SUM(M71:M72) -> 0 | N73: =SUM(N71:N72) -> 0 | O73: =SUM(O71:O72) -> 0 | P73: =SUM(P71:P72) -> 0 | ... X73: =SUM(X71:X72) -> 0 | Z73: 1760 Subtotal Investment property
A74: 1768 累折-投資性不動產-建築物 | F74: =SUM(D74:E74) -> 0 | G74: =+F74+H74 -> 0 | H74: =SUM(I74:T74) -> 0 | Z74: 1768 AD_ Investment property-buildings
A75: 1760 投資性不動產淨額 | E75: =SUM(E73:E74) -> 0 | F75: =SUM(F73:F74) -> 0 | G75: =+F75+H75 -> 0 | H75: =SUM(I75:T75) -> 0 | I75: =SUM(I73:I74) -> 0 | J75: =SUM(J73:J74) -> 0 | K75: =SUM(K73:K74) -> 0 | L75: =SUM(L73:L74) -> 0 | M75: =SUM(M73:M74) -> 0 | N75: =SUM(N73:N74) -> 0 | O75: =SUM(O73:O74) -> 0 | P75: =SUM(P73:P74) -> 0 | ... X75: =SUM(X73:X74) -> 0 | Z75: 1760 Investment property - net
A76: 1900 其他非流動資產 | E76: =SUMIF('A0 BS 1240在建'!$A$226:$A$245, $A76,'A0 BS 1240在建'!G$226:G$245) -> 0 | F76: =+D76+E76 -> 0 | G76: =+F76+H76 -> 0 | H76: =SUM(I76:T76) -> 0 | Z76: 1900 Other Non-current assets
A78: 非流動資產小計 | E78: =E61+E70+E75+E76+E77 -> 0 | F78: =F61+F70+F75+F76+F77 -> 0 | G78: =+F78+H78 -> 0 | H78: =SUM(I78:T78) -> 0 | I78: =I61+I70+I75+I76+I77 -> 0 | J78: =J61+J70+J75+J76+J77 -> 0 | K78: =K61+K70+K75+K76+K77 -> 0 | L78: =L61+L70+L75+L76+L77 -> 0 | M78: =M61+M70+M75+M76+M77 -> 0 | N78: =N61+N70+N75+N76+N77 -> 0 | O78: =O61+O70+O75+O76+O77 -> 0 | P78: =P61+P70+P75+P76+P77 -> 0 | ... X78: =X61+X70+X75+X76+X77 -> 0 | Z78: Subtotal Non-current assets
A79: 資產總計 | D79: =D41+D78 -> #REF! | E79: =E41+E78 -> 21367000 | F79: =F41+F78 -> #REF! | G79: =+F79+H79 -> #REF! | H79: =SUM(I79:T79) -> #N/A | I79: =I41+I78 -> #N/A | J79: =J41+J78 -> #N/A | K79: =K41+K78 -> #N/A | L79: =L41+L78 -> #N/A | M79: =M41+M78 -> #N/A | N79: =N41+N78 -> #N/A | O79: =O41+O78 -> #N/A | P79: =P41+P78 -> #N/A | ... X79: =X41+X78 -> #REF! | Z79: TOTAL ASSETS
A81: 流動負債: | B81: 以下*-1 | E81: 以下*-1 | I81: 以下*-1 | J81: 以下*-1 | K81: 以下*-1 | L81: 以下*-1 | M81: 以下*-1 | N81: 以下*-1 | O81: 以下*-1 | P81: 以下*-1 | Q81: 以下*-1 | R81: 以下*-1 | S81: 以下*-1 | T81: 以下*-1 | U81: 以下*-1 | V81: 以下*-1 | W81: 以下*-1 | X81: 以下*-1 | Z81: Current Liabilities:
A82: 2100 短期借款 | F82: =SUM(D82:E82) -> 0 | G82: =+F82+H82 -> 0 | H82: =SUM(I82:T82) -> 0 | Z82: 2100 Short-term borrowings
A83: 2110 應付短期票券 | F83: =SUM(D83:E83) -> 0 | G83: =+F83+H83 -> 0 | H83: =SUM(I83:T83) -> 0 | Z83: 2110 Short-term notes & bill payable
A84: 1190 應付建造合約款 | D84: =-#REF! -> #REF! | E84: =VLOOKUP($A84,'Over Under Bill 2'!$1:$1048576,4,0) -> 0 | F84: =+D84+E84 -> #REF! | G84: =+F84+H84 -> #REF! | H84: =SUM(I84:T84) -> 0 | I84: =VLOOKUP($A84,'Over Under Bill 2'!$1:$1048576,5,0) -> 0 | J84: =VLOOKUP($A84,'Over Under Bill 2'!$1:$1048576,6,0) -> 0 | K84: =VLOOKUP($A84,'Over Under Bill 2'!$1:$1048576,7,0) -> 0 | L84: =VLOOKUP($A84,'Over Under Bill 2'!$1:$1048576,8,0) -> 0 | M84: =VLOOKUP($A84,'Over Under Bill 2'!$1:$1048576,9,0) -> 0 | N84: =VLOOKUP($A84,'Over Under Bill 2'!$1:$1048576,10,0) -> 0 | O84: =VLOOKUP($A84,'Over Under Bill 2'!$1:$1048576,11,0) -> 0 | P84: =VLOOKUP($A84,'Over Under Bill 2'!$1:$1048576,12,0) -> 0 | Q84: =VLOOKUP($A84,'Over Under Bill 2'!$1:$1048576,13,0) -> 0 | R84: =VLOOKUP($A84,'Over Under Bill 2'!$1:$1048576,14,0) -> 0 | S84: =VLOOKUP($A84,'Over Under Bill 2'!$1:$1048576,15,0) -> 0 | T84: =VLOOKUP($A84,'Over Under Bill 2'!$1:$1048576,16,0) -> 0 | U84: =VLOOKUP($A84,'Over Under Bill 2'!$1:$1048576,17,0) -> 0 | V84: =VLOOKUP($A84,'Over Under Bill 2'!$1:$1048576,18,0) -> 0 | W84: =VLOOKUP($A84,'Over Under Bill 2'!$1:$1048576,19,0) -> 0 | X84: =VLOOKUP($A84,'Over Under Bill 2'!$1:$1048576,20,0) -> 0 | Z84: 2190 Construction contracts payable
A85: 2264X 工程合約-其他預收工程款 | G85: =+F85+H85 -> 0 | H85: =SUM(I85:T85) -> 0 | I85: =-SUMIF('A0 BS 1240在建'!$A$226:$A$245,$A85,'A0 BS 1240在建'!O$226:O$245) -> 0 | Z85: 2264X Construction contracts - Progress billing
A86: 2264X 工程合約-業主預付款 | G86: =+F86+H86 -> 0 | H86: =SUM(I86:T86) -> 0 | I86: =-SUMIF('A0 BS 1240在建'!$A$226:$A$245,$A86,'A0 BS 1240在建'!O$226:O$245) -> 0 | Z86: 2264X Construction contracts -Client's Advance Payment
A87: 1240 X 在建工程_成本 | G87: =+F87+H87 -> 0 | H87: =SUM(I87:T87) -> 0 | Z87: 1240 X WIP -Cost Incurred
A88: 1247X 在建損益 | G88: =+F88+H88 -> 0 | H88: =SUM(I88:T88) -> 0 | Z88: 1247X WIP - P&L (by POC)
A89: 2300 預收工程款-業主預付款 | E89: =-SUMIF('A0 BS 1240在建'!$A$226:$A$245, $A89,'A0 BS 1240在建'!G$226:G$245) -> 0 | F89: =SUM(D89:E89) -> 0 | G89: =+F89+H89 -> 0 | H89: =SUM(I89:T89) -> 0 | I89: =-SUMIF('A0 BS 1240在建'!$A$226:$A$245,$A89,'A0 BS 1240在建'!O$226:O$245) -> 0 | J89: =-IFERROR(VLOOKUP($A89,'A0 BS 1240在建'!$228:$243,19,0),0)-IFERROR(SUMIF(#REF!,BS2_WIP!$A89,#REF!),0) -> 0 | K89: =-SUMIF('A0 BS 1240在建'!$A$226:$A$245,$A89,'A0 BS 1240在建'!W$226:W$245) -> 0 | L89: =-SUMIF('A0 BS 1240在建'!$A$226:$A$245,$A89,'A0 BS 1240在建'!AA$226:AA$245) -> 0 | M89: =-SUMIF('A0 BS 1240在建'!$A$226:$A$245,$A89,'A0 BS 1240在建'!AE$226:AE$245) -> 0 | N89: =-SUMIF('A0 BS 1240在建'!$A$226:$A$245,$A89,'A0 BS 1240在建'!AI$226:AI$245) -> 0 | O89: =-SUMIF('A0 BS 1240在建'!$A$226:$A$245,$A89,'A0 BS 1240在建'!AM$226:AM$245) -> 0 | P89: =-SUMIF('A0 BS 1240在建'!$A$226:$A$245,$A89,'A0 BS 1240在建'!AQ$226:AQ$245) -> 0 | Q89: =-SUMIF('A0 BS 1240在建'!$A$226:$A$245,$A89,'A0 BS 1240在建'!AU$226:AU$245) -> 0 | R89: =-SUMIF('A0 BS 1240在建'!$A$226:$A$245,$A89,'A0 BS 1240在建'!AY$226:AY$245) -> 0 | S89: =-SUMIF('A0 BS 1240在建'!$A$226:$A$245,$A89,'A0 BS 1240在建'!BC$226:BC$245) -> 0 | T89: =-SUMIF('A0 BS 1240在建'!$A$226:$A$245,$A89,'A0 BS 1240在建'!BG$226:BG$245) -> 0 | U89: =-SUMIF('A0 BS 1240在建'!$A$226:$A$245,$A89,'A0 BS 1240在建'!BS$226:BS$245) -> 0 | V89: =-SUMIF('A0 BS 1240在建'!$A$226:$A$245,$A89,'A0 BS 1240在建'!CA$226:CA$245) -> 0 | W89: =-SUMIF('A0 BS 1240在建'!$A$226:$A$245,$A89,'A0 BS 1240在建'!CI$226:CI$245) -> 0 | X89: =-SUMIF('A0 BS 1240在建'!$A$226:$A$245,$A89,'A0 BS 1240在建'!CQ$226:CQ$245) -> 0 | Z89: 2300 Advance receipts - client advance payment
A90: 2170 應付帳款 | B90: 應付款項 | E90: =-SUMIF('A0 BS 1240在建'!$A$226:$A$245, $A90,'A0 BS 1240在建'!G$226:G$245) -> 0 | F90: =SUM(D90:E90) -> 0 | G90: =+F90+H90 -> 0 | H90: =SUM(I90:T90) -> 0 | I90: =-SUMIF('A0 BS 1240在建'!$A$226:$A$245,$A90,'A0 BS 1240在建'!O$226:O$245) -> 0 | J90: =-IFERROR(VLOOKUP($A90,'A0 BS 1240在建'!$228:$243,19,0),0)-IFERROR(SUMIF(#REF!,BS2_WIP!$A90,#REF!),0) -> 0 | K90: =-SUMIF('A0 BS 1240在建'!$A$226:$A$245,$A90,'A0 BS 1240在建'!W$226:W$245) -> 0 | L90: =-SUMIF('A0 BS 1240在建'!$A$226:$A$245,$A90,'A0 BS 1240在建'!AA$226:AA$245) -> 0 | M90: =-SUMIF('A0 BS 1240在建'!$A$226:$A$245,$A90,'A0 BS 1240在建'!AE$226:AE$245) -> 0 | N90: =-SUMIF('A0 BS 1240在建'!$A$226:$A$245,$A90,'A0 BS 1240在建'!AI$226:AI$245) -> 0 | O90: =-SUMIF('A0 BS 1240在建'!$A$226:$A$245,$A90,'A0 BS 1240在建'!AM$226:AM$245) -> 0 | P90: =-SUMIF('A0 BS 1240在建'!$A$226:$A$245,$A90,'A0 BS 1240在建'!AQ$226:AQ$245) -> 0 | Q90: =-SUMIF('A0 BS 1240在建'!$A$226:$A$245,$A90,'A0 BS 1240在建'!AU$226:AU$245) -> 0 | R90: =-SUMIF('A0 BS 1240在建'!$A$226:$A$245,$A90,'A0 BS 1240在建'!AY$226:AY$245) -> 0 | S90: =-SUMIF('A0 BS 1240在建'!$A$226:$A$245,$A90,'A0 BS 1240在建'!BC$226:BC$245) -> 0 | T90: =-SUMIF('A0 BS 1240在建'!$A$226:$A$245,$A90,'A0 BS 1240在建'!BG$226:BG$245) -> 0 | U90: =-SUMIF('A0 BS 1240在建'!$A$226:$A$245,$A90,'A0 BS 1240在建'!BS$226:BS$245) -> 0 | V90: =-SUMIF('A0 BS 1240在建'!$A$226:$A$245,$A90,'A0 BS 1240在建'!CA$226:CA$245) -> 0 | W90: =-SUMIF('A0 BS 1240在建'!$A$226:$A$245,$A90,'A0 BS 1240在建'!CI$226:CI$245) -> 0 | X90: =-SUMIF('A0 BS 1240在建'!$A$226:$A$245,$A90,'A0 BS 1240在建'!CQ$226:CQ$245) -> 0 | Z90: 2170 Accounts payable
A91: 2180 應付帳款-關係人 | E91: =-SUMIF('A0 BS 1240在建'!$A$226:$A$245, $A91,'A0 BS 1240在建'!G$226:G$245) -> 0 | F91: =SUM(D91:E91) -> 0 | G91: =+F91+H91 -> 0 | H91: =SUM(I91:T91) -> 0 | I91: =-SUMIF('A0 BS 1240在建'!$A$226:$A$245,$A91,'A0 BS 1240在建'!O$226:O$245) -> 0 | J91: =-IFERROR(VLOOKUP($A91,'A0 BS 1240在建'!$228:$243,19,0),0)-IFERROR(SUMIF(#REF!,BS2_WIP!$A91,#REF!),0) -> 0 | K91: =-SUMIF('A0 BS 1240在建'!$A$226:$A$245,$A91,'A0 BS 1240在建'!W$226:W$245) -> 0 | L91: =-SUMIF('A0 BS 1240在建'!$A$226:$A$245,$A91,'A0 BS 1240在建'!AA$226:AA$245) -> 0 | M91: =-SUMIF('A0 BS 1240在建'!$A$226:$A$245,$A91,'A0 BS 1240在建'!AE$226:AE$245) -> 0 | N91: =-SUMIF('A0 BS 1240在建'!$A$226:$A$245,$A91,'A0 BS 1240在建'!AI$226:AI$245) -> 0 | O91: =-SUMIF('A0 BS 1240在建'!$A$226:$A$245,$A91,'A0 BS 1240在建'!AM$226:AM$245) -> 0 | P91: =-SUMIF('A0 BS 1240在建'!$A$226:$A$245,$A91,'A0 BS 1240在建'!AQ$226:AQ$245) -> 0 | Q91: =-SUMIF('A0 BS 1240在建'!$A$226:$A$245,$A91,'A0 BS 1240在建'!AU$226:AU$245) -> 0 | R91: =-SUMIF('A0 BS 1240在建'!$A$226:$A$245,$A91,'A0 BS 1240在建'!AY$226:AY$245) -> 0 | S91: =-SUMIF('A0 BS 1240在建'!$A$226:$A$245,$A91,'A0 BS 1240在建'!BC$226:BC$245) -> 0 | T91: =-SUMIF('A0 BS 1240在建'!$A$226:$A$245,$A91,'A0 BS 1240在建'!BG$226:BG$245) -> 0 | U91: =-SUMIF('A0 BS 1240在建'!$A$226:$A$245,$A91,'A0 BS 1240在建'!BS$226:BS$245) -> 0 | V91: =-SUMIF('A0 BS 1240在建'!$A$226:$A$245,$A91,'A0 BS 1240在建'!CA$226:CA$245) -> 0 | W91: =-SUMIF('A0 BS 1240在建'!$A$226:$A$245,$A91,'A0 BS 1240在建'!CI$226:CI$245) -> 0 | X91: =-SUMIF('A0 BS 1240在建'!$A$226:$A$245,$A91,'A0 BS 1240在建'!CQ$226:CQ$245) -> 0 | Z91: 2180 Accouts payable - related parties
A92: 2200 其他應付款 | B92: 其他流動負債 | E92: =-SUMIF('A0 BS 1240在建'!$A$226:$A$245, $A92,'A0 BS 1240在建'!G$226:G$245) -> 0 | F92: =SUM(D92:E92) -> 0 | G92: =+F92+H92 -> 0 | H92: =SUM(I92:T92) -> 0 | I92: =-SUMIF('A0 BS 1240在建'!$A$226:$A$245,$A92,'A0 BS 1240在建'!O$226:O$245) -> 0 | J92: =-IFERROR(VLOOKUP($A92,'A0 BS 1240在建'!$228:$243,19,0),0)-IFERROR(SUMIF(#REF!,BS2_WIP!$A92,#REF!),0) -> 0 | K92: =-SUMIF('A0 BS 1240在建'!$A$226:$A$245,$A92,'A0 BS 1240在建'!W$226:W$245) -> 0 | L92: =-SUMIF('A0 BS 1240在建'!$A$226:$A$245,$A92,'A0 BS 1240在建'!AA$226:AA$245) -> 0 | M92: =-SUMIF('A0 BS 1240在建'!$A$226:$A$245,$A92,'A0 BS 1240在建'!AE$226:AE$245) -> 0 | N92: =-SUMIF('A0 BS 1240在建'!$A$226:$A$245,$A92,'A0 BS 1240在建'!AI$226:AI$245) -> 0 | O92: =-SUMIF('A0 BS 1240在建'!$A$226:$A$245,$A92,'A0 BS 1240在建'!AM$226:AM$245) -> 0 | P92: =-SUMIF('A0 BS 1240在建'!$A$226:$A$245,$A92,'A0 BS 1240在建'!AQ$226:AQ$245) -> 0 | Q92: =-SUMIF('A0 BS 1240在建'!$A$226:$A$245,$A92,'A0 BS 1240在建'!AU$226:AU$245) -> 0 | R92: =-SUMIF('A0 BS 1240在建'!$A$226:$A$245,$A92,'A0 BS 1240在建'!AY$226:AY$245) -> 0 | S92: =-SUMIF('A0 BS 1240在建'!$A$226:$A$245,$A92,'A0 BS 1240在建'!BC$226:BC$245) -> 0 | T92: =-SUMIF('A0 BS 1240在建'!$A$226:$A$245,$A92,'A0 BS 1240在建'!BG$226:BG$245) -> 0 | U92: =-SUMIF('A0 BS 1240在建'!$A$226:$A$245,$A92,'A0 BS 1240在建'!BS$226:BS$245) -> 0 | V92: =-SUMIF('A0 BS 1240在建'!$A$226:$A$245,$A92,'A0 BS 1240在建'!CA$226:CA$245) -> 0 | W92: =-SUMIF('A0 BS 1240在建'!$A$226:$A$245,$A92,'A0 BS 1240在建'!CI$226:CI$245) -> 0 | X92: =-SUMIF('A0 BS 1240在建'!$A$226:$A$245,$A92,'A0 BS 1240在建'!CQ$226:CQ$245) -> 0 | Z92: 2200 Other payable
A93: 2214 銷項-1264 進項 | B93: 其他流動負債 | E93: =-SUMIF('A0 BS 1240在建'!$A$226:$A$245, $A93,'A0 BS 1240在建'!G$226:G$245) -> -346975 | F93: =SUM(D93:E93) -> -346975 | G93: =+F93+H93 -> #N/A | H93: =SUM(I93:T93) -> #N/A | I93: =-SUMIF('A0 BS 1240在建'!$A$226:$A$245,$A93,'A0 BS 1240在建'!O$226:O$245) -> #N/A | J93: =-IFERROR(VLOOKUP($A93,'A0 BS 1240在建'!$228:$243,19,0),0)-IFERROR(SUMIF(#REF!,BS2_WIP!$A93,#REF!),0) -> 0 | K93: =-SUMIF('A0 BS 1240在建'!$A$226:$A$245,$A93,'A0 BS 1240在建'!W$226:W$245) -> #N/A | L93: =-SUMIF('A0 BS 1240在建'!$A$226:$A$245,$A93,'A0 BS 1240在建'!AA$226:AA$245) -> #N/A | M93: =-SUMIF('A0 BS 1240在建'!$A$226:$A$245,$A93,'A0 BS 1240在建'!AE$226:AE$245) -> #N/A | N93: =-SUMIF('A0 BS 1240在建'!$A$226:$A$245,$A93,'A0 BS 1240在建'!AI$226:AI$245) -> #N/A | O93: =-SUMIF('A0 BS 1240在建'!$A$226:$A$245,$A93,'A0 BS 1240在建'!AM$226:AM$245) -> #N/A | P93: =-SUMIF('A0 BS 1240在建'!$A$226:$A$245,$A93,'A0 BS 1240在建'!AQ$226:AQ$245) -> #N/A | Q93: =-SUMIF('A0 BS 1240在建'!$A$226:$A$245,$A93,'A0 BS 1240在建'!AU$226:AU$245) -> #N/A | R93: =-SUMIF('A0 BS 1240在建'!$A$226:$A$245,$A93,'A0 BS 1240在建'!AY$226:AY$245) -> #N/A | S93: =-SUMIF('A0 BS 1240在建'!$A$226:$A$245,$A93,'A0 BS 1240在建'!BC$226:BC$245) -> #N/A | T93: =-SUMIF('A0 BS 1240在建'!$A$226:$A$245,$A93,'A0 BS 1240在建'!BG$226:BG$245) -> #N/A | U93: =-SUMIF('A0 BS 1240在建'!$A$226:$A$245,$A93,'A0 BS 1240在建'!BS$226:BS$245) -> #N/A | V93: =-SUMIF('A0 BS 1240在建'!$A$226:$A$245,$A93,'A0 BS 1240在建'!CA$226:CA$245) -> #N/A | W93: =-SUMIF('A0 BS 1240在建'!$A$226:$A$245,$A93,'A0 BS 1240在建'!CI$226:CI$245) -> #N/A | X93: =-SUMIF('A0 BS 1240在建'!$A$226:$A$245,$A93,'A0 BS 1240在建'!CQ$226:CQ$245) -> #N/A | Z93: 2220 Other payable - related parties
A94: 2250 負債準備-流動 | B94: 其他流動負債 | E94: =SUM(E95:E97) -> 0 | F94: =SUM(F95:F97) -> 0 | G94: =SUM(G95:G97) -> 0 | H94: =SUM(H95:H97) -> 0 | I94: =SUM(I95:I97) -> 0 | J94: =SUM(J95:J97) -> 0 | K94: =SUM(K95:K97) -> 0 | L94: =SUM(L95:L97) -> 0 | ... X94: =SUM(X95:X97) -> 0 | Z94: 2250 Current provision
A95: 應付帳款-保固修繕估列款 | B95: 應付款項 | E95: =-SUMIF('A0 BS 1240在建'!$A$226:$A$245, $A95,'A0 BS 1240在建'!G$226:G$245) -> 0 | F95: =SUM(D95:E95) -> 0 | G95: =+F95+H95 -> 0 | H95: =SUM(I95:T95) -> 0 | I95: =-SUMIF('A0 BS 1240在建'!$A$226:$A$245,$A95,'A0 BS 1240在建'!O$226:O$245) -> 0 | J95: =-IFERROR(VLOOKUP($A95,'A0 BS 1240在建'!$228:$243,19,0),0)-IFERROR(SUMIF(#REF!,BS2_WIP!$A95,#REF!),0) -> 0 | K95: =-SUMIF('A0 BS 1240在建'!$A$226:$A$245,$A95,'A0 BS 1240在建'!W$226:W$245) -> 0 | L95: =-SUMIF('A0 BS 1240在建'!$A$226:$A$245,$A95,'A0 BS 1240在建'!AA$226:AA$245) -> 0 | M95: =-SUMIF('A0 BS 1240在建'!$A$226:$A$245,$A95,'A0 BS 1240在建'!AE$226:AE$245) -> 0 | N95: =-SUMIF('A0 BS 1240在建'!$A$226:$A$245,$A95,'A0 BS 1240在建'!AI$226:AI$245) -> 0 | O95: =-SUMIF('A0 BS 1240在建'!$A$226:$A$245,$A95,'A0 BS 1240在建'!AM$226:AM$245) -> 0 | P95: =-SUMIF('A0 BS 1240在建'!$A$226:$A$245,$A95,'A0 BS 1240在建'!AQ$226:AQ$245) -> 0 | Q95: =-SUMIF('A0 BS 1240在建'!$A$226:$A$245,$A95,'A0 BS 1240在建'!AU$226:AU$245) -> 0 | R95: =-SUMIF('A0 BS 1240在建'!$A$226:$A$245,$A95,'A0 BS 1240在建'!AY$226:AY$245) -> 0 | S95: =-SUMIF('A0 BS 1240在建'!$A$226:$A$245,$A95,'A0 BS 1240在建'!BC$226:BC$245) -> 0 | T95: =-SUMIF('A0 BS 1240在建'!$A$226:$A$245,$A95,'A0 BS 1240在建'!BG$226:BG$245) -> 0 | U95: =-SUMIF('A0 BS 1240在建'!$A$226:$A$245,$A95,'A0 BS 1240在建'!BS$226:BS$245) -> 0 | V95: =-SUMIF('A0 BS 1240在建'!$A$226:$A$245,$A95,'A0 BS 1240在建'!CA$226:CA$245) -> 0 | W95: =-SUMIF('A0 BS 1240在建'!$A$226:$A$245,$A95,'A0 BS 1240在建'!CI$226:CI$245) -> 0 | X95: =-SUMIF('A0 BS 1240在建'!$A$226:$A$245,$A95,'A0 BS 1240在建'!CQ$226:CQ$245) -> 0
A96: 保固準備 | B96: 其他流動負債 | E96: =-SUMIF('A0 BS 1240在建'!$A$226:$A$245, $A96,'A0 BS 1240在建'!G$226:G$245) -> 0 | F96: =SUM(D96:E96) -> 0 | G96: =+F96+H96 -> 0 | H96: =SUM(I96:T96) -> 0 | I96: =-SUMIF('A0 BS 1240在建'!$A$226:$A$245,$A96,'A0 BS 1240在建'!O$226:O$245) -> 0 | J96: =-IFERROR(VLOOKUP($A96,'A0 BS 1240在建'!$228:$243,19,0),0)-IFERROR(SUMIF(#REF!,BS2_WIP!$A96,#REF!),0) -> 0 | K96: =-SUMIF('A0 BS 1240在建'!$A$226:$A$245,$A96,'A0 BS 1240在建'!W$226:W$245) -> 0 | L96: =-SUMIF('A0 BS 1240在建'!$A$226:$A$245,$A96,'A0 BS 1240在建'!AA$226:AA$245) -> 0 | M96: =-SUMIF('A0 BS 1240在建'!$A$226:$A$245,$A96,'A0 BS 1240在建'!AE$226:AE$245) -> 0 | N96: =-SUMIF('A0 BS 1240在建'!$A$226:$A$245,$A96,'A0 BS 1240在建'!AI$226:AI$245) -> 0 | O96: =-SUMIF('A0 BS 1240在建'!$A$226:$A$245,$A96,'A0 BS 1240在建'!AM$226:AM$245) -> 0 | P96: =-SUMIF('A0 BS 1240在建'!$A$226:$A$245,$A96,'A0 BS 1240在建'!AQ$226:AQ$245) -> 0 | Q96: =-SUMIF('A0 BS 1240在建'!$A$226:$A$245,$A96,'A0 BS 1240在建'!AU$226:AU$245) -> 0 | R96: =-SUMIF('A0 BS 1240在建'!$A$226:$A$245,$A96,'A0 BS 1240在建'!AY$226:AY$245) -> 0 | S96: =-SUMIF('A0 BS 1240在建'!$A$226:$A$245,$A96,'A0 BS 1240在建'!BC$226:BC$245) -> 0 | T96: =-SUMIF('A0 BS 1240在建'!$A$226:$A$245,$A96,'A0 BS 1240在建'!BG$226:BG$245) -> 0 | U96: =-SUMIF('A0 BS 1240在建'!$A$226:$A$245,$A96,'A0 BS 1240在建'!BS$226:BS$245) -> 0 | V96: =-SUMIF('A0 BS 1240在建'!$A$226:$A$245,$A96,'A0 BS 1240在建'!CA$226:CA$245) -> 0 | W96: =-SUMIF('A0 BS 1240在建'!$A$226:$A$245,$A96,'A0 BS 1240在建'!CI$226:CI$245) -> 0 | X96: =-SUMIF('A0 BS 1240在建'!$A$226:$A$245,$A96,'A0 BS 1240在建'!CQ$226:CQ$245) -> 0
A97: 負債準備-在建損失 | B97: NA | E97: =-SUMIF('A0 BS 1240在建'!$A$226:$A$245, $A97,'A0 BS 1240在建'!G$226:G$245) -> 0 | F97: =SUM(D97:E97) -> 0 | G97: =+F97+H97 -> 0 | H97: =SUM(I97:T97) -> 0 | I97: =-SUMIF('A0 BS 1240在建'!$A$226:$A$245,$A97,'A0 BS 1240在建'!O$226:O$245) -> 0 | J97: =-IFERROR(VLOOKUP($A97,'A0 BS 1240在建'!$228:$243,19,0),0)-IFERROR(SUMIF(#REF!,BS2_WIP!$A97,#REF!),0) -> 0 | K97: =-SUMIF('A0 BS 1240在建'!$A$226:$A$245,$A97,'A0 BS 1240在建'!W$226:W$245) -> 0 | L97: =-SUMIF('A0 BS 1240在建'!$A$226:$A$245,$A97,'A0 BS 1240在建'!AA$226:AA$245) -> 0 | M97: =-SUMIF('A0 BS 1240在建'!$A$226:$A$245,$A97,'A0 BS 1240在建'!AE$226:AE$245) -> 0 | N97: =-SUMIF('A0 BS 1240在建'!$A$226:$A$245,$A97,'A0 BS 1240在建'!AI$226:AI$245) -> 0 | O97: =-SUMIF('A0 BS 1240在建'!$A$226:$A$245,$A97,'A0 BS 1240在建'!AM$226:AM$245) -> 0 | P97: =-SUMIF('A0 BS 1240在建'!$A$226:$A$245,$A97,'A0 BS 1240在建'!AQ$226:AQ$245) -> 0 | Q97: =-SUMIF('A0 BS 1240在建'!$A$226:$A$245,$A97,'A0 BS 1240在建'!AU$226:AU$245) -> 0 | R97: =-SUMIF('A0 BS 1240在建'!$A$226:$A$245,$A97,'A0 BS 1240在建'!AY$226:AY$245) -> 0 | S97: =-SUMIF('A0 BS 1240在建'!$A$226:$A$245,$A97,'A0 BS 1240在建'!BC$226:BC$245) -> 0 | T97: =-SUMIF('A0 BS 1240在建'!$A$226:$A$245,$A97,'A0 BS 1240在建'!BG$226:BG$245) -> 0 | U97: =-SUMIF('A0 BS 1240在建'!$A$226:$A$245,$A97,'A0 BS 1240在建'!BS$226:BS$245) -> 0 | V97: =-SUMIF('A0 BS 1240在建'!$A$226:$A$245,$A97,'A0 BS 1240在建'!CA$226:CA$245) -> 0 | W97: =-SUMIF('A0 BS 1240在建'!$A$226:$A$245,$A97,'A0 BS 1240在建'!CI$226:CI$245) -> 0 | X97: =-SUMIF('A0 BS 1240在建'!$A$226:$A$245,$A97,'A0 BS 1240在建'!CQ$226:CQ$245) -> 0
A98: 2280 租賃負債-流動 | B98: 其他流動負債 | E98: =-SUMIF('A0 BS 1240在建'!$A$226:$A$245, $A98,'A0 BS 1240在建'!G$226:G$245) -> 0 | F98: =SUM(D98:E98) -> 0 | G98: =+F98+H98 -> 0 | H98: =SUM(I98:T98) -> 0 | I98: =-SUMIF('A0 BS 1240在建'!$A$226:$A$245,$A98,'A0 BS 1240在建'!O$226:O$245) -> 0 | J98: =-IFERROR(VLOOKUP($A98,'A0 BS 1240在建'!$228:$243,19,0),0)-IFERROR(SUMIF(#REF!,BS2_WIP!$A98,#REF!),0) -> 0 | K98: =-SUMIF('A0 BS 1240在建'!$A$226:$A$245,$A98,'A0 BS 1240在建'!W$226:W$245) -> 0 | L98: =-SUMIF('A0 BS 1240在建'!$A$226:$A$245,$A98,'A0 BS 1240在建'!AA$226:AA$245) -> 0 | M98: =-SUMIF('A0 BS 1240在建'!$A$226:$A$245,$A98,'A0 BS 1240在建'!AE$226:AE$245) -> 0 | N98: =-SUMIF('A0 BS 1240在建'!$A$226:$A$245,$A98,'A0 BS 1240在建'!AI$226:AI$245) -> 0 | O98: =-SUMIF('A0 BS 1240在建'!$A$226:$A$245,$A98,'A0 BS 1240在建'!AM$226:AM$245) -> 0 | P98: =-SUMIF('A0 BS 1240在建'!$A$226:$A$245,$A98,'A0 BS 1240在建'!AQ$226:AQ$245) -> 0 | Q98: =-SUMIF('A0 BS 1240在建'!$A$226:$A$245,$A98,'A0 BS 1240在建'!AU$226:AU$245) -> 0 | R98: =-SUMIF('A0 BS 1240在建'!$A$226:$A$245,$A98,'A0 BS 1240在建'!AY$226:AY$245) -> 0 | S98: =-SUMIF('A0 BS 1240在建'!$A$226:$A$245,$A98,'A0 BS 1240在建'!BC$226:BC$245) -> 0 | T98: =-SUMIF('A0 BS 1240在建'!$A$226:$A$245,$A98,'A0 BS 1240在建'!BG$226:BG$245) -> 0 | U98: =-SUMIF('A0 BS 1240在建'!$A$226:$A$245,$A98,'A0 BS 1240在建'!BS$226:BS$245) -> 0 | V98: =-SUMIF('A0 BS 1240在建'!$A$226:$A$245,$A98,'A0 BS 1240在建'!CA$226:CA$245) -> 0 | W98: =-SUMIF('A0 BS 1240在建'!$A$226:$A$245,$A98,'A0 BS 1240在建'!CI$226:CI$245) -> 0 | X98: =-SUMIF('A0 BS 1240在建'!$A$226:$A$245,$A98,'A0 BS 1240在建'!CQ$226:CQ$245) -> 0 | Z98: 2280 Lease liabilities - current (IFRS 16)
A99: 2310 預收款項 | B99: 其他流動負債 | E99: =-SUMIF('A0 BS 1240在建'!$A$226:$A$245, $A99,'A0 BS 1240在建'!G$226:G$245) -> 0 | F99: =SUM(D99:E99) -> 0 | G99: =+F99+H99 -> 0 | H99: =SUM(I99:T99) -> 0 | I99: =-SUMIF('A0 BS 1240在建'!$A$226:$A$245,$A99,'A0 BS 1240在建'!O$226:O$245) -> 0 | J99: =-IFERROR(VLOOKUP($A99,'A0 BS 1240在建'!$228:$243,19,0),0)-IFERROR(SUMIF(#REF!,BS2_WIP!$A99,#REF!),0) -> 0 | K99: =-SUMIF('A0 BS 1240在建'!$A$226:$A$245,$A99,'A0 BS 1240在建'!W$226:W$245) -> 0 | L99: =-SUMIF('A0 BS 1240在建'!$A$226:$A$245,$A99,'A0 BS 1240在建'!AA$226:AA$245) -> 0 | M99: =-SUMIF('A0 BS 1240在建'!$A$226:$A$245,$A99,'A0 BS 1240在建'!AE$226:AE$245) -> 0 | N99: =-SUMIF('A0 BS 1240在建'!$A$226:$A$245,$A99,'A0 BS 1240在建'!AI$226:AI$245) -> 0 | O99: =-SUMIF('A0 BS 1240在建'!$A$226:$A$245,$A99,'A0 BS 1240在建'!AM$226:AM$245) -> 0 | P99: =-SUMIF('A0 BS 1240在建'!$A$226:$A$245,$A99,'A0 BS 1240在建'!AQ$226:AQ$245) -> 0 | Q99: =-SUMIF('A0 BS 1240在建'!$A$226:$A$245,$A99,'A0 BS 1240在建'!AU$226:AU$245) -> 0 | R99: =-SUMIF('A0 BS 1240在建'!$A$226:$A$245,$A99,'A0 BS 1240在建'!AY$226:AY$245) -> 0 | S99: =-SUMIF('A0 BS 1240在建'!$A$226:$A$245,$A99,'A0 BS 1240在建'!BC$226:BC$245) -> 0 | T99: =-SUMIF('A0 BS 1240在建'!$A$226:$A$245,$A99,'A0 BS 1240在建'!BG$226:BG$245) -> 0 | U99: =-SUMIF('A0 BS 1240在建'!$A$226:$A$245,$A99,'A0 BS 1240在建'!BS$226:BS$245) -> 0 | V99: =-SUMIF('A0 BS 1240在建'!$A$226:$A$245,$A99,'A0 BS 1240在建'!CA$226:CA$245) -> 0 | W99: =-SUMIF('A0 BS 1240在建'!$A$226:$A$245,$A99,'A0 BS 1240在建'!CI$226:CI$245) -> 0 | X99: =-SUMIF('A0 BS 1240在建'!$A$226:$A$245,$A99,'A0 BS 1240在建'!CQ$226:CQ$245) -> 0 | Z99: 2310 Advance receipts
A100: 2399 其他流動負債 | B100: 其他流動負債 | E100: =-SUMIF('A0 BS 1240在建'!$A$226:$A$245, $A100,'A0 BS 1240在建'!G$226:G$245) -> 0 | F100: =SUM(D100:E100) -> 0 | G100: =+F100+H100 -> 0 | H100: =SUM(I100:T100) -> 0 | I100: =-SUMIF('A0 BS 1240在建'!$A$226:$A$245,$A100,'A0 BS 1240在建'!O$226:O$245) -> 0 | J100: =-IFERROR(VLOOKUP($A100,'A0 BS 1240在建'!$228:$243,19,0),0)-IFERROR(SUMIF(#REF!,BS2_WIP!$A100,#REF!),0) -> 0 | K100: =-SUMIF('A0 BS 1240在建'!$A$226:$A$245,$A100,'A0 BS 1240在建'!W$226:W$245) -> 0 | L100: =-SUMIF('A0 BS 1240在建'!$A$226:$A$245,$A100,'A0 BS 1240在建'!AA$226:AA$245) -> 0 | M100: =-SUMIF('A0 BS 1240在建'!$A$226:$A$245,$A100,'A0 BS 1240在建'!AE$226:AE$245) -> 0 | N100: =-SUMIF('A0 BS 1240在建'!$A$226:$A$245,$A100,'A0 BS 1240在建'!AI$226:AI$245) -> 0 | O100: =-SUMIF('A0 BS 1240在建'!$A$226:$A$245,$A100,'A0 BS 1240在建'!AM$226:AM$245) -> 0 | P100: =-SUMIF('A0 BS 1240在建'!$A$226:$A$245,$A100,'A0 BS 1240在建'!AQ$226:AQ$245) -> 0 | Q100: =-SUMIF('A0 BS 1240在建'!$A$226:$A$245,$A100,'A0 BS 1240在建'!AU$226:AU$245) -> 0 | R100: =-SUMIF('A0 BS 1240在建'!$A$226:$A$245,$A100,'A0 BS 1240在建'!AY$226:AY$245) -> 0 | S100: =-SUMIF('A0 BS 1240在建'!$A$226:$A$245,$A100,'A0 BS 1240在建'!BC$226:BC$245) -> 0 | T100: =-SUMIF('A0 BS 1240在建'!$A$226:$A$245,$A100,'A0 BS 1240在建'!BG$226:BG$245) -> 0 | U100: =-SUMIF('A0 BS 1240在建'!$A$226:$A$245,$A100,'A0 BS 1240在建'!BS$226:BS$245) -> 0 | V100: =-SUMIF('A0 BS 1240在建'!$A$226:$A$245,$A100,'A0 BS 1240在建'!CA$226:CA$245) -> 0 | W100: =-SUMIF('A0 BS 1240在建'!$A$226:$A$245,$A100,'A0 BS 1240在建'!CI$226:CI$245) -> 0 | X100: =-SUMIF('A0 BS 1240在建'!$A$226:$A$245,$A100,'A0 BS 1240在建'!CQ$226:CQ$245) -> 0 | Z100: 2399 Other current liabilities
A101: TO & BIM - Trading 2 | F101: =+D101+E101 -> 0 | G101: =+G100 -> 0 | H101: =+H100 -> 0
A102: 流動負債小計 | D102: =SUM(D82:D84,D89,D90:D100)-SUM(D95:D97) -> #REF! | E102: =SUM(E82:E84,E89,E90:E100)-SUM(E95:E97) -> -346975 | F102: =SUM(F82:F84,F89,F90:F100)-SUM(F95:F97) -> #REF! | G102: =+F102+H102 -> #REF! | H102: =SUM(I102:T102) -> #N/A | I102: =SUM(I82:I84,I89,I90:I100)-SUM(I95:I97) -> #N/A | J102: =SUM(J82:J84,J89,J90:J100)-SUM(J95:J97) -> 0 | K102: =SUM(K82:K84,K89,K90:K100)-SUM(K95:K97) -> #N/A | L102: =SUM(L82:L84,L89,L90:L100)-SUM(L95:L97) -> #N/A | M102: =SUM(M82:M84,M89,M90:M100)-SUM(M95:M97) -> #N/A | N102: =SUM(N82:N84,N89,N90:N100)-SUM(N95:N97) -> #N/A | O102: =SUM(O82:O84,O89,O90:O100)-SUM(O95:O97) -> #N/A | P102: =SUM(P82:P84,P89,P90:P100)-SUM(P95:P97) -> #N/A | ... X102: =SUM(X82:X84,X89,X90:X100)-SUM(X95:X97) -> #N/A | Z102: Subtotal Current liabilities
A104: 非流動負債: | Z104: Non-current liabilities:
A105: 2540 長期借款 | F105: =SUM(D105:E105) -> 0 | G105: =+F105+H105 -> 0 | H105: =SUM(I105:T105) -> 0 | Z105: 2540 Long-term borrowings
...

Sheet Over Under Bill 1 COPY 到CO欄位
A1: 2026年 | B1: Budget | C1: 3 | D1: 4 | E1: 5 | F1: 6 | G1: 7 | H1: 8 | I1: 9 | J1: 10 | K1: 11 | L1: 12 | M1: 13 | N1: 14 | O1: 15 | P1: 16 | Q1: 17 | R1: 18 | S1: 19 | T1: 20 | U1: 21 | V1: 22 | W1: 23 | X1: 24 | Y1: 25 | Z1: 26 | AA1: 27 | AB1: 28 | AC1: 29 | AD1: 30 | AE1: 31 | AF1: 32 | AG1: 33 | AH1: 34 | AI1: 35 | AJ1: 36 | AK1: 37 | AL1: 38 | AM1: 39 | AN1: 40 | AO1: 41 | AP1: 42 | AQ1: 43 | AR1: 44 | AS1: 45 | AT1: 46 | AU1: 47 | AV1: 48 | AW1: 49 | AX1: 50 | AY1: 51 | AZ1: 52 | BA1: 53 | BB1: 54 | BC1: 55 | BD1: 56 | BE1: 57 | BF1: 58 | BG1: 59 | BH1: 60 | BI1: 61 | BJ1: 62 | BK1: 63 | BL1: 64 | BM1: 65 | BN1: 66 | BO1: 67 | BP1: 68 | BQ1: 69 | BR1: 70 | BS1: 71 | BT1: 72 | BU1: 73 | BV1: 74 | BW1: 75 | BX1: 76 | BY1: 77 | BZ1: 78 | CA1: 79 | CB1: 80 | CC1: 81 | CD1: 82 | CE1: 83 | CF1: 84 | CG1: 85 | CH1: 86 | CI1: 87 | CJ1: 88 | CK1: 89 | CL1: 90 | CM1: 91 | CN1: 92 | CP1: 公式詳註解,其他年度以此類推 | CY1: Year 2026 (內部使用)
A2: WIP - IPC | B2: 公式不同 | E2: 累計至2025/8 | J2: 累計2025/12 | O2: 累計2026/1 | T2: 累計2026/2 | Y2: 累計2026/3 | AD2: 累計2026/4 | AI2: 累計2026/5 | AN2: 累計2026/6 | AS2: 累計2026/7 | AX2: 累計2026/8 | BC2: 累計2026/9 | BH2: 累計2026/10 | BM2: 累計2026/11 | BR2: 累計2026/12 | BW2: 累計2027/12 | CB2: 累計2028/12 | CG2: 累計2029/12 | CL2: 累計2030/12 | CQ2: 2024/9 - 2024/12 | CV2: Year 2025 | CY2: 應收建造變動數(正數增加,負數減少) | DD2: 應付建造變動數(正數增加,負數減少)
C3: 1240+1247 | D3: 2264+22641 | E3: 應收(付)建造 | F3: 22642業主預付款 | G3: 合約資產 | H3: 1240+1247 | I3: 2264+22641 | J3: 應收(付)建造 | K3: 22642業主預付款 | L3: 合約資產 | M3: 1240+1247 | N3: 2264+22641 | O3: 應收(付)建造 | P3: 22642業主預付款 | Q3: 合約資產 | R3: 1240+1247 | S3: 2264+22641 | T3: 應收(付)建造 | U3: 22642業主預付款 | V3: 合約資產 | W3: 1240+1247 | X3: 2264+22641 | Y3: 應收(付)建造 | Z3: 22642業主預付款 | AA3: 合約資產 | AB3: 1240+1247 | AC3: 2264+22641 | AD3: 應收(付)建造 | AE3: 22642業主預付款 | AF3: 合約資產 | AG3: 1240+1247 | AH3: 2264+22641 | AI3: 應收(付)建造 | AJ3: 22642業主預付款 | AK3: 合約資產 | AL3: 1240+1247 | AM3: 2264+22641 | AN3: 應收(付)建造 | AO3: 22642業主預付款 | AP3: 合約資產 | AQ3: 1240+1247 | AR3: 2264+22641 | AS3: 應收(付)建造 | AT3: 22642業主預付款 | AU3: 合約資產 | AV3: 1240+1247 | AW3: 2264+22641 | AX3: 應收(付)建造 | AY3: 22642業主預付款 | AZ3: 合約資產 | BA3: 1240+1247 | BB3: 2264+22641 | BC3: 應收(付)建造 | BD3: 22642業主預付款 | BE3: 合約資產 | BF3: 1240+1247 | BG3: 2264+22641 | BH3: 應收(付)建造 | BI3: 22642業主預付款 | BJ3: 合約資產 | BK3: 1240+1247 | BL3: 2264+22641 | BM3: 應收(付)建造 | BN3: 22642業主預付款 | BO3: 合約資產 | BP3: 1240+1247 | BQ3: 2264+22641 | BR3: 應收(付)建造 | BS3: 22642業主預付款 | BT3: 合約資產 | BU3: 1240+1247 | BV3: 2264+22641 | BW3: 應收(付)建造 | BX3: 22642業主預付款 | BY3: 合約資產 | BZ3: 1240+1247 | CA3: 2264+22641 | CB3: 應收(付)建造 | CC3: 22642業主預付款 | CD3: 合約資產 | CE3: 1240+1247 | CF3: 2264+22641 | CG3: 應收(付)建造 | CH3: 22642業主預付款 | CI3: 合約資產 | CJ3: 1240+1247 | CK3: 2264+22641 | CL3: 應收(付)建造 | CM3: 22642業主預付款 | CN3: 合約資產 | CP3: 應收(付)建造 | CQ3: 應收建造 | CR3: 應付建造 | CU3: 應收(付)建造 | CV3: 應收建造 | CW3: 應付建造 | CY3: 情況一 | CZ3: 情況二 | DA3: 情況三 | DB3: 情況四 | DC3: Total | DD3: 情況一 | DE3: 情況二 | DF3: 情況三 | DG3: 情況四 | DH3: Total
A4: 工程代碼 | B4: 工 程 名 稱 | C4: Revenue | D4: IPC from Client | E4: Under(Over) Bill | F4: Adv. Payment | G4: (合約負債) | H4: Revenue | I4: IPC from Client | J4: Under(Over) Bill | K4: Adv. Payment | L4: (合約負債) | M4: Revenue | N4: IPC from Client | O4: Under(Over) Bill | P4: Adv. Payment | Q4: (合約負債) | R4: Revenue | S4: IPC from Client | T4: Under(Over) Bill | U4: Adv. Payment | V4: (合約負債) | W4: Revenue | X4: IPC from Client | Y4: Under(Over) Bill | Z4: Adv. Payment | AA4: (合約負債) | AB4: Revenue | AC4: IPC from Client | AD4: Under(Over) Bill | AE4: Adv. Payment | AF4: (合約負債) | AG4: Revenue | AH4: IPC from Client | AI4: Under(Over) Bill | AJ4: Adv. Payment | AK4: (合約負債) | AL4: Revenue | AM4: IPC from Client | AN4: Under(Over) Bill | AO4: Adv. Payment | AP4: (合約負債) | AQ4: Revenue | AR4: IPC from Client | AS4: Under(Over) Bill | AT4: Adv. Payment | AU4: (合約負債) | AV4: Revenue | AW4: IPC from Client | AX4: Under(Over) Bill | AY4: Adv. Payment | AZ4: (合約負債) | BA4: Revenue | BB4: IPC from Client | BC4: Under(Over) Bill | BD4: Adv. Payment | BE4: (合約負債) | BF4: Revenue | BG4: IPC from Client | BH4: Under(Over) Bill | BI4: Adv. Payment | BJ4: (合約負債) | BK4: Revenue | BL4: IPC from Client | BM4: Under(Over) Bill | BN4: Adv. Payment | BO4: (合約負債) | BP4: Revenue | BQ4: IPC from Client | BR4: Under(Over) Bill | BS4: Adv. Payment | BT4: (合約負債) | BU4: Revenue | BV4: IPC from Client | BW4: Under(Over) Bill | BX4: Adv. Payment | BY4: (合約負債) | BZ4: Revenue | CA4: IPC from Client | CB4: Under(Over) Bill | CC4: Adv. Payment | CD4: (合約負債) | CE4: Revenue | CF4: IPC from Client | CG4: Under(Over) Bill | CH4: Adv. Payment | CI4: (合約負債) | CJ4: Revenue | CK4: IPC from Client | CL4: Under(Over) Bill | CM4: Adv. Payment | CN4: (合約負債) | CP4: Under(Over) Bill | CQ4: Under Bill | CR4: Over Bill | CU4: Under(Over) Bill | CV4: Under Bill | CW4: Over Bill | CY4: 2年年底皆應收 | CZ4: 由應收轉應付 | DA4: 由應付轉應收 | DB4: 上年應收，本年0 | DD4: 2年年底皆應付 | DE4: 由應付轉應收 | DF4: 由應收轉應付 | DG4: 上年0，本年應付
A5: C/4120P | B5: 大安洞道(含未來損失) | C5: =IFERROR(VLOOKUP($A5,'A0 BS 1240在建'!$1:$1048576,5,0),0) -> 0 | D5: =IFERROR(VLOOKUP($A5,'B0 2264預收'!$1:$1048576,5,0),0) -> 0 | E5: =+C5-D5 -> 0 | F5: =IFERROR(VLOOKUP($A5,'B0 2264預收'!$1:$1048576,6,0),0) -> 0 | G5: =+E5-F5 -> 0 | H5: =IFERROR(VLOOKUP($A5,'A0 BS 1240在建'!$1:$1048576,13,0),0) -> 0 | I5: =IFERROR(VLOOKUP($A5,'B0 2264預收'!$1:$1048576,13,0),0) -> 0 | J5: =+H5-I5 -> 0 | K5: =IFERROR(VLOOKUP($A5,'B0 2264預收'!$1:$1048576,14,0),0) -> 0 | L5: =+H5-I5-K5 -> 0 | M5: =H5+IFERROR(VLOOKUP($A5,'A0 BS 1240在建'!$1:$1048576,17,0),0) -> 0 | N5: =I5+IFERROR(VLOOKUP($A5,'B0 2264預收'!$1:$1048576,17,0),0) -> 0 | O5: =+M5-N5 -> 0 | P5: =K5+IFERROR(+VLOOKUP($A5,'B0 2264預收'!$1:$1048576,18,0),0) -> 0 | Q5: =+O5-P5 -> 0 | R5: =M5+IFERROR(VLOOKUP($A5,'A0 BS 1240在建'!$1:$1048576,21,0),0) -> 0 | S5: =+N5+IFERROR(VLOOKUP($A5,'B0 2264預收'!$1:$1048576,21,0),0) -> 0 | T5: =+R5-S5 -> 0 | U5: =+P5+IFERROR(+VLOOKUP($A5,'B0 2264預收'!$1:$1048576,22,0),0) -> 0 | V5: =+T5-U5 -> 0 | W5: =+R5+IFERROR(VLOOKUP($A5,'A0 BS 1240在建'!$1:$1048576,25,0),0) -> 0 | X5: =+S5+IFERROR(VLOOKUP($A5,'B0 2264預收'!$1:$1048576,25,0),0) -> 0 | Y5: =+W5-X5 -> 0 | Z5: =+U5+IFERROR(+VLOOKUP($A5,'B0 2264預收'!$1:$1048576,26,0),0) -> 0 | AA5: =+Y5-Z5 -> 0 | AB5: =+W5+IFERROR(VLOOKUP($A5,'A0 BS 1240在建'!$1:$1048576,29,0),0) -> 0 | AC5: =+X5+IFERROR(VLOOKUP($A5,'B0 2264預收'!$1:$1048576,29,0),0) -> 0 | AD5: =+AB5-AC5 -> 0 | AE5: =+Z5+IFERROR(+VLOOKUP($A5,'B0 2264預收'!$1:$1048576,30,0),0) -> 0 | AF5: =+AD5-AE5 -> 0 | AG5: =+AB5+IFERROR(VLOOKUP($A5,'A0 BS 1240在建'!$1:$1048576,33,0),0) -> 0 | AH5: =+AC5+IFERROR(VLOOKUP($A5,'B0 2264預收'!$1:$1048576,33,0),0) -> 0 | AI5: =+AG5-AH5 -> 0 | AJ5: =+AE5+IFERROR(+VLOOKUP($A5,'B0 2264預收'!$1:$1048576,34,0),0) -> 0 | AK5: =+AI5-AJ5 -> 0 | AL5: =+AG5+IFERROR(VLOOKUP($A5,'A0 BS 1240在建'!$1:$1048576,37,0),0) -> 0 | AM5: =+AH5+IFERROR(VLOOKUP($A5,'B0 2264預收'!$1:$1048576,37,0),0) -> 0 | AN5: =+AL5-AM5 -> 0 | AO5: =+AJ5+IFERROR(+VLOOKUP($A5,'B0 2264預收'!$1:$1048576,38,0),0) -> 0 | AP5: =+AN5-AO5 -> 0 | AQ5: =+AL5+IFERROR(VLOOKUP($A5,'A0 BS 1240在建'!$1:$1048576,41,0),0) -> 0 | AR5: =+AM5+IFERROR(VLOOKUP($A5,'B0 2264預收'!$1:$1048576,41,0),0) -> 0 | AS5: =+AQ5-AR5 -> 0 | AT5: =+AO5+IFERROR(+VLOOKUP($A5,'B0 2264預收'!$1:$1048576,42,0),0) -> 0 | AU5: =+AS5-AT5 -> 0 | AV5: =+AQ5+IFERROR(VLOOKUP($A5,'A0 BS 1240在建'!$1:$1048576,45,0),0) -> 0 | AW5: =+AR5+IFERROR(VLOOKUP($A5,'B0 2264預收'!$1:$1048576,45,0),0) -> 0 | AX5: =+AV5-AW5 -> 0 | AY5: =+AT5+IFERROR(+VLOOKUP($A5,'B0 2264預收'!$1:$1048576,46,0),0) -> 0 | AZ5: =+AX5-AY5 -> 0 | BA5: =+AV5+IFERROR(VLOOKUP($A5,'A0 BS 1240在建'!$1:$1048576,49,0),0) -> 0 | BB5: =+AW5+IFERROR(VLOOKUP($A5,'B0 2264預收'!$1:$1048576,49,0),0) -> 0 | BC5: =+BA5-BB5 -> 0 | BD5: =+AY5+IFERROR(+VLOOKUP($A5,'B0 2264預收'!$1:$1048576,50,0),0) -> 0 | BE5: =+BC5-BD5 -> 0 | BF5: =+BA5+IFERROR(VLOOKUP($A5,'A0 BS 1240在建'!$1:$1048576,53,0),0) -> 0 | BG5: =+BB5+IFERROR(VLOOKUP($A5,'B0 2264預收'!$1:$1048576,53,0),0) -> 0 | BH5: =+BF5-BG5 -> 0 | BI5: =+BD5+IFERROR(+VLOOKUP($A5,'B0 2264預收'!$1:$1048576,54,0),0) -> 0 | BJ5: =+BH5-BI5 -> 0 | BK5: =+BF5+IFERROR(VLOOKUP($A5,'A0 BS 1240在建'!$1:$1048576,57,0),0) -> 0 | BL5: =+BG5+IFERROR(VLOOKUP($A5,'B0 2264預收'!$1:$1048576,57,0),0) -> 0 | BM5: =+BK5-BL5 -> 0 | BN5: =+BI5+IFERROR(+VLOOKUP($A5,'B0 2264預收'!$1:$1048576,58,0),0) -> 0 | BO5: =+BM5-BN5 -> 0 | BP5: =+BK5+IFERROR(VLOOKUP($A5,'A0 BS 1240在建'!$1:$1048576,61,0),0) -> 0 | BQ5: =+BL5+IFERROR(VLOOKUP($A5,'B0 2264預收'!$1:$1048576,61,0),0) -> 0 | BR5: =+BP5-BQ5 -> 0 | BS5: =+BN5+IFERROR(+VLOOKUP($A5,'B0 2264預收'!$1:$1048576,62,0),0) -> 0 | BT5: =+BR5-BS5 -> 0 | BU5: =+IFERROR(VLOOKUP($A5,'A0 BS 1240在建'!$1:$1048576,77,0),0) -> 0 | BV5: =+IFERROR(VLOOKUP($A5,'B0 2264預收'!$1:$1048576,77,0),0) -> 0 | BW5: =+BU5-BV5 -> 0 | BX5: =+IFERROR(+VLOOKUP($A5,'B0 2264預收'!$1:$1048576,78,0),0) -> 0 | BY5: =+BW5-BX5 -> 0 | BZ5: =IFERROR(+VLOOKUP($A5,'A0 BS 1240在建'!$1:$1048576,85,0),0) -> 0 | CA5: =IFERROR(+VLOOKUP($A5,'B0 2264預收'!$1:$1048576,85,0),0) -> 0 | CB5: =+BZ5-CA5 -> 0 | CC5: =+IFERROR(+VLOOKUP($A5,'B0 2264預收'!$1:$1048576,86,0),0) -> 0 | CD5: =+CB5-CC5 -> 0 | CE5: =+IFERROR(VLOOKUP($A5,'A0 BS 1240在建'!$1:$1048576,93,0),0) -> 0 | CF5: =+IFERROR(VLOOKUP($A5,'B0 2264預收'!$1:$1048576,93,0),0) -> 0 | CG5: =+CE5-CF5 -> 0 | CH5: =+IFERROR(+VLOOKUP($A5,'B0 2264預收'!$1:$1048576,94,0),0) -> 0 | CI5: =+CG5-CH5 -> 0 | CJ5: =IFERROR(+VLOOKUP($A5,'A0 BS 1240在建'!$1:$1048576,101,0),0) -> 0 | CK5: =IFERROR(+VLOOKUP($A5,'B0 2264預收'!$1:$1048576,101,0),0) -> 0 | CL5: =+CJ5-CK5 -> 0 | CM5: =+IFERROR(+VLOOKUP($A5,'B0 2264預收'!$1:$1048576,102,0),0) -> 0 | CN5: =+CL5-CM5 -> 0 | CP5: =+J5-E5 -> 0 | CQ5: =-E5 -> 0 | CR5: =+J5 -> 0 | CU5: =+BR5-J5 -> 0 | CV5: =+BR5 -> 0 | CW5: =-J5 -> 0 | CY5: =IF(AND(BR5>0, J5>0), BR5-J5, "") | CZ5: =IF(AND(BR5<0,J5>0),-J5," ") | DA5: =IF(AND(BR5>0,J5<0),BR5," ") | DB5: =IF(AND(L5=0,BR5<0),-BR5," ") | DC5: =SUM(CY5:DB5) -> 0 | DD5: =IF(AND(BR5<0, J5<0), BR5-J5, "") | DE5: =IF(AND(BR5<0,J5>0),BR5," ") | DF5: =IF(AND(BR5>0,J5<0),-J5," ") | DG5: =IF(AND(L5<0,BR5=0),-L5," ") | DH5: =SUM(DD5:DG5) -> 0
A6: C/4130P | B6: CM01機場捷運 | C6: =IFERROR(VLOOKUP($A6,'A0 BS 1240在建'!$1:$1048576,5,0),0) -> 0 | D6: =IFERROR(VLOOKUP($A6,'B0 2264預收'!$1:$1048576,5,0),0) -> 0 | E6: =+C6-D6 -> 0 | F6: =IFERROR(VLOOKUP($A6,'B0 2264預收'!$1:$1048576,6,0),0) -> 0 | G6: =+E6-F6 -> 0 | H6: =IFERROR(VLOOKUP($A6,'A0 BS 1240在建'!$1:$1048576,13,0),0) -> 0 | I6: =IFERROR(VLOOKUP($A6,'B0 2264預收'!$1:$1048576,13,0),0) -> 0 | J6: =+H6-I6 -> 0 | K6: =IFERROR(VLOOKUP($A6,'B0 2264預收'!$1:$1048576,14,0),0) -> 0 | L6: =+H6-I6-K6 -> 0 | M6: =H6+IFERROR(VLOOKUP($A6,'A0 BS 1240在建'!$1:$1048576,17,0),0) -> 0 | N6: =I6+IFERROR(VLOOKUP($A6,'B0 2264預收'!$1:$1048576,17,0),0) -> 0 | O6: =+M6-N6 -> 0 | P6: =K6+IFERROR(+VLOOKUP($A6,'B0 2264預收'!$1:$1048576,18,0),0) -> 0 | Q6: =+O6-P6 -> 0 | R6: =M6+IFERROR(VLOOKUP($A6,'A0 BS 1240在建'!$1:$1048576,21,0),0) -> 0 | S6: =+N6+IFERROR(VLOOKUP($A6,'B0 2264預收'!$1:$1048576,21,0),0) -> 0 | T6: =+R6-S6 -> 0 | U6: =+P6+IFERROR(+VLOOKUP($A6,'B0 2264預收'!$1:$1048576,22,0),0) -> 0 | V6: =+T6-U6 -> 0 | W6: =+R6+IFERROR(VLOOKUP($A6,'A0 BS 1240在建'!$1:$1048576,25,0),0) -> 0 | X6: =+S6+IFERROR(VLOOKUP($A6,'B0 2264預收'!$1:$1048576,25,0),0) -> 0 | Y6: =+W6-X6 -> 0 | Z6: =+U6+IFERROR(+VLOOKUP($A6,'B0 2264預收'!$1:$1048576,26,0),0) -> 0 | AA6: =+Y6-Z6 -> 0 | AB6: =+W6+IFERROR(VLOOKUP($A6,'A0 BS 1240在建'!$1:$1048576,29,0),0) -> 0 | AC6: =+X6+IFERROR(VLOOKUP($A6,'B0 2264預收'!$1:$1048576,29,0),0) -> 0 | AD6: =+AB6-AC6 -> 0 | AE6: =+Z6+IFERROR(+VLOOKUP($A6,'B0 2264預收'!$1:$1048576,30,0),0) -> 0 | AF6: =+AD6-AE6 -> 0 | AG6: =+AB6+IFERROR(VLOOKUP($A6,'A0 BS 1240在建'!$1:$1048576,33,0),0) -> 0 | AH6: =+AC6+IFERROR(VLOOKUP($A6,'B0 2264預收'!$1:$1048576,33,0),0) -> 0 | AI6: =+AG6-AH6 -> 0 | AJ6: =+AE6+IFERROR(+VLOOKUP($A6,'B0 2264預收'!$1:$1048576,34,0),0) -> 0 | AK6: =+AI6-AJ6 -> 0 | AL6: =+AG6+IFERROR(VLOOKUP($A6,'A0 BS 1240在建'!$1:$1048576,37,0),0) -> 0 | AM6: =+AH6+IFERROR(VLOOKUP($A6,'B0 2264預收'!$1:$1048576,37,0),0) -> 0 | AN6: =+AL6-AM6 -> 0 | AO6: =+AJ6+IFERROR(+VLOOKUP($A6,'B0 2264預收'!$1:$1048576,38,0),0) -> 0 | AP6: =+AN6-AO6 -> 0 | AQ6: =+AL6+IFERROR(VLOOKUP($A6,'A0 BS 1240在建'!$1:$1048576,41,0),0) -> 0 | AR6: =+AM6+IFERROR(VLOOKUP($A6,'B0 2264預收'!$1:$1048576,41,0),0) -> 0 | AS6: =+AQ6-AR6 -> 0 | AT6: =+AO6+IFERROR(+VLOOKUP($A6,'B0 2264預收'!$1:$1048576,42,0),0) -> 0 | AU6: =+AS6-AT6 -> 0 | AV6: =+AQ6+IFERROR(VLOOKUP($A6,'A0 BS 1240在建'!$1:$1048576,45,0),0) -> 0 | AW6: =+AR6+IFERROR(VLOOKUP($A6,'B0 2264預收'!$1:$1048576,45,0),0) -> 0 | AX6: =+AV6-AW6 -> 0 | AY6: =+AT6+IFERROR(+VLOOKUP($A6,'B0 2264預收'!$1:$1048576,46,0),0) -> 0 | AZ6: =+AX6-AY6 -> 0 | BA6: =+AV6+IFERROR(VLOOKUP($A6,'A0 BS 1240在建'!$1:$1048576,49,0),0) -> 0 | BB6: =+AW6+IFERROR(VLOOKUP($A6,'B0 2264預收'!$1:$1048576,49,0),0) -> 0 | BC6: =+BA6-BB6 -> 0 | BD6: =+AY6+IFERROR(+VLOOKUP($A6,'B0 2264預收'!$1:$1048576,50,0),0) -> 0 | BE6: =+BC6-BD6 -> 0 | BF6: =+BA6+IFERROR(VLOOKUP($A6,'A0 BS 1240在建'!$1:$1048576,53,0),0) -> 0 | BG6: =+BB6+IFERROR(VLOOKUP($A6,'B0 2264預收'!$1:$1048576,53,0),0) -> 0 | BH6: =+BF6-BG6 -> 0 | BI6: =+BD6+IFERROR(+VLOOKUP($A6,'B0 2264預收'!$1:$1048576,54,0),0) -> 0 | BJ6: =+BH6-BI6 -> 0 | BK6: =+BF6+IFERROR(VLOOKUP($A6,'A0 BS 1240在建'!$1:$1048576,57,0),0) -> 0 | BL6: =+BG6+IFERROR(VLOOKUP($A6,'B0 2264預收'!$1:$1048576,57,0),0) -> 0 | BM6: =+BK6-BL6 -> 0 | BN6: =+BI6+IFERROR(+VLOOKUP($A6,'B0 2264預收'!$1:$1048576,58,0),0) -> 0 | BO6: =+BM6-BN6 -> 0 | BP6: =+BK6+IFERROR(VLOOKUP($A6,'A0 BS 1240在建'!$1:$1048576,61,0),0) -> 0 | BQ6: =+BL6+IFERROR(VLOOKUP($A6,'B0 2264預收'!$1:$1048576,61,0),0) -> 0 | BR6: =+BP6-BQ6 -> 0 | BS6: =+BN6+IFERROR(+VLOOKUP($A6,'B0 2264預收'!$1:$1048576,62,0),0) -> 0 | BT6: =+BR6-BS6 -> 0 | BU6: =+IFERROR(VLOOKUP($A6,'A0 BS 1240在建'!$1:$1048576,77,0),0) -> 0 | BV6: =+IFERROR(VLOOKUP($A6,'B0 2264預收'!$1:$1048576,77,0),0) -> 0 | BW6: =+BU6-BV6 -> 0 | BX6: =+IFERROR(+VLOOKUP($A6,'B0 2264預收'!$1:$1048576,78,0),0) -> 0 | BY6: =+BW6-BX6 -> 0 | BZ6: =IFERROR(+VLOOKUP($A6,'A0 BS 1240在建'!$1:$1048576,85,0),0) -> 0 | CA6: =IFERROR(+VLOOKUP($A6,'B0 2264預收'!$1:$1048576,85,0),0) -> 0 | CB6: =+BZ6-CA6 -> 0 | CC6: =+IFERROR(+VLOOKUP($A6,'B0 2264預收'!$1:$1048576,86,0),0) -> 0 | CD6: =+CB6-CC6 -> 0 | CE6: =+IFERROR(VLOOKUP($A6,'A0 BS 1240在建'!$1:$1048576,93,0),0) -> 0 | CF6: =+IFERROR(VLOOKUP($A6,'B0 2264預收'!$1:$1048576,93,0),0) -> 0 | CG6: =+CE6-CF6 -> 0 | CH6: =+IFERROR(+VLOOKUP($A6,'B0 2264預收'!$1:$1048576,94,0),0) -> 0 | CI6: =+CG6-CH6 -> 0 | CJ6: =IFERROR(+VLOOKUP($A6,'A0 BS 1240在建'!$1:$1048576,101,0),0) -> 0 | CK6: =IFERROR(+VLOOKUP($A6,'B0 2264預收'!$1:$1048576,101,0),0) -> 0 | CL6: =+CJ6-CK6 -> 0 | CM6: =+IFERROR(+VLOOKUP($A6,'B0 2264預收'!$1:$1048576,102,0),0) -> 0 | CN6: =+CL6-CM6 -> 0 | CP6: =+J6-E6 -> 0 | CR6: =+CP6 -> 0 | CU6: =+BR6-J6 -> 0 | CW6: =+CU6 -> 0 | CY6: =IF(AND(BR6>0, J6>0), BR6-J6, "") | CZ6: =IF(AND(BR6<0,J6>0),-J6," ") | DA6: =IF(AND(BR6>0,J6<0),BR6," ") | DB6: =IF(AND(L6=0,BR6<0),-BR6," ") | DC6: =SUM(CY6:DB6) -> 0 | DD6: =IF(AND(BR6<0, J6<0), (BR6-J6)*-1, "") | DE6: =IF(AND(BR6<0,J6>0),-BR6," ") | DF6: =IF(AND(BR6>0,J6<0),-J6*-1," ") | DG6: =IF(AND(L6<0,BR6=0),-L6*-1," ") | DH6: =SUM(DD6:DG6) -> 0
A7: C/4140N | B7: CQ842萬大線 | C7: =IFERROR(VLOOKUP($A7,'A0 BS 1240在建'!$1:$1048576,5,0),0) -> 0 | D7: =IFERROR(VLOOKUP($A7,'B0 2264預收'!$1:$1048576,5,0),0) -> 0 | E7: =+C7-D7 -> 0 | F7: =IFERROR(VLOOKUP($A7,'B0 2264預收'!$1:$1048576,6,0),0) -> 0 | G7: =+E7-F7 -> 0 | H7: =IFERROR(VLOOKUP($A7,'A0 BS 1240在建'!$1:$1048576,13,0),0) -> 0 | I7: =IFERROR(VLOOKUP($A7,'B0 2264預收'!$1:$1048576,13,0),0) -> 0 | J7: =+H7-I7 -> 0 | K7: =IFERROR(VLOOKUP($A7,'B0 2264預收'!$1:$1048576,14,0),0) -> 0 | L7: =+H7-I7-K7 -> 0 | M7: =H7+IFERROR(VLOOKUP($A7,'A0 BS 1240在建'!$1:$1048576,17,0),0) -> 0 | N7: =I7+IFERROR(VLOOKUP($A7,'B0 2264預收'!$1:$1048576,17,0),0) -> 0 | O7: =+M7-N7 -> 0 | P7: =K7+IFERROR(+VLOOKUP($A7,'B0 2264預收'!$1:$1048576,18,0),0) -> 0 | Q7: =+O7-P7 -> 0 | R7: =M7+IFERROR(VLOOKUP($A7,'A0 BS 1240在建'!$1:$1048576,21,0),0) -> 0 | S7: =+N7+IFERROR(VLOOKUP($A7,'B0 2264預收'!$1:$1048576,21,0),0) -> 0 | T7: =+R7-S7 -> 0 | U7: =+P7+IFERROR(+VLOOKUP($A7,'B0 2264預收'!$1:$1048576,22,0),0) -> 0 | V7: =+T7-U7 -> 0 | W7: =+R7+IFERROR(VLOOKUP($A7,'A0 BS 1240在建'!$1:$1048576,25,0),0) -> 0 | X7: =+S7+IFERROR(VLOOKUP($A7,'B0 2264預收'!$1:$1048576,25,0),0) -> 0 | Y7: =+W7-X7 -> 0 | Z7: =+U7+IFERROR(+VLOOKUP($A7,'B0 2264預收'!$1:$1048576,26,0),0) -> 0 | AA7: =+Y7-Z7 -> 0 | AB7: =+W7+IFERROR(VLOOKUP($A7,'A0 BS 1240在建'!$1:$1048576,29,0),0) -> 0 | AC7: =+X7+IFERROR(VLOOKUP($A7,'B0 2264預收'!$1:$1048576,29,0),0) -> 0 | AD7: =+AB7-AC7 -> 0 | AE7: =+Z7+IFERROR(+VLOOKUP($A7,'B0 2264預收'!$1:$1048576,30,0),0) -> 0 | AF7: =+AD7-AE7 -> 0 | AG7: =+AB7+IFERROR(VLOOKUP($A7,'A0 BS 1240在建'!$1:$1048576,33,0),0) -> 0 | AH7: =+AC7+IFERROR(VLOOKUP($A7,'B0 2264預收'!$1:$1048576,33,0),0) -> 0 | AI7: =+AG7-AH7 -> 0 | AJ7: =+AE7+IFERROR(+VLOOKUP($A7,'B0 2264預收'!$1:$1048576,34,0),0) -> 0 | AK7: =+AI7-AJ7 -> 0 | AL7: =+AG7+IFERROR(VLOOKUP($A7,'A0 BS 1240在建'!$1:$1048576,37,0),0) -> 0 | AM7: =+AH7+IFERROR(VLOOKUP($A7,'B0 2264預收'!$1:$1048576,37,0),0) -> 0 | AN7: =+AL7-AM7 -> 0 | AO7: =+AJ7+IFERROR(+VLOOKUP($A7,'B0 2264預收'!$1:$1048576,38,0),0) -> 0 | AP7: =+AN7-AO7 -> 0 | AQ7: =+AL7+IFERROR(VLOOKUP($A7,'A0 BS 1240在建'!$1:$1048576,41,0),0) -> 0 | AR7: =+AM7+IFERROR(VLOOKUP($A7,'B0 2264預收'!$1:$1048576,41,0),0) -> 0 | AS7: =+AQ7-AR7 -> 0 | AT7: =+AO7+IFERROR(+VLOOKUP($A7,'B0 2264預收'!$1:$1048576,42,0),0) -> 0 | AU7: =+AS7-AT7 -> 0 | AV7: =+AQ7+IFERROR(VLOOKUP($A7,'A0 BS 1240在建'!$1:$1048576,45,0),0) -> 0 | AW7: =+AR7+IFERROR(VLOOKUP($A7,'B0 2264預收'!$1:$1048576,45,0),0) -> 0 | AX7: =+AV7-AW7 -> 0 | AY7: =+AT7+IFERROR(+VLOOKUP($A7,'B0 2264預收'!$1:$1048576,46,0),0) -> 0 | AZ7: =+AX7-AY7 -> 0 | BA7: =+AV7+IFERROR(VLOOKUP($A7,'A0 BS 1240在建'!$1:$1048576,49,0),0) -> 0 | BB7: =+AW7+IFERROR(VLOOKUP($A7,'B0 2264預收'!$1:$1048576,49,0),0) -> 0 | BC7: =+BA7-BB7 -> 0 | BD7: =+AY7+IFERROR(+VLOOKUP($A7,'B0 2264預收'!$1:$1048576,50,0),0) -> 0 | BE7: =+BC7-BD7 -> 0 | BF7: =+BA7+IFERROR(VLOOKUP($A7,'A0 BS 1240在建'!$1:$1048576,53,0),0) -> 0 | BG7: =+BB7+IFERROR(VLOOKUP($A7,'B0 2264預收'!$1:$1048576,53,0),0) -> 0 | BH7: =+BF7-BG7 -> 0 | BI7: =+BD7+IFERROR(+VLOOKUP($A7,'B0 2264預收'!$1:$1048576,54,0),0) -> 0 | BJ7: =+BH7-BI7 -> 0 | BK7: =+BF7+IFERROR(VLOOKUP($A7,'A0 BS 1240在建'!$1:$1048576,57,0),0) -> 0 | BL7: =+BG7+IFERROR(VLOOKUP($A7,'B0 2264預收'!$1:$1048576,57,0),0) -> 0 | BM7: =+BK7-BL7 -> 0 | BN7: =+BI7+IFERROR(+VLOOKUP($A7,'B0 2264預收'!$1:$1048576,58,0),0) -> 0 | BO7: =+BM7-BN7 -> 0 | BP7: =+BK7+IFERROR(VLOOKUP($A7,'A0 BS 1240在建'!$1:$1048576,61,0),0) -> 0 | BQ7: =+BL7+IFERROR(VLOOKUP($A7,'B0 2264預收'!$1:$1048576,61,0),0) -> 0 | BR7: =+BP7-BQ7 -> 0 | BS7: =+BN7+IFERROR(+VLOOKUP($A7,'B0 2264預收'!$1:$1048576,62,0),0) -> 0 | BT7: =+BR7-BS7 -> 0 | BU7: =+IFERROR(VLOOKUP($A7,'A0 BS 1240在建'!$1:$1048576,77,0),0) -> 0 | BV7: =+IFERROR(VLOOKUP($A7,'B0 2264預收'!$1:$1048576,77,0),0) -> 0 | BW7: =+BU7-BV7 -> 0 | BX7: =+IFERROR(+VLOOKUP($A7,'B0 2264預收'!$1:$1048576,78,0),0) -> 0 | BY7: =+BW7-BX7 -> 0 | BZ7: =IFERROR(+VLOOKUP($A7,'A0 BS 1240在建'!$1:$1048576,85,0),0) -> 0 | CA7: =IFERROR(+VLOOKUP($A7,'B0 2264預收'!$1:$1048576,85,0),0) -> 0 | CB7: =+BZ7-CA7 -> 0 | CC7: =+IFERROR(+VLOOKUP($A7,'B0 2264預收'!$1:$1048576,86,0),0) -> 0 | CD7: =+CB7-CC7 -> 0 | CE7: =+IFERROR(VLOOKUP($A7,'A0 BS 1240在建'!$1:$1048576,93,0),0) -> 0 | CF7: =+IFERROR(VLOOKUP($A7,'B0 2264預收'!$1:$1048576,93,0),0) -> 0 | CG7: =+CE7-CF7 -> 0 | CH7: =+IFERROR(+VLOOKUP($A7,'B0 2264預收'!$1:$1048576,94,0),0) -> 0 | CI7: =+CG7-CH7 -> 0 | CJ7: =IFERROR(+VLOOKUP($A7,'A0 BS 1240在建'!$1:$1048576,101,0),0) -> 0 | CK7: =IFERROR(+VLOOKUP($A7,'B0 2264預收'!$1:$1048576,101,0),0) -> 0 | CL7: =+CJ7-CK7 -> 0 | CM7: =+IFERROR(+VLOOKUP($A7,'B0 2264預收'!$1:$1048576,102,0),0) -> 0 | CN7: =+CL7-CM7 -> 0 | CP7: =+J7-E7 -> 0 | CR7: =+CP7 -> 0 | CU7: =+BR7-J7 -> 0 | CW7: =+CU7 -> 0 | CY7: =IF(AND(BR7>0, J7>0), BR7-J7, "") | CZ7: =IF(AND(BR7<0,J7>0),-J7," ") | DA7: =IF(AND(BR7>0,J7<0),BR7," ") | DB7: =IF(AND(L7=0,BR7<0),-BR7," ") | DC7: =SUM(CY7:DB7) -> 0 | DD7: =IF(AND(BR7<0, J7<0), (BR7-J7)*-1, "") | DE7: =IF(AND(BR7<0,J7>0),-BR7," ") | DF7: =IF(AND(BR7>0,J7<0),-J7*-1," ") | DG7: =IF(AND(L7<0,BR7=0),-L7*-1," ") | DH7: =SUM(DD7:DG7) -> 0
A8: C/4160H | B8: CQ850A標萬大線 | C8: =IFERROR(VLOOKUP($A8,'A0 BS 1240在建'!$1:$1048576,5,0),0) -> 0 | D8: =IFERROR(VLOOKUP($A8,'B0 2264預收'!$1:$1048576,5,0),0) -> 0 | E8: =+C8-D8 -> 0 | F8: =IFERROR(VLOOKUP($A8,'B0 2264預收'!$1:$1048576,6,0),0) -> 0 | G8: =+E8-F8 -> 0 | H8: =IFERROR(VLOOKUP($A8,'A0 BS 1240在建'!$1:$1048576,13,0),0) -> 0 | I8: =IFERROR(VLOOKUP($A8,'B0 2264預收'!$1:$1048576,13,0),0) -> 0 | J8: =+H8-I8 -> 0 | K8: =IFERROR(VLOOKUP($A8,'B0 2264預收'!$1:$1048576,14,0),0) -> 0 | L8: =+H8-I8-K8 -> 0 | M8: =H8+IFERROR(VLOOKUP($A8,'A0 BS 1240在建'!$1:$1048576,17,0),0) -> 0 | N8: =I8+IFERROR(VLOOKUP($A8,'B0 2264預收'!$1:$1048576,17,0),0) -> 0 | O8: =+M8-N8 -> 0 | P8: =K8+IFERROR(+VLOOKUP($A8,'B0 2264預收'!$1:$1048576,18,0),0) -> 0 | Q8: =+O8-P8 -> 0 | R8: =M8+IFERROR(VLOOKUP($A8,'A0 BS 1240在建'!$1:$1048576,21,0),0) -> 0 | S8: =+N8+IFERROR(VLOOKUP($A8,'B0 2264預收'!$1:$1048576,21,0),0) -> 0 | T8: =+R8-S8 -> 0 | U8: =+P8+IFERROR(+VLOOKUP($A8,'B0 2264預收'!$1:$1048576,22,0),0) -> 0 | V8: =+T8-U8 -> 0 | W8: =+R8+IFERROR(VLOOKUP($A8,'A0 BS 1240在建'!$1:$1048576,25,0),0) -> 0 | X8: =+S8+IFERROR(VLOOKUP($A8,'B0 2264預收'!$1:$1048576,25,0),0) -> 0 | Y8: =+W8-X8 -> 0 | Z8: =+U8+IFERROR(+VLOOKUP($A8,'B0 2264預收'!$1:$1048576,26,0),0) -> 0 | AA8: =+Y8-Z8 -> 0 | AB8: =+W8+IFERROR(VLOOKUP($A8,'A0 BS 1240在建'!$1:$1048576,29,0),0) -> 0 | AC8: =+X8+IFERROR(VLOOKUP($A8,'B0 2264預收'!$1:$1048576,29,0),0) -> 0 | AD8: =+AB8-AC8 -> 0 | AE8: =+Z8+IFERROR(+VLOOKUP($A8,'B0 2264預收'!$1:$1048576,30,0),0) -> 0 | AF8: =+AD8-AE8 -> 0 | AG8: =+AB8+IFERROR(VLOOKUP($A8,'A0 BS 1240在建'!$1:$1048576,33,0),0) -> 0 | AH8: =+AC8+IFERROR(VLOOKUP($A8,'B0 2264預收'!$1:$1048576,33,0),0) -> 0 | AI8: =+AG8-AH8 -> 0 | AJ8: =+AE8+IFERROR(+VLOOKUP($A8,'B0 2264預收'!$1:$1048576,34,0),0) -> 0 | AK8: =+AI8-AJ8 -> 0 | AL8: =+AG8+IFERROR(VLOOKUP($A8,'A0 BS 1240在建'!$1:$1048576,37,0),0) -> 0 | AM8: =+AH8+IFERROR(VLOOKUP($A8,'B0 2264預收'!$1:$1048576,37,0),0) -> 0 | AN8: =+AL8-AM8 -> 0 | AO8: =+AJ8+IFERROR(+VLOOKUP($A8,'B0 2264預收'!$1:$1048576,38,0),0) -> 0 | AP8: =+AN8-AO8 -> 0 | AQ8: =+AL8+IFERROR(VLOOKUP($A8,'A0 BS 1240在建'!$1:$1048576,41,0),0) -> 0 | AR8: =+AM8+IFERROR(VLOOKUP($A8,'B0 2264預收'!$1:$1048576,41,0),0) -> 0 | AS8: =+AQ8-AR8 -> 0 | AT8: =+AO8+IFERROR(+VLOOKUP($A8,'B0 2264預收'!$1:$1048576,42,0),0) -> 0 | AU8: =+AS8-AT8 -> 0 | AV8: =+AQ8+IFERROR(VLOOKUP($A8,'A0 BS 1240在建'!$1:$1048576,45,0),0) -> 0 | AW8: =+AR8+IFERROR(VLOOKUP($A8,'B0 2264預收'!$1:$1048576,45,0),0) -> 0 | AX8: =+AV8-AW8 -> 0 | AY8: =+AT8+IFERROR(+VLOOKUP($A8,'B0 2264預收'!$1:$1048576,46,0),0) -> 0 | AZ8: =+AX8-AY8 -> 0 | BA8: =+AV8+IFERROR(VLOOKUP($A8,'A0 BS 1240在建'!$1:$1048576,49,0),0) -> 0 | BB8: =+AW8+IFERROR(VLOOKUP($A8,'B0 2264預收'!$1:$1048576,49,0),0) -> 0 | BC8: =+BA8-BB8 -> 0 | BD8: =+AY8+IFERROR(+VLOOKUP($A8,'B0 2264預收'!$1:$1048576,50,0),0) -> 0 | BE8: =+BC8-BD8 -> 0 | BF8: =+BA8+IFERROR(VLOOKUP($A8,'A0 BS 1240在建'!$1:$1048576,53,0),0) -> 0 | BG8: =+BB8+IFERROR(VLOOKUP($A8,'B0 2264預收'!$1:$1048576,53,0),0) -> 0 | BH8: =+BF8-BG8 -> 0 | BI8: =+BD8+IFERROR(+VLOOKUP($A8,'B0 2264預收'!$1:$1048576,54,0),0) -> 0 | BJ8: =+BH8-BI8 -> 0 | BK8: =+BF8+IFERROR(VLOOKUP($A8,'A0 BS 1240在建'!$1:$1048576,57,0),0) -> 0 | BL8: =+BG8+IFERROR(VLOOKUP($A8,'B0 2264預收'!$1:$1048576,57,0),0) -> 0 | BM8: =+BK8-BL8 -> 0 | BN8: =+BI8+IFERROR(+VLOOKUP($A8,'B0 2264預收'!$1:$1048576,58,0),0) -> 0 | BO8: =+BM8-BN8 -> 0 | BP8: =+BK8+IFERROR(VLOOKUP($A8,'A0 BS 1240在建'!$1:$1048576,61,0),0) -> 0 | BQ8: =+BL8+IFERROR(VLOOKUP($A8,'B0 2264預收'!$1:$1048576,61,0),0) -> 0 | BR8: =+BP8-BQ8 -> 0 | BS8: =+BN8+IFERROR(+VLOOKUP($A8,'B0 2264預收'!$1:$1048576,62,0),0) -> 0 | BT8: =+BR8-BS8 -> 0 | BU8: =+IFERROR(VLOOKUP($A8,'A0 BS 1240在建'!$1:$1048576,77,0),0) -> 0 | BV8: =+IFERROR(VLOOKUP($A8,'B0 2264預收'!$1:$1048576,77,0),0) -> 0 | BW8: =+BU8-BV8 -> 0 | BX8: =+IFERROR(+VLOOKUP($A8,'B0 2264預收'!$1:$1048576,78,0),0) -> 0 | BY8: =+BW8-BX8 -> 0 | BZ8: =IFERROR(+VLOOKUP($A8,'A0 BS 1240在建'!$1:$1048576,85,0),0) -> 0 | CA8: =IFERROR(+VLOOKUP($A8,'B0 2264預收'!$1:$1048576,85,0),0) -> 0 | CB8: =+BZ8-CA8 -> 0 | CC8: =+IFERROR(+VLOOKUP($A8,'B0 2264預收'!$1:$1048576,86,0),0) -> 0 | CD8: =+CB8-CC8 -> 0 | CE8: =+IFERROR(VLOOKUP($A8,'A0 BS 1240在建'!$1:$1048576,93,0),0) -> 0 | CF8: =+IFERROR(VLOOKUP($A8,'B0 2264預收'!$1:$1048576,93,0),0) -> 0 | CG8: =+CE8-CF8 -> 0 | CH8: =+IFERROR(+VLOOKUP($A8,'B0 2264預收'!$1:$1048576,94,0),0) -> 0 | CI8: =+CG8-CH8 -> 0 | CJ8: =IFERROR(+VLOOKUP($A8,'A0 BS 1240在建'!$1:$1048576,101,0),0) -> 0 | CK8: =IFERROR(+VLOOKUP($A8,'B0 2264預收'!$1:$1048576,101,0),0) -> 0 | CL8: =+CJ8-CK8 -> 0 | CM8: =+IFERROR(+VLOOKUP($A8,'B0 2264預收'!$1:$1048576,102,0),0) -> 0 | CN8: =+CL8-CM8 -> 0 | CP8: =+J8-E8 -> 0 | CQ8: =+CP8 -> 0 | CU8: =+BR8-J8 -> 0 | CV8: =-J8 -> 0 | CW8: =+BR8 -> 0 | CY8: =IF(AND(BR8>0, J8>0), BR8-J8, "") | CZ8: =IF(AND(BR8<0,J8>0),-J8," ") | DA8: =IF(AND(BR8>0,J8<0),BR8," ") | DB8: =IF(AND(L8=0,BR8<0),-BR8," ") | DC8: =SUM(CY8:DB8) -> 0 | DD8: =IF(AND(BR8<0, J8<0), (BR8-J8)*-1, "") | DE8: =IF(AND(BR8<0,J8>0),-BR8," ") | DF8: =IF(AND(BR8>0,J8<0),-J8*-1," ") | DG8: =IF(AND(L8<0,BR8=0),-L8*-1," ") | DH8: =SUM(DD8:DG8) -> 0
A9: C/4160J | B9: CQ840標萬大線 | C9: =IFERROR(VLOOKUP($A9,'A0 BS 1240在建'!$1:$1048576,5,0),0) -> 0 | D9: =IFERROR(VLOOKUP($A9,'B0 2264預收'!$1:$1048576,5,0),0) -> 0 | E9: =+C9-D9 -> 0 | F9: =IFERROR(VLOOKUP($A9,'B0 2264預收'!$1:$1048576,6,0),0) -> 0 | G9: =+E9-F9 -> 0 | H9: =IFERROR(VLOOKUP($A9,'A0 BS 1240在建'!$1:$1048576,13,0),0) -> 0 | I9: =IFERROR(VLOOKUP($A9,'B0 2264預收'!$1:$1048576,13,0),0) -> 0 | J9: =+H9-I9 -> 0 | K9: =IFERROR(VLOOKUP($A9,'B0 2264預收'!$1:$1048576,14,0),0) -> 0 | L9: =+H9-I9-K9 -> 0 | M9: =H9+IFERROR(VLOOKUP($A9,'A0 BS 1240在建'!$1:$1048576,17,0),0) -> 0 | N9: =I9+IFERROR(VLOOKUP($A9,'B0 2264預收'!$1:$1048576,17,0),0) -> 0 | O9: =+M9-N9 -> 0 | P9: =K9+IFERROR(+VLOOKUP($A9,'B0 2264預收'!$1:$1048576,18,0),0) -> 0 | Q9: =+O9-P9 -> 0 | R9: =M9+IFERROR(VLOOKUP($A9,'A0 BS 1240在建'!$1:$1048576,21,0),0) -> 0 | S9: =+N9+IFERROR(VLOOKUP($A9,'B0 2264預收'!$1:$1048576,21,0),0) -> 0 | T9: =+R9-S9 -> 0 | U9: =+P9+IFERROR(+VLOOKUP($A9,'B0 2264預收'!$1:$1048576,22,0),0) -> 0 | V9: =+T9-U9 -> 0 | W9: =+R9+IFERROR(VLOOKUP($A9,'A0 BS 1240在建'!$1:$1048576,25,0),0) -> 0 | X9: =+S9+IFERROR(VLOOKUP($A9,'B0 2264預收'!$1:$1048576,25,0),0) -> 0 | Y9: =+W9-X9 -> 0 | Z9: =+U9+IFERROR(+VLOOKUP($A9,'B0 2264預收'!$1:$1048576,26,0),0) -> 0 | AA9: =+Y9-Z9 -> 0 | AB9: =+W9+IFERROR(VLOOKUP($A9,'A0 BS 1240在建'!$1:$1048576,29,0),0) -> 0 | AC9: =+X9+IFERROR(VLOOKUP($A9,'B0 2264預收'!$1:$1048576,29,0),0) -> 0 | AD9: =+AB9-AC9 -> 0 | AE9: =+Z9+IFERROR(+VLOOKUP($A9,'B0 2264預收'!$1:$1048576,30,0),0) -> 0 | AF9: =+AD9-AE9 -> 0 | AG9: =+AB9+IFERROR(VLOOKUP($A9,'A0 BS 1240在建'!$1:$1048576,33,0),0) -> 0 | AH9: =+AC9+IFERROR(VLOOKUP($A9,'B0 2264預收'!$1:$1048576,33,0),0) -> 0 | AI9: =+AG9-AH9 -> 0 | AJ9: =+AE9+IFERROR(+VLOOKUP($A9,'B0 2264預收'!$1:$1048576,34,0),0) -> 0 | AK9: =+AI9-AJ9 -> 0 | AL9: =+AG9+IFERROR(VLOOKUP($A9,'A0 BS 1240在建'!$1:$1048576,37,0),0) -> 0 | AM9: =+AH9+IFERROR(VLOOKUP($A9,'B0 2264預收'!$1:$1048576,37,0),0) -> 0 | AN9: =+AL9-AM9 -> 0 | AO9: =+AJ9+IFERROR(+VLOOKUP($A9,'B0 2264預收'!$1:$1048576,38,0),0) -> 0 | AP9: =+AN9-AO9 -> 0 | AQ9: =+AL9+IFERROR(VLOOKUP($A9,'A0 BS 1240在建'!$1:$1048576,41,0),0) -> 0 | AR9: =+AM9+IFERROR(VLOOKUP($A9,'B0 2264預收'!$1:$1048576,41,0),0) -> 0 | AS9: =+AQ9-AR9 -> 0 | AT9: =+AO9+IFERROR(+VLOOKUP($A9,'B0 2264預收'!$1:$1048576,42,0),0) -> 0 | AU9: =+AS9-AT9 -> 0 | AV9: =+AQ9+IFERROR(VLOOKUP($A9,'A0 BS 1240在建'!$1:$1048576,45,0),0) -> 0 | AW9: =+AR9+IFERROR(VLOOKUP($A9,'B0 2264預收'!$1:$1048576,45,0),0) -> 0 | AX9: =+AV9-AW9 -> 0 | AY9: =+AT9+IFERROR(+VLOOKUP($A9,'B0 2264預收'!$1:$1048576,46,0),0) -> 0 | AZ9: =+AX9-AY9 -> 0 | BA9: =+AV9+IFERROR(VLOOKUP($A9,'A0 BS 1240在建'!$1:$1048576,49,0),0) -> 0 | BB9: =+AW9+IFERROR(VLOOKUP($A9,'B0 2264預收'!$1:$1048576,49,0),0) -> 0 | BC9: =+BA9-BB9 -> 0 | BD9: =+AY9+IFERROR(+VLOOKUP($A9,'B0 2264預收'!$1:$1048576,50,0),0) -> 0 | BE9: =+BC9-BD9 -> 0 | BF9: =+BA9+IFERROR(VLOOKUP($A9,'A0 BS 1240在建'!$1:$1048576,53,0),0) -> 0 | BG9: =+BB9+IFERROR(VLOOKUP($A9,'B0 2264預收'!$1:$1048576,53,0),0) -> 0 | BH9: =+BF9-BG9 -> 0 | BI9: =+BD9+IFERROR(+VLOOKUP($A9,'B0 2264預收'!$1:$1048576,54,0),0) -> 0 | BJ9: =+BH9-BI9 -> 0 | BK9: =+BF9+IFERROR(VLOOKUP($A9,'A0 BS 1240在建'!$1:$1048576,57,0),0) -> 0 | BL9: =+BG9+IFERROR(VLOOKUP($A9,'B0 2264預收'!$1:$1048576,57,0),0) -> 0 | BM9: =+BK9-BL9 -> 0 | BN9: =+BI9+IFERROR(+VLOOKUP($A9,'B0 2264預收'!$1:$1048576,58,0),0) -> 0 | BO9: =+BM9-BN9 -> 0 | BP9: =+BK9+IFERROR(VLOOKUP($A9,'A0 BS 1240在建'!$1:$1048576,61,0),0) -> 0 | BQ9: =+BL9+IFERROR(VLOOKUP($A9,'B0 2264預收'!$1:$1048576,61,0),0) -> 0 | BR9: =+BP9-BQ9 -> 0 | BS9: =+BN9+IFERROR(+VLOOKUP($A9,'B0 2264預收'!$1:$1048576,62,0),0) -> 0 | BT9: =+BR9-BS9 -> 0 | BU9: =+IFERROR(VLOOKUP($A9,'A0 BS 1240在建'!$1:$1048576,77,0),0) -> 0 | BV9: =+IFERROR(VLOOKUP($A9,'B0 2264預收'!$1:$1048576,77,0),0) -> 0 | BW9: =+BU9-BV9 -> 0 | BX9: =+IFERROR(+VLOOKUP($A9,'B0 2264預收'!$1:$1048576,78,0),0) -> 0 | BY9: =+BW9-BX9 -> 0 | BZ9: =IFERROR(+VLOOKUP($A9,'A0 BS 1240在建'!$1:$1048576,85,0),0) -> 0 | CA9: =IFERROR(+VLOOKUP($A9,'B0 2264預收'!$1:$1048576,85,0),0) -> 0 | CB9: =+BZ9-CA9 -> 0 | CC9: =+IFERROR(+VLOOKUP($A9,'B0 2264預收'!$1:$1048576,86,0),0) -> 0 | CD9: =+CB9-CC9 -> 0 | CE9: =+IFERROR(VLOOKUP($A9,'A0 BS 1240在建'!$1:$1048576,93,0),0) -> 0 | CF9: =+IFERROR(VLOOKUP($A9,'B0 2264預收'!$1:$1048576,93,0),0) -> 0 | CG9: =+CE9-CF9 -> 0 | CH9: =+IFERROR(+VLOOKUP($A9,'B0 2264預收'!$1:$1048576,94,0),0) -> 0 | CI9: =+CG9-CH9 -> 0 | CJ9: =IFERROR(+VLOOKUP($A9,'A0 BS 1240在建'!$1:$1048576,101,0),0) -> 0 | CK9: =IFERROR(+VLOOKUP($A9,'B0 2264預收'!$1:$1048576,101,0),0) -> 0 | CL9: =+CJ9-CK9 -> 0 | CM9: =+IFERROR(+VLOOKUP($A9,'B0 2264預收'!$1:$1048576,102,0),0) -> 0 | CN9: =+CL9-CM9 -> 0 | CP9: =+J9-E9 -> 0 | CQ9: =-E9 -> 0 | CR9: =+J9 -> 0 | CU9: =+BR9-J9 -> 0 | CW9: =+CU9 -> 0 | CY9: =IF(AND(BR9>0, J9>0), BR9-J9, "") | CZ9: =IF(AND(BR9<0,J9>0),-J9," ") | DA9: =IF(AND(BR9>0,J9<0),BR9," ") | DB9: =IF(AND(L9=0,BR9<0),-BR9," ") | DC9: =SUM(CY9:DB9) -> 0 | DD9: =IF(AND(BR9<0, J9<0), (BR9-J9)*-1, "") | DE9: =IF(AND(BR9<0,J9>0),-BR9," ") | DF9: =IF(AND(BR9>0,J9<0),-J9*-1," ") | DG9: =IF(AND(L9<0,BR9=0),-L9*-1," ") | DH9: =SUM(DD9:DG9) -> 0
A10: C/4170A | B10: C214標台南鐵路 | C10: =IFERROR(VLOOKUP($A10,'A0 BS 1240在建'!$1:$1048576,5,0),0) -> 0 | D10: =IFERROR(VLOOKUP($A10,'B0 2264預收'!$1:$1048576,5,0),0) -> 0 | E10: =+C10-D10 -> 0 | F10: =IFERROR(VLOOKUP($A10,'B0 2264預收'!$1:$1048576,6,0),0) -> 0 | G10: =+E10-F10 -> 0 | H10: =IFERROR(VLOOKUP($A10,'A0 BS 1240在建'!$1:$1048576,13,0),0) -> 0 | I10: =IFERROR(VLOOKUP($A10,'B0 2264預收'!$1:$1048576,13,0),0) -> 0 | J10: =+H10-I10 -> 0 | K10: =IFERROR(VLOOKUP($A10,'B0 2264預收'!$1:$1048576,14,0),0) -> 0 | L10: =+H10-I10-K10 -> 0 | M10: =H10+IFERROR(VLOOKUP($A10,'A0 BS 1240在建'!$1:$1048576,17,0),0) -> 0 | N10: =I10+IFERROR(VLOOKUP($A10,'B0 2264預收'!$1:$1048576,17,0),0) -> 0 | O10: =+M10-N10 -> 0 | P10: =K10+IFERROR(+VLOOKUP($A10,'B0 2264預收'!$1:$1048576,18,0),0) -> 0 | Q10: =+O10-P10 -> 0 | R10: =M10+IFERROR(VLOOKUP($A10,'A0 BS 1240在建'!$1:$1048576,21,0),0) -> 0 | S10: =+N10+IFERROR(VLOOKUP($A10,'B0 2264預收'!$1:$1048576,21,0),0) -> 0 | T10: =+R10-S10 -> 0 | U10: =+P10+IFERROR(+VLOOKUP($A10,'B0 2264預收'!$1:$1048576,22,0),0) -> 0 | V10: =+T10-U10 -> 0 | W10: =+R10+IFERROR(VLOOKUP($A10,'A0 BS 1240在建'!$1:$1048576,25,0),0) -> 0 | X10: =+S10+IFERROR(VLOOKUP($A10,'B0 2264預收'!$1:$1048576,25,0),0) -> 0 | Y10: =+W10-X10 -> 0 | Z10: =+U10+IFERROR(+VLOOKUP($A10,'B0 2264預收'!$1:$1048576,26,0),0) -> 0 | AA10: =+Y10-Z10 -> 0 | AB10: =+W10+IFERROR(VLOOKUP($A10,'A0 BS 1240在建'!$1:$1048576,29,0),0) -> 0 | AC10: =+X10+IFERROR(VLOOKUP($A10,'B0 2264預收'!$1:$1048576,29,0),0) -> 0 | AD10: =+AB10-AC10 -> 0 | AE10: =+Z10+IFERROR(+VLOOKUP($A10,'B0 2264預收'!$1:$1048576,30,0),0) -> 0 | AF10: =+AD10-AE10 -> 0 | AG10: =+AB10+IFERROR(VLOOKUP($A10,'A0 BS 1240在建'!$1:$1048576,33,0),0) -> 0 | AH10: =+AC10+IFERROR(VLOOKUP($A10,'B0 2264預收'!$1:$1048576,33,0),0) -> 0 | AI10: =+AG10-AH10 -> 0 | AJ10: =+AE10+IFERROR(+VLOOKUP($A10,'B0 2264預收'!$1:$1048576,34,0),0) -> 0 | AK10: =+AI10-AJ10 -> 0 | AL10: =+AG10+IFERROR(VLOOKUP($A10,'A0 BS 1240在建'!$1:$1048576,37,0),0) -> 0 | AM10: =+AH10+IFERROR(VLOOKUP($A10,'B0 2264預收'!$1:$1048576,37,0),0) -> 0 | AN10: =+AL10-AM10 -> 0 | AO10: =+AJ10+IFERROR(+VLOOKUP($A10,'B0 2264預收'!$1:$1048576,38,0),0) -> 0 | AP10: =+AN10-AO10 -> 0 | AQ10: =+AL10+IFERROR(VLOOKUP($A10,'A0 BS 1240在建'!$1:$1048576,41,0),0) -> 0 | AR10: =+AM10+IFERROR(VLOOKUP($A10,'B0 2264預收'!$1:$1048576,41,0),0) -> 0 | AS10: =+AQ10-AR10 -> 0 | AT10: =+AO10+IFERROR(+VLOOKUP($A10,'B0 2264預收'!$1:$1048576,42,0),0) -> 0 | AU10: =+AS10-AT10 -> 0 | AV10: =+AQ10+IFERROR(VLOOKUP($A10,'A0 BS 1240在建'!$1:$1048576,45,0),0) -> 0 | AW10: =+AR10+IFERROR(VLOOKUP($A10,'B0 2264預收'!$1:$1048576,45,0),0) -> 0 | AX10: =+AV10-AW10 -> 0 | AY10: =+AT10+IFERROR(+VLOOKUP($A10,'B0 2264預收'!$1:$1048576,46,0),0) -> 0 | AZ10: =+AX10-AY10 -> 0 | BA10: =+AV10+IFERROR(VLOOKUP($A10,'A0 BS 1240在建'!$1:$1048576,49,0),0) -> 0 | BB10: =+AW10+IFERROR(VLOOKUP($A10,'B0 2264預收'!$1:$1048576,49,0),0) -> 0 | BC10: =+BA10-BB10 -> 0 | BD10: =+AY10+IFERROR(+VLOOKUP($A10,'B0 2264預收'!$1:$1048576,50,0),0) -> 0 | BE10: =+BC10-BD10 -> 0 | BF10: =+BA10+IFERROR(VLOOKUP($A10,'A0 BS 1240在建'!$1:$1048576,53,0),0) -> 0 | BG10: =+BB10+IFERROR(VLOOKUP($A10,'B0 2264預收'!$1:$1048576,53,0),0) -> 0 | BH10: =+BF10-BG10 -> 0 | BI10: =+BD10+IFERROR(+VLOOKUP($A10,'B0 2264預收'!$1:$1048576,54,0),0) -> 0 | BJ10: =+BH10-BI10 -> 0 | BK10: =+BF10+IFERROR(VLOOKUP($A10,'A0 BS 1240在建'!$1:$1048576,57,0),0) -> 0 | BL10: =+BG10+IFERROR(VLOOKUP($A10,'B0 2264預收'!$1:$1048576,57,0),0) -> 0 | BM10: =+BK10-BL10 -> 0 | BN10: =+BI10+IFERROR(+VLOOKUP($A10,'B0 2264預收'!$1:$1048576,58,0),0) -> 0 | BO10: =+BM10-BN10 -> 0 | BP10: =+BK10+IFERROR(VLOOKUP($A10,'A0 BS 1240在建'!$1:$1048576,61,0),0) -> 0 | BQ10: =+BL10+IFERROR(VLOOKUP($A10,'B0 2264預收'!$1:$1048576,61,0),0) -> 0 | BR10: =+BP10-BQ10 -> 0 | BS10: =+BN10+IFERROR(+VLOOKUP($A10,'B0 2264預收'!$1:$1048576,62,0),0) -> 0 | BT10: =+BR10-BS10 -> 0 | BU10: =+IFERROR(VLOOKUP($A10,'A0 BS 1240在建'!$1:$1048576,77,0),0) -> 0 | BV10: =+IFERROR(VLOOKUP($A10,'B0 2264預收'!$1:$1048576,77,0),0) -> 0 | BW10: =+BU10-BV10 -> 0 | BX10: =+IFERROR(+VLOOKUP($A10,'B0 2264預收'!$1:$1048576,78,0),0) -> 0 | BY10: =+BW10-BX10 -> 0 | BZ10: =IFERROR(+VLOOKUP($A10,'A0 BS 1240在建'!$1:$1048576,85,0),0) -> 0 | CA10: =IFERROR(+VLOOKUP($A10,'B0 2264預收'!$1:$1048576,85,0),0) -> 0 | CB10: =+BZ10-CA10 -> 0 | CC10: =+IFERROR(+VLOOKUP($A10,'B0 2264預收'!$1:$1048576,86,0),0) -> 0 | CD10: =+CB10-CC10 -> 0 | CE10: =+IFERROR(VLOOKUP($A10,'A0 BS 1240在建'!$1:$1048576,93,0),0) -> 0 | CF10: =+IFERROR(VLOOKUP($A10,'B0 2264預收'!$1:$1048576,93,0),0) -> 0 | CG10: =+CE10-CF10 -> 0 | CH10: =+IFERROR(+VLOOKUP($A10,'B0 2264預收'!$1:$1048576,94,0),0) -> 0 | CI10: =+CG10-CH10 -> 0 | CJ10: =IFERROR(+VLOOKUP($A10,'A0 BS 1240在建'!$1:$1048576,101,0),0) -> 0 | CK10: =IFERROR(+VLOOKUP($A10,'B0 2264預收'!$1:$1048576,101,0),0) -> 0 | CL10: =+CJ10-CK10 -> 0 | CM10: =+IFERROR(+VLOOKUP($A10,'B0 2264預收'!$1:$1048576,102,0),0) -> 0 | CN10: =+CL10-CM10 -> 0 | CP10: =+J10-E10 -> 0 | CR10: =+CP10 -> 0 | CU10: =+BR10-J10 -> 0 | CW10: =+CU10 -> 0 | CY10: =IF(AND(BR10>0, J10>0), BR10-J10, "") | CZ10: =IF(AND(BR10<0,J10>0),-J10," ") | DA10: =IF(AND(BR10>0,J10<0),BR10," ") | DB10: =IF(AND(L10=0,BR10<0),-BR10," ") | DC10: =SUM(CY10:DB10) -> 0 | DD10: =IF(AND(BR10<0, J10<0), (BR10-J10)*-1, "") | DE10: =IF(AND(BR10<0,J10>0),-BR10," ") | DF10: =IF(AND(BR10>0,J10<0),-J10*-1," ") | DG10: =IF(AND(L10<0,BR10=0),-L10*-1," ") | DH10: =SUM(DD10:DG10) -> 0
A11: C/4170G | B11: C211標台南鐵路 | C11: =IFERROR(VLOOKUP($A11,'A0 BS 1240在建'!$1:$1048576,5,0),0) -> 0 | D11: =IFERROR(VLOOKUP($A11,'B0 2264預收'!$1:$1048576,5,0),0) -> 0 | E11: =+C11-D11 -> 0 | F11: =IFERROR(VLOOKUP($A11,'B0 2264預收'!$1:$1048576,6,0),0) -> 0 | G11: =+E11-F11 -> 0 | H11: =IFERROR(VLOOKUP($A11,'A0 BS 1240在建'!$1:$1048576,13,0),0) -> 0 | I11: =IFERROR(VLOOKUP($A11,'B0 2264預收'!$1:$1048576,13,0),0) -> 0 | J11: =+H11-I11 -> 0 | K11: =IFERROR(VLOOKUP($A11,'B0 2264預收'!$1:$1048576,14,0),0) -> 0 | L11: =+H11-I11-K11 -> 0 | M11: =H11+IFERROR(VLOOKUP($A11,'A0 BS 1240在建'!$1:$1048576,17,0),0) -> 0 | N11: =I11+IFERROR(VLOOKUP($A11,'B0 2264預收'!$1:$1048576,17,0),0) -> 0 | O11: =+M11-N11 -> 0 | P11: =K11+IFERROR(+VLOOKUP($A11,'B0 2264預收'!$1:$1048576,18,0),0) -> 0 | Q11: =+O11-P11 -> 0 | R11: =M11+IFERROR(VLOOKUP($A11,'A0 BS 1240在建'!$1:$1048576,21,0),0) -> 0 | S11: =+N11+IFERROR(VLOOKUP($A11,'B0 2264預收'!$1:$1048576,21,0),0) -> 0 | T11: =+R11-S11 -> 0 | U11: =+P11+IFERROR(+VLOOKUP($A11,'B0 2264預收'!$1:$1048576,22,0),0) -> 0 | V11: =+T11-U11 -> 0 | W11: =+R11+IFERROR(VLOOKUP($A11,'A0 BS 1240在建'!$1:$1048576,25,0),0) -> 0 | X11: =+S11+IFERROR(VLOOKUP($A11,'B0 2264預收'!$1:$1048576,25,0),0) -> 0 | Y11: =+W11-X11 -> 0 | Z11: =+U11+IFERROR(+VLOOKUP($A11,'B0 2264預收'!$1:$1048576,26,0),0) -> 0 | AA11: =+Y11-Z11 -> 0 | AB11: =+W11+IFERROR(VLOOKUP($A11,'A0 BS 1240在建'!$1:$1048576,29,0),0) -> 0 | AC11: =+X11+IFERROR(VLOOKUP($A11,'B0 2264預收'!$1:$1048576,29,0),0) -> 0 | AD11: =+AB11-AC11 -> 0 | AE11: =+Z11+IFERROR(+VLOOKUP($A11,'B0 2264預收'!$1:$1048576,30,0),0) -> 0 | AF11: =+AD11-AE11 -> 0 | AG11: =+AB11+IFERROR(VLOOKUP($A11,'A0 BS 1240在建'!$1:$1048576,33,0),0) -> 0 | AH11: =+AC11+IFERROR(VLOOKUP($A11,'B0 2264預收'!$1:$1048576,33,0),0) -> 0 | AI11: =+AG11-AH11 -> 0 | AJ11: =+AE11+IFERROR(+VLOOKUP($A11,'B0 2264預收'!$1:$1048576,34,0),0) -> 0 | AK11: =+AI11-AJ11 -> 0 | AL11: =+AG11+IFERROR(VLOOKUP($A11,'A0 BS 1240在建'!$1:$1048576,37,0),0) -> 0 | AM11: =+AH11+IFERROR(VLOOKUP($A11,'B0 2264預收'!$1:$1048576,37,0),0) -> 0 | AN11: =+AL11-AM11 -> 0 | AO11: =+AJ11+IFERROR(+VLOOKUP($A11,'B0 2264預收'!$1:$1048576,38,0),0) -> 0 | AP11: =+AN11-AO11 -> 0 | AQ11: =+AL11+IFERROR(VLOOKUP($A11,'A0 BS 1240在建'!$1:$1048576,41,0),0) -> 0 | AR11: =+AM11+IFERROR(VLOOKUP($A11,'B0 2264預收'!$1:$1048576,41,0),0) -> 0 | AS11: =+AQ11-AR11 -> 0 | AT11: =+AO11+IFERROR(+VLOOKUP($A11,'B0 2264預收'!$1:$1048576,42,0),0) -> 0 | AU11: =+AS11-AT11 -> 0 | AV11: =+AQ11+IFERROR(VLOOKUP($A11,'A0 BS 1240在建'!$1:$1048576,45,0),0) -> 0 | AW11: =+AR11+IFERROR(VLOOKUP($A11,'B0 2264預收'!$1:$1048576,45,0),0) -> 0 | AX11: =+AV11-AW11 -> 0 | AY11: =+AT11+IFERROR(+VLOOKUP($A11,'B0 2264預收'!$1:$1048576,46,0),0) -> 0 | AZ11: =+AX11-AY11 -> 0 | BA11: =+AV11+IFERROR(VLOOKUP($A11,'A0 BS 1240在建'!$1:$1048576,49,0),0) -> 0 | BB11: =+AW11+IFERROR(VLOOKUP($A11,'B0 2264預收'!$1:$1048576,49,0),0) -> 0 | BC11: =+BA11-BB11 -> 0 | BD11: =+AY11+IFERROR(+VLOOKUP($A11,'B0 2264預收'!$1:$1048576,50,0),0) -> 0 | BE11: =+BC11-BD11 -> 0 | BF11: =+BA11+IFERROR(VLOOKUP($A11,'A0 BS 1240在建'!$1:$1048576,53,0),0) -> 0 | BG11: =+BB11+IFERROR(VLOOKUP($A11,'B0 2264預收'!$1:$1048576,53,0),0) -> 0 | BH11: =+BF11-BG11 -> 0 | BI11: =+BD11+IFERROR(+VLOOKUP($A11,'B0 2264預收'!$1:$1048576,54,0),0) -> 0 | BJ11: =+BH11-BI11 -> 0 | BK11: =+BF11+IFERROR(VLOOKUP($A11,'A0 BS 1240在建'!$1:$1048576,57,0),0) -> 0 | BL11: =+BG11+IFERROR(VLOOKUP($A11,'B0 2264預收'!$1:$1048576,57,0),0) -> 0 | BM11: =+BK11-BL11 -> 0 | BN11: =+BI11+IFERROR(+VLOOKUP($A11,'B0 2264預收'!$1:$1048576,58,0),0) -> 0 | BO11: =+BM11-BN11 -> 0 | BP11: =+BK11+IFERROR(VLOOKUP($A11,'A0 BS 1240在建'!$1:$1048576,61,0),0) -> 0 | BQ11: =+BL11+IFERROR(VLOOKUP($A11,'B0 2264預收'!$1:$1048576,61,0),0) -> 0 | BR11: =+BP11-BQ11 -> 0 | BS11: =+BN11+IFERROR(+VLOOKUP($A11,'B0 2264預收'!$1:$1048576,62,0),0) -> 0 | BT11: =+BR11-BS11 -> 0 | BU11: =+IFERROR(VLOOKUP($A11,'A0 BS 1240在建'!$1:$1048576,77,0),0) -> 0 | BV11: =+IFERROR(VLOOKUP($A11,'B0 2264預收'!$1:$1048576,77,0),0) -> 0 | BW11: =+BU11-BV11 -> 0 | BX11: =+IFERROR(+VLOOKUP($A11,'B0 2264預收'!$1:$1048576,78,0),0) -> 0 | BY11: =+BW11-BX11 -> 0 | BZ11: =IFERROR(+VLOOKUP($A11,'A0 BS 1240在建'!$1:$1048576,85,0),0) -> 0 | CA11: =IFERROR(+VLOOKUP($A11,'B0 2264預收'!$1:$1048576,85,0),0) -> 0 | CB11: =+BZ11-CA11 -> 0 | CC11: =+IFERROR(+VLOOKUP($A11,'B0 2264預收'!$1:$1048576,86,0),0) -> 0 | CD11: =+CB11-CC11 -> 0 | CE11: =+IFERROR(VLOOKUP($A11,'A0 BS 1240在建'!$1:$1048576,93,0),0) -> 0 | CF11: =+IFERROR(VLOOKUP($A11,'B0 2264預收'!$1:$1048576,93,0),0) -> 0 | CG11: =+CE11-CF11 -> 0 | CH11: =+IFERROR(+VLOOKUP($A11,'B0 2264預收'!$1:$1048576,94,0),0) -> 0 | CI11: =+CG11-CH11 -> 0 | CJ11: =IFERROR(+VLOOKUP($A11,'A0 BS 1240在建'!$1:$1048576,101,0),0) -> 0 | CK11: =IFERROR(+VLOOKUP($A11,'B0 2264預收'!$1:$1048576,101,0),0) -> 0 | CL11: =+CJ11-CK11 -> 0 | CM11: =+IFERROR(+VLOOKUP($A11,'B0 2264預收'!$1:$1048576,102,0),0) -> 0 | CN11: =+CL11-CM11 -> 0 | CP11: =+J11-E11 -> 0 | CR11: =+CP11 -> 0 | CU11: =+BR11-J11 -> 0 | CW11: =+CU11 -> 0 | CY11: =IF(AND(BR11>0, J11>0), BR11-J11, "") | CZ11: =IF(AND(BR11<0,J11>0),-J11," ") | DA11: =IF(AND(BR11>0,J11<0),BR11," ") | DB11: =IF(AND(L11=0,BR11<0),-BR11," ") | DC11: =SUM(CY11:DB11) -> 0 | DD11: =IF(AND(BR11<0, J11<0), (BR11-J11)*-1, "") | DE11: =IF(AND(BR11<0,J11>0),-BR11," ") | DF11: =IF(AND(BR11>0,J11<0),-J11*-1," ") | DG11: =IF(AND(L11<0,BR11=0),-L11*-1," ") | DH11: =SUM(DD11:DG11) -> 0
A12: C/4180E | B12: 桃園捷運綠線GC01 | C12: =IFERROR(VLOOKUP($A12,'A0 BS 1240在建'!$1:$1048576,5,0),0) -> 0 | D12: =IFERROR(VLOOKUP($A12,'B0 2264預收'!$1:$1048576,5,0),0) -> 0 | E12: =+C12-D12 -> 0 | F12: =IFERROR(VLOOKUP($A12,'B0 2264預收'!$1:$1048576,6,0),0) -> 0 | G12: =+E12-F12 -> 0 | H12: =IFERROR(VLOOKUP($A12,'A0 BS 1240在建'!$1:$1048576,13,0),0) -> 0 | I12: =IFERROR(VLOOKUP($A12,'B0 2264預收'!$1:$1048576,13,0),0) -> 0 | J12: =+H12-I12 -> 0 | K12: =IFERROR(VLOOKUP($A12,'B0 2264預收'!$1:$1048576,14,0),0) -> 0 | L12: =+H12-I12-K12 -> 0 | M12: =H12+IFERROR(VLOOKUP($A12,'A0 BS 1240在建'!$1:$1048576,17,0),0) -> 0 | N12: =I12+IFERROR(VLOOKUP($A12,'B0 2264預收'!$1:$1048576,17,0),0) -> 0 | O12: =+M12-N12 -> 0 | P12: =K12+IFERROR(+VLOOKUP($A12,'B0 2264預收'!$1:$1048576,18,0),0) -> 0 | Q12: =+O12-P12 -> 0 | R12: =M12+IFERROR(VLOOKUP($A12,'A0 BS 1240在建'!$1:$1048576,21,0),0) -> 0 | S12: =+N12+IFERROR(VLOOKUP($A12,'B0 2264預收'!$1:$1048576,21,0),0) -> 0 | T12: =+R12-S12 -> 0 | U12: =+P12+IFERROR(+VLOOKUP($A12,'B0 2264預收'!$1:$1048576,22,0),0) -> 0 | V12: =+T12-U12 -> 0 | W12: =+R12+IFERROR(VLOOKUP($A12,'A0 BS 1240在建'!$1:$1048576,25,0),0) -> 0 | X12: =+S12+IFERROR(VLOOKUP($A12,'B0 2264預收'!$1:$1048576,25,0),0) -> 0 | Y12: =+W12-X12 -> 0 | Z12: =+U12+IFERROR(+VLOOKUP($A12,'B0 2264預收'!$1:$1048576,26,0),0) -> 0 | AA12: =+Y12-Z12 -> 0 | AB12: =+W12+IFERROR(VLOOKUP($A12,'A0 BS 1240在建'!$1:$1048576,29,0),0) -> 0 | AC12: =+X12+IFERROR(VLOOKUP($A12,'B0 2264預收'!$1:$1048576,29,0),0) -> 0 | AD12: =+AB12-AC12 -> 0 | AE12: =+Z12+IFERROR(+VLOOKUP($A12,'B0 2264預收'!$1:$1048576,30,0),0) -> 0 | AF12: =+AD12-AE12 -> 0 | AG12: =+AB12+IFERROR(VLOOKUP($A12,'A0 BS 1240在建'!$1:$1048576,33,0),0) -> 0 | AH12: =+AC12+IFERROR(VLOOKUP($A12,'B0 2264預收'!$1:$1048576,33,0),0) -> 0 | AI12: =+AG12-AH12 -> 0 | AJ12: =+AE12+IFERROR(+VLOOKUP($A12,'B0 2264預收'!$1:$1048576,34,0),0) -> 0 | AK12: =+AI12-AJ12 -> 0 | AL12: =+AG12+IFERROR(VLOOKUP($A12,'A0 BS 1240在建'!$1:$1048576,37,0),0) -> 0 | AM12: =+AH12+IFERROR(VLOOKUP($A12,'B0 2264預收'!$1:$1048576,37,0),0) -> 0 | AN12: =+AL12-AM12 -> 0 | AO12: =+AJ12+IFERROR(+VLOOKUP($A12,'B0 2264預收'!$1:$1048576,38,0),0) -> 0 | AP12: =+AN12-AO12 -> 0 | AQ12: =+AL12+IFERROR(VLOOKUP($A12,'A0 BS 1240在建'!$1:$1048576,41,0),0) -> 0 | AR12: =+AM12+IFERROR(VLOOKUP($A12,'B0 2264預收'!$1:$1048576,41,0),0) -> 0 | AS12: =+AQ12-AR12 -> 0 | AT12: =+AO12+IFERROR(+VLOOKUP($A12,'B0 2264預收'!$1:$1048576,42,0),0) -> 0 | AU12: =+AS12-AT12 -> 0 | AV12: =+AQ12+IFERROR(VLOOKUP($A12,'A0 BS 1240在建'!$1:$1048576,45,0),0) -> 0 | AW12: =+AR12+IFERROR(VLOOKUP($A12,'B0 2264預收'!$1:$1048576,45,0),0) -> 0 | AX12: =+AV12-AW12 -> 0 | AY12: =+AT12+IFERROR(+VLOOKUP($A12,'B0 2264預收'!$1:$1048576,46,0),0) -> 0 | AZ12: =+AX12-AY12 -> 0 | BA12: =+AV12+IFERROR(VLOOKUP($A12,'A0 BS 1240在建'!$1:$1048576,49,0),0) -> 0 | BB12: =+AW12+IFERROR(VLOOKUP($A12,'B0 2264預收'!$1:$1048576,49,0),0) -> 0 | BC12: =+BA12-BB12 -> 0 | BD12: =+AY12+IFERROR(+VLOOKUP($A12,'B0 2264預收'!$1:$1048576,50,0),0) -> 0 | BE12: =+BC12-BD12 -> 0 | BF12: =+BA12+IFERROR(VLOOKUP($A12,'A0 BS 1240在建'!$1:$1048576,53,0),0) -> 0 | BG12: =+BB12+IFERROR(VLOOKUP($A12,'B0 2264預收'!$1:$1048576,53,0),0) -> 0 | BH12: =+BF12-BG12 -> 0 | BI12: =+BD12+IFERROR(+VLOOKUP($A12,'B0 2264預收'!$1:$1048576,54,0),0) -> 0 | BJ12: =+BH12-BI12 -> 0 | BK12: =+BF12+IFERROR(VLOOKUP($A12,'A0 BS 1240在建'!$1:$1048576,57,0),0) -> 0 | BL12: =+BG12+IFERROR(VLOOKUP($A12,'B0 2264預收'!$1:$1048576,57,0),0) -> 0 | BM12: =+BK12-BL12 -> 0 | BN12: =+BI12+IFERROR(+VLOOKUP($A12,'B0 2264預收'!$1:$1048576,58,0),0) -> 0 | BO12: =+BM12-BN12 -> 0 | BP12: =+BK12+IFERROR(VLOOKUP($A12,'A0 BS 1240在建'!$1:$1048576,61,0),0) -> 0 | BQ12: =+BL12+IFERROR(VLOOKUP($A12,'B0 2264預收'!$1:$1048576,61,0),0) -> 0 | BR12: =+BP12-BQ12 -> 0 | BS12: =+BN12+IFERROR(+VLOOKUP($A12,'B0 2264預收'!$1:$1048576,62,0),0) -> 0 | BT12: =+BR12-BS12 -> 0 | BU12: =+IFERROR(VLOOKUP($A12,'A0 BS 1240在建'!$1:$1048576,77,0),0) -> 0 | BV12: =+IFERROR(VLOOKUP($A12,'B0 2264預收'!$1:$1048576,77,0),0) -> 0 | BW12: =+BU12-BV12 -> 0 | BX12: =+IFERROR(+VLOOKUP($A12,'B0 2264預收'!$1:$1048576,78,0),0) -> 0 | BY12: =+BW12-BX12 -> 0 | BZ12: =IFERROR(+VLOOKUP($A12,'A0 BS 1240在建'!$1:$1048576,85,0),0) -> 0 | CA12: =IFERROR(+VLOOKUP($A12,'B0 2264預收'!$1:$1048576,85,0),0) -> 0 | CB12: =+BZ12-CA12 -> 0 | CC12: =+IFERROR(+VLOOKUP($A12,'B0 2264預收'!$1:$1048576,86,0),0) -> 0 | CD12: =+CB12-CC12 -> 0 | CE12: =+IFERROR(VLOOKUP($A12,'A0 BS 1240在建'!$1:$1048576,93,0),0) -> 0 | CF12: =+IFERROR(VLOOKUP($A12,'B0 2264預收'!$1:$1048576,93,0),0) -> 0 | CG12: =+CE12-CF12 -> 0 | CH12: =+IFERROR(+VLOOKUP($A12,'B0 2264預收'!$1:$1048576,94,0),0) -> 0 | CI12: =+CG12-CH12 -> 0 | CJ12: =IFERROR(+VLOOKUP($A12,'A0 BS 1240在建'!$1:$1048576,101,0),0) -> 0 | CK12: =IFERROR(+VLOOKUP($A12,'B0 2264預收'!$1:$1048576,101,0),0) -> 0 | CL12: =+CJ12-CK12 -> 0 | CM12: =+IFERROR(+VLOOKUP($A12,'B0 2264預收'!$1:$1048576,102,0),0) -> 0 | CN12: =+CL12-CM12 -> 0 | CP12: =+J12-E12 -> 0 | CQ12: =-E12 -> 0 | CR12: =+J12 -> 0 | CU12: =+BR12-J12 -> 0 | CW12: =+CU12 -> 0 | CY12: =IF(AND(BR12>0, J12>0), BR12-J12, "") | CZ12: =IF(AND(BR12<0,J12>0),-J12," ") | DA12: =IF(AND(BR12>0,J12<0),BR12," ") | DB12: =IF(AND(L12=0,BR12<0),-BR12," ") | DC12: =SUM(CY12:DB12) -> 0 | DD12: =IF(AND(BR12<0, J12<0), (BR12-J12)*-1, "") | DE12: =IF(AND(BR12<0,J12>0),-BR12," ") | DF12: =IF(AND(BR12>0,J12<0),-J12*-1," ") | DG12: =IF(AND(L12<0,BR12=0),-L12*-1," ") | DH12: =SUM(DD12:DG12) -> 0
A13: C/4190E | B13: 桃園捷運綠線GC03 | C13: =IFERROR(VLOOKUP($A13,'A0 BS 1240在建'!$1:$1048576,5,0),0) -> 0 | D13: =IFERROR(VLOOKUP($A13,'B0 2264預收'!$1:$1048576,5,0),0) -> 0 | E13: =+C13-D13 -> 0 | F13: =IFERROR(VLOOKUP($A13,'B0 2264預收'!$1:$1048576,6,0),0) -> 0 | G13: =+E13-F13 -> 0 | H13: =IFERROR(VLOOKUP($A13,'A0 BS 1240在建'!$1:$1048576,13,0),0) -> 0 | I13: =IFERROR(VLOOKUP($A13,'B0 2264預收'!$1:$1048576,13,0),0) -> 0 | J13: =+H13-I13 -> 0 | K13: =IFERROR(VLOOKUP($A13,'B0 2264預收'!$1:$1048576,14,0),0) -> 0 | L13: =+H13-I13-K13 -> 0 | M13: =H13+IFERROR(VLOOKUP($A13,'A0 BS 1240在建'!$1:$1048576,17,0),0) -> 0 | N13: =I13+IFERROR(VLOOKUP($A13,'B0 2264預收'!$1:$1048576,17,0),0) -> 0 | O13: =+M13-N13 -> 0 | P13: =K13+IFERROR(+VLOOKUP($A13,'B0 2264預收'!$1:$1048576,18,0),0) -> 0 | Q13: =+O13-P13 -> 0 | R13: =M13+IFERROR(VLOOKUP($A13,'A0 BS 1240在建'!$1:$1048576,21,0),0) -> 0 | S13: =+N13+IFERROR(VLOOKUP($A13,'B0 2264預收'!$1:$1048576,21,0),0) -> 0 | T13: =+R13-S13 -> 0 | U13: =+P13+IFERROR(+VLOOKUP($A13,'B0 2264預收'!$1:$1048576,22,0),0) -> 0 | V13: =+T13-U13 -> 0 | W13: =+R13+IFERROR(VLOOKUP($A13,'A0 BS 1240在建'!$1:$1048576,25,0),0) -> 0 | X13: =+S13+IFERROR(VLOOKUP($A13,'B0 2264預收'!$1:$1048576,25,0),0) -> 0 | Y13: =+W13-X13 -> 0 | Z13: =+U13+IFERROR(+VLOOKUP($A13,'B0 2264預收'!$1:$1048576,26,0),0) -> 0 | AA13: =+Y13-Z13 -> 0 | AB13: =+W13+IFERROR(VLOOKUP($A13,'A0 BS 1240在建'!$1:$1048576,29,0),0) -> 0 | AC13: =+X13+IFERROR(VLOOKUP($A13,'B0 2264預收'!$1:$1048576,29,0),0) -> 0 | AD13: =+AB13-AC13 -> 0 | AE13: =+Z13+IFERROR(+VLOOKUP($A13,'B0 2264預收'!$1:$1048576,30,0),0) -> 0 | AF13: =+AD13-AE13 -> 0 | AG13: =+AB13+IFERROR(VLOOKUP($A13,'A0 BS 1240在建'!$1:$1048576,33,0),0) -> 0 | AH13: =+AC13+IFERROR(VLOOKUP($A13,'B0 2264預收'!$1:$1048576,33,0),0) -> 0 | AI13: =+AG13-AH13 -> 0 | AJ13: =+AE13+IFERROR(+VLOOKUP($A13,'B0 2264預收'!$1:$1048576,34,0),0) -> 0 | AK13: =+AI13-AJ13 -> 0 | AL13: =+AG13+IFERROR(VLOOKUP($A13,'A0 BS 1240在建'!$1:$1048576,37,0),0) -> 0 | AM13: =+AH13+IFERROR(VLOOKUP($A13,'B0 2264預收'!$1:$1048576,37,0),0) -> 0 | AN13: =+AL13-AM13 -> 0 | AO13: =+AJ13+IFERROR(+VLOOKUP($A13,'B0 2264預收'!$1:$1048576,38,0),0) -> 0 | AP13: =+AN13-AO13 -> 0 | AQ13: =+AL13+IFERROR(VLOOKUP($A13,'A0 BS 1240在建'!$1:$1048576,41,0),0) -> 0 | AR13: =+AM13+IFERROR(VLOOKUP($A13,'B0 2264預收'!$1:$1048576,41,0),0) -> 0 | AS13: =+AQ13-AR13 -> 0 | AT13: =+AO13+IFERROR(+VLOOKUP($A13,'B0 2264預收'!$1:$1048576,42,0),0) -> 0 | AU13: =+AS13-AT13 -> 0 | AV13: =+AQ13+IFERROR(VLOOKUP($A13,'A0 BS 1240在建'!$1:$1048576,45,0),0) -> 0 | AW13: =+AR13+IFERROR(VLOOKUP($A13,'B0 2264預收'!$1:$1048576,45,0),0) -> 0 | AX13: =+AV13-AW13 -> 0 | AY13: =+AT13+IFERROR(+VLOOKUP($A13,'B0 2264預收'!$1:$1048576,46,0),0) -> 0 | AZ13: =+AX13-AY13 -> 0 | BA13: =+AV13+IFERROR(VLOOKUP($A13,'A0 BS 1240在建'!$1:$1048576,49,0),0) -> 0 | BB13: =+AW13+IFERROR(VLOOKUP($A13,'B0 2264預收'!$1:$1048576,49,0),0) -> 0 | BC13: =+BA13-BB13 -> 0 | BD13: =+AY13+IFERROR(+VLOOKUP($A13,'B0 2264預收'!$1:$1048576,50,0),0) -> 0 | BE13: =+BC13-BD13 -> 0 | BF13: =+BA13+IFERROR(VLOOKUP($A13,'A0 BS 1240在建'!$1:$1048576,53,0),0) -> 0 | BG13: =+BB13+IFERROR(VLOOKUP($A13,'B0 2264預收'!$1:$1048576,53,0),0) -> 0 | BH13: =+BF13-BG13 -> 0 | BI13: =+BD13+IFERROR(+VLOOKUP($A13,'B0 2264預收'!$1:$1048576,54,0),0) -> 0 | BJ13: =+BH13-BI13 -> 0 | BK13: =+BF13+IFERROR(VLOOKUP($A13,'A0 BS 1240在建'!$1:$1048576,57,0),0) -> 0 | BL13: =+BG13+IFERROR(VLOOKUP($A13,'B0 2264預收'!$1:$1048576,57,0),0) -> 0 | BM13: =+BK13-BL13 -> 0 | BN13: =+BI13+IFERROR(+VLOOKUP($A13,'B0 2264預收'!$1:$1048576,58,0),0) -> 0 | BO13: =+BM13-BN13 -> 0 | BP13: =+BK13+IFERROR(VLOOKUP($A13,'A0 BS 1240在建'!$1:$1048576,61,0),0) -> 0 | BQ13: =+BL13+IFERROR(VLOOKUP($A13,'B0 2264預收'!$1:$1048576,61,0),0) -> 0 | BR13: =+BP13-BQ13 -> 0 | BS13: =+BN13+IFERROR(+VLOOKUP($A13,'B0 2264預收'!$1:$1048576,62,0),0) -> 0 | BT13: =+BR13-BS13 -> 0 | BU13: =+IFERROR(VLOOKUP($A13,'A0 BS 1240在建'!$1:$1048576,77,0),0) -> 0 | BV13: =+IFERROR(VLOOKUP($A13,'B0 2264預收'!$1:$1048576,77,0),0) -> 0 | BW13: =+BU13-BV13 -> 0 | BX13: =+IFERROR(+VLOOKUP($A13,'B0 2264預收'!$1:$1048576,78,0),0) -> 0 | BY13: =+BW13-BX13 -> 0 | BZ13: =IFERROR(+VLOOKUP($A13,'A0 BS 1240在建'!$1:$1048576,85,0),0) -> 0 | CA13: =IFERROR(+VLOOKUP($A13,'B0 2264預收'!$1:$1048576,85,0),0) -> 0 | CB13: =+BZ13-CA13 -> 0 | CC13: =+IFERROR(+VLOOKUP($A13,'B0 2264預收'!$1:$1048576,86,0),0) -> 0 | CD13: =+CB13-CC13 -> 0 | CE13: =+IFERROR(VLOOKUP($A13,'A0 BS 1240在建'!$1:$1048576,93,0),0) -> 0 | CF13: =+IFERROR(VLOOKUP($A13,'B0 2264預收'!$1:$1048576,93,0),0) -> 0 | CG13: =+CE13-CF13 -> 0 | CH13: =+IFERROR(+VLOOKUP($A13,'B0 2264預收'!$1:$1048576,94,0),0) -> 0 | CI13: =+CG13-CH13 -> 0 | CJ13: =IFERROR(+VLOOKUP($A13,'A0 BS 1240在建'!$1:$1048576,101,0),0) -> 0 | CK13: =IFERROR(+VLOOKUP($A13,'B0 2264預收'!$1:$1048576,101,0),0) -> 0 | CL13: =+CJ13-CK13 -> 0 | CM13: =+IFERROR(+VLOOKUP($A13,'B0 2264預收'!$1:$1048576,102,0),0) -> 0 | CN13: =+CL13-CM13 -> 0 | CP13: =+J13-E13 -> 0 | CQ13: =+CP13 -> 0 | CU13: =+BR13-J13 -> 0 | CV13: =-J13 -> 0 | CW13: =+BR13 -> 0 | CY13: =IF(AND(BR13>0, J13>0), BR13-J13, "") | CZ13: =IF(AND(BR13<0,J13>0),-J13," ") | DA13: =IF(AND(BR13>0,J13<0),BR13," ") | DB13: =IF(AND(L13=0,BR13<0),-BR13," ") | DC13: =SUM(CY13:DB13) -> 0 | DD13: =IF(AND(BR13<0, J13<0), (BR13-J13)*-1, "") | DE13: =IF(AND(BR13<0,J13>0),-BR13," ") | DF13: =IF(AND(BR13>0,J13<0),-J13*-1," ") | DG13: =IF(AND(L13<0,BR13=0),-L13*-1," ") | DH13: =SUM(DD13:DG13) -> 0
A14: C/4200F | B14: C003 | C14: =IFERROR(VLOOKUP($A14,'A0 BS 1240在建'!$1:$1048576,5,0),0) -> 0 | D14: =IFERROR(VLOOKUP($A14,'B0 2264預收'!$1:$1048576,5,0),0) -> 0 | E14: =+C14-D14 -> 0 | F14: =IFERROR(VLOOKUP($A14,'B0 2264預收'!$1:$1048576,6,0),0) -> 0 | G14: =+E14-F14 -> 0 | H14: =IFERROR(VLOOKUP($A14,'A0 BS 1240在建'!$1:$1048576,13,0),0) -> 0 | I14: =IFERROR(VLOOKUP($A14,'B0 2264預收'!$1:$1048576,13,0),0) -> 0 | J14: =+H14-I14 -> 0 | K14: =IFERROR(VLOOKUP($A14,'B0 2264預收'!$1:$1048576,14,0),0) -> 0 | L14: =+H14-I14-K14 -> 0 | M14: =H14+IFERROR(VLOOKUP($A14,'A0 BS 1240在建'!$1:$1048576,17,0),0) -> 0 | N14: =I14+IFERROR(VLOOKUP($A14,'B0 2264預收'!$1:$1048576,17,0),0) -> 0 | O14: =+M14-N14 -> 0 | P14: =K14+IFERROR(+VLOOKUP($A14,'B0 2264預收'!$1:$1048576,18,0),0) -> 0 | Q14: =+O14-P14 -> 0 | R14: =M14+IFERROR(VLOOKUP($A14,'A0 BS 1240在建'!$1:$1048576,21,0),0) -> 0 | S14: =+N14+IFERROR(VLOOKUP($A14,'B0 2264預收'!$1:$1048576,21,0),0) -> 0 | T14: =+R14-S14 -> 0 | U14: =+P14+IFERROR(+VLOOKUP($A14,'B0 2264預收'!$1:$1048576,22,0),0) -> 0 | V14: =+T14-U14 -> 0 | W14: =+R14+IFERROR(VLOOKUP($A14,'A0 BS 1240在建'!$1:$1048576,25,0),0) -> 0 | X14: =+S14+IFERROR(VLOOKUP($A14,'B0 2264預收'!$1:$1048576,25,0),0) -> 0 | Y14: =+W14-X14 -> 0 | Z14: =+U14+IFERROR(+VLOOKUP($A14,'B0 2264預收'!$1:$1048576,26,0),0) -> 0 | AA14: =+Y14-Z14 -> 0 | AB14: =+W14+IFERROR(VLOOKUP($A14,'A0 BS 1240在建'!$1:$1048576,29,0),0) -> 0 | AC14: =+X14+IFERROR(VLOOKUP($A14,'B0 2264預收'!$1:$1048576,29,0),0) -> 0 | AD14: =+AB14-AC14 -> 0 | AE14: =+Z14+IFERROR(+VLOOKUP($A14,'B0 2264預收'!$1:$1048576,30,0),0) -> 0 | AF14: =+AD14-AE14 -> 0 | AG14: =+AB14+IFERROR(VLOOKUP($A14,'A0 BS 1240在建'!$1:$1048576,33,0),0) -> 0 | AH14: =+AC14+IFERROR(VLOOKUP($A14,'B0 2264預收'!$1:$1048576,33,0),0) -> 0 | AI14: =+AG14-AH14 -> 0 | AJ14: =+AE14+IFERROR(+VLOOKUP($A14,'B0 2264預收'!$1:$1048576,34,0),0) -> 0 | AK14: =+AI14-AJ14 -> 0 | AL14: =+AG14+IFERROR(VLOOKUP($A14,'A0 BS 1240在建'!$1:$1048576,37,0),0) -> 0 | AM14: =+AH14+IFERROR(VLOOKUP($A14,'B0 2264預收'!$1:$1048576,37,0),0) -> 0 | AN14: =+AL14-AM14 -> 0 | AO14: =+AJ14+IFERROR(+VLOOKUP($A14,'B0 2264預收'!$1:$1048576,38,0),0) -> 0 | AP14: =+AN14-AO14 -> 0 | AQ14: =+AL14+IFERROR(VLOOKUP($A14,'A0 BS 1240在建'!$1:$1048576,41,0),0) -> 0 | AR14: =+AM14+IFERROR(VLOOKUP($A14,'B0 2264預收'!$1:$1048576,41,0),0) -> 0 | AS14: =+AQ14-AR14 -> 0 | AT14: =+AO14+IFERROR(+VLOOKUP($A14,'B0 2264預收'!$1:$1048576,42,0),0) -> 0 | AU14: =+AS14-AT14 -> 0 | AV14: =+AQ14+IFERROR(VLOOKUP($A14,'A0 BS 1240在建'!$1:$1048576,45,0),0) -> 0 | AW14: =+AR14+IFERROR(VLOOKUP($A14,'B0 2264預收'!$1:$1048576,45,0),0) -> 0 | AX14: =+AV14-AW14 -> 0 | AY14: =+AT14+IFERROR(+VLOOKUP($A14,'B0 2264預收'!$1:$1048576,46,0),0) -> 0 | AZ14: =+AX14-AY14 -> 0 | BA14: =+AV14+IFERROR(VLOOKUP($A14,'A0 BS 1240在建'!$1:$1048576,49,0),0) -> 0 | BB14: =+AW14+IFERROR(VLOOKUP($A14,'B0 2264預收'!$1:$1048576,49,0),0) -> 0 | BC14: =+BA14-BB14 -> 0 | BD14: =+AY14+IFERROR(+VLOOKUP($A14,'B0 2264預收'!$1:$1048576,50,0),0) -> 0 | BE14: =+BC14-BD14 -> 0 | BF14: =+BA14+IFERROR(VLOOKUP($A14,'A0 BS 1240在建'!$1:$1048576,53,0),0) -> 0 | BG14: =+BB14+IFERROR(VLOOKUP($A14,'B0 2264預收'!$1:$1048576,53,0),0) -> 0 | BH14: =+BF14-BG14 -> 0 | BI14: =+BD14+IFERROR(+VLOOKUP($A14,'B0 2264預收'!$1:$1048576,54,0),0) -> 0 | BJ14: =+BH14-BI14 -> 0 | BK14: =+BF14+IFERROR(VLOOKUP($A14,'A0 BS 1240在建'!$1:$1048576,57,0),0) -> 0 | BL14: =+BG14+IFERROR(VLOOKUP($A14,'B0 2264預收'!$1:$1048576,57,0),0) -> 0 | BM14: =+BK14-BL14 -> 0 | BN14: =+BI14+IFERROR(+VLOOKUP($A14,'B0 2264預收'!$1:$1048576,58,0),0) -> 0 | BO14: =+BM14-BN14 -> 0 | BP14: =+BK14+IFERROR(VLOOKUP($A14,'A0 BS 1240在建'!$1:$1048576,61,0),0) -> 0 | BQ14: =+BL14+IFERROR(VLOOKUP($A14,'B0 2264預收'!$1:$1048576,61,0),0) -> 0 | BR14: =+BP14-BQ14 -> 0 | BS14: =+BN14+IFERROR(+VLOOKUP($A14,'B0 2264預收'!$1:$1048576,62,0),0) -> 0 | BT14: =+BR14-BS14 -> 0 | BU14: =+IFERROR(VLOOKUP($A14,'A0 BS 1240在建'!$1:$1048576,77,0),0) -> 0 | BV14: =+IFERROR(VLOOKUP($A14,'B0 2264預收'!$1:$1048576,77,0),0) -> 0 | BW14: =+BU14-BV14 -> 0 | BX14: =+IFERROR(+VLOOKUP($A14,'B0 2264預收'!$1:$1048576,78,0),0) -> 0 | BY14: =+BW14-BX14 -> 0 | BZ14: =IFERROR(+VLOOKUP($A14,'A0 BS 1240在建'!$1:$1048576,85,0),0) -> 0 | CA14: =IFERROR(+VLOOKUP($A14,'B0 2264預收'!$1:$1048576,85,0),0) -> 0 | CB14: =+BZ14-CA14 -> 0 | CC14: =+IFERROR(+VLOOKUP($A14,'B0 2264預收'!$1:$1048576,86,0),0) -> 0 | CD14: =+CB14-CC14 -> 0 | CE14: =+IFERROR(VLOOKUP($A14,'A0 BS 1240在建'!$1:$1048576,93,0),0) -> 0 | CF14: =+IFERROR(VLOOKUP($A14,'B0 2264預收'!$1:$1048576,93,0),0) -> 0 | CG14: =+CE14-CF14 -> 0 | CH14: =+IFERROR(+VLOOKUP($A14,'B0 2264預收'!$1:$1048576,94,0),0) -> 0 | CI14: =+CG14-CH14 -> 0 | CJ14: =IFERROR(+VLOOKUP($A14,'A0 BS 1240在建'!$1:$1048576,101,0),0) -> 0 | CK14: =IFERROR(+VLOOKUP($A14,'B0 2264預收'!$1:$1048576,101,0),0) -> 0 | CL14: =+CJ14-CK14 -> 0 | CM14: =+IFERROR(+VLOOKUP($A14,'B0 2264預收'!$1:$1048576,102,0),0) -> 0 | CN14: =+CL14-CM14 -> 0 | CP14: =+J14-E14 -> 0 | CR14: =+CP14 -> 0 | CU14: =+BR14-J14 -> 0 | CW14: =+CU14 -> 0 | CY14: =IF(AND(BR14>0, J14>0), BR14-J14, "") | CZ14: =IF(AND(BR14<0,J14>0),-J14," ") | DA14: =IF(AND(BR14>0,J14<0),BR14," ") | DB14: =IF(AND(L14=0,BR14<0),-BR14," ") | DC14: =SUM(CY14:DB14) -> 0 | DD14: =IF(AND(BR14<0, J14<0), (BR14-J14)*-1, "") | DE14: =IF(AND(BR14<0,J14>0),-BR14," ") | DF14: =IF(AND(BR14>0,J14<0),-J14*-1," ") | DG14: =IF(AND(L14<0,BR14=0),-L14*-1," ") | DH14: =SUM(DD14:DG14) -> 0
A15: C/4210F | B15: C006 | C15: =IFERROR(VLOOKUP($A15,'A0 BS 1240在建'!$1:$1048576,5,0),0) -> 0 | D15: =IFERROR(VLOOKUP($A15,'B0 2264預收'!$1:$1048576,5,0),0) -> 0 | E15: =+C15-D15 -> 0 | F15: =IFERROR(VLOOKUP($A15,'B0 2264預收'!$1:$1048576,6,0),0) -> 0 | G15: =+E15-F15 -> 0 | H15: =IFERROR(VLOOKUP($A15,'A0 BS 1240在建'!$1:$1048576,13,0),0) -> 0 | I15: =IFERROR(VLOOKUP($A15,'B0 2264預收'!$1:$1048576,13,0),0) -> 0 | J15: =+H15-I15 -> 0 | K15: =IFERROR(VLOOKUP($A15,'B0 2264預收'!$1:$1048576,14,0),0) -> 0 | L15: =+H15-I15-K15 -> 0 | M15: =H15+IFERROR(VLOOKUP($A15,'A0 BS 1240在建'!$1:$1048576,17,0),0) -> 0 | N15: =I15+IFERROR(VLOOKUP($A15,'B0 2264預收'!$1:$1048576,17,0),0) -> 0 | O15: =+M15-N15 -> 0 | P15: =K15+IFERROR(+VLOOKUP($A15,'B0 2264預收'!$1:$1048576,18,0),0) -> 0 | Q15: =+O15-P15 -> 0 | R15: =M15+IFERROR(VLOOKUP($A15,'A0 BS 1240在建'!$1:$1048576,21,0),0) -> 0 | S15: =+N15+IFERROR(VLOOKUP($A15,'B0 2264預收'!$1:$1048576,21,0),0) -> 0 | T15: =+R15-S15 -> 0 | U15: =+P15+IFERROR(+VLOOKUP($A15,'B0 2264預收'!$1:$1048576,22,0),0) -> 0 | V15: =+T15-U15 -> 0 | W15: =+R15+IFERROR(VLOOKUP($A15,'A0 BS 1240在建'!$1:$1048576,25,0),0) -> 0 | X15: =+S15+IFERROR(VLOOKUP($A15,'B0 2264預收'!$1:$1048576,25,0),0) -> 0 | Y15: =+W15-X15 -> 0 | Z15: =+U15+IFERROR(+VLOOKUP($A15,'B0 2264預收'!$1:$1048576,26,0),0) -> 0 | AA15: =+Y15-Z15 -> 0 | AB15: =+W15+IFERROR(VLOOKUP($A15,'A0 BS 1240在建'!$1:$1048576,29,0),0) -> 0 | AC15: =+X15+IFERROR(VLOOKUP($A15,'B0 2264預收'!$1:$1048576,29,0),0) -> 0 | AD15: =+AB15-AC15 -> 0 | AE15: =+Z15+IFERROR(+VLOOKUP($A15,'B0 2264預收'!$1:$1048576,30,0),0) -> 0 | AF15: =+AD15-AE15 -> 0 | AG15: =+AB15+IFERROR(VLOOKUP($A15,'A0 BS 1240在建'!$1:$1048576,33,0),0) -> 0 | AH15: =+AC15+IFERROR(VLOOKUP($A15,'B0 2264預收'!$1:$1048576,33,0),0) -> 0 | AI15: =+AG15-AH15 -> 0 | AJ15: =+AE15+IFERROR(+VLOOKUP($A15,'B0 2264預收'!$1:$1048576,34,0),0) -> 0 | AK15: =+AI15-AJ15 -> 0 | AL15: =+AG15+IFERROR(VLOOKUP($A15,'A0 BS 1240在建'!$1:$1048576,37,0),0) -> 0 | AM15: =+AH15+IFERROR(VLOOKUP($A15,'B0 2264預收'!$1:$1048576,37,0),0) -> 0 | AN15: =+AL15-AM15 -> 0 | AO15: =+AJ15+IFERROR(+VLOOKUP($A15,'B0 2264預收'!$1:$1048576,38,0),0) -> 0 | AP15: =+AN15-AO15 -> 0 | AQ15: =+AL15+IFERROR(VLOOKUP($A15,'A0 BS 1240在建'!$1:$1048576,41,0),0) -> 0 | AR15: =+AM15+IFERROR(VLOOKUP($A15,'B0 2264預收'!$1:$1048576,41,0),0) -> 0 | AS15: =+AQ15-AR15 -> 0 | AT15: =+AO15+IFERROR(+VLOOKUP($A15,'B0 2264預收'!$1:$1048576,42,0),0) -> 0 | AU15: =+AS15-AT15 -> 0 | AV15: =+AQ15+IFERROR(VLOOKUP($A15,'A0 BS 1240在建'!$1:$1048576,45,0),0) -> 0 | AW15: =+AR15+IFERROR(VLOOKUP($A15,'B0 2264預收'!$1:$1048576,45,0),0) -> 0 | AX15: =+AV15-AW15 -> 0 | AY15: =+AT15+IFERROR(+VLOOKUP($A15,'B0 2264預收'!$1:$1048576,46,0),0) -> 0 | AZ15: =+AX15-AY15 -> 0 | BA15: =+AV15+IFERROR(VLOOKUP($A15,'A0 BS 1240在建'!$1:$1048576,49,0),0) -> 0 | BB15: =+AW15+IFERROR(VLOOKUP($A15,'B0 2264預收'!$1:$1048576,49,0),0) -> 0 | BC15: =+BA15-BB15 -> 0 | BD15: =+AY15+IFERROR(+VLOOKUP($A15,'B0 2264預收'!$1:$1048576,50,0),0) -> 0 | BE15: =+BC15-BD15 -> 0 | BF15: =+BA15+IFERROR(VLOOKUP($A15,'A0 BS 1240在建'!$1:$1048576,53,0),0) -> 0 | BG15: =+BB15+IFERROR(VLOOKUP($A15,'B0 2264預收'!$1:$1048576,53,0),0) -> 0 | BH15: =+BF15-BG15 -> 0 | BI15: =+BD15+IFERROR(+VLOOKUP($A15,'B0 2264預收'!$1:$1048576,54,0),0) -> 0 | BJ15: =+BH15-BI15 -> 0 | BK15: =+BF15+IFERROR(VLOOKUP($A15,'A0 BS 1240在建'!$1:$1048576,57,0),0) -> 0 | BL15: =+BG15+IFERROR(VLOOKUP($A15,'B0 2264預收'!$1:$1048576,57,0),0) -> 0 | BM15: =+BK15-BL15 -> 0 | BN15: =+BI15+IFERROR(+VLOOKUP($A15,'B0 2264預收'!$1:$1048576,58,0),0) -> 0 | BO15: =+BM15-BN15 -> 0 | BP15: =+BK15+IFERROR(VLOOKUP($A15,'A0 BS 1240在建'!$1:$1048576,61,0),0) -> 0 | BQ15: =+BL15+IFERROR(VLOOKUP($A15,'B0 2264預收'!$1:$1048576,61,0),0) -> 0 | BR15: =+BP15-BQ15 -> 0 | BS15: =+BN15+IFERROR(+VLOOKUP($A15,'B0 2264預收'!$1:$1048576,62,0),0) -> 0 | BT15: =+BR15-BS15 -> 0 | BU15: =+IFERROR(VLOOKUP($A15,'A0 BS 1240在建'!$1:$1048576,77,0),0) -> 0 | BV15: =+IFERROR(VLOOKUP($A15,'B0 2264預收'!$1:$1048576,77,0),0) -> 0 | BW15: =+BU15-BV15 -> 0 | BX15: =+IFERROR(+VLOOKUP($A15,'B0 2264預收'!$1:$1048576,78,0),0) -> 0 | BY15: =+BW15-BX15 -> 0 | BZ15: =IFERROR(+VLOOKUP($A15,'A0 BS 1240在建'!$1:$1048576,85,0),0) -> 0 | CA15: =IFERROR(+VLOOKUP($A15,'B0 2264預收'!$1:$1048576,85,0),0) -> 0 | CB15: =+BZ15-CA15 -> 0 | CC15: =+IFERROR(+VLOOKUP($A15,'B0 2264預收'!$1:$1048576,86,0),0) -> 0 | CD15: =+CB15-CC15 -> 0 | CE15: =+IFERROR(VLOOKUP($A15,'A0 BS 1240在建'!$1:$1048576,93,0),0) -> 0 | CF15: =+IFERROR(VLOOKUP($A15,'B0 2264預收'!$1:$1048576,93,0),0) -> 0 | CG15: =+CE15-CF15 -> 0 | CH15: =+IFERROR(+VLOOKUP($A15,'B0 2264預收'!$1:$1048576,94,0),0) -> 0 | CI15: =+CG15-CH15 -> 0 | CJ15: =IFERROR(+VLOOKUP($A15,'A0 BS 1240在建'!$1:$1048576,101,0),0) -> 0 | CK15: =IFERROR(+VLOOKUP($A15,'B0 2264預收'!$1:$1048576,101,0),0) -> 0 | CL15: =+CJ15-CK15 -> 0 | CM15: =+IFERROR(+VLOOKUP($A15,'B0 2264預收'!$1:$1048576,102,0),0) -> 0 | CN15: =+CL15-CM15 -> 0 | CP15: =+J15-E15 -> 0 | CQ15: =+CP15 -> 0 | CU15: =+BR15-J15 -> 0 | CV15: =+CU15 -> 0 | CY15: =IF(AND(BR15>0, J15>0), BR15-J15, "") | CZ15: =IF(AND(BR15<0,J15>0),-J15," ") | DA15: =IF(AND(BR15>0,J15<0),BR15," ") | DB15: =IF(AND(L15=0,BR15<0),-BR15," ") | DC15: =SUM(CY15:DB15) -> 0 | DD15: =IF(AND(BR15<0, J15<0), (BR15-J15)*-1, "") | DE15: =IF(AND(BR15<0,J15>0),-BR15," ") | DF15: =IF(AND(BR15>0,J15<0),-J15*-1," ") | DG15: =IF(AND(L15<0,BR15=0),-L15*-1," ") | DH15: =SUM(DD15:DG15) -> 0
A16: C/4210L | B16: 北環段CF680C | C16: =IFERROR(VLOOKUP($A16,'A0 BS 1240在建'!$1:$1048576,5,0),0) -> 0 | D16: =IFERROR(VLOOKUP($A16,'B0 2264預收'!$1:$1048576,5,0),0) -> 0 | E16: =+C16-D16 -> 0 | F16: =IFERROR(VLOOKUP($A16,'B0 2264預收'!$1:$1048576,6,0),0) -> 0 | G16: =+E16-F16 -> 0 | H16: =IFERROR(VLOOKUP($A16,'A0 BS 1240在建'!$1:$1048576,13,0),0) -> 0 | I16: =IFERROR(VLOOKUP($A16,'B0 2264預收'!$1:$1048576,13,0),0) -> 0 | J16: =+H16-I16 -> 0 | K16: =IFERROR(VLOOKUP($A16,'B0 2264預收'!$1:$1048576,14,0),0) -> 0 | L16: =+H16-I16-K16 -> 0 | M16: =H16+IFERROR(VLOOKUP($A16,'A0 BS 1240在建'!$1:$1048576,17,0),0) -> 0 | N16: =I16+IFERROR(VLOOKUP($A16,'B0 2264預收'!$1:$1048576,17,0),0) -> 0 | O16: =+M16-N16 -> 0 | P16: =K16+IFERROR(+VLOOKUP($A16,'B0 2264預收'!$1:$1048576,18,0),0) -> 0 | Q16: =+O16-P16 -> 0 | R16: =M16+IFERROR(VLOOKUP($A16,'A0 BS 1240在建'!$1:$1048576,21,0),0) -> 0 | S16: =+N16+IFERROR(VLOOKUP($A16,'B0 2264預收'!$1:$1048576,21,0),0) -> 0 | T16: =+R16-S16 -> 0 | U16: =+P16+IFERROR(+VLOOKUP($A16,'B0 2264預收'!$1:$1048576,22,0),0) -> 0 | V16: =+T16-U16 -> 0 | W16: =+R16+IFERROR(VLOOKUP($A16,'A0 BS 1240在建'!$1:$1048576,25,0),0) -> 0 | X16: =+S16+IFERROR(VLOOKUP($A16,'B0 2264預收'!$1:$1048576,25,0),0) -> 0 | Y16: =+W16-X16 -> 0 | Z16: =+U16+IFERROR(+VLOOKUP($A16,'B0 2264預收'!$1:$1048576,26,0),0) -> 0 | AA16: =+Y16-Z16 -> 0 | AB16: =+W16+IFERROR(VLOOKUP($A16,'A0 BS 1240在建'!$1:$1048576,29,0),0) -> 0 | AC16: =+X16+IFERROR(VLOOKUP($A16,'B0 2264預收'!$1:$1048576,29,0),0) -> 0 | AD16: =+AB16-AC16 -> 0 | AE16: =+Z16+IFERROR(+VLOOKUP($A16,'B0 2264預收'!$1:$1048576,30,0),0) -> 0 | AF16: =+AD16-AE16 -> 0 | AG16: =+AB16+IFERROR(VLOOKUP($A16,'A0 BS 1240在建'!$1:$1048576,33,0),0) -> 0 | AH16: =+AC16+IFERROR(VLOOKUP($A16,'B0 2264預收'!$1:$1048576,33,0),0) -> 0 | AI16: =+AG16-AH16 -> 0 | AJ16: =+AE16+IFERROR(+VLOOKUP($A16,'B0 2264預收'!$1:$1048576,34,0),0) -> 0 | AK16: =+AI16-AJ16 -> 0 | AL16: =+AG16+IFERROR(VLOOKUP($A16,'A0 BS 1240在建'!$1:$1048576,37,0),0) -> 0 | AM16: =+AH16+IFERROR(VLOOKUP($A16,'B0 2264預收'!$1:$1048576,37,0),0) -> 0 | AN16: =+AL16-AM16 -> 0 | AO16: =+AJ16+IFERROR(+VLOOKUP($A16,'B0 2264預收'!$1:$1048576,38,0),0) -> 0 | AP16: =+AN16-AO16 -> 0 | AQ16: =+AL16+IFERROR(VLOOKUP($A16,'A0 BS 1240在建'!$1:$1048576,41,0),0) -> 0 | AR16: =+AM16+IFERROR(VLOOKUP($A16,'B0 2264預收'!$1:$1048576,41,0),0) -> 0 | AS16: =+AQ16-AR16 -> 0 | AT16: =+AO16+IFERROR(+VLOOKUP($A16,'B0 2264預收'!$1:$1048576,42,0),0) -> 0 | AU16: =+AS16-AT16 -> 0 | AV16: =+AQ16+IFERROR(VLOOKUP($A16,'A0 BS 1240在建'!$1:$1048576,45,0),0) -> 0 | AW16: =+AR16+IFERROR(VLOOKUP($A16,'B0 2264預收'!$1:$1048576,45,0),0) -> 0 | AX16: =+AV16-AW16 -> 0 | AY16: =+AT16+IFERROR(+VLOOKUP($A16,'B0 2264預收'!$1:$1048576,46,0),0) -> 0 | AZ16: =+AX16-AY16 -> 0 | BA16: =+AV16+IFERROR(VLOOKUP($A16,'A0 BS 1240在建'!$1:$1048576,49,0),0) -> 0 | BB16: =+AW16+IFERROR(VLOOKUP($A16,'B0 2264預收'!$1:$1048576,49,0),0) -> 0 | BC16: =+BA16-BB16 -> 0 | BD16: =+AY16+IFERROR(+VLOOKUP($A16,'B0 2264預收'!$1:$1048576,50,0),0) -> 0 | BE16: =+BC16-BD16 -> 0 | BF16: =+BA16+IFERROR(VLOOKUP($A16,'A0 BS 1240在建'!$1:$1048576,53,0),0) -> 0 | BG16: =+BB16+IFERROR(VLOOKUP($A16,'B0 2264預收'!$1:$1048576,53,0),0) -> 0 | BH16: =+BF16-BG16 -> 0 | BI16: =+BD16+IFERROR(+VLOOKUP($A16,'B0 2264預收'!$1:$1048576,54,0),0) -> 0 | BJ16: =+BH16-BI16 -> 0 | BK16: =+BF16+IFERROR(VLOOKUP($A16,'A0 BS 1240在建'!$1:$1048576,57,0),0) -> 0 | BL16: =+BG16+IFERROR(VLOOKUP($A16,'B0 2264預收'!$1:$1048576,57,0),0) -> 0 | BM16: =+BK16-BL16 -> 0 | BN16: =+BI16+IFERROR(+VLOOKUP($A16,'B0 2264預收'!$1:$1048576,58,0),0) -> 0 | BO16: =+BM16-BN16 -> 0 | BP16: =+BK16+IFERROR(VLOOKUP($A16,'A0 BS 1240在建'!$1:$1048576,61,0),0) -> 0 | BQ16: =+BL16+IFERROR(VLOOKUP($A16,'B0 2264預收'!$1:$1048576,61,0),0) -> 0 | BR16: =+BP16-BQ16 -> 0 | BS16: =+BN16+IFERROR(+VLOOKUP($A16,'B0 2264預收'!$1:$1048576,62,0),0) -> 0 | BT16: =+BR16-BS16 -> 0 | BU16: =+IFERROR(VLOOKUP($A16,'A0 BS 1240在建'!$1:$1048576,77,0),0) -> 0 | BV16: =+IFERROR(VLOOKUP($A16,'B0 2264預收'!$1:$1048576,77,0),0) -> 0 | BW16: =+BU16-BV16 -> 0 | BX16: =+IFERROR(+VLOOKUP($A16,'B0 2264預收'!$1:$1048576,78,0),0) -> 0 | BY16: =+BW16-BX16 -> 0 | BZ16: =IFERROR(+VLOOKUP($A16,'A0 BS 1240在建'!$1:$1048576,85,0),0) -> 0 | CA16: =IFERROR(+VLOOKUP($A16,'B0 2264預收'!$1:$1048576,85,0),0) -> 0 | CB16: =+BZ16-CA16 -> 0 | CC16: =+IFERROR(+VLOOKUP($A16,'B0 2264預收'!$1:$1048576,86,0),0) -> 0 | CD16: =+CB16-CC16 -> 0 | CE16: =+IFERROR(VLOOKUP($A16,'A0 BS 1240在建'!$1:$1048576,93,0),0) -> 0 | CF16: =+IFERROR(VLOOKUP($A16,'B0 2264預收'!$1:$1048576,93,0),0) -> 0 | CG16: =+CE16-CF16 -> 0 | CH16: =+IFERROR(+VLOOKUP($A16,'B0 2264預收'!$1:$1048576,94,0),0) -> 0 | CI16: =+CG16-CH16 -> 0 | CJ16: =IFERROR(+VLOOKUP($A16,'A0 BS 1240在建'!$1:$1048576,101,0),0) -> 0 | CK16: =IFERROR(+VLOOKUP($A16,'B0 2264預收'!$1:$1048576,101,0),0) -> 0 | CL16: =+CJ16-CK16 -> 0 | CM16: =+IFERROR(+VLOOKUP($A16,'B0 2264預收'!$1:$1048576,102,0),0) -> 0 | CN16: =+CL16-CM16 -> 0 | CP16: =+J16-E16 -> 0 | CQ16: =-E16 -> 0 | CR16: =+J16 -> 0 | CU16: =+BR16-J16 -> 0 | CV16: =+BR16 -> 0 | CW16: =-J16 -> 0 | CY16: =IF(AND(BR16>0, J16>0), BR16-J16, "") | CZ16: =IF(AND(BR16<0,J16>0),-J16," ") | DA16: =IF(AND(BR16>0,J16<0),BR16," ") | DB16: =IF(AND(L16=0,BR16<0),-BR16," ") | DC16: =SUM(CY16:DB16) -> 0 | DD16: =IF(AND(BR16<0, J16<0), (BR16-J16)*-1, "") | DE16: =IF(AND(BR16<0,J16>0),-BR16," ") | DF16: =IF(AND(BR16>0,J16<0),-J16*-1," ") | DG16: =IF(AND(L16<0,BR16=0),-L16*-1," ") | DH16: =SUM(DD16:DG16) -> 0
A17: C/4220C | B17: N-WH過港隧道 | C17: =IFERROR(VLOOKUP($A17,'A0 BS 1240在建'!$1:$1048576,5,0),0) -> 0 | D17: =IFERROR(VLOOKUP($A17,'B0 2264預收'!$1:$1048576,5,0),0) -> 0 | E17: =+C17-D17 -> 0 | F17: =IFERROR(VLOOKUP($A17,'B0 2264預收'!$1:$1048576,6,0),0) -> 0 | G17: =+E17-F17 -> 0 | H17: =IFERROR(VLOOKUP($A17,'A0 BS 1240在建'!$1:$1048576,13,0),0) -> 0 | I17: =IFERROR(VLOOKUP($A17,'B0 2264預收'!$1:$1048576,13,0),0) -> 0 | J17: =+H17-I17 -> 0 | K17: =IFERROR(VLOOKUP($A17,'B0 2264預收'!$1:$1048576,14,0),0) -> 0 | L17: =+H17-I17-K17 -> 0 | M17: =H17+IFERROR(VLOOKUP($A17,'A0 BS 1240在建'!$1:$1048576,17,0),0) -> 0 | N17: =I17+IFERROR(VLOOKUP($A17,'B0 2264預收'!$1:$1048576,17,0),0) -> 0 | O17: =+M17-N17 -> 0 | P17: =K17+IFERROR(+VLOOKUP($A17,'B0 2264預收'!$1:$1048576,18,0),0) -> 0 | Q17: =+O17-P17 -> 0 | R17: =M17+IFERROR(VLOOKUP($A17,'A0 BS 1240在建'!$1:$1048576,21,0),0) -> 0 | S17: =+N17+IFERROR(VLOOKUP($A17,'B0 2264預收'!$1:$1048576,21,0),0) -> 0 | T17: =+R17-S17 -> 0 | U17: =+P17+IFERROR(+VLOOKUP($A17,'B0 2264預收'!$1:$1048576,22,0),0) -> 0 | V17: =+T17-U17 -> 0 | W17: =+R17+IFERROR(VLOOKUP($A17,'A0 BS 1240在建'!$1:$1048576,25,0),0) -> 0 | X17: =+S17+IFERROR(VLOOKUP($A17,'B0 2264預收'!$1:$1048576,25,0),0) -> 0 | Y17: =+W17-X17 -> 0 | Z17: =+U17+IFERROR(+VLOOKUP($A17,'B0 2264預收'!$1:$1048576,26,0),0) -> 0 | AA17: =+Y17-Z17 -> 0 | AB17: =+W17+IFERROR(VLOOKUP($A17,'A0 BS 1240在建'!$1:$1048576,29,0),0) -> 0 | AC17: =+X17+IFERROR(VLOOKUP($A17,'B0 2264預收'!$1:$1048576,29,0),0) -> 0 | AD17: =+AB17-AC17 -> 0 | AE17: =+Z17+IFERROR(+VLOOKUP($A17,'B0 2264預收'!$1:$1048576,30,0),0) -> 0 | AF17: =+AD17-AE17 -> 0 | AG17: =+AB17+IFERROR(VLOOKUP($A17,'A0 BS 1240在建'!$1:$1048576,33,0),0) -> 0 | AH17: =+AC17+IFERROR(VLOOKUP($A17,'B0 2264預收'!$1:$1048576,33,0),0) -> 0 | AI17: =+AG17-AH17 -> 0 | AJ17: =+AE17+IFERROR(+VLOOKUP($A17,'B0 2264預收'!$1:$1048576,34,0),0) -> 0 | AK17: =+AI17-AJ17 -> 0 | AL17: =+AG17+IFERROR(VLOOKUP($A17,'A0 BS 1240在建'!$1:$1048576,37,0),0) -> 0 | AM17: =+AH17+IFERROR(VLOOKUP($A17,'B0 2264預收'!$1:$1048576,37,0),0) -> 0 | AN17: =+AL17-AM17 -> 0 | AO17: =+AJ17+IFERROR(+VLOOKUP($A17,'B0 2264預收'!$1:$1048576,38,0),0) -> 0 | AP17: =+AN17-AO17 -> 0 | AQ17: =+AL17+IFERROR(VLOOKUP($A17,'A0 BS 1240在建'!$1:$1048576,41,0),0) -> 0 | AR17: =+AM17+IFERROR(VLOOKUP($A17,'B0 2264預收'!$1:$1048576,41,0),0) -> 0 | AS17: =+AQ17-AR17 -> 0 | AT17: =+AO17+IFERROR(+VLOOKUP($A17,'B0 2264預收'!$1:$1048576,42,0),0) -> 0 | AU17: =+AS17-AT17 -> 0 | AV17: =+AQ17+IFERROR(VLOOKUP($A17,'A0 BS 1240在建'!$1:$1048576,45,0),0) -> 0 | AW17: =+AR17+IFERROR(VLOOKUP($A17,'B0 2264預收'!$1:$1048576,45,0),0) -> 0 | AX17: =+AV17-AW17 -> 0 | AY17: =+AT17+IFERROR(+VLOOKUP($A17,'B0 2264預收'!$1:$1048576,46,0),0) -> 0 | AZ17: =+AX17-AY17 -> 0 | BA17: =+AV17+IFERROR(VLOOKUP($A17,'A0 BS 1240在建'!$1:$1048576,49,0),0) -> 0 | BB17: =+AW17+IFERROR(VLOOKUP($A17,'B0 2264預收'!$1:$1048576,49,0),0) -> 0 | BC17: =+BA17-BB17 -> 0 | BD17: =+AY17+IFERROR(+VLOOKUP($A17,'B0 2264預收'!$1:$1048576,50,0),0) -> 0 | BE17: =+BC17-BD17 -> 0 | BF17: =+BA17+IFERROR(VLOOKUP($A17,'A0 BS 1240在建'!$1:$1048576,53,0),0) -> 0 | BG17: =+BB17+IFERROR(VLOOKUP($A17,'B0 2264預收'!$1:$1048576,53,0),0) -> 0 | BH17: =+BF17-BG17 -> 0 | BI17: =+BD17+IFERROR(+VLOOKUP($A17,'B0 2264預收'!$1:$1048576,54,0),0) -> 0 | BJ17: =+BH17-BI17 -> 0 | BK17: =+BF17+IFERROR(VLOOKUP($A17,'A0 BS 1240在建'!$1:$1048576,57,0),0) -> 0 | BL17: =+BG17+IFERROR(VLOOKUP($A17,'B0 2264預收'!$1:$1048576,57,0),0) -> 0 | BM17: =+BK17-BL17 -> 0 | BN17: =+BI17+IFERROR(+VLOOKUP($A17,'B0 2264預收'!$1:$1048576,58,0),0) -> 0 | BO17: =+BM17-BN17 -> 0 | BP17: =+BK17+IFERROR(VLOOKUP($A17,'A0 BS 1240在建'!$1:$1048576,61,0),0) -> 0 | BQ17: =+BL17+IFERROR(VLOOKUP($A17,'B0 2264預收'!$1:$1048576,61,0),0) -> 0 | BR17: =+BP17-BQ17 -> 0 | BS17: =+BN17+IFERROR(+VLOOKUP($A17,'B0 2264預收'!$1:$1048576,62,0),0) -> 0 | BT17: =+BR17-BS17 -> 0 | BU17: =+IFERROR(VLOOKUP($A17,'A0 BS 1240在建'!$1:$1048576,77,0),0) -> 0 | BV17: =+IFERROR(VLOOKUP($A17,'B0 2264預收'!$1:$1048576,77,0),0) -> 0 | BW17: =+BU17-BV17 -> 0 | BX17: =+IFERROR(+VLOOKUP($A17,'B0 2264預收'!$1:$1048576,78,0),0) -> 0 | BY17: =+BW17-BX17 -> 0 | BZ17: =IFERROR(+VLOOKUP($A17,'A0 BS 1240在建'!$1:$1048576,85,0),0) -> 0 | CA17: =IFERROR(+VLOOKUP($A17,'B0 2264預收'!$1:$1048576,85,0),0) -> 0 | CB17: =+BZ17-CA17 -> 0 | CC17: =+IFERROR(+VLOOKUP($A17,'B0 2264預收'!$1:$1048576,86,0),0) -> 0 | CD17: =+CB17-CC17 -> 0 | CE17: =+IFERROR(VLOOKUP($A17,'A0 BS 1240在建'!$1:$1048576,93,0),0) -> 0 | CF17: =+IFERROR(VLOOKUP($A17,'B0 2264預收'!$1:$1048576,93,0),0) -> 0 | CG17: =+CE17-CF17 -> 0 | CH17: =+IFERROR(+VLOOKUP($A17,'B0 2264預收'!$1:$1048576,94,0),0) -> 0 | CI17: =+CG17-CH17 -> 0 | CJ17: =IFERROR(+VLOOKUP($A17,'A0 BS 1240在建'!$1:$1048576,101,0),0) -> 0 | CK17: =IFERROR(+VLOOKUP($A17,'B0 2264預收'!$1:$1048576,101,0),0) -> 0 | CL17: =+CJ17-CK17 -> 0 | CM17: =+IFERROR(+VLOOKUP($A17,'B0 2264預收'!$1:$1048576,102,0),0) -> 0 | CN17: =+CL17-CM17 -> 0 | CP17: =+J17-E17 -> 0 | CQ17: =+CP17 -> 0 | CU17: =+BR17-J17 -> 0 | CV17: =+CU17 -> 0 | CY17: =IF(AND(BR17>0, J17>0), BR17-J17, "") | CZ17: =IF(AND(BR17<0,J17>0),-J17," ") | DA17: =IF(AND(BR17>0,J17<0),BR17," ") | DB17: =IF(AND(L17=0,BR17<0),-BR17," ") | DC17: =SUM(CY17:DB17) -> 0 | DD17: =IF(AND(BR17<0, J17<0), (BR17-J17)*-1, "") | DE17: =IF(AND(BR17<0,J17>0),-BR17," ") | DF17: =IF(AND(BR17>0,J17<0),-J17*-1," ") | DG17: =IF(AND(L17<0,BR17=0),-L17*-1," ") | DH17: =SUM(DD17:DG17) -> 0
A18: C/4230B | B18: CF670A南環段 | C18: =IFERROR(VLOOKUP($A18,'A0 BS 1240在建'!$1:$1048576,5,0),0) -> 0 | D18: =IFERROR(VLOOKUP($A18,'B0 2264預收'!$1:$1048576,5,0),0) -> 0 | E18: =+C18-D18 -> 0 | F18: =IFERROR(VLOOKUP($A18,'B0 2264預收'!$1:$1048576,6,0),0) -> 0 | G18: =+E18-F18 -> 0 | H18: =IFERROR(VLOOKUP($A18,'A0 BS 1240在建'!$1:$1048576,13,0),0) -> 0 | I18: =IFERROR(VLOOKUP($A18,'B0 2264預收'!$1:$1048576,13,0),0) -> 0 | J18: =+H18-I18 -> 0 | K18: =IFERROR(VLOOKUP($A18,'B0 2264預收'!$1:$1048576,14,0),0) -> 0 | L18: =+H18-I18-K18 -> 0 | M18: =H18+IFERROR(VLOOKUP($A18,'A0 BS 1240在建'!$1:$1048576,17,0),0) -> 0 | N18: =I18+IFERROR(VLOOKUP($A18,'B0 2264預收'!$1:$1048576,17,0),0) -> 0 | O18: =+M18-N18 -> 0 | P18: =K18+IFERROR(+VLOOKUP($A18,'B0 2264預收'!$1:$1048576,18,0),0) -> 0 | Q18: =+O18-P18 -> 0 | R18: =M18+IFERROR(VLOOKUP($A18,'A0 BS 1240在建'!$1:$1048576,21,0),0) -> 0 | S18: =+N18+IFERROR(VLOOKUP($A18,'B0 2264預收'!$1:$1048576,21,0),0) -> 0 | T18: =+R18-S18 -> 0 | U18: =+P18+IFERROR(+VLOOKUP($A18,'B0 2264預收'!$1:$1048576,22,0),0) -> 0 | V18: =+T18-U18 -> 0 | W18: =+R18+IFERROR(VLOOKUP($A18,'A0 BS 1240在建'!$1:$1048576,25,0),0) -> 0 | X18: =+S18+IFERROR(VLOOKUP($A18,'B0 2264預收'!$1:$1048576,25,0),0) -> 0 | Y18: =+W18-X18 -> 0 | Z18: =+U18+IFERROR(+VLOOKUP($A18,'B0 2264預收'!$1:$1048576,26,0),0) -> 0 | AA18: =+Y18-Z18 -> 0 | AB18: =+W18+IFERROR(VLOOKUP($A18,'A0 BS 1240在建'!$1:$1048576,29,0),0) -> 0 | AC18: =+X18+IFERROR(VLOOKUP($A18,'B0 2264預收'!$1:$1048576,29,0),0) -> 0 | AD18: =+AB18-AC18 -> 0 | AE18: =+Z18+IFERROR(+VLOOKUP($A18,'B0 2264預收'!$1:$1048576,30,0),0) -> 0 | AF18: =+AD18-AE18 -> 0 | AG18: =+AB18+IFERROR(VLOOKUP($A18,'A0 BS 1240在建'!$1:$1048576,33,0),0) -> 0 | AH18: =+AC18+IFERROR(VLOOKUP($A18,'B0 2264預收'!$1:$1048576,33,0),0) -> 0 | AI18: =+AG18-AH18 -> 0 | AJ18: =+AE18+IFERROR(+VLOOKUP($A18,'B0 2264預收'!$1:$1048576,34,0),0) -> 0 | AK18: =+AI18-AJ18 -> 0 | AL18: =+AG18+IFERROR(VLOOKUP($A18,'A0 BS 1240在建'!$1:$1048576,37,0),0) -> 0 | AM18: =+AH18+IFERROR(VLOOKUP($A18,'B0 2264預收'!$1:$1048576,37,0),0) -> 0 | AN18: =+AL18-AM18 -> 0 | AO18: =+AJ18+IFERROR(+VLOOKUP($A18,'B0 2264預收'!$1:$1048576,38,0),0) -> 0 | AP18: =+AN18-AO18 -> 0 | AQ18: =+AL18+IFERROR(VLOOKUP($A18,'A0 BS 1240在建'!$1:$1048576,41,0),0) -> 0 | AR18: =+AM18+IFERROR(VLOOKUP($A18,'B0 2264預收'!$1:$1048576,41,0),0) -> 0 | AS18: =+AQ18-AR18 -> 0 | AT18: =+AO18+IFERROR(+VLOOKUP($A18,'B0 2264預收'!$1:$1048576,42,0),0) -> 0 | AU18: =+AS18-AT18 -> 0 | AV18: =+AQ18+IFERROR(VLOOKUP($A18,'A0 BS 1240在建'!$1:$1048576,45,0),0) -> 0 | AW18: =+AR18+IFERROR(VLOOKUP($A18,'B0 2264預收'!$1:$1048576,45,0),0) -> 0 | AX18: =+AV18-AW18 -> 0 | AY18: =+AT18+IFERROR(+VLOOKUP($A18,'B0 2264預收'!$1:$1048576,46,0),0) -> 0 | AZ18: =+AX18-AY18 -> 0 | BA18: =+AV18+IFERROR(VLOOKUP($A18,'A0 BS 1240在建'!$1:$1048576,49,0),0) -> 0 | BB18: =+AW18+IFERROR(VLOOKUP($A18,'B0 2264預收'!$1:$1048576,49,0),0) -> 0 | BC18: =+BA18-BB18 -> 0 | BD18: =+AY18+IFERROR(+VLOOKUP($A18,'B0 2264預收'!$1:$1048576,50,0),0) -> 0 | BE18: =+BC18-BD18 -> 0 | BF18: =+BA18+IFERROR(VLOOKUP($A18,'A0 BS 1240在建'!$1:$1048576,53,0),0) -> 0 | BG18: =+BB18+IFERROR(VLOOKUP($A18,'B0 2264預收'!$1:$1048576,53,0),0) -> 0 | BH18: =+BF18-BG18 -> 0 | BI18: =+BD18+IFERROR(+VLOOKUP($A18,'B0 2264預收'!$1:$1048576,54,0),0) -> 0 | BJ18: =+BH18-BI18 -> 0 | BK18: =+BF18+IFERROR(VLOOKUP($A18,'A0 BS 1240在建'!$1:$1048576,57,0),0) -> 0 | BL18: =+BG18+IFERROR(VLOOKUP($A18,'B0 2264預收'!$1:$1048576,57,0),0) -> 0 | BM18: =+BK18-BL18 -> 0 | BN18: =+BI18+IFERROR(+VLOOKUP($A18,'B0 2264預收'!$1:$1048576,58,0),0) -> 0 | BO18: =+BM18-BN18 -> 0 | BP18: =+BK18+IFERROR(VLOOKUP($A18,'A0 BS 1240在建'!$1:$1048576,61,0),0) -> 0 | BQ18: =+BL18+IFERROR(VLOOKUP($A18,'B0 2264預收'!$1:$1048576,61,0),0) -> 0 | BR18: =+BP18-BQ18 -> 0 | BS18: =+BN18+IFERROR(+VLOOKUP($A18,'B0 2264預收'!$1:$1048576,62,0),0) -> 0 | BT18: =+BR18-BS18 -> 0 | BU18: =+IFERROR(VLOOKUP($A18,'A0 BS 1240在建'!$1:$1048576,77,0),0) -> 0 | BV18: =+IFERROR(VLOOKUP($A18,'B0 2264預收'!$1:$1048576,77,0),0) -> 0 | BW18: =+BU18-BV18 -> 0 | BX18: =+IFERROR(+VLOOKUP($A18,'B0 2264預收'!$1:$1048576,78,0),0) -> 0 | BY18: =+BW18-BX18 -> 0 | BZ18: =IFERROR(+VLOOKUP($A18,'A0 BS 1240在建'!$1:$1048576,85,0),0) -> 0 | CA18: =IFERROR(+VLOOKUP($A18,'B0 2264預收'!$1:$1048576,85,0),0) -> 0 | CB18: =+BZ18-CA18 -> 0 | CC18: =+IFERROR(+VLOOKUP($A18,'B0 2264預收'!$1:$1048576,86,0),0) -> 0 | CD18: =+CB18-CC18 -> 0 | CE18: =+IFERROR(VLOOKUP($A18,'A0 BS 1240在建'!$1:$1048576,93,0),0) -> 0 | CF18: =+IFERROR(VLOOKUP($A18,'B0 2264預收'!$1:$1048576,93,0),0) -> 0 | CG18: =+CE18-CF18 -> 0 | CH18: =+IFERROR(+VLOOKUP($A18,'B0 2264預收'!$1:$1048576,94,0),0) -> 0 | CI18: =+CG18-CH18 -> 0 | CJ18: =IFERROR(+VLOOKUP($A18,'A0 BS 1240在建'!$1:$1048576,101,0),0) -> 0 | CK18: =IFERROR(+VLOOKUP($A18,'B0 2264預收'!$1:$1048576,101,0),0) -> 0 | CL18: =+CJ18-CK18 -> 0 | CM18: =+IFERROR(+VLOOKUP($A18,'B0 2264預收'!$1:$1048576,102,0),0) -> 0 | CN18: =+CL18-CM18 -> 0 | CP18: =+J18-E18 -> 0 | CQ18: =+CP18 -> 0 | CU18: =+BR18-J18 -> 0 | CV18: =-J18 -> 0 | CW18: =+BR18 -> 0 | CY18: =IF(AND(BR18>0, J18>0), BR18-J18, "") | CZ18: =IF(AND(BR18<0,J18>0),-J18," ") | DA18: =IF(AND(BR18>0,J18<0),BR18," ") | DB18: =IF(AND(L18=0,BR18<0),-BR18," ") | DC18: =SUM(CY18:DB18) -> 0 | DD18: =IF(AND(BR18<0, J18<0), (BR18-J18)*-1, "") | DE18: =IF(AND(BR18<0,J18>0),-BR18," ") | DF18: =IF(AND(BR18>0,J18<0),-J18*-1," ") | DG18: =IF(AND(L18<0,BR18=0),-L18*-1," ") | DH18: =SUM(DD18:DG18) -> 0
A19: C/4240C | B19: CJ17標桃園鐵路 | C19: =IFERROR(VLOOKUP($A19,'A0 BS 1240在建'!$1:$1048576,5,0),0) -> 0 | D19: =IFERROR(VLOOKUP($A19,'B0 2264預收'!$1:$1048576,5,0),0) -> 0 | E19: =+C19-D19 -> 0 | F19: =IFERROR(VLOOKUP($A19,'B0 2264預收'!$1:$1048576,6,0),0) -> 0 | G19: =+E19-F19 -> 0 | H19: =IFERROR(VLOOKUP($A19,'A0 BS 1240在建'!$1:$1048576,13,0),0) -> 0 | I19: =IFERROR(VLOOKUP($A19,'B0 2264預收'!$1:$1048576,13,0),0) -> 0 | J19: =+H19-I19 -> 0 | K19: =IFERROR(VLOOKUP($A19,'B0 2264預收'!$1:$1048576,14,0),0) -> 0 | L19: =+H19-I19-K19 -> 0 | M19: =H19+IFERROR(VLOOKUP($A19,'A0 BS 1240在建'!$1:$1048576,17,0),0) -> 0 | N19: =I19+IFERROR(VLOOKUP($A19,'B0 2264預收'!$1:$1048576,17,0),0) -> 0 | O19: =+M19-N19 -> 0 | P19: =K19+IFERROR(+VLOOKUP($A19,'B0 2264預收'!$1:$1048576,18,0),0) -> 0 | Q19: =+O19-P19 -> 0 | R19: =M19+IFERROR(VLOOKUP($A19,'A0 BS 1240在建'!$1:$1048576,21,0),0) -> 0 | S19: =+N19+IFERROR(VLOOKUP($A19,'B0 2264預收'!$1:$1048576,21,0),0) -> 0 | T19: =+R19-S19 -> 0 | U19: =+P19+IFERROR(+VLOOKUP($A19,'B0 2264預收'!$1:$1048576,22,0),0) -> 0 | V19: =+T19-U19 -> 0 | W19: =+R19+IFERROR(VLOOKUP($A19,'A0 BS 1240在建'!$1:$1048576,25,0),0) -> 0 | X19: =+S19+IFERROR(VLOOKUP($A19,'B0 2264預收'!$1:$1048576,25,0),0) -> 0 | Y19: =+W19-X19 -> 0 | Z19: =+U19+IFERROR(+VLOOKUP($A19,'B0 2264預收'!$1:$1048576,26,0),0) -> 0 | AA19: =+Y19-Z19 -> 0 | AB19: =+W19+IFERROR(VLOOKUP($A19,'A0 BS 1240在建'!$1:$1048576,29,0),0) -> 0 | AC19: =+X19+IFERROR(VLOOKUP($A19,'B0 2264預收'!$1:$1048576,29,0),0) -> 0 | AD19: =+AB19-AC19 -> 0 | AE19: =+Z19+IFERROR(+VLOOKUP($A19,'B0 2264預收'!$1:$1048576,30,0),0) -> 0 | AF19: =+AD19-AE19 -> 0 | AG19: =+AB19+IFERROR(VLOOKUP($A19,'A0 BS 1240在建'!$1:$1048576,33,0),0) -> 0 | AH19: =+AC19+IFERROR(VLOOKUP($A19,'B0 2264預收'!$1:$1048576,33,0),0) -> 0 | AI19: =+AG19-AH19 -> 0 | AJ19: =+AE19+IFERROR(+VLOOKUP($A19,'B0 2264預收'!$1:$1048576,34,0),0) -> 0 | AK19: =+AI19-AJ19 -> 0 | AL19: =+AG19+IFERROR(VLOOKUP($A19,'A0 BS 1240在建'!$1:$1048576,37,0),0) -> 0 | AM19: =+AH19+IFERROR(VLOOKUP($A19,'B0 2264預收'!$1:$1048576,37,0),0) -> 0 | AN19: =+AL19-AM19 -> 0 | AO19: =+AJ19+IFERROR(+VLOOKUP($A19,'B0 2264預收'!$1:$1048576,38,0),0) -> 0 | AP19: =+AN19-AO19 -> 0 | AQ19: =+AL19+IFERROR(VLOOKUP($A19,'A0 BS 1240在建'!$1:$1048576,41,0),0) -> 0 | AR19: =+AM19+IFERROR(VLOOKUP($A19,'B0 2264預收'!$1:$1048576,41,0),0) -> 0 | AS19: =+AQ19-AR19 -> 0 | AT19: =+AO19+IFERROR(+VLOOKUP($A19,'B0 2264預收'!$1:$1048576,42,0),0) -> 0 | AU19: =+AS19-AT19 -> 0 | AV19: =+AQ19+IFERROR(VLOOKUP($A19,'A0 BS 1240在建'!$1:$1048576,45,0),0) -> 0 | AW19: =+AR19+IFERROR(VLOOKUP($A19,'B0 2264預收'!$1:$1048576,45,0),0) -> 0 | AX19: =+AV19-AW19 -> 0 | AY19: =+AT19+IFERROR(+VLOOKUP($A19,'B0 2264預收'!$1:$1048576,46,0),0) -> 0 | AZ19: =+AX19-AY19 -> 0 | BA19: =+AV19+IFERROR(VLOOKUP($A19,'A0 BS 1240在建'!$1:$1048576,49,0),0) -> 0 | BB19: =+AW19+IFERROR(VLOOKUP($A19,'B0 2264預收'!$1:$1048576,49,0),0) -> 0 | BC19: =+BA19-BB19 -> 0 | BD19: =+AY19+IFERROR(+VLOOKUP($A19,'B0 2264預收'!$1:$1048576,50,0),0) -> 0 | BE19: =+BC19-BD19 -> 0 | BF19: =+BA19+IFERROR(VLOOKUP($A19,'A0 BS 1240在建'!$1:$1048576,53,0),0) -> 0 | BG19: =+BB19+IFERROR(VLOOKUP($A19,'B0 2264預收'!$1:$1048576,53,0),0) -> 0 | BH19: =+BF19-BG19 -> 0 | BI19: =+BD19+IFERROR(+VLOOKUP($A19,'B0 2264預收'!$1:$1048576,54,0),0) -> 0 | BJ19: =+BH19-BI19 -> 0 | BK19: =+BF19+IFERROR(VLOOKUP($A19,'A0 BS 1240在建'!$1:$1048576,57,0),0) -> 0 | BL19: =+BG19+IFERROR(VLOOKUP($A19,'B0 2264預收'!$1:$1048576,57,0),0) -> 0 | BM19: =+BK19-BL19 -> 0 | BN19: =+BI19+IFERROR(+VLOOKUP($A19,'B0 2264預收'!$1:$1048576,58,0),0) -> 0 | BO19: =+BM19-BN19 -> 0 | BP19: =+BK19+IFERROR(VLOOKUP($A19,'A0 BS 1240在建'!$1:$1048576,61,0),0) -> 0 | BQ19: =+BL19+IFERROR(VLOOKUP($A19,'B0 2264預收'!$1:$1048576,61,0),0) -> 0 | BR19: =+BP19-BQ19 -> 0 | BS19: =+BN19+IFERROR(+VLOOKUP($A19,'B0 2264預收'!$1:$1048576,62,0),0) -> 0 | BT19: =+BR19-BS19 -> 0 | BU19: =+IFERROR(VLOOKUP($A19,'A0 BS 1240在建'!$1:$1048576,77,0),0) -> 0 | BV19: =+IFERROR(VLOOKUP($A19,'B0 2264預收'!$1:$1048576,77,0),0) -> 0 | BW19: =+BU19-BV19 -> 0 | BX19: =+IFERROR(+VLOOKUP($A19,'B0 2264預收'!$1:$1048576,78,0),0) -> 0 | BY19: =+BW19-BX19 -> 0 | BZ19: =IFERROR(+VLOOKUP($A19,'A0 BS 1240在建'!$1:$1048576,85,0),0) -> 0 | CA19: =IFERROR(+VLOOKUP($A19,'B0 2264預收'!$1:$1048576,85,0),0) -> 0 | CB19: =+BZ19-CA19 -> 0 | CC19: =+IFERROR(+VLOOKUP($A19,'B0 2264預收'!$1:$1048576,86,0),0) -> 0 | CD19: =+CB19-CC19 -> 0 | CE19: =+IFERROR(VLOOKUP($A19,'A0 BS 1240在建'!$1:$1048576,93,0),0) -> 0 | CF19: =+IFERROR(VLOOKUP($A19,'B0 2264預收'!$1:$1048576,93,0),0) -> 0 | CG19: =+CE19-CF19 -> 0 | CH19: =+IFERROR(+VLOOKUP($A19,'B0 2264預收'!$1:$1048576,94,0),0) -> 0 | CI19: =+CG19-CH19 -> 0 | CJ19: =IFERROR(+VLOOKUP($A19,'A0 BS 1240在建'!$1:$1048576,101,0),0) -> 0 | CK19: =IFERROR(+VLOOKUP($A19,'B0 2264預收'!$1:$1048576,101,0),0) -> 0 | CL19: =+CJ19-CK19 -> 0 | CM19: =+IFERROR(+VLOOKUP($A19,'B0 2264預收'!$1:$1048576,102,0),0) -> 0 | CN19: =+CL19-CM19 -> 0 | CP19: =+J19-E19 -> 0 | CQ19: =+CP19 -> 0 | CU19: =+BR19-J19 -> 0 | CV19: =-J19 -> 0 | CW19: =+BR19 -> 0 | CY19: =IF(AND(BR19>0, J19>0), BR19-J19, "") | CZ19: =IF(AND(BR19<0,J19>0),-J19," ") | DA19: =IF(AND(BR19>0,J19<0),BR19," ") | DB19: =IF(AND(L19=0,BR19<0),-BR19," ") | DC19: =SUM(CY19:DB19) -> 0 | DD19: =IF(AND(BR19<0, J19<0), (BR19-J19)*-1, "") | DE19: =IF(AND(BR19<0,J19>0),-BR19," ") | DF19: =IF(AND(BR19>0,J19<0),-J19*-1," ") | DG19: =IF(AND(L19<0,BR19=0),-L19*-1," ") | DH19: =SUM(DD19:DG19) -> 0
A20: C/4250A | B20: CF690B北環段(JV/CEC51%) | C20: =IFERROR(VLOOKUP($A20,'A0 BS 1240在建'!$1:$1048576,5,0),0) -> 0 | D20: =IFERROR(VLOOKUP($A20,'B0 2264預收'!$1:$1048576,5,0),0) -> 0 | E20: =+C20-D20 -> 0 | F20: =IFERROR(VLOOKUP($A20,'B0 2264預收'!$1:$1048576,6,0),0) -> 0 | G20: =+E20-F20 -> 0 | H20: =IFERROR(VLOOKUP($A20,'A0 BS 1240在建'!$1:$1048576,13,0),0) -> 0 | I20: =IFERROR(VLOOKUP($A20,'B0 2264預收'!$1:$1048576,13,0),0) -> 0 | J20: =+H20-I20 -> 0 | K20: =IFERROR(VLOOKUP($A20,'B0 2264預收'!$1:$1048576,14,0),0) -> 0 | L20: =+H20-I20-K20 -> 0 | M20: =H20+IFERROR(VLOOKUP($A20,'A0 BS 1240在建'!$1:$1048576,17,0),0) -> 0 | N20: =I20+IFERROR(VLOOKUP($A20,'B0 2264預收'!$1:$1048576,17,0),0) -> 0 | O20: =+M20-N20 -> 0 | P20: =K20+IFERROR(+VLOOKUP($A20,'B0 2264預收'!$1:$1048576,18,0),0) -> 0 | Q20: =+O20-P20 -> 0 | R20: =M20+IFERROR(VLOOKUP($A20,'A0 BS 1240在建'!$1:$1048576,21,0),0) -> 0 | S20: =+N20+IFERROR(VLOOKUP($A20,'B0 2264預收'!$1:$1048576,21,0),0) -> 0 | T20: =+R20-S20 -> 0 | U20: =+P20+IFERROR(+VLOOKUP($A20,'B0 2264預收'!$1:$1048576,22,0),0) -> 0 | V20: =+T20-U20 -> 0 | W20: =+R20+IFERROR(VLOOKUP($A20,'A0 BS 1240在建'!$1:$1048576,25,0),0) -> 0 | X20: =+S20+IFERROR(VLOOKUP($A20,'B0 2264預收'!$1:$1048576,25,0),0) -> 0 | Y20: =+W20-X20 -> 0 | Z20: =+U20+IFERROR(+VLOOKUP($A20,'B0 2264預收'!$1:$1048576,26,0),0) -> 0 | AA20: =+Y20-Z20 -> 0 | AB20: =+W20+IFERROR(VLOOKUP($A20,'A0 BS 1240在建'!$1:$1048576,29,0),0) -> 0 | AC20: =+X20+IFERROR(VLOOKUP($A20,'B0 2264預收'!$1:$1048576,29,0),0) -> 0 | AD20: =+AB20-AC20 -> 0 | AE20: =+Z20+IFERROR(+VLOOKUP($A20,'B0 2264預收'!$1:$1048576,30,0),0) -> 0 | AF20: =+AD20-AE20 -> 0 | AG20: =+AB20+IFERROR(VLOOKUP($A20,'A0 BS 1240在建'!$1:$1048576,33,0),0) -> 0 | AH20: =+AC20+IFERROR(VLOOKUP($A20,'B0 2264預收'!$1:$1048576,33,0),0) -> 0 | AI20: =+AG20-AH20 -> 0 | AJ20: =+AE20+IFERROR(+VLOOKUP($A20,'B0 2264預收'!$1:$1048576,34,0),0) -> 0 | AK20: =+AI20-AJ20 -> 0 | AL20: =+AG20+IFERROR(VLOOKUP($A20,'A0 BS 1240在建'!$1:$1048576,37,0),0) -> 0 | AM20: =+AH20+IFERROR(VLOOKUP($A20,'B0 2264預收'!$1:$1048576,37,0),0) -> 0 | AN20: =+AL20-AM20 -> 0 | AO20: =+AJ20+IFERROR(+VLOOKUP($A20,'B0 2264預收'!$1:$1048576,38,0),0) -> 0 | AP20: =+AN20-AO20 -> 0 | AQ20: =+AL20+IFERROR(VLOOKUP($A20,'A0 BS 1240在建'!$1:$1048576,41,0),0) -> 0 | AR20: =+AM20+IFERROR(VLOOKUP($A20,'B0 2264預收'!$1:$1048576,41,0),0) -> 0 | AS20: =+AQ20-AR20 -> 0 | AT20: =+AO20+IFERROR(+VLOOKUP($A20,'B0 2264預收'!$1:$1048576,42,0),0) -> 0 | AU20: =+AS20-AT20 -> 0 | AV20: =+AQ20+IFERROR(VLOOKUP($A20,'A0 BS 1240在建'!$1:$1048576,45,0),0) -> 0 | AW20: =+AR20+IFERROR(VLOOKUP($A20,'B0 2264預收'!$1:$1048576,45,0),0) -> 0 | AX20: =+AV20-AW20 -> 0 | AY20: =+AT20+IFERROR(+VLOOKUP($A20,'B0 2264預收'!$1:$1048576,46,0),0) -> 0 | AZ20: =+AX20-AY20 -> 0 | BA20: =+AV20+IFERROR(VLOOKUP($A20,'A0 BS 1240在建'!$1:$1048576,49,0),0) -> 0 | BB20: =+AW20+IFERROR(VLOOKUP($A20,'B0 2264預收'!$1:$1048576,49,0),0) -> 0 | BC20: =+BA20-BB20 -> 0 | BD20: =+AY20+IFERROR(+VLOOKUP($A20,'B0 2264預收'!$1:$1048576,50,0),0) -> 0 | BE20: =+BC20-BD20 -> 0 | BF20: =+BA20+IFERROR(VLOOKUP($A20,'A0 BS 1240在建'!$1:$1048576,53,0),0) -> 0 | BG20: =+BB20+IFERROR(VLOOKUP($A20,'B0 2264預收'!$1:$1048576,53,0),0) -> 0 | BH20: =+BF20-BG20 -> 0 | BI20: =+BD20+IFERROR(+VLOOKUP($A20,'B0 2264預收'!$1:$1048576,54,0),0) -> 0 | BJ20: =+BH20-BI20 -> 0 | BK20: =+BF20+IFERROR(VLOOKUP($A20,'A0 BS 1240在建'!$1:$1048576,57,0),0) -> 0 | BL20: =+BG20+IFERROR(VLOOKUP($A20,'B0 2264預收'!$1:$1048576,57,0),0) -> 0 | BM20: =+BK20-BL20 -> 0 | BN20: =+BI20+IFERROR(+VLOOKUP($A20,'B0 2264預收'!$1:$1048576,58,0),0) -> 0 | BO20: =+BM20-BN20 -> 0 | BP20: =+BK20+IFERROR(VLOOKUP($A20,'A0 BS 1240在建'!$1:$1048576,61,0),0) -> 0 | BQ20: =+BL20+IFERROR(VLOOKUP($A20,'B0 2264預收'!$1:$1048576,61,0),0) -> 0 | BR20: =+BP20-BQ20 -> 0 | BS20: =+BN20+IFERROR(+VLOOKUP($A20,'B0 2264預收'!$1:$1048576,62,0),0) -> 0 | BT20: =+BR20-BS20 -> 0 | BU20: =+IFERROR(VLOOKUP($A20,'A0 BS 1240在建'!$1:$1048576,77,0),0) -> 0 | BV20: =+IFERROR(VLOOKUP($A20,'B0 2264預收'!$1:$1048576,77,0),0) -> 0 | BW20: =+BU20-BV20 -> 0 | BX20: =+IFERROR(+VLOOKUP($A20,'B0 2264預收'!$1:$1048576,78,0),0) -> 0 | BY20: =+BW20-BX20 -> 0 | BZ20: =IFERROR(+VLOOKUP($A20,'A0 BS 1240在建'!$1:$1048576,85,0),0) -> 0 | CA20: =IFERROR(+VLOOKUP($A20,'B0 2264預收'!$1:$1048576,85,0),0) -> 0 | CB20: =+BZ20-CA20 -> 0 | CC20: =+IFERROR(+VLOOKUP($A20,'B0 2264預收'!$1:$1048576,86,0),0) -> 0 | CD20: =+CB20-CC20 -> 0 | CE20: =+IFERROR(VLOOKUP($A20,'A0 BS 1240在建'!$1:$1048576,93,0),0) -> 0 | CF20: =+IFERROR(VLOOKUP($A20,'B0 2264預收'!$1:$1048576,93,0),0) -> 0 | CG20: =+CE20-CF20 -> 0 | CH20: =+IFERROR(+VLOOKUP($A20,'B0 2264預收'!$1:$1048576,94,0),0) -> 0 | CI20: =+CG20-CH20 -> 0 | CJ20: =IFERROR(+VLOOKUP($A20,'A0 BS 1240在建'!$1:$1048576,101,0),0) -> 0 | CK20: =IFERROR(+VLOOKUP($A20,'B0 2264預收'!$1:$1048576,101,0),0) -> 0 | CL20: =+CJ20-CK20 -> 0 | CM20: =+IFERROR(+VLOOKUP($A20,'B0 2264預收'!$1:$1048576,102,0),0) -> 0 | CN20: =+CL20-CM20 -> 0 | CY20: =IF(AND(BR20>0, J20>0), BR20-J20, "") | CZ20: =IF(AND(BR20<0,J20>0),-J20," ") | DA20: =IF(AND(BR20>0,J20<0),BR20," ") | DB20: =IF(AND(L20=0,BR20<0),-BR20," ") | DC20: =SUM(CY20:DB20) -> 0 | DD20: =IF(AND(BR20<0, J20<0), (BR20-J20)*-1, "") | DE20: =IF(AND(BR20<0,J20>0),-BR20," ") | DF20: =IF(AND(BR20>0,J20<0),-J20*-1," ") | DG20: =IF(AND(L20<0,BR20=0),-L20*-1," ") | DH20: =SUM(DD20:DG20) -> 0
A21: C/4250B | B21: CF670南環段 | C21: =IFERROR(VLOOKUP($A21,'A0 BS 1240在建'!$1:$1048576,5,0),0) -> 0 | D21: =IFERROR(VLOOKUP($A21,'B0 2264預收'!$1:$1048576,5,0),0) -> 0 | E21: =+C21-D21 -> 0 | F21: =IFERROR(VLOOKUP($A21,'B0 2264預收'!$1:$1048576,6,0),0) -> 0 | G21: =+E21-F21 -> 0 | H21: =IFERROR(VLOOKUP($A21,'A0 BS 1240在建'!$1:$1048576,13,0),0) -> 0 | I21: =IFERROR(VLOOKUP($A21,'B0 2264預收'!$1:$1048576,13,0),0) -> 0 | J21: =+H21-I21 -> 0 | K21: =IFERROR(VLOOKUP($A21,'B0 2264預收'!$1:$1048576,14,0),0) -> 0 | L21: =+H21-I21-K21 -> 0 | M21: =H21+IFERROR(VLOOKUP($A21,'A0 BS 1240在建'!$1:$1048576,17,0),0) -> 0 | N21: =I21+IFERROR(VLOOKUP($A21,'B0 2264預收'!$1:$1048576,17,0),0) -> 0 | O21: =+M21-N21 -> 0 | P21: =K21+IFERROR(+VLOOKUP($A21,'B0 2264預收'!$1:$1048576,18,0),0) -> 0 | Q21: =+O21-P21 -> 0 | R21: =M21+IFERROR(VLOOKUP($A21,'A0 BS 1240在建'!$1:$1048576,21,0),0) -> 0 | S21: =+N21+IFERROR(VLOOKUP($A21,'B0 2264預收'!$1:$1048576,21,0),0) -> 0 | T21: =+R21-S21 -> 0 | U21: =+P21+IFERROR(+VLOOKUP($A21,'B0 2264預收'!$1:$1048576,22,0),0) -> 0 | V21: =+T21-U21 -> 0 | W21: =+R21+IFERROR(VLOOKUP($A21,'A0 BS 1240在建'!$1:$1048576,25,0),0) -> 0 | X21: =+S21+IFERROR(VLOOKUP($A21,'B0 2264預收'!$1:$1048576,25,0),0) -> 0 | Y21: =+W21-X21 -> 0 | Z21: =+U21+IFERROR(+VLOOKUP($A21,'B0 2264預收'!$1:$1048576,26,0),0) -> 0 | AA21: =+Y21-Z21 -> 0 | AB21: =+W21+IFERROR(VLOOKUP($A21,'A0 BS 1240在建'!$1:$1048576,29,0),0) -> 0 | AC21: =+X21+IFERROR(VLOOKUP($A21,'B0 2264預收'!$1:$1048576,29,0),0) -> 0 | AD21: =+AB21-AC21 -> 0 | AE21: =+Z21+IFERROR(+VLOOKUP($A21,'B0 2264預收'!$1:$1048576,30,0),0) -> 0 | AF21: =+AD21-AE21 -> 0 | AG21: =+AB21+IFERROR(VLOOKUP($A21,'A0 BS 1240在建'!$1:$1048576,33,0),0) -> 0 | AH21: =+AC21+IFERROR(VLOOKUP($A21,'B0 2264預收'!$1:$1048576,33,0),0) -> 0 | AI21: =+AG21-AH21 -> 0 | AJ21: =+AE21+IFERROR(+VLOOKUP($A21,'B0 2264預收'!$1:$1048576,34,0),0) -> 0 | AK21: =+AI21-AJ21 -> 0 | AL21: =+AG21+IFERROR(VLOOKUP($A21,'A0 BS 1240在建'!$1:$1048576,37,0),0) -> 0 | AM21: =+AH21+IFERROR(VLOOKUP($A21,'B0 2264預收'!$1:$1048576,37,0),0) -> 0 | AN21: =+AL21-AM21 -> 0 | AO21: =+AJ21+IFERROR(+VLOOKUP($A21,'B0 2264預收'!$1:$1048576,38,0),0) -> 0 | AP21: =+AN21-AO21 -> 0 | AQ21: =+AL21+IFERROR(VLOOKUP($A21,'A0 BS 1240在建'!$1:$1048576,41,0),0) -> 0 | AR21: =+AM21+IFERROR(VLOOKUP($A21,'B0 2264預收'!$1:$1048576,41,0),0) -> 0 | AS21: =+AQ21-AR21 -> 0 | AT21: =+AO21+IFERROR(+VLOOKUP($A21,'B0 2264預收'!$1:$1048576,42,0),0) -> 0 | AU21: =+AS21-AT21 -> 0 | AV21: =+AQ21+IFERROR(VLOOKUP($A21,'A0 BS 1240在建'!$1:$1048576,45,0),0) -> 0 | AW21: =+AR21+IFERROR(VLOOKUP($A21,'B0 2264預收'!$1:$1048576,45,0),0) -> 0 | AX21: =+AV21-AW21 -> 0 | AY21: =+AT21+IFERROR(+VLOOKUP($A21,'B0 2264預收'!$1:$1048576,46,0),0) -> 0 | AZ21: =+AX21-AY21 -> 0 | BA21: =+AV21+IFERROR(VLOOKUP($A21,'A0 BS 1240在建'!$1:$1048576,49,0),0) -> 0 | BB21: =+AW21+IFERROR(VLOOKUP($A21,'B0 2264預收'!$1:$1048576,49,0),0) -> 0 | BC21: =+BA21-BB21 -> 0 | BD21: =+AY21+IFERROR(+VLOOKUP($A21,'B0 2264預收'!$1:$1048576,50,0),0) -> 0 | BE21: =+BC21-BD21 -> 0 | BF21: =+BA21+IFERROR(VLOOKUP($A21,'A0 BS 1240在建'!$1:$1048576,53,0),0) -> 0 | BG21: =+BB21+IFERROR(VLOOKUP($A21,'B0 2264預收'!$1:$1048576,53,0),0) -> 0 | BH21: =+BF21-BG21 -> 0 | BI21: =+BD21+IFERROR(+VLOOKUP($A21,'B0 2264預收'!$1:$1048576,54,0),0) -> 0 | BJ21: =+BH21-BI21 -> 0 | BK21: =+BF21+IFERROR(VLOOKUP($A21,'A0 BS 1240在建'!$1:$1048576,57,0),0) -> 0 | BL21: =+BG21+IFERROR(VLOOKUP($A21,'B0 2264預收'!$1:$1048576,57,0),0) -> 0 | BM21: =+BK21-BL21 -> 0 | BN21: =+BI21+IFERROR(+VLOOKUP($A21,'B0 2264預收'!$1:$1048576,58,0),0) -> 0 | BO21: =+BM21-BN21 -> 0 | BP21: =+BK21+IFERROR(VLOOKUP($A21,'A0 BS 1240在建'!$1:$1048576,61,0),0) -> 0 | BQ21: =+BL21+IFERROR(VLOOKUP($A21,'B0 2264預收'!$1:$1048576,61,0),0) -> 0 | BR21: =+BP21-BQ21 -> 0 | BS21: =+BN21+IFERROR(+VLOOKUP($A21,'B0 2264預收'!$1:$1048576,62,0),0) -> 0 | BT21: =+BR21-BS21 -> 0 | BU21: =+IFERROR(VLOOKUP($A21,'A0 BS 1240在建'!$1:$1048576,77,0),0) -> 0 | BV21: =+IFERROR(VLOOKUP($A21,'B0 2264預收'!$1:$1048576,77,0),0) -> 0 | BW21: =+BU21-BV21 -> 0 | BX21: =+IFERROR(+VLOOKUP($A21,'B0 2264預收'!$1:$1048576,78,0),0) -> 0 | BY21: =+BW21-BX21 -> 0 | BZ21: =IFERROR(+VLOOKUP($A21,'A0 BS 1240在建'!$1:$1048576,85,0),0) -> 0 | CA21: =IFERROR(+VLOOKUP($A21,'B0 2264預收'!$1:$1048576,85,0),0) -> 0 | CB21: =+BZ21-CA21 -> 0 | CC21: =+IFERROR(+VLOOKUP($A21,'B0 2264預收'!$1:$1048576,86,0),0) -> 0 | CD21: =+CB21-CC21 -> 0 | CE21: =+IFERROR(VLOOKUP($A21,'A0 BS 1240在建'!$1:$1048576,93,0),0) -> 0 | CF21: =+IFERROR(VLOOKUP($A21,'B0 2264預收'!$1:$1048576,93,0),0) -> 0 | CG21: =+CE21-CF21 -> 0 | CH21: =+IFERROR(+VLOOKUP($A21,'B0 2264預收'!$1:$1048576,94,0),0) -> 0 | CI21: =+CG21-CH21 -> 0 | CJ21: =IFERROR(+VLOOKUP($A21,'A0 BS 1240在建'!$1:$1048576,101,0),0) -> 0 | CK21: =IFERROR(+VLOOKUP($A21,'B0 2264預收'!$1:$1048576,101,0),0) -> 0 | CL21: =+CJ21-CK21 -> 0 | CM21: =+IFERROR(+VLOOKUP($A21,'B0 2264預收'!$1:$1048576,102,0),0) -> 0 | CN21: =+CL21-CM21 -> 0 | CY21: =IF(AND(BR21>0, J21>0), BR21-J21, "") | CZ21: =IF(AND(BR21<0,J21>0),-J21," ") | DA21: =IF(AND(BR21>0,J21<0),BR21," ") | DB21: =IF(AND(L21=0,BR21<0),-BR21," ") | DC21: =SUM(CY21:DB21) -> 0 | DD21: =IF(AND(BR21<0, J21<0), (BR21-J21)*-1, "") | DE21: =IF(AND(BR21<0,J21>0),-BR21," ") | DF21: =IF(AND(BR21>0,J21<0),-J21*-1," ") | DG21: =IF(AND(L21<0,BR21=0),-L21*-1," ") | DH21: =SUM(DD21:DG21) -> 0
A22: C/49990_26 | B22: 新取得工程-2025年 | C22: =IFERROR(VLOOKUP($A22,'A0 BS 1240在建'!$1:$1048576,5,0),0) -> 0 | D22: =IFERROR(VLOOKUP($A22,'B0 2264預收'!$1:$1048576,5,0),0) -> 0 | E22: =+C22-D22 -> 0 | F22: =IFERROR(VLOOKUP($A22,'B0 2264預收'!$1:$1048576,6,0),0) -> 0 | G22: =+E22-F22 -> 0 | H22: =IFERROR(VLOOKUP($A22,'A0 BS 1240在建'!$1:$1048576,13,0),0) -> 0 | I22: =IFERROR(VLOOKUP($A22,'B0 2264預收'!$1:$1048576,13,0),0) -> 0 | J22: =+H22-I22 -> 0 | K22: =IFERROR(VLOOKUP($A22,'B0 2264預收'!$1:$1048576,14,0),0) -> 0 | L22: =+H22-I22-K22 -> 0 | M22: =H22+IFERROR(VLOOKUP($A22,'A0 BS 1240在建'!$1:$1048576,17,0),0) -> 0 | N22: =I22+IFERROR(VLOOKUP($A22,'B0 2264預收'!$1:$1048576,17,0),0) -> 0 | O22: =+M22-N22 -> 0 | P22: =K22+IFERROR(+VLOOKUP($A22,'B0 2264預收'!$1:$1048576,18,0),0) -> 0 | Q22: =+O22-P22 -> 0 | R22: =M22+IFERROR(VLOOKUP($A22,'A0 BS 1240在建'!$1:$1048576,21,0),0) -> 0 | S22: =+N22+IFERROR(VLOOKUP($A22,'B0 2264預收'!$1:$1048576,21,0),0) -> 0 | T22: =+R22-S22 -> 0 | U22: =+P22+IFERROR(+VLOOKUP($A22,'B0 2264預收'!$1:$1048576,22,0),0) -> 0 | V22: =+T22-U22 -> 0 | W22: =+R22+IFERROR(VLOOKUP($A22,'A0 BS 1240在建'!$1:$1048576,25,0),0) -> 0 | X22: =+S22+IFERROR(VLOOKUP($A22,'B0 2264預收'!$1:$1048576,25,0),0) -> 0 | Y22: =+W22-X22 -> 0 | Z22: =+U22+IFERROR(+VLOOKUP($A22,'B0 2264預收'!$1:$1048576,26,0),0) -> 0 | AA22: =+Y22-Z22 -> 0 | AB22: =+W22+IFERROR(VLOOKUP($A22,'A0 BS 1240在建'!$1:$1048576,29,0),0) -> 0 | AC22: =+X22+IFERROR(VLOOKUP($A22,'B0 2264預收'!$1:$1048576,29,0),0) -> 0 | AD22: =+AB22-AC22 -> 0 | AE22: =+Z22+IFERROR(+VLOOKUP($A22,'B0 2264預收'!$1:$1048576,30,0),0) -> 0 | AF22: =+AD22-AE22 -> 0 | AG22: =+AB22+IFERROR(VLOOKUP($A22,'A0 BS 1240在建'!$1:$1048576,33,0),0) -> 0 | AH22: =+AC22+IFERROR(VLOOKUP($A22,'B0 2264預收'!$1:$1048576,33,0),0) -> 0 | AI22: =+AG22-AH22 -> 0 | AJ22: =+AE22+IFERROR(+VLOOKUP($A22,'B0 2264預收'!$1:$1048576,34,0),0) -> 0 | AK22: =+AI22-AJ22 -> 0 | AL22: =+AG22+IFERROR(VLOOKUP($A22,'A0 BS 1240在建'!$1:$1048576,37,0),0) -> 0 | AM22: =+AH22+IFERROR(VLOOKUP($A22,'B0 2264預收'!$1:$1048576,37,0),0) -> 0 | AN22: =+AL22-AM22 -> 0 | AO22: =+AJ22+IFERROR(+VLOOKUP($A22,'B0 2264預收'!$1:$1048576,38,0),0) -> 0 | AP22: =+AN22-AO22 -> 0 | AQ22: =+AL22+IFERROR(VLOOKUP($A22,'A0 BS 1240在建'!$1:$1048576,41,0),0) -> 0 | AR22: =+AM22+IFERROR(VLOOKUP($A22,'B0 2264預收'!$1:$1048576,41,0),0) -> 0 | AS22: =+AQ22-AR22 -> 0 | AT22: =+AO22+IFERROR(+VLOOKUP($A22,'B0 2264預收'!$1:$1048576,42,0),0) -> 0 | AU22: =+AS22-AT22 -> 0 | AV22: =+AQ22+IFERROR(VLOOKUP($A22,'A0 BS 1240在建'!$1:$1048576,45,0),0) -> 0 | AW22: =+AR22+IFERROR(VLOOKUP($A22,'B0 2264預收'!$1:$1048576,45,0),0) -> 0 | AX22: =+AV22-AW22 -> 0 | AY22: =+AT22+IFERROR(+VLOOKUP($A22,'B0 2264預收'!$1:$1048576,46,0),0) -> 0 | AZ22: =+AX22-AY22 -> 0 | BA22: =+AV22+IFERROR(VLOOKUP($A22,'A0 BS 1240在建'!$1:$1048576,49,0),0) -> 0 | BB22: =+AW22+IFERROR(VLOOKUP($A22,'B0 2264預收'!$1:$1048576,49,0),0) -> 0 | BC22: =+BA22-BB22 -> 0 | BD22: =+AY22+IFERROR(+VLOOKUP($A22,'B0 2264預收'!$1:$1048576,50,0),0) -> 0 | BE22: =+BC22-BD22 -> 0 | BF22: =+BA22+IFERROR(VLOOKUP($A22,'A0 BS 1240在建'!$1:$1048576,53,0),0) -> 0 | BG22: =+BB22+IFERROR(VLOOKUP($A22,'B0 2264預收'!$1:$1048576,53,0),0) -> 0 | BH22: =+BF22-BG22 -> 0 | BI22: =+BD22+IFERROR(+VLOOKUP($A22,'B0 2264預收'!$1:$1048576,54,0),0) -> 0 | BJ22: =+BH22-BI22 -> 0 | BK22: =+BF22+IFERROR(VLOOKUP($A22,'A0 BS 1240在建'!$1:$1048576,57,0),0) -> 0 | BL22: =+BG22+IFERROR(VLOOKUP($A22,'B0 2264預收'!$1:$1048576,57,0),0) -> 0 | BM22: =+BK22-BL22 -> 0 | BN22: =+BI22+IFERROR(+VLOOKUP($A22,'B0 2264預收'!$1:$1048576,58,0),0) -> 0 | BO22: =+BM22-BN22 -> 0 | BP22: =+BK22+IFERROR(VLOOKUP($A22,'A0 BS 1240在建'!$1:$1048576,61,0),0) -> 0 | BQ22: =+BL22+IFERROR(VLOOKUP($A22,'B0 2264預收'!$1:$1048576,61,0),0) -> 0 | BR22: =+BP22-BQ22 -> 0 | BS22: =+BN22+IFERROR(+VLOOKUP($A22,'B0 2264預收'!$1:$1048576,62,0),0) -> 0 | BT22: =+BR22-BS22 -> 0 | BU22: =+IFERROR(VLOOKUP($A22,'A0 BS 1240在建'!$1:$1048576,77,0),0) -> 0 | BV22: =+IFERROR(VLOOKUP($A22,'B0 2264預收'!$1:$1048576,77,0),0) -> 0 | BW22: =+BU22-BV22 -> 0 | BX22: =+IFERROR(+VLOOKUP($A22,'B0 2264預收'!$1:$1048576,78,0),0) -> 0 | BY22: =+BW22-BX22 -> 0 | BZ22: =IFERROR(+VLOOKUP($A22,'A0 BS 1240在建'!$1:$1048576,85,0),0) -> 0 | CA22: =IFERROR(+VLOOKUP($A22,'B0 2264預收'!$1:$1048576,85,0),0) -> 0 | CB22: =+BZ22-CA22 -> 0 | CC22: =+IFERROR(+VLOOKUP($A22,'B0 2264預收'!$1:$1048576,86,0),0) -> 0 | CD22: =+CB22-CC22 -> 0 | CE22: =+IFERROR(VLOOKUP($A22,'A0 BS 1240在建'!$1:$1048576,93,0),0) -> 0 | CF22: =+IFERROR(VLOOKUP($A22,'B0 2264預收'!$1:$1048576,93,0),0) -> 0 | CG22: =+CE22-CF22 -> 0 | CH22: =+IFERROR(+VLOOKUP($A22,'B0 2264預收'!$1:$1048576,94,0),0) -> 0 | CI22: =+CG22-CH22 -> 0 | CJ22: =IFERROR(+VLOOKUP($A22,'A0 BS 1240在建'!$1:$1048576,101,0),0) -> 0 | CK22: =IFERROR(+VLOOKUP($A22,'B0 2264預收'!$1:$1048576,101,0),0) -> 0 | CL22: =+CJ22-CK22 -> 0 | CM22: =+IFERROR(+VLOOKUP($A22,'B0 2264預收'!$1:$1048576,102,0),0) -> 0 | CN22: =+CL22-CM22 -> 0 | CP22: =+J22-E22 -> 0 | CU22: =+BR22-J22 -> 0 | CY22: =IF(AND(BR22>0, J22>0), BR22-J22, "") | CZ22: =IF(AND(BR22<0,J22>0),-J22," ") | DA22: =IF(AND(BR22>0,J22<0),BR22," ") | DB22: =IF(AND(L22=0,BR22<0),-BR22," ") | DC22: =SUM(CY22:DB22) -> 0 | DD22: =IF(AND(BR22<0, J22<0), (BR22-J22)*-1, "") | DE22: =IF(AND(BR22<0,J22>0),-BR22," ") | DF22: =IF(AND(BR22>0,J22<0),-J22*-1," ") | DG22: =IF(AND(L22<0,BR22=0),-L22*-1," ") | DH22: =SUM(DD22:DG22) -> 0
A23: C/49991_26 | B23: 新取得工程-2026年 | C23: =IFERROR(VLOOKUP($A23,'A0 BS 1240在建'!$1:$1048576,5,0),0) -> 0 | D23: =IFERROR(VLOOKUP($A23,'B0 2264預收'!$1:$1048576,5,0),0) -> 0 | E23: =+C23-D23 -> 0 | F23: =IFERROR(VLOOKUP($A23,'B0 2264預收'!$1:$1048576,6,0),0) -> 0 | G23: =+E23-F23 -> 0 | H23: =IFERROR(VLOOKUP($A23,'A0 BS 1240在建'!$1:$1048576,13,0),0) -> 0 | I23: =IFERROR(VLOOKUP($A23,'B0 2264預收'!$1:$1048576,13,0),0) -> 0 | J23: =+H23-I23 -> 0 | K23: =IFERROR(VLOOKUP($A23,'B0 2264預收'!$1:$1048576,14,0),0) -> 0 | L23: =+H23-I23-K23 -> 0 | M23: =H23+IFERROR(VLOOKUP($A23,'A0 BS 1240在建'!$1:$1048576,17,0),0) -> 0 | N23: =I23+IFERROR(VLOOKUP($A23,'B0 2264預收'!$1:$1048576,17,0),0) -> 0 | O23: =+M23-N23 -> 0 | P23: =K23+IFERROR(+VLOOKUP($A23,'B0 2264預收'!$1:$1048576,18,0),0) -> 0 | Q23: =+O23-P23 -> 0 | R23: =M23+IFERROR(VLOOKUP($A23,'A0 BS 1240在建'!$1:$1048576,21,0),0) -> 0 | S23: =+N23+IFERROR(VLOOKUP($A23,'B0 2264預收'!$1:$1048576,21,0),0) -> 0 | T23: =+R23-S23 -> 0 | U23: =+P23+IFERROR(+VLOOKUP($A23,'B0 2264預收'!$1:$1048576,22,0),0) -> 0 | V23: =+T23-U23 -> 0 | W23: =+R23+IFERROR(VLOOKUP($A23,'A0 BS 1240在建'!$1:$1048576,25,0),0) -> 0 | X23: =+S23+IFERROR(VLOOKUP($A23,'B0 2264預收'!$1:$1048576,25,0),0) -> 0 | Y23: =+W23-X23 -> 0 | Z23: =+U23+IFERROR(+VLOOKUP($A23,'B0 2264預收'!$1:$1048576,26,0),0) -> 0 | AA23: =+Y23-Z23 -> 0 | AB23: =+W23+IFERROR(VLOOKUP($A23,'A0 BS 1240在建'!$1:$1048576,29,0),0) -> 0 | AC23: =+X23+IFERROR(VLOOKUP($A23,'B0 2264預收'!$1:$1048576,29,0),0) -> 0 | AD23: =+AB23-AC23 -> 0 | AE23: =+Z23+IFERROR(+VLOOKUP($A23,'B0 2264預收'!$1:$1048576,30,0),0) -> 0 | AF23: =+AD23-AE23 -> 0 | AG23: =+AB23+IFERROR(VLOOKUP($A23,'A0 BS 1240在建'!$1:$1048576,33,0),0) -> 0 | AH23: =+AC23+IFERROR(VLOOKUP($A23,'B0 2264預收'!$1:$1048576,33,0),0) -> 0 | AI23: =+AG23-AH23 -> 0 | AJ23: =+AE23+IFERROR(+VLOOKUP($A23,'B0 2264預收'!$1:$1048576,34,0),0) -> 0 | AK23: =+AI23-AJ23 -> 0 | AL23: =+AG23+IFERROR(VLOOKUP($A23,'A0 BS 1240在建'!$1:$1048576,37,0),0) -> 0 | AM23: =+AH23+IFERROR(VLOOKUP($A23,'B0 2264預收'!$1:$1048576,37,0),0) -> 0 | AN23: =+AL23-AM23 -> 0 | AO23: =+AJ23+IFERROR(+VLOOKUP($A23,'B0 2264預收'!$1:$1048576,38,0),0) -> 0 | AP23: =+AN23-AO23 -> 0 | AQ23: =+AL23+IFERROR(VLOOKUP($A23,'A0 BS 1240在建'!$1:$1048576,41,0),0) -> 0 | AR23: =+AM23+IFERROR(VLOOKUP($A23,'B0 2264預收'!$1:$1048576,41,0),0) -> 0 | AS23: =+AQ23-AR23 -> 0 | AT23: =+AO23+IFERROR(+VLOOKUP($A23,'B0 2264預收'!$1:$1048576,42,0),0) -> 0 | AU23: =+AS23-AT23 -> 0 | AV23: =+AQ23+IFERROR(VLOOKUP($A23,'A0 BS 1240在建'!$1:$1048576,45,0),0) -> 0 | AW23: =+AR23+IFERROR(VLOOKUP($A23,'B0 2264預收'!$1:$1048576,45,0),0) -> 0 | AX23: =+AV23-AW23 -> 0 | AY23: =+AT23+IFERROR(+VLOOKUP($A23,'B0 2264預收'!$1:$1048576,46,0),0) -> 0 | AZ23: =+AX23-AY23 -> 0 | BA23: =+AV23+IFERROR(VLOOKUP($A23,'A0 BS 1240在建'!$1:$1048576,49,0),0) -> 0 | BB23: =+AW23+IFERROR(VLOOKUP($A23,'B0 2264預收'!$1:$1048576,49,0),0) -> 0 | BC23: =+BA23-BB23 -> 0 | BD23: =+AY23+IFERROR(+VLOOKUP($A23,'B0 2264預收'!$1:$1048576,50,0),0) -> 0 | BE23: =+BC23-BD23 -> 0 | BF23: =+BA23+IFERROR(VLOOKUP($A23,'A0 BS 1240在建'!$1:$1048576,53,0),0) -> 0 | BG23: =+BB23+IFERROR(VLOOKUP($A23,'B0 2264預收'!$1:$1048576,53,0),0) -> 0 | BH23: =+BF23-BG23 -> 0 | BI23: =+BD23+IFERROR(+VLOOKUP($A23,'B0 2264預收'!$1:$1048576,54,0),0) -> 0 | BJ23: =+BH23-BI23 -> 0 | BK23: =+BF23+IFERROR(VLOOKUP($A23,'A0 BS 1240在建'!$1:$1048576,57,0),0) -> 0 | BL23: =+BG23+IFERROR(VLOOKUP($A23,'B0 2264預收'!$1:$1048576,57,0),0) -> 0 | BM23: =+BK23-BL23 -> 0 | BN23: =+BI23+IFERROR(+VLOOKUP($A23,'B0 2264預收'!$1:$1048576,58,0),0) -> 0 | BO23: =+BM23-BN23 -> 0 | BP23: =+BK23+IFERROR(VLOOKUP($A23,'A0 BS 1240在建'!$1:$1048576,61,0),0) -> 0 | BQ23: =+BL23+IFERROR(VLOOKUP($A23,'B0 2264預收'!$1:$1048576,61,0),0) -> 0 | BR23: =+BP23-BQ23 -> 0 | BS23: =+BN23+IFERROR(+VLOOKUP($A23,'B0 2264預收'!$1:$1048576,62,0),0) -> 0 | BT23: =+BR23-BS23 -> 0 | BU23: =+IFERROR(VLOOKUP($A23,'A0 BS 1240在建'!$1:$1048576,77,0),0) -> 0 | BV23: =+IFERROR(VLOOKUP($A23,'B0 2264預收'!$1:$1048576,77,0),0) -> 0 | BW23: =+BU23-BV23 -> 0 | BX23: =+IFERROR(+VLOOKUP($A23,'B0 2264預收'!$1:$1048576,78,0),0) -> 0 | BY23: =+BW23-BX23 -> 0 | BZ23: =IFERROR(+VLOOKUP($A23,'A0 BS 1240在建'!$1:$1048576,85,0),0) -> 0 | CA23: =IFERROR(+VLOOKUP($A23,'B0 2264預收'!$1:$1048576,85,0),0) -> 0 | CB23: =+BZ23-CA23 -> 0 | CC23: =+IFERROR(+VLOOKUP($A23,'B0 2264預收'!$1:$1048576,86,0),0) -> 0 | CD23: =+CB23-CC23 -> 0 | CE23: =+IFERROR(VLOOKUP($A23,'A0 BS 1240在建'!$1:$1048576,93,0),0) -> 0 | CF23: =+IFERROR(VLOOKUP($A23,'B0 2264預收'!$1:$1048576,93,0),0) -> 0 | CG23: =+CE23-CF23 -> 0 | CH23: =+IFERROR(+VLOOKUP($A23,'B0 2264預收'!$1:$1048576,94,0),0) -> 0 | CI23: =+CG23-CH23 -> 0 | CJ23: =IFERROR(+VLOOKUP($A23,'A0 BS 1240在建'!$1:$1048576,101,0),0) -> 0 | CK23: =IFERROR(+VLOOKUP($A23,'B0 2264預收'!$1:$1048576,101,0),0) -> 0 | CL23: =+CJ23-CK23 -> 0 | CM23: =+IFERROR(+VLOOKUP($A23,'B0 2264預收'!$1:$1048576,102,0),0) -> 0 | CN23: =+CL23-CM23 -> 0 | CP23: =+J23-E23 -> 0 | CU23: =+BR23-J23 -> 0 | CV23: =+CU23 -> 0 | CY23: =IF(AND(BR23>0, J23>0), BR23-J23, "") | CZ23: =IF(AND(BR23<0,J23>0),-J23," ") | DA23: =IF(AND(BR23>0,J23<0),BR23," ") | DB23: =IF(AND(L23=0,BR23<0),-BR23," ") | DC23: =SUM(CY23:DB23) -> 0 | DD23: =IF(AND(BR23<0, J23<0), (BR23-J23)*-1, "") | DE23: =IF(AND(BR23<0,J23>0),-BR23," ") | DF23: =IF(AND(BR23>0,J23<0),-J23*-1," ") | DG23: =IF(AND(L23<0,BR23=0),-L23*-1," ") | DH23: =SUM(DD23:DG23) -> 0
A24: C/49992_26 | B24: 新取得工程-2027年 | C24: =IFERROR(VLOOKUP($A24,'A0 BS 1240在建'!$1:$1048576,5,0),0) -> 0 | D24: =IFERROR(VLOOKUP($A24,'B0 2264預收'!$1:$1048576,5,0),0) -> 0 | E24: =+C24-D24 -> 0 | F24: =IFERROR(VLOOKUP($A24,'B0 2264預收'!$1:$1048576,6,0),0) -> 0 | G24: =+E24-F24 -> 0 | H24: =IFERROR(VLOOKUP($A24,'A0 BS 1240在建'!$1:$1048576,13,0),0) -> 0 | I24: =IFERROR(VLOOKUP($A24,'B0 2264預收'!$1:$1048576,13,0),0) -> 0 | J24: =+H24-I24 -> 0 | K24: =IFERROR(VLOOKUP($A24,'B0 2264預收'!$1:$1048576,14,0),0) -> 0 | L24: =+H24-I24-K24 -> 0 | M24: =H24+IFERROR(VLOOKUP($A24,'A0 BS 1240在建'!$1:$1048576,17,0),0) -> 0 | N24: =I24+IFERROR(VLOOKUP($A24,'B0 2264預收'!$1:$1048576,17,0),0) -> 0 | O24: =+M24-N24 -> 0 | P24: =K24+IFERROR(+VLOOKUP($A24,'B0 2264預收'!$1:$1048576,18,0),0) -> 0 | Q24: =+O24-P24 -> 0 | R24: =M24+IFERROR(VLOOKUP($A24,'A0 BS 1240在建'!$1:$1048576,21,0),0) -> 0 | S24: =+N24+IFERROR(VLOOKUP($A24,'B0 2264預收'!$1:$1048576,21,0),0) -> 0 | T24: =+R24-S24 -> 0 | U24: =+P24+IFERROR(+VLOOKUP($A24,'B0 2264預收'!$1:$1048576,22,0),0) -> 0 | V24: =+T24-U24 -> 0 | W24: =+R24+IFERROR(VLOOKUP($A24,'A0 BS 1240在建'!$1:$1048576,25,0),0) -> 0 | X24: =+S24+IFERROR(VLOOKUP($A24,'B0 2264預收'!$1:$1048576,25,0),0) -> 0 | Y24: =+W24-X24 -> 0 | Z24: =+U24+IFERROR(+VLOOKUP($A24,'B0 2264預收'!$1:$1048576,26,0),0) -> 0 | AA24: =+Y24-Z24 -> 0 | AB24: =+W24+IFERROR(VLOOKUP($A24,'A0 BS 1240在建'!$1:$1048576,29,0),0) -> 0 | AC24: =+X24+IFERROR(VLOOKUP($A24,'B0 2264預收'!$1:$1048576,29,0),0) -> 0 | AD24: =+AB24-AC24 -> 0 | AE24: =+Z24+IFERROR(+VLOOKUP($A24,'B0 2264預收'!$1:$1048576,30,0),0) -> 0 | AF24: =+AD24-AE24 -> 0 | AG24: =+AB24+IFERROR(VLOOKUP($A24,'A0 BS 1240在建'!$1:$1048576,33,0),0) -> 0 | AH24: =+AC24+IFERROR(VLOOKUP($A24,'B0 2264預收'!$1:$1048576,33,0),0) -> 0 | AI24: =+AG24-AH24 -> 0 | AJ24: =+AE24+IFERROR(+VLOOKUP($A24,'B0 2264預收'!$1:$1048576,34,0),0) -> 0 | AK24: =+AI24-AJ24 -> 0 | AL24: =+AG24+IFERROR(VLOOKUP($A24,'A0 BS 1240在建'!$1:$1048576,37,0),0) -> 0 | AM24: =+AH24+IFERROR(VLOOKUP($A24,'B0 2264預收'!$1:$1048576,37,0),0) -> 0 | AN24: =+AL24-AM24 -> 0 | AO24: =+AJ24+IFERROR(+VLOOKUP($A24,'B0 2264預收'!$1:$1048576,38,0),0) -> 0 | AP24: =+AN24-AO24 -> 0 | AQ24: =+AL24+IFERROR(VLOOKUP($A24,'A0 BS 1240在建'!$1:$1048576,41,0),0) -> 0 | AR24: =+AM24+IFERROR(VLOOKUP($A24,'B0 2264預收'!$1:$1048576,41,0),0) -> 0 | AS24: =+AQ24-AR24 -> 0 | AT24: =+AO24+IFERROR(+VLOOKUP($A24,'B0 2264預收'!$1:$1048576,42,0),0) -> 0 | AU24: =+AS24-AT24 -> 0 | AV24: =+AQ24+IFERROR(VLOOKUP($A24,'A0 BS 1240在建'!$1:$1048576,45,0),0) -> 0 | AW24: =+AR24+IFERROR(VLOOKUP($A24,'B0 2264預收'!$1:$1048576,45,0),0) -> 0 | AX24: =+AV24-AW24 -> 0 | AY24: =+AT24+IFERROR(+VLOOKUP($A24,'B0 2264預收'!$1:$1048576,46,0),0) -> 0 | AZ24: =+AX24-AY24 -> 0 | BA24: =+AV24+IFERROR(VLOOKUP($A24,'A0 BS 1240在建'!$1:$1048576,49,0),0) -> 0 | BB24: =+AW24+IFERROR(VLOOKUP($A24,'B0 2264預收'!$1:$1048576,49,0),0) -> 0 | BC24: =+BA24-BB24 -> 0 | BD24: =+AY24+IFERROR(+VLOOKUP($A24,'B0 2264預收'!$1:$1048576,50,0),0) -> 0 | BE24: =+BC24-BD24 -> 0 | BF24: =+BA24+IFERROR(VLOOKUP($A24,'A0 BS 1240在建'!$1:$1048576,53,0),0) -> 0 | BG24: =+BB24+IFERROR(VLOOKUP($A24,'B0 2264預收'!$1:$1048576,53,0),0) -> 0 | BH24: =+BF24-BG24 -> 0 | BI24: =+BD24+IFERROR(+VLOOKUP($A24,'B0 2264預收'!$1:$1048576,54,0),0) -> 0 | BJ24: =+BH24-BI24 -> 0 | BK24: =+BF24+IFERROR(VLOOKUP($A24,'A0 BS 1240在建'!$1:$1048576,57,0),0) -> 0 | BL24: =+BG24+IFERROR(VLOOKUP($A24,'B0 2264預收'!$1:$1048576,57,0),0) -> 0 | BM24: =+BK24-BL24 -> 0 | BN24: =+BI24+IFERROR(+VLOOKUP($A24,'B0 2264預收'!$1:$1048576,58,0),0) -> 0 | BO24: =+BM24-BN24 -> 0 | BP24: =+BK24+IFERROR(VLOOKUP($A24,'A0 BS 1240在建'!$1:$1048576,61,0),0) -> 0 | BQ24: =+BL24+IFERROR(VLOOKUP($A24,'B0 2264預收'!$1:$1048576,61,0),0) -> 0 | BR24: =+BP24-BQ24 -> 0 | BS24: =+BN24+IFERROR(+VLOOKUP($A24,'B0 2264預收'!$1:$1048576,62,0),0) -> 0 | BT24: =+BR24-BS24 -> 0 | BU24: =+IFERROR(VLOOKUP($A24,'A0 BS 1240在建'!$1:$1048576,77,0),0) -> 0 | BV24: =+IFERROR(VLOOKUP($A24,'B0 2264預收'!$1:$1048576,77,0),0) -> 0 | BW24: =+BU24-BV24 -> 0 | BX24: =+IFERROR(+VLOOKUP($A24,'B0 2264預收'!$1:$1048576,78,0),0) -> 0 | BY24: =+BW24-BX24 -> 0 | BZ24: =IFERROR(+VLOOKUP($A24,'A0 BS 1240在建'!$1:$1048576,85,0),0) -> 0 | CA24: =IFERROR(+VLOOKUP($A24,'B0 2264預收'!$1:$1048576,85,0),0) -> 0 | CB24: =+BZ24-CA24 -> 0 | CC24: =+IFERROR(+VLOOKUP($A24,'B0 2264預收'!$1:$1048576,86,0),0) -> 0 | CD24: =+CB24-CC24 -> 0 | CE24: =+IFERROR(VLOOKUP($A24,'A0 BS 1240在建'!$1:$1048576,93,0),0) -> 0 | CF24: =+IFERROR(VLOOKUP($A24,'B0 2264預收'!$1:$1048576,93,0),0) -> 0 | CG24: =+CE24-CF24 -> 0 | CH24: =+IFERROR(+VLOOKUP($A24,'B0 2264預收'!$1:$1048576,94,0),0) -> 0 | CI24: =+CG24-CH24 -> 0 | CJ24: =IFERROR(+VLOOKUP($A24,'A0 BS 1240在建'!$1:$1048576,101,0),0) -> 0 | CK24: =IFERROR(+VLOOKUP($A24,'B0 2264預收'!$1:$1048576,101,0),0) -> 0 | CL24: =+CJ24-CK24 -> 0 | CM24: =+IFERROR(+VLOOKUP($A24,'B0 2264預收'!$1:$1048576,102,0),0) -> 0 | CN24: =+CL24-CM24 -> 0 | CP24: =+J24-E24 -> 0 | CU24: =+BR24-J24 -> 0 | CY24: =IF(AND(BR24>0, J24>0), BR24-J24, "") | CZ24: =IF(AND(BR24<0,J24>0),-J24," ") | DA24: =IF(AND(BR24>0,J24<0),BR24," ") | DB24: =IF(AND(L24=0,BR24<0),-BR24," ") | DC24: =SUM(CY24:DB24) -> 0 | DD24: =IF(AND(BR24<0, J24<0), (BR24-J24)*-1, "") | DE24: =IF(AND(BR24<0,J24>0),-BR24," ") | DF24: =IF(AND(BR24>0,J24<0),-J24*-1," ") | DG24: =IF(AND(L24<0,BR24=0),-L24*-1," ") | DH24: =SUM(DD24:DG24) -> 0
A25: C/49993_26 | B25: 新取得工程-2028年 | C25: =IFERROR(VLOOKUP($A25,'A0 BS 1240在建'!$1:$1048576,5,0),0) -> 0 | D25: =IFERROR(VLOOKUP($A25,'B0 2264預收'!$1:$1048576,5,0),0) -> 0 | E25: =+C25-D25 -> 0 | F25: =IFERROR(VLOOKUP($A25,'B0 2264預收'!$1:$1048576,6,0),0) -> 0 | G25: =+E25-F25 -> 0 | H25: =IFERROR(VLOOKUP($A25,'A0 BS 1240在建'!$1:$1048576,13,0),0) -> 0 | I25: =IFERROR(VLOOKUP($A25,'B0 2264預收'!$1:$1048576,13,0),0) -> 0 | J25: =+H25-I25 -> 0 | K25: =IFERROR(VLOOKUP($A25,'B0 2264預收'!$1:$1048576,14,0),0) -> 0 | L25: =+H25-I25-K25 -> 0 | M25: =H25+IFERROR(VLOOKUP($A25,'A0 BS 1240在建'!$1:$1048576,17,0),0) -> 0 | N25: =I25+IFERROR(VLOOKUP($A25,'B0 2264預收'!$1:$1048576,17,0),0) -> 0 | O25: =+M25-N25 -> 0 | P25: =K25+IFERROR(+VLOOKUP($A25,'B0 2264預收'!$1:$1048576,18,0),0) -> 0 | Q25: =+O25-P25 -> 0 | R25: =M25+IFERROR(VLOOKUP($A25,'A0 BS 1240在建'!$1:$1048576,21,0),0) -> 0 | S25: =+N25+IFERROR(VLOOKUP($A25,'B0 2264預收'!$1:$1048576,21,0),0) -> 0 | T25: =+R25-S25 -> 0 | U25: =+P25+IFERROR(+VLOOKUP($A25,'B0 2264預收'!$1:$1048576,22,0),0) -> 0 | V25: =+T25-U25 -> 0 | W25: =+R25+IFERROR(VLOOKUP($A25,'A0 BS 1240在建'!$1:$1048576,25,0),0) -> 0 | X25: =+S25+IFERROR(VLOOKUP($A25,'B0 2264預收'!$1:$1048576,25,0),0) -> 0 | Y25: =+W25-X25 -> 0 | Z25: =+U25+IFERROR(+VLOOKUP($A25,'B0 2264預收'!$1:$1048576,26,0),0) -> 0 | AA25: =+Y25-Z25 -> 0 | AB25: =+W25+IFERROR(VLOOKUP($A25,'A0 BS 1240在建'!$1:$1048576,29,0),0) -> 0 | AC25: =+X25+IFERROR(VLOOKUP($A25,'B0 2264預收'!$1:$1048576,29,0),0) -> 0 | AD25: =+AB25-AC25 -> 0 | AE25: =+Z25+IFERROR(+VLOOKUP($A25,'B0 2264預收'!$1:$1048576,30,0),0) -> 0 | AF25: =+AD25-AE25 -> 0 | AG25: =+AB25+IFERROR(VLOOKUP($A25,'A0 BS 1240在建'!$1:$1048576,33,0),0) -> 0 | AH25: =+AC25+IFERROR(VLOOKUP($A25,'B0 2264預收'!$1:$1048576,33,0),0) -> 0 | AI25: =+AG25-AH25 -> 0 | AJ25: =+AE25+IFERROR(+VLOOKUP($A25,'B0 2264預收'!$1:$1048576,34,0),0) -> 0 | AK25: =+AI25-AJ25 -> 0 | AL25: =+AG25+IFERROR(VLOOKUP($A25,'A0 BS 1240在建'!$1:$1048576,37,0),0) -> 0 | AM25: =+AH25+IFERROR(VLOOKUP($A25,'B0 2264預收'!$1:$1048576,37,0),0) -> 0 | AN25: =+AL25-AM25 -> 0 | AO25: =+AJ25+IFERROR(+VLOOKUP($A25,'B0 2264預收'!$1:$1048576,38,0),0) -> 0 | AP25: =+AN25-AO25 -> 0 | AQ25: =+AL25+IFERROR(VLOOKUP($A25,'A0 BS 1240在建'!$1:$1048576,41,0),0) -> 0 | AR25: =+AM25+IFERROR(VLOOKUP($A25,'B0 2264預收'!$1:$1048576,41,0),0) -> 0 | AS25: =+AQ25-AR25 -> 0 | AT25: =+AO25+IFERROR(+VLOOKUP($A25,'B0 2264預收'!$1:$1048576,42,0),0) -> 0 | AU25: =+AS25-AT25 -> 0 | AV25: =+AQ25+IFERROR(VLOOKUP($A25,'A0 BS 1240在建'!$1:$1048576,45,0),0) -> 0 | AW25: =+AR25+IFERROR(VLOOKUP($A25,'B0 2264預收'!$1:$1048576,45,0),0) -> 0 | AX25: =+AV25-AW25 -> 0 | AY25: =+AT25+IFERROR(+VLOOKUP($A25,'B0 2264預收'!$1:$1048576,46,0),0) -> 0 | AZ25: =+AX25-AY25 -> 0 | BA25: =+AV25+IFERROR(VLOOKUP($A25,'A0 BS 1240在建'!$1:$1048576,49,0),0) -> 0 | BB25: =+AW25+IFERROR(VLOOKUP($A25,'B0 2264預收'!$1:$1048576,49,0),0) -> 0 | BC25: =+BA25-BB25 -> 0 | BD25: =+AY25+IFERROR(+VLOOKUP($A25,'B0 2264預收'!$1:$1048576,50,0),0) -> 0 | BE25: =+BC25-BD25 -> 0 | BF25: =+BA25+IFERROR(VLOOKUP($A25,'A0 BS 1240在建'!$1:$1048576,53,0),0) -> 0 | BG25: =+BB25+IFERROR(VLOOKUP($A25,'B0 2264預收'!$1:$1048576,53,0),0) -> 0 | BH25: =+BF25-BG25 -> 0 | BI25: =+BD25+IFERROR(+VLOOKUP($A25,'B0 2264預收'!$1:$1048576,54,0),0) -> 0 | BJ25: =+BH25-BI25 -> 0 | BK25: =+BF25+IFERROR(VLOOKUP($A25,'A0 BS 1240在建'!$1:$1048576,57,0),0) -> 0 | BL25: =+BG25+IFERROR(VLOOKUP($A25,'B0 2264預收'!$1:$1048576,57,0),0) -> 0 | BM25: =+BK25-BL25 -> 0 | BN25: =+BI25+IFERROR(+VLOOKUP($A25,'B0 2264預收'!$1:$1048576,58,0),0) -> 0 | BO25: =+BM25-BN25 -> 0 | BP25: =+BK25+IFERROR(VLOOKUP($A25,'A0 BS 1240在建'!$1:$1048576,61,0),0) -> 0 | BQ25: =+BL25+IFERROR(VLOOKUP($A25,'B0 2264預收'!$1:$1048576,61,0),0) -> 0 | BR25: =+BP25-BQ25 -> 0 | BS25: =+BN25+IFERROR(+VLOOKUP($A25,'B0 2264預收'!$1:$1048576,62,0),0) -> 0 | BT25: =+BR25-BS25 -> 0 | BU25: =+IFERROR(VLOOKUP($A25,'A0 BS 1240在建'!$1:$1048576,77,0),0) -> 0 | BV25: =+IFERROR(VLOOKUP($A25,'B0 2264預收'!$1:$1048576,77,0),0) -> 0 | BW25: =+BU25-BV25 -> 0 | BX25: =+IFERROR(+VLOOKUP($A25,'B0 2264預收'!$1:$1048576,78,0),0) -> 0 | BY25: =+BW25-BX25 -> 0 | BZ25: =IFERROR(+VLOOKUP($A25,'A0 BS 1240在建'!$1:$1048576,85,0),0) -> 0 | CA25: =IFERROR(+VLOOKUP($A25,'B0 2264預收'!$1:$1048576,85,0),0) -> 0 | CB25: =+BZ25-CA25 -> 0 | CC25: =+IFERROR(+VLOOKUP($A25,'B0 2264預收'!$1:$1048576,86,0),0) -> 0 | CD25: =+CB25-CC25 -> 0 | CE25: =+IFERROR(VLOOKUP($A25,'A0 BS 1240在建'!$1:$1048576,93,0),0) -> 0 | CF25: =+IFERROR(VLOOKUP($A25,'B0 2264預收'!$1:$1048576,93,0),0) -> 0 | CG25: =+CE25-CF25 -> 0 | CH25: =+IFERROR(+VLOOKUP($A25,'B0 2264預收'!$1:$1048576,94,0),0) -> 0 | CI25: =+CG25-CH25 -> 0 | CJ25: =IFERROR(+VLOOKUP($A25,'A0 BS 1240在建'!$1:$1048576,101,0),0) -> 0 | CK25: =IFERROR(+VLOOKUP($A25,'B0 2264預收'!$1:$1048576,101,0),0) -> 0 | CL25: =+CJ25-CK25 -> 0 | CM25: =+IFERROR(+VLOOKUP($A25,'B0 2264預收'!$1:$1048576,102,0),0) -> 0 | CN25: =+CL25-CM25 -> 0 | CP25: =+J25-E25 -> 0 | CU25: =+BR25-J25 -> 0 | CY25: =IF(AND(BR25>0, J25>0), BR25-J25, "") | CZ25: =IF(AND(BR25<0,J25>0),-J25," ") | DA25: =IF(AND(BR25>0,J25<0),BR25," ") | DB25: =IF(AND(L25=0,BR25<0),-BR25," ") | DC25: =SUM(CY25:DB25) -> 0 | DD25: =IF(AND(BR25<0, J25<0), (BR25-J25)*-1, "") | DE25: =IF(AND(BR25<0,J25>0),-BR25," ") | DF25: =IF(AND(BR25>0,J25<0),-J25*-1," ") | DG25: =IF(AND(L25<0,BR25=0),-L25*-1," ") | DH25: =SUM(DD25:DG25) -> 0
A26: C/49994_26 | B26: 新取得工程-2029年 | C26: =IFERROR(VLOOKUP($A26,'A0 BS 1240在建'!$1:$1048576,5,0),0) -> 0 | D26: =IFERROR(VLOOKUP($A26,'B0 2264預收'!$1:$1048576,5,0),0) -> 0 | E26: =+C26-D26 -> 0 | F26: =IFERROR(VLOOKUP($A26,'B0 2264預收'!$1:$1048576,6,0),0) -> 0 | G26: =+E26-F26 -> 0 | H26: =IFERROR(VLOOKUP($A26,'A0 BS 1240在建'!$1:$1048576,13,0),0) -> 0 | I26: =IFERROR(VLOOKUP($A26,'B0 2264預收'!$1:$1048576,13,0),0) -> 0 | J26: =+H26-I26 -> 0 | K26: =IFERROR(VLOOKUP($A26,'B0 2264預收'!$1:$1048576,14,0),0) -> 0 | L26: =+H26-I26-K26 -> 0 | M26: =H26+IFERROR(VLOOKUP($A26,'A0 BS 1240在建'!$1:$1048576,17,0),0) -> 0 | N26: =I26+IFERROR(VLOOKUP($A26,'B0 2264預收'!$1:$1048576,17,0),0) -> 0 | O26: =+M26-N26 -> 0 | P26: =K26+IFERROR(+VLOOKUP($A26,'B0 2264預收'!$1:$1048576,18,0),0) -> 0 | Q26: =+O26-P26 -> 0 | R26: =M26+IFERROR(VLOOKUP($A26,'A0 BS 1240在建'!$1:$1048576,21,0),0) -> 0 | S26: =+N26+IFERROR(VLOOKUP($A26,'B0 2264預收'!$1:$1048576,21,0),0) -> 0 | T26: =+R26-S26 -> 0 | U26: =+P26+IFERROR(+VLOOKUP($A26,'B0 2264預收'!$1:$1048576,22,0),0) -> 0 | V26: =+T26-U26 -> 0 | W26: =+R26+IFERROR(VLOOKUP($A26,'A0 BS 1240在建'!$1:$1048576,25,0),0) -> 0 | X26: =+S26+IFERROR(VLOOKUP($A26,'B0 2264預收'!$1:$1048576,25,0),0) -> 0 | Y26: =+W26-X26 -> 0 | Z26: =+U26+IFERROR(+VLOOKUP($A26,'B0 2264預收'!$1:$1048576,26,0),0) -> 0 | AA26: =+Y26-Z26 -> 0 | AB26: =+W26+IFERROR(VLOOKUP($A26,'A0 BS 1240在建'!$1:$1048576,29,0),0) -> 0 | AC26: =+X26+IFERROR(VLOOKUP($A26,'B0 2264預收'!$1:$1048576,29,0),0) -> 0 | AD26: =+AB26-AC26 -> 0 | AE26: =+Z26+IFERROR(+VLOOKUP($A26,'B0 2264預收'!$1:$1048576,30,0),0) -> 0 | AF26: =+AD26-AE26 -> 0 | AG26: =+AB26+IFERROR(VLOOKUP($A26,'A0 BS 1240在建'!$1:$1048576,33,0),0) -> 0 | AH26: =+AC26+IFERROR(VLOOKUP($A26,'B0 2264預收'!$1:$1048576,33,0),0) -> 0 | AI26: =+AG26-AH26 -> 0 | AJ26: =+AE26+IFERROR(+VLOOKUP($A26,'B0 2264預收'!$1:$1048576,34,0),0) -> 0 | AK26: =+AI26-AJ26 -> 0 | AL26: =+AG26+IFERROR(VLOOKUP($A26,'A0 BS 1240在建'!$1:$1048576,37,0),0) -> 0 | AM26: =+AH26+IFERROR(VLOOKUP($A26,'B0 2264預收'!$1:$1048576,37,0),0) -> 0 | AN26: =+AL26-AM26 -> 0 | AO26: =+AJ26+IFERROR(+VLOOKUP($A26,'B0 2264預收'!$1:$1048576,38,0),0) -> 0 | AP26: =+AN26-AO26 -> 0 | AQ26: =+AL26+IFERROR(VLOOKUP($A26,'A0 BS 1240在建'!$1:$1048576,41,0),0) -> 0 | AR26: =+AM26+IFERROR(VLOOKUP($A26,'B0 2264預收'!$1:$1048576,41,0),0) -> 0 | AS26: =+AQ26-AR26 -> 0 | AT26: =+AO26+IFERROR(+VLOOKUP($A26,'B0 2264預收'!$1:$1048576,42,0),0) -> 0 | AU26: =+AS26-AT26 -> 0 | AV26: =+AQ26+IFERROR(VLOOKUP($A26,'A0 BS 1240在建'!$1:$1048576,45,0),0) -> 0 | AW26: =+AR26+IFERROR(VLOOKUP($A26,'B0 2264預收'!$1:$1048576,45,0),0) -> 0 | AX26: =+AV26-AW26 -> 0 | AY26: =+AT26+IFERROR(+VLOOKUP($A26,'B0 2264預收'!$1:$1048576,46,0),0) -> 0 | AZ26: =+AX26-AY26 -> 0 | BA26: =+AV26+IFERROR(VLOOKUP($A26,'A0 BS 1240在建'!$1:$1048576,49,0),0) -> 0 | BB26: =+AW26+IFERROR(VLOOKUP($A26,'B0 2264預收'!$1:$1048576,49,0),0) -> 0 | BC26: =+BA26-BB26 -> 0 | BD26: =+AY26+IFERROR(+VLOOKUP($A26,'B0 2264預收'!$1:$1048576,50,0),0) -> 0 | BE26: =+BC26-BD26 -> 0 | BF26: =+BA26+IFERROR(VLOOKUP($A26,'A0 BS 1240在建'!$1:$1048576,53,0),0) -> 0 | BG26: =+BB26+IFERROR(VLOOKUP($A26,'B0 2264預收'!$1:$1048576,53,0),0) -> 0 | BH26: =+BF26-BG26 -> 0 | BI26: =+BD26+IFERROR(+VLOOKUP($A26,'B0 2264預收'!$1:$1048576,54,0),0) -> 0 | BJ26: =+BH26-BI26 -> 0 | BK26: =+BF26+IFERROR(VLOOKUP($A26,'A0 BS 1240在建'!$1:$1048576,57,0),0) -> 0 | BL26: =+BG26+IFERROR(VLOOKUP($A26,'B0 2264預收'!$1:$1048576,57,0),0) -> 0 | BM26: =+BK26-BL26 -> 0 | BN26: =+BI26+IFERROR(+VLOOKUP($A26,'B0 2264預收'!$1:$1048576,58,0),0) -> 0 | BO26: =+BM26-BN26 -> 0 | BP26: =+BK26+IFERROR(VLOOKUP($A26,'A0 BS 1240在建'!$1:$1048576,61,0),0) -> 0 | BQ26: =+BL26+IFERROR(VLOOKUP($A26,'B0 2264預收'!$1:$1048576,61,0),0) -> 0 | BR26: =+BP26-BQ26 -> 0 | BS26: =+BN26+IFERROR(+VLOOKUP($A26,'B0 2264預收'!$1:$1048576,62,0),0) -> 0 | BT26: =+BR26-BS26 -> 0 | BU26: =+IFERROR(VLOOKUP($A26,'A0 BS 1240在建'!$1:$1048576,77,0),0) -> 0 | BV26: =+IFERROR(VLOOKUP($A26,'B0 2264預收'!$1:$1048576,77,0),0) -> 0 | BW26: =+BU26-BV26 -> 0 | BX26: =+IFERROR(+VLOOKUP($A26,'B0 2264預收'!$1:$1048576,78,0),0) -> 0 | BY26: =+BW26-BX26 -> 0 | BZ26: =IFERROR(+VLOOKUP($A26,'A0 BS 1240在建'!$1:$1048576,85,0),0) -> 0 | CA26: =IFERROR(+VLOOKUP($A26,'B0 2264預收'!$1:$1048576,85,0),0) -> 0 | CB26: =+BZ26-CA26 -> 0 | CC26: =+IFERROR(+VLOOKUP($A26,'B0 2264預收'!$1:$1048576,86,0),0) -> 0 | CD26: =+CB26-CC26 -> 0 | CE26: =+IFERROR(VLOOKUP($A26,'A0 BS 1240在建'!$1:$1048576,93,0),0) -> 0 | CF26: =+IFERROR(VLOOKUP($A26,'B0 2264預收'!$1:$1048576,93,0),0) -> 0 | CG26: =+CE26-CF26 -> 0 | CH26: =+IFERROR(+VLOOKUP($A26,'B0 2264預收'!$1:$1048576,94,0),0) -> 0 | CI26: =+CG26-CH26 -> 0 | CJ26: =IFERROR(+VLOOKUP($A26,'A0 BS 1240在建'!$1:$1048576,101,0),0) -> 0 | CK26: =IFERROR(+VLOOKUP($A26,'B0 2264預收'!$1:$1048576,101,0),0) -> 0 | CL26: =+CJ26-CK26 -> 0 | CM26: =+IFERROR(+VLOOKUP($A26,'B0 2264預收'!$1:$1048576,102,0),0) -> 0 | CN26: =+CL26-CM26 -> 0 | CP26: =+J26-E26 -> 0 | CU26: =+BR26-J26 -> 0 | CY26: =IF(AND(BR26>0, J26>0), BR26-J26, "") | CZ26: =IF(AND(BR26<0,J26>0),-J26," ") | DA26: =IF(AND(BR26>0,J26<0),BR26," ") | DB26: =IF(AND(L26=0,BR26<0),-BR26," ") | DC26: =SUM(CY26:DB26) -> 0 | DD26: =IF(AND(BR26<0, J26<0), (BR26-J26)*-1, "") | DE26: =IF(AND(BR26<0,J26>0),-BR26," ") | DF26: =IF(AND(BR26>0,J26<0),-J26*-1," ") | DG26: =IF(AND(L26<0,BR26=0),-L26*-1," ") | DH26: =SUM(DD26:DG26) -> 0
A27: C/49995_26 | B27: 新取得工程-2030年 | C27: =IFERROR(VLOOKUP($A27,'A0 BS 1240在建'!$1:$1048576,5,0),0) -> 0 | D27: =IFERROR(VLOOKUP($A27,'B0 2264預收'!$1:$1048576,5,0),0) -> 0 | E27: =+C27-D27 -> 0 | F27: =IFERROR(VLOOKUP($A27,'B0 2264預收'!$1:$1048576,6,0),0) -> 0 | G27: =+E27-F27 -> 0 | H27: =IFERROR(VLOOKUP($A27,'A0 BS 1240在建'!$1:$1048576,13,0),0) -> 0 | I27: =IFERROR(VLOOKUP($A27,'B0 2264預收'!$1:$1048576,13,0),0) -> 0 | J27: =+H27-I27 -> 0 | K27: =IFERROR(VLOOKUP($A27,'B0 2264預收'!$1:$1048576,14,0),0) -> 0 | L27: =+H27-I27-K27 -> 0 | M27: =H27+IFERROR(VLOOKUP($A27,'A0 BS 1240在建'!$1:$1048576,17,0),0) -> 0 | N27: =I27+IFERROR(VLOOKUP($A27,'B0 2264預收'!$1:$1048576,17,0),0) -> 0 | O27: =+M27-N27 -> 0 | P27: =K27+IFERROR(+VLOOKUP($A27,'B0 2264預收'!$1:$1048576,18,0),0) -> 0 | Q27: =+O27-P27 -> 0 | R27: =M27+IFERROR(VLOOKUP($A27,'A0 BS 1240在建'!$1:$1048576,21,0),0) -> 0 | S27: =+N27+IFERROR(VLOOKUP($A27,'B0 2264預收'!$1:$1048576,21,0),0) -> 0 | T27: =+R27-S27 -> 0 | U27: =+P27+IFERROR(+VLOOKUP($A27,'B0 2264預收'!$1:$1048576,22,0),0) -> 0 | V27: =+T27-U27 -> 0 | W27: =+R27+IFERROR(VLOOKUP($A27,'A0 BS 1240在建'!$1:$1048576,25,0),0) -> 0 | X27: =+S27+IFERROR(VLOOKUP($A27,'B0 2264預收'!$1:$1048576,25,0),0) -> 0 | Y27: =+W27-X27 -> 0 | Z27: =+U27+IFERROR(+VLOOKUP($A27,'B0 2264預收'!$1:$1048576,26,0),0) -> 0 | AA27: =+Y27-Z27 -> 0 | AB27: =+W27+IFERROR(VLOOKUP($A27,'A0 BS 1240在建'!$1:$1048576,29,0),0) -> 0 | AC27: =+X27+IFERROR(VLOOKUP($A27,'B0 2264預收'!$1:$1048576,29,0),0) -> 0 | AD27: =+AB27-AC27 -> 0 | AE27: =+Z27+IFERROR(+VLOOKUP($A27,'B0 2264預收'!$1:$1048576,30,0),0) -> 0 | AF27: =+AD27-AE27 -> 0 | AG27: =+AB27+IFERROR(VLOOKUP($A27,'A0 BS 1240在建'!$1:$1048576,33,0),0) -> 0 | AH27: =+AC27+IFERROR(VLOOKUP($A27,'B0 2264預收'!$1:$1048576,33,0),0) -> 0 | AI27: =+AG27-AH27 -> 0 | AJ27: =+AE27+IFERROR(+VLOOKUP($A27,'B0 2264預收'!$1:$1048576,34,0),0) -> 0 | AK27: =+AI27-AJ27 -> 0 | AL27: =+AG27+IFERROR(VLOOKUP($A27,'A0 BS 1240在建'!$1:$1048576,37,0),0) -> 0 | AM27: =+AH27+IFERROR(VLOOKUP($A27,'B0 2264預收'!$1:$1048576,37,0),0) -> 0 | AN27: =+AL27-AM27 -> 0 | AO27: =+AJ27+IFERROR(+VLOOKUP($A27,'B0 2264預收'!$1:$1048576,38,0),0) -> 0 | AP27: =+AN27-AO27 -> 0 | AQ27: =+AL27+IFERROR(VLOOKUP($A27,'A0 BS 1240在建'!$1:$1048576,41,0),0) -> 0 | AR27: =+AM27+IFERROR(VLOOKUP($A27,'B0 2264預收'!$1:$1048576,41,0),0) -> 0 | AS27: =+AQ27-AR27 -> 0 | AT27: =+AO27+IFERROR(+VLOOKUP($A27,'B0 2264預收'!$1:$1048576,42,0),0) -> 0 | AU27: =+AS27-AT27 -> 0 | AV27: =+AQ27+IFERROR(VLOOKUP($A27,'A0 BS 1240在建'!$1:$1048576,45,0),0) -> 0 | AW27: =+AR27+IFERROR(VLOOKUP($A27,'B0 2264預收'!$1:$1048576,45,0),0) -> 0 | AX27: =+AV27-AW27 -> 0 | AY27: =+AT27+IFERROR(+VLOOKUP($A27,'B0 2264預收'!$1:$1048576,46,0),0) -> 0 | AZ27: =+AX27-AY27 -> 0 | BA27: =+AV27+IFERROR(VLOOKUP($A27,'A0 BS 1240在建'!$1:$1048576,49,0),0) -> 0 | BB27: =+AW27+IFERROR(VLOOKUP($A27,'B0 2264預收'!$1:$1048576,49,0),0) -> 0 | BC27: =+BA27-BB27 -> 0 | BD27: =+AY27+IFERROR(+VLOOKUP($A27,'B0 2264預收'!$1:$1048576,50,0),0) -> 0 | BE27: =+BC27-BD27 -> 0 | BF27: =+BA27+IFERROR(VLOOKUP($A27,'A0 BS 1240在建'!$1:$1048576,53,0),0) -> 0 | BG27: =+BB27+IFERROR(VLOOKUP($A27,'B0 2264預收'!$1:$1048576,53,0),0) -> 0 | BH27: =+BF27-BG27 -> 0 | BI27: =+BD27+IFERROR(+VLOOKUP($A27,'B0 2264預收'!$1:$1048576,54,0),0) -> 0 | BJ27: =+BH27-BI27 -> 0 | BK27: =+BF27+IFERROR(VLOOKUP($A27,'A0 BS 1240在建'!$1:$1048576,57,0),0) -> 0 | BL27: =+BG27+IFERROR(VLOOKUP($A27,'B0 2264預收'!$1:$1048576,57,0),0) -> 0 | BM27: =+BK27-BL27 -> 0 | BN27: =+BI27+IFERROR(+VLOOKUP($A27,'B0 2264預收'!$1:$1048576,58,0),0) -> 0 | BO27: =+BM27-BN27 -> 0 | BP27: =+BK27+IFERROR(VLOOKUP($A27,'A0 BS 1240在建'!$1:$1048576,61,0),0) -> 0 | BQ27: =+BL27+IFERROR(VLOOKUP($A27,'B0 2264預收'!$1:$1048576,61,0),0) -> 0 | BR27: =+BP27-BQ27 -> 0 | BS27: =+BN27+IFERROR(+VLOOKUP($A27,'B0 2264預收'!$1:$1048576,62,0),0) -> 0 | BT27: =+BR27-BS27 -> 0 | BU27: =+IFERROR(VLOOKUP($A27,'A0 BS 1240在建'!$1:$1048576,77,0),0) -> 0 | BV27: =+IFERROR(VLOOKUP($A27,'B0 2264預收'!$1:$1048576,77,0),0) -> 0 | BW27: =+BU27-BV27 -> 0 | BX27: =+IFERROR(+VLOOKUP($A27,'B0 2264預收'!$1:$1048576,78,0),0) -> 0 | BY27: =+BW27-BX27 -> 0 | BZ27: =IFERROR(+VLOOKUP($A27,'A0 BS 1240在建'!$1:$1048576,85,0),0) -> 0 | CA27: =IFERROR(+VLOOKUP($A27,'B0 2264預收'!$1:$1048576,85,0),0) -> 0 | CB27: =+BZ27-CA27 -> 0 | CC27: =+IFERROR(+VLOOKUP($A27,'B0 2264預收'!$1:$1048576,86,0),0) -> 0 | CD27: =+CB27-CC27 -> 0 | CE27: =+IFERROR(VLOOKUP($A27,'A0 BS 1240在建'!$1:$1048576,93,0),0) -> 0 | CF27: =+IFERROR(VLOOKUP($A27,'B0 2264預收'!$1:$1048576,93,0),0) -> 0 | CG27: =+CE27-CF27 -> 0 | CH27: =+IFERROR(+VLOOKUP($A27,'B0 2264預收'!$1:$1048576,94,0),0) -> 0 | CI27: =+CG27-CH27 -> 0 | CJ27: =IFERROR(+VLOOKUP($A27,'A0 BS 1240在建'!$1:$1048576,101,0),0) -> 0 | CK27: =IFERROR(+VLOOKUP($A27,'B0 2264預收'!$1:$1048576,101,0),0) -> 0 | CL27: =+CJ27-CK27 -> 0 | CM27: =+IFERROR(+VLOOKUP($A27,'B0 2264預收'!$1:$1048576,102,0),0) -> 0 | CN27: =+CL27-CM27 -> 0 | CP27: =+J27-E27 -> 0 | CU27: =+BR27-J27 -> 0 | CY27: =IF(AND(BR27>0, J27>0), BR27-J27, "") | CZ27: =IF(AND(BR27<0,J27>0),-J27," ") | DA27: =IF(AND(BR27>0,J27<0),BR27," ") | DB27: =IF(AND(L27=0,BR27<0),-BR27," ") | DC27: =SUM(CY27:DB27) -> 0 | DD27: =IF(AND(BR27<0, J27<0), (BR27-J27)*-1, "") | DE27: =IF(AND(BR27<0,J27>0),-BR27," ") | DF27: =IF(AND(BR27>0,J27<0),-J27*-1," ") | DG27: =IF(AND(L27<0,BR27=0),-L27*-1," ") | DH27: =SUM(DD27:DG27) -> 0
A28: C/1100K | B28: 南京琢豐 | C28: =IFERROR(VLOOKUP($A28,'A0 BS 1240在建'!$1:$1048576,5,0),0) -> 0 | D28: =IFERROR(VLOOKUP($A28,'B0 2264預收'!$1:$1048576,5,0),0) -> 0 | E28: =+C28-D28 -> 0 | F28: =IFERROR(VLOOKUP($A28,'B0 2264預收'!$1:$1048576,6,0),0) -> 0 | G28: =+E28-F28 -> 0 | H28: =IFERROR(VLOOKUP($A28,'A0 BS 1240在建'!$1:$1048576,13,0),0) -> 0 | I28: =IFERROR(VLOOKUP($A28,'B0 2264預收'!$1:$1048576,13,0),0) -> 0 | J28: =+H28-I28 -> 0 | K28: =IFERROR(VLOOKUP($A28,'B0 2264預收'!$1:$1048576,14,0),0) -> 0 | L28: =+H28-I28-K28 -> 0 | M28: =H28+IFERROR(VLOOKUP($A28,'A0 BS 1240在建'!$1:$1048576,17,0),0) -> 0 | N28: =I28+IFERROR(VLOOKUP($A28,'B0 2264預收'!$1:$1048576,17,0),0) -> 0 | O28: =+M28-N28 -> 0 | P28: =K28+IFERROR(+VLOOKUP($A28,'B0 2264預收'!$1:$1048576,18,0),0) -> 0 | Q28: =+O28-P28 -> 0 | R28: =M28+IFERROR(VLOOKUP($A28,'A0 BS 1240在建'!$1:$1048576,21,0),0) -> 0 | S28: =+N28+IFERROR(VLOOKUP($A28,'B0 2264預收'!$1:$1048576,21,0),0) -> 0 | T28: =+R28-S28 -> 0 | U28: =+P28+IFERROR(+VLOOKUP($A28,'B0 2264預收'!$1:$1048576,22,0),0) -> 0 | V28: =+T28-U28 -> 0 | W28: =+R28+IFERROR(VLOOKUP($A28,'A0 BS 1240在建'!$1:$1048576,25,0),0) -> 0 | X28: =+S28+IFERROR(VLOOKUP($A28,'B0 2264預收'!$1:$1048576,25,0),0) -> 0 | Y28: =+W28-X28 -> 0 | Z28: =+U28+IFERROR(+VLOOKUP($A28,'B0 2264預收'!$1:$1048576,26,0),0) -> 0 | AA28: =+Y28-Z28 -> 0 | AB28: =+W28+IFERROR(VLOOKUP($A28,'A0 BS 1240在建'!$1:$1048576,29,0),0) -> 0 | AC28: =+X28+IFERROR(VLOOKUP($A28,'B0 2264預收'!$1:$1048576,29,0),0) -> 0 | AD28: =+AB28-AC28 -> 0 | AE28: =+Z28+IFERROR(+VLOOKUP($A28,'B0 2264預收'!$1:$1048576,30,0),0) -> 0 | AF28: =+AD28-AE28 -> 0 | AG28: =+AB28+IFERROR(VLOOKUP($A28,'A0 BS 1240在建'!$1:$1048576,33,0),0) -> 0 | AH28: =+AC28+IFERROR(VLOOKUP($A28,'B0 2264預收'!$1:$1048576,33,0),0) -> 0 | AI28: =+AG28-AH28 -> 0 | AJ28: =+AE28+IFERROR(+VLOOKUP($A28,'B0 2264預收'!$1:$1048576,34,0),0) -> 0 | AK28: =+AI28-AJ28 -> 0 | AL28: =+AG28+IFERROR(VLOOKUP($A28,'A0 BS 1240在建'!$1:$1048576,37,0),0) -> 0 | AM28: =+AH28+IFERROR(VLOOKUP($A28,'B0 2264預收'!$1:$1048576,37,0),0) -> 0 | AN28: =+AL28-AM28 -> 0 | AO28: =+AJ28+IFERROR(+VLOOKUP($A28,'B0 2264預收'!$1:$1048576,38,0),0) -> 0 | AP28: =+AN28-AO28 -> 0 | AQ28: =+AL28+IFERROR(VLOOKUP($A28,'A0 BS 1240在建'!$1:$1048576,41,0),0) -> 0 | AR28: =+AM28+IFERROR(VLOOKUP($A28,'B0 2264預收'!$1:$1048576,41,0),0) -> 0 | AS28: =+AQ28-AR28 -> 0 | AT28: =+AO28+IFERROR(+VLOOKUP($A28,'B0 2264預收'!$1:$1048576,42,0),0) -> 0 | AU28: =+AS28-AT28 -> 0 | AV28: =+AQ28+IFERROR(VLOOKUP($A28,'A0 BS 1240在建'!$1:$1048576,45,0),0) -> 0 | AW28: =+AR28+IFERROR(VLOOKUP($A28,'B0 2264預收'!$1:$1048576,45,0),0) -> 0 | AX28: =+AV28-AW28 -> 0 | AY28: =+AT28+IFERROR(+VLOOKUP($A28,'B0 2264預收'!$1:$1048576,46,0),0) -> 0 | AZ28: =+AX28-AY28 -> 0 | BA28: =+AV28+IFERROR(VLOOKUP($A28,'A0 BS 1240在建'!$1:$1048576,49,0),0) -> 0 | BB28: =+AW28+IFERROR(VLOOKUP($A28,'B0 2264預收'!$1:$1048576,49,0),0) -> 0 | BC28: =+BA28-BB28 -> 0 | BD28: =+AY28+IFERROR(+VLOOKUP($A28,'B0 2264預收'!$1:$1048576,50,0),0) -> 0 | BE28: =+BC28-BD28 -> 0 | BF28: =+BA28+IFERROR(VLOOKUP($A28,'A0 BS 1240在建'!$1:$1048576,53,0),0) -> 0 | BG28: =+BB28+IFERROR(VLOOKUP($A28,'B0 2264預收'!$1:$1048576,53,0),0) -> 0 | BH28: =+BF28-BG28 -> 0 | BI28: =+BD28+IFERROR(+VLOOKUP($A28,'B0 2264預收'!$1:$1048576,54,0),0) -> 0 | BJ28: =+BH28-BI28 -> 0 | BK28: =+BF28+IFERROR(VLOOKUP($A28,'A0 BS 1240在建'!$1:$1048576,57,0),0) -> 0 | BL28: =+BG28+IFERROR(VLOOKUP($A28,'B0 2264預收'!$1:$1048576,57,0),0) -> 0 | BM28: =+BK28-BL28 -> 0 | BN28: =+BI28+IFERROR(+VLOOKUP($A28,'B0 2264預收'!$1:$1048576,58,0),0) -> 0 | BO28: =+BM28-BN28 -> 0 | BP28: =+BK28+IFERROR(VLOOKUP($A28,'A0 BS 1240在建'!$1:$1048576,61,0),0) -> 0 | BQ28: =+BL28+IFERROR(VLOOKUP($A28,'B0 2264預收'!$1:$1048576,61,0),0) -> 0 | BR28: =+BP28-BQ28 -> 0 | BS28: =+BN28+IFERROR(+VLOOKUP($A28,'B0 2264預收'!$1:$1048576,62,0),0) -> 0 | BT28: =+BR28-BS28 -> 0 | BU28: =+IFERROR(VLOOKUP($A28,'A0 BS 1240在建'!$1:$1048576,77,0),0) -> 0 | BV28: =+IFERROR(VLOOKUP($A28,'B0 2264預收'!$1:$1048576,77,0),0) -> 0 | BW28: =+BU28-BV28 -> 0 | BX28: =+IFERROR(+VLOOKUP($A28,'B0 2264預收'!$1:$1048576,78,0),0) -> 0 | BY28: =+BW28-BX28 -> 0 | BZ28: =IFERROR(+VLOOKUP($A28,'A0 BS 1240在建'!$1:$1048576,85,0),0) -> 0 | CA28: =IFERROR(+VLOOKUP($A28,'B0 2264預收'!$1:$1048576,85,0),0) -> 0 | CB28: =+BZ28-CA28 -> 0 | CC28: =+IFERROR(+VLOOKUP($A28,'B0 2264預收'!$1:$1048576,86,0),0) -> 0 | CD28: =+CB28-CC28 -> 0 | CE28: =+IFERROR(VLOOKUP($A28,'A0 BS 1240在建'!$1:$1048576,93,0),0) -> 0 | CF28: =+IFERROR(VLOOKUP($A28,'B0 2264預收'!$1:$1048576,93,0),0) -> 0 | CG28: =+CE28-CF28 -> 0 | CH28: =+IFERROR(+VLOOKUP($A28,'B0 2264預收'!$1:$1048576,94,0),0) -> 0 | CI28: =+CG28-CH28 -> 0 | CJ28: =IFERROR(+VLOOKUP($A28,'A0 BS 1240在建'!$1:$1048576,101,0),0) -> 0 | CK28: =IFERROR(+VLOOKUP($A28,'B0 2264預收'!$1:$1048576,101,0),0) -> 0 | CL28: =+CJ28-CK28 -> 0 | CM28: =+IFERROR(+VLOOKUP($A28,'B0 2264預收'!$1:$1048576,102,0),0) -> 0 | CN28: =+CL28-CM28 -> 0 | CP28: =+J28-E28 -> 0 | CQ28: =-E28 -> 0 | CR28: =+J28 -> 0 | CU28: =+BR28-J28 -> 0 | CW28: =+CU28 -> 0 | CY28: =IF(AND(BR28>0, J28>0), BR28-J28, "") | CZ28: =IF(AND(BR28<0,J28>0),-J28," ") | DA28: =IF(AND(BR28>0,J28<0),BR28," ") | DB28: =IF(AND(L28=0,BR28<0),-BR28," ") | DC28: =SUM(CY28:DB28) -> 0 | DD28: =IF(AND(BR28<0, J28<0), (BR28-J28)*-1, "") | DE28: =IF(AND(BR28<0,J28>0),-BR28," ") | DF28: =IF(AND(BR28>0,J28<0),-J28*-1," ") | DG28: =IF(AND(L28<0,BR28=0),-L28*-1," ") | DH28: =SUM(DD28:DG28) -> 0
A29: C/1110O | B29: 忠孝耑序 | C29: =IFERROR(VLOOKUP($A29,'A0 BS 1240在建'!$1:$1048576,5,0),0) -> 0 | D29: =IFERROR(VLOOKUP($A29,'B0 2264預收'!$1:$1048576,5,0),0) -> 0 | E29: =+C29-D29 -> 0 | F29: =IFERROR(VLOOKUP($A29,'B0 2264預收'!$1:$1048576,6,0),0) -> 0 | G29: =+E29-F29 -> 0 | H29: =IFERROR(VLOOKUP($A29,'A0 BS 1240在建'!$1:$1048576,13,0),0) -> 0 | I29: =IFERROR(VLOOKUP($A29,'B0 2264預收'!$1:$1048576,13,0),0) -> 0 | J29: =+H29-I29 -> 0 | K29: =IFERROR(VLOOKUP($A29,'B0 2264預收'!$1:$1048576,14,0),0) -> 0 | L29: =+H29-I29-K29 -> 0 | M29: =H29+IFERROR(VLOOKUP($A29,'A0 BS 1240在建'!$1:$1048576,17,0),0) -> 0 | N29: =I29+IFERROR(VLOOKUP($A29,'B0 2264預收'!$1:$1048576,17,0),0) -> 0 | O29: =+M29-N29 -> 0 | P29: =K29+IFERROR(+VLOOKUP($A29,'B0 2264預收'!$1:$1048576,18,0),0) -> 0 | Q29: =+O29-P29 -> 0 | R29: =M29+IFERROR(VLOOKUP($A29,'A0 BS 1240在建'!$1:$1048576,21,0),0) -> 0 | S29: =+N29+IFERROR(VLOOKUP($A29,'B0 2264預收'!$1:$1048576,21,0),0) -> 0 | T29: =+R29-S29 -> 0 | U29: =+P29+IFERROR(+VLOOKUP($A29,'B0 2264預收'!$1:$1048576,22,0),0) -> 0 | V29: =+T29-U29 -> 0 | W29: =+R29+IFERROR(VLOOKUP($A29,'A0 BS 1240在建'!$1:$1048576,25,0),0) -> 0 | X29: =+S29+IFERROR(VLOOKUP($A29,'B0 2264預收'!$1:$1048576,25,0),0) -> 0 | Y29: =+W29-X29 -> 0 | Z29: =+U29+IFERROR(+VLOOKUP($A29,'B0 2264預收'!$1:$1048576,26,0),0) -> 0 | AA29: =+Y29-Z29 -> 0 | AB29: =+W29+IFERROR(VLOOKUP($A29,'A0 BS 1240在建'!$1:$1048576,29,0),0) -> 0 | AC29: =+X29+IFERROR(VLOOKUP($A29,'B0 2264預收'!$1:$1048576,29,0),0) -> 0 | AD29: =+AB29-AC29 -> 0 | AE29: =+Z29+IFERROR(+VLOOKUP($A29,'B0 2264預收'!$1:$1048576,30,0),0) -> 0 | AF29: =+AD29-AE29 -> 0 | AG29: =+AB29+IFERROR(VLOOKUP($A29,'A0 BS 1240在建'!$1:$1048576,33,0),0) -> 0 | AH29: =+AC29+IFERROR(VLOOKUP($A29,'B0 2264預收'!$1:$1048576,33,0),0) -> 0 | AI29: =+AG29-AH29 -> 0 | AJ29: =+AE29+IFERROR(+VLOOKUP($A29,'B0 2264預收'!$1:$1048576,34,0),0) -> 0 | AK29: =+AI29-AJ29 -> 0 | AL29: =+AG29+IFERROR(VLOOKUP($A29,'A0 BS 1240在建'!$1:$1048576,37,0),0) -> 0 | AM29: =+AH29+IFERROR(VLOOKUP($A29,'B0 2264預收'!$1:$1048576,37,0),0) -> 0 | AN29: =+AL29-AM29 -> 0 | AO29: =+AJ29+IFERROR(+VLOOKUP($A29,'B0 2264預收'!$1:$1048576,38,0),0) -> 0 | AP29: =+AN29-AO29 -> 0 | AQ29: =+AL29+IFERROR(VLOOKUP($A29,'A0 BS 1240在建'!$1:$1048576,41,0),0) -> 0 | AR29: =+AM29+IFERROR(VLOOKUP($A29,'B0 2264預收'!$1:$1048576,41,0),0) -> 0 | AS29: =+AQ29-AR29 -> 0 | AT29: =+AO29+IFERROR(+VLOOKUP($A29,'B0 2264預收'!$1:$1048576,42,0),0) -> 0 | AU29: =+AS29-AT29 -> 0 | AV29: =+AQ29+IFERROR(VLOOKUP($A29,'A0 BS 1240在建'!$1:$1048576,45,0),0) -> 0 | AW29: =+AR29+IFERROR(VLOOKUP($A29,'B0 2264預收'!$1:$1048576,45,0),0) -> 0 | AX29: =+AV29-AW29 -> 0 | AY29: =+AT29+IFERROR(+VLOOKUP($A29,'B0 2264預收'!$1:$1048576,46,0),0) -> 0 | AZ29: =+AX29-AY29 -> 0 | BA29: =+AV29+IFERROR(VLOOKUP($A29,'A0 BS 1240在建'!$1:$1048576,49,0),0) -> 0 | BB29: =+AW29+IFERROR(VLOOKUP($A29,'B0 2264預收'!$1:$1048576,49,0),0) -> 0 | BC29: =+BA29-BB29 -> 0 | BD29: =+AY29+IFERROR(+VLOOKUP($A29,'B0 2264預收'!$1:$1048576,50,0),0) -> 0 | BE29: =+BC29-BD29 -> 0 | BF29: =+BA29+IFERROR(VLOOKUP($A29,'A0 BS 1240在建'!$1:$1048576,53,0),0) -> 0 | BG29: =+BB29+IFERROR(VLOOKUP($A29,'B0 2264預收'!$1:$1048576,53,0),0) -> 0 | BH29: =+BF29-BG29 -> 0 | BI29: =+BD29+IFERROR(+VLOOKUP($A29,'B0 2264預收'!$1:$1048576,54,0),0) -> 0 | BJ29: =+BH29-BI29 -> 0 | BK29: =+BF29+IFERROR(VLOOKUP($A29,'A0 BS 1240在建'!$1:$1048576,57,0),0) -> 0 | BL29: =+BG29+IFERROR(VLOOKUP($A29,'B0 2264預收'!$1:$1048576,57,0),0) -> 0 | BM29: =+BK29-BL29 -> 0 | BN29: =+BI29+IFERROR(+VLOOKUP($A29,'B0 2264預收'!$1:$1048576,58,0),0) -> 0 | BO29: =+BM29-BN29 -> 0 | BP29: =+BK29+IFERROR(VLOOKUP($A29,'A0 BS 1240在建'!$1:$1048576,61,0),0) -> 0 | BQ29: =+BL29+IFERROR(VLOOKUP($A29,'B0 2264預收'!$1:$1048576,61,0),0) -> 0 | BR29: =+BP29-BQ29 -> 0 | BS29: =+BN29+IFERROR(+VLOOKUP($A29,'B0 2264預收'!$1:$1048576,62,0),0) -> 0 | BT29: =+BR29-BS29 -> 0 | BU29: =+IFERROR(VLOOKUP($A29,'A0 BS 1240在建'!$1:$1048576,77,0),0) -> 0 | BV29: =+IFERROR(VLOOKUP($A29,'B0 2264預收'!$1:$1048576,77,0),0) -> 0 | BW29: =+BU29-BV29 -> 0 | BX29: =+IFERROR(+VLOOKUP($A29,'B0 2264預收'!$1:$1048576,78,0),0) -> 0 | BY29: =+BW29-BX29 -> 0 | BZ29: =IFERROR(+VLOOKUP($A29,'A0 BS 1240在建'!$1:$1048576,85,0),0) -> 0 | CA29: =IFERROR(+VLOOKUP($A29,'B0 2264預收'!$1:$1048576,85,0),0) -> 0 | CB29: =+BZ29-CA29 -> 0 | CC29: =+IFERROR(+VLOOKUP($A29,'B0 2264預收'!$1:$1048576,86,0),0) -> 0 | CD29: =+CB29-CC29 -> 0 | CE29: =+IFERROR(VLOOKUP($A29,'A0 BS 1240在建'!$1:$1048576,93,0),0) -> 0 | CF29: =+IFERROR(VLOOKUP($A29,'B0 2264預收'!$1:$1048576,93,0),0) -> 0 | CG29: =+CE29-CF29 -> 0 | CH29: =+IFERROR(+VLOOKUP($A29,'B0 2264預收'!$1:$1048576,94,0),0) -> 0 | CI29: =+CG29-CH29 -> 0 | CJ29: =IFERROR(+VLOOKUP($A29,'A0 BS 1240在建'!$1:$1048576,101,0),0) -> 0 | CK29: =IFERROR(+VLOOKUP($A29,'B0 2264預收'!$1:$1048576,101,0),0) -> 0 | CL29: =+CJ29-CK29 -> 0 | CM29: =+IFERROR(+VLOOKUP($A29,'B0 2264預收'!$1:$1048576,102,0),0) -> 0 | CN29: =+CL29-CM29 -> 0 | CP29: =+J29-E29 -> 0 | CR29: =+CP29 -> 0 | CU29: =+BR29-J29 -> 0 | CW29: =+CU29 -> 0 | CY29: =IF(AND(BR29>0, J29>0), BR29-J29, "") | CZ29: =IF(AND(BR29<0,J29>0),-J29," ") | DA29: =IF(AND(BR29>0,J29<0),BR29," ") | DB29: =IF(AND(L29=0,BR29<0),-BR29," ") | DC29: =SUM(CY29:DB29) -> 0 | DD29: =IF(AND(BR29<0, J29<0), (BR29-J29)*-1, "") | DE29: =IF(AND(BR29<0,J29>0),-BR29," ") | DF29: =IF(AND(BR29>0,J29<0),-J29*-1," ") | DG29: =IF(AND(L29<0,BR29=0),-L29*-1," ") | DH29: =SUM(DD29:DG29) -> 0
A30: C/1110P | B30: 天津都更 | C30: =IFERROR(VLOOKUP($A30,'A0 BS 1240在建'!$1:$1048576,5,0),0) -> 0 | D30: =IFERROR(VLOOKUP($A30,'B0 2264預收'!$1:$1048576,5,0),0) -> 0 | E30: =+C30-D30 -> 0 | F30: =IFERROR(VLOOKUP($A30,'B0 2264預收'!$1:$1048576,6,0),0) -> 0 | G30: =+E30-F30 -> 0 | H30: =IFERROR(VLOOKUP($A30,'A0 BS 1240在建'!$1:$1048576,13,0),0) -> 0 | I30: =IFERROR(VLOOKUP($A30,'B0 2264預收'!$1:$1048576,13,0),0) -> 0 | J30: =+H30-I30 -> 0 | K30: =IFERROR(VLOOKUP($A30,'B0 2264預收'!$1:$1048576,14,0),0) -> 0 | L30: =+H30-I30-K30 -> 0 | M30: =H30+IFERROR(VLOOKUP($A30,'A0 BS 1240在建'!$1:$1048576,17,0),0) -> 0 | N30: =I30+IFERROR(VLOOKUP($A30,'B0 2264預收'!$1:$1048576,17,0),0) -> 0 | O30: =+M30-N30 -> 0 | P30: =K30+IFERROR(+VLOOKUP($A30,'B0 2264預收'!$1:$1048576,18,0),0) -> 0 | Q30: =+O30-P30 -> 0 | R30: =M30+IFERROR(VLOOKUP($A30,'A0 BS 1240在建'!$1:$1048576,21,0),0) -> 0 | S30: =+N30+IFERROR(VLOOKUP($A30,'B0 2264預收'!$1:$1048576,21,0),0) -> 0 | T30: =+R30-S30 -> 0 | U30: =+P30+IFERROR(+VLOOKUP($A30,'B0 2264預收'!$1:$1048576,22,0),0) -> 0 | V30: =+T30-U30 -> 0 | W30: =+R30+IFERROR(VLOOKUP($A30,'A0 BS 1240在建'!$1:$1048576,25,0),0) -> 0 | X30: =+S30+IFERROR(VLOOKUP($A30,'B0 2264預收'!$1:$1048576,25,0),0) -> 0 | Y30: =+W30-X30 -> 0 | Z30: =+U30+IFERROR(+VLOOKUP($A30,'B0 2264預收'!$1:$1048576,26,0),0) -> 0 | AA30: =+Y30-Z30 -> 0 | AB30: =+W30+IFERROR(VLOOKUP($A30,'A0 BS 1240在建'!$1:$1048576,29,0),0) -> 0 | AC30: =+X30+IFERROR(VLOOKUP($A30,'B0 2264預收'!$1:$1048576,29,0),0) -> 0 | AD30: =+AB30-AC30 -> 0 | AE30: =+Z30+IFERROR(+VLOOKUP($A30,'B0 2264預收'!$1:$1048576,30,0),0) -> 0 | AF30: =+AD30-AE30 -> 0 | AG30: =+AB30+IFERROR(VLOOKUP($A30,'A0 BS 1240在建'!$1:$1048576,33,0),0) -> 0 | AH30: =+AC30+IFERROR(VLOOKUP($A30,'B0 2264預收'!$1:$1048576,33,0),0) -> 0 | AI30: =+AG30-AH30 -> 0 | AJ30: =+AE30+IFERROR(+VLOOKUP($A30,'B0 2264預收'!$1:$1048576,34,0),0) -> 0 | AK30: =+AI30-AJ30 -> 0 | AL30: =+AG30+IFERROR(VLOOKUP($A30,'A0 BS 1240在建'!$1:$1048576,37,0),0) -> 0 | AM30: =+AH30+IFERROR(VLOOKUP($A30,'B0 2264預收'!$1:$1048576,37,0),0) -> 0 | AN30: =+AL30-AM30 -> 0 | AO30: =+AJ30+IFERROR(+VLOOKUP($A30,'B0 2264預收'!$1:$1048576,38,0),0) -> 0 | AP30: =+AN30-AO30 -> 0 | AQ30: =+AL30+IFERROR(VLOOKUP($A30,'A0 BS 1240在建'!$1:$1048576,41,0),0) -> 0 | AR30: =+AM30+IFERROR(VLOOKUP($A30,'B0 2264預收'!$1:$1048576,41,0),0) -> 0 | AS30: =+AQ30-AR30 -> 0 | AT30: =+AO30+IFERROR(+VLOOKUP($A30,'B0 2264預收'!$1:$1048576,42,0),0) -> 0 | AU30: =+AS30-AT30 -> 0 | AV30: =+AQ30+IFERROR(VLOOKUP($A30,'A0 BS 1240在建'!$1:$1048576,45,0),0) -> 0 | AW30: =+AR30+IFERROR(VLOOKUP($A30,'B0 2264預收'!$1:$1048576,45,0),0) -> 0 | AX30: =+AV30-AW30 -> 0 | AY30: =+AT30+IFERROR(+VLOOKUP($A30,'B0 2264預收'!$1:$1048576,46,0),0) -> 0 | AZ30: =+AX30-AY30 -> 0 | BA30: =+AV30+IFERROR(VLOOKUP($A30,'A0 BS 1240在建'!$1:$1048576,49,0),0) -> 0 | BB30: =+AW30+IFERROR(VLOOKUP($A30,'B0 2264預收'!$1:$1048576,49,0),0) -> 0 | BC30: =+BA30-BB30 -> 0 | BD30: =+AY30+IFERROR(+VLOOKUP($A30,'B0 2264預收'!$1:$1048576,50,0),0) -> 0 | BE30: =+BC30-BD30 -> 0 | BF30: =+BA30+IFERROR(VLOOKUP($A30,'A0 BS 1240在建'!$1:$1048576,53,0),0) -> 0 | BG30: =+BB30+IFERROR(VLOOKUP($A30,'B0 2264預收'!$1:$1048576,53,0),0) -> 0 | BH30: =+BF30-BG30 -> 0 | BI30: =+BD30+IFERROR(+VLOOKUP($A30,'B0 2264預收'!$1:$1048576,54,0),0) -> 0 | BJ30: =+BH30-BI30 -> 0 | BK30: =+BF30+IFERROR(VLOOKUP($A30,'A0 BS 1240在建'!$1:$1048576,57,0),0) -> 0 | BL30: =+BG30+IFERROR(VLOOKUP($A30,'B0 2264預收'!$1:$1048576,57,0),0) -> 0 | BM30: =+BK30-BL30 -> 0 | BN30: =+BI30+IFERROR(+VLOOKUP($A30,'B0 2264預收'!$1:$1048576,58,0),0) -> 0 | BO30: =+BM30-BN30 -> 0 | BP30: =+BK30+IFERROR(VLOOKUP($A30,'A0 BS 1240在建'!$1:$1048576,61,0),0) -> 0 | BQ30: =+BL30+IFERROR(VLOOKUP($A30,'B0 2264預收'!$1:$1048576,61,0),0) -> 0 | BR30: =+BP30-BQ30 -> 0 | BS30: =+BN30+IFERROR(+VLOOKUP($A30,'B0 2264預收'!$1:$1048576,62,0),0) -> 0 | BT30: =+BR30-BS30 -> 0 | BU30: =+IFERROR(VLOOKUP($A30,'A0 BS 1240在建'!$1:$1048576,77,0),0) -> 0 | BV30: =+IFERROR(VLOOKUP($A30,'B0 2264預收'!$1:$1048576,77,0),0) -> 0 | BW30: =+BU30-BV30 -> 0 | BX30: =+IFERROR(+VLOOKUP($A30,'B0 2264預收'!$1:$1048576,78,0),0) -> 0 | BY30: =+BW30-BX30 -> 0 | BZ30: =IFERROR(+VLOOKUP($A30,'A0 BS 1240在建'!$1:$1048576,85,0),0) -> 0 | CA30: =IFERROR(+VLOOKUP($A30,'B0 2264預收'!$1:$1048576,85,0),0) -> 0 | CB30: =+BZ30-CA30 -> 0 | CC30: =+IFERROR(+VLOOKUP($A30,'B0 2264預收'!$1:$1048576,86,0),0) -> 0 | CD30: =+CB30-CC30 -> 0 | CE30: =+IFERROR(VLOOKUP($A30,'A0 BS 1240在建'!$1:$1048576,93,0),0) -> 0 | CF30: =+IFERROR(VLOOKUP($A30,'B0 2264預收'!$1:$1048576,93,0),0) -> 0 | CG30: =+CE30-CF30 -> 0 | CH30: =+IFERROR(+VLOOKUP($A30,'B0 2264預收'!$1:$1048576,94,0),0) -> 0 | CI30: =+CG30-CH30 -> 0 | CJ30: =IFERROR(+VLOOKUP($A30,'A0 BS 1240在建'!$1:$1048576,101,0),0) -> 0 | CK30: =IFERROR(+VLOOKUP($A30,'B0 2264預收'!$1:$1048576,101,0),0) -> 0 | CL30: =+CJ30-CK30 -> 0 | CM30: =+IFERROR(+VLOOKUP($A30,'B0 2264預收'!$1:$1048576,102,0),0) -> 0 | CN30: =+CL30-CM30 -> 0 | CP30: =+J30-E30 -> 0 | CQ30: =+CP30 -> 0 | CU30: =+BR30-J30 -> 0 | CV30: =-J30 -> 0 | CW30: =+BR30 -> 0 | CY30: =IF(AND(BR30>0, J30>0), BR30-J30, "") | CZ30: =IF(AND(BR30<0,J30>0),-J30," ") | DA30: =IF(AND(BR30>0,J30<0),BR30," ") | DB30: =IF(AND(L30=0,BR30<0),-BR30," ") | DC30: =SUM(CY30:DB30) -> 0 | DD30: =IF(AND(BR30<0, J30<0), (BR30-J30)*-1, "") | DE30: =IF(AND(BR30<0,J30>0),-BR30," ") | DF30: =IF(AND(BR30>0,J30<0),-J30*-1," ") | DG30: =IF(AND(L30<0,BR30=0),-L30*-1," ") | DH30: =SUM(DD30:DG30) -> 0
A31: C/1110Q | B31: 信義文昌 | C31: =IFERROR(VLOOKUP($A31,'A0 BS 1240在建'!$1:$1048576,5,0),0) -> 0 | D31: =IFERROR(VLOOKUP($A31,'B0 2264預收'!$1:$1048576,5,0),0) -> 0 | E31: =+C31-D31 -> 0 | F31: =IFERROR(VLOOKUP($A31,'B0 2264預收'!$1:$1048576,6,0),0) -> 0 | G31: =+E31-F31 -> 0 | H31: =IFERROR(VLOOKUP($A31,'A0 BS 1240在建'!$1:$1048576,13,0),0) -> 0 | I31: =IFERROR(VLOOKUP($A31,'B0 2264預收'!$1:$1048576,13,0),0) -> 0 | J31: =+H31-I31 -> 0 | K31: =IFERROR(VLOOKUP($A31,'B0 2264預收'!$1:$1048576,14,0),0) -> 0 | L31: =+H31-I31-K31 -> 0 | M31: =H31+IFERROR(VLOOKUP($A31,'A0 BS 1240在建'!$1:$1048576,17,0),0) -> 0 | N31: =I31+IFERROR(VLOOKUP($A31,'B0 2264預收'!$1:$1048576,17,0),0) -> 0 | O31: =+M31-N31 -> 0 | P31: =K31+IFERROR(+VLOOKUP($A31,'B0 2264預收'!$1:$1048576,18,0),0) -> 0 | Q31: =+O31-P31 -> 0 | R31: =M31+IFERROR(VLOOKUP($A31,'A0 BS 1240在建'!$1:$1048576,21,0),0) -> 0 | S31: =+N31+IFERROR(VLOOKUP($A31,'B0 2264預收'!$1:$1048576,21,0),0) -> 0 | T31: =+R31-S31 -> 0 | U31: =+P31+IFERROR(+VLOOKUP($A31,'B0 2264預收'!$1:$1048576,22,0),0) -> 0 | V31: =+T31-U31 -> 0 | W31: =+R31+IFERROR(VLOOKUP($A31,'A0 BS 1240在建'!$1:$1048576,25,0),0) -> 0 | X31: =+S31+IFERROR(VLOOKUP($A31,'B0 2264預收'!$1:$1048576,25,0),0) -> 0 | Y31: =+W31-X31 -> 0 | Z31: =+U31+IFERROR(+VLOOKUP($A31,'B0 2264預收'!$1:$1048576,26,0),0) -> 0 | AA31: =+Y31-Z31 -> 0 | AB31: =+W31+IFERROR(VLOOKUP($A31,'A0 BS 1240在建'!$1:$1048576,29,0),0) -> 0 | AC31: =+X31+IFERROR(VLOOKUP($A31,'B0 2264預收'!$1:$1048576,29,0),0) -> 0 | AD31: =+AB31-AC31 -> 0 | AE31: =+Z31+IFERROR(+VLOOKUP($A31,'B0 2264預收'!$1:$1048576,30,0),0) -> 0 | AF31: =+AD31-AE31 -> 0 | AG31: =+AB31+IFERROR(VLOOKUP($A31,'A0 BS 1240在建'!$1:$1048576,33,0),0) -> 0 | AH31: =+AC31+IFERROR(VLOOKUP($A31,'B0 2264預收'!$1:$1048576,33,0),0) -> 0 | AI31: =+AG31-AH31 -> 0 | AJ31: =+AE31+IFERROR(+VLOOKUP($A31,'B0 2264預收'!$1:$1048576,34,0),0) -> 0 | AK31: =+AI31-AJ31 -> 0 | AL31: =+AG31+IFERROR(VLOOKUP($A31,'A0 BS 1240在建'!$1:$1048576,37,0),0) -> 0 | AM31: =+AH31+IFERROR(VLOOKUP($A31,'B0 2264預收'!$1:$1048576,37,0),0) -> 0 | AN31: =+AL31-AM31 -> 0 | AO31: =+AJ31+IFERROR(+VLOOKUP($A31,'B0 2264預收'!$1:$1048576,38,0),0) -> 0 | AP31: =+AN31-AO31 -> 0 | AQ31: =+AL31+IFERROR(VLOOKUP($A31,'A0 BS 1240在建'!$1:$1048576,41,0),0) -> 0 | AR31: =+AM31+IFERROR(VLOOKUP($A31,'B0 2264預收'!$1:$1048576,41,0),0) -> 0 | AS31: =+AQ31-AR31 -> 0 | AT31: =+AO31+IFERROR(+VLOOKUP($A31,'B0 2264預收'!$1:$1048576,42,0),0) -> 0 | AU31: =+AS31-AT31 -> 0 | AV31: =+AQ31+IFERROR(VLOOKUP($A31,'A0 BS 1240在建'!$1:$1048576,45,0),0) -> 0 | AW31: =+AR31+IFERROR(VLOOKUP($A31,'B0 2264預收'!$1:$1048576,45,0),0) -> 0 | AX31: =+AV31-AW31 -> 0 | AY31: =+AT31+IFERROR(+VLOOKUP($A31,'B0 2264預收'!$1:$1048576,46,0),0) -> 0 | AZ31: =+AX31-AY31 -> 0 | BA31: =+AV31+IFERROR(VLOOKUP($A31,'A0 BS 1240在建'!$1:$1048576,49,0),0) -> 0 | BB31: =+AW31+IFERROR(VLOOKUP($A31,'B0 2264預收'!$1:$1048576,49,0),0) -> 0 | BC31: =+BA31-BB31 -> 0 | BD31: =+AY31+IFERROR(+VLOOKUP($A31,'B0 2264預收'!$1:$1048576,50,0),0) -> 0 | BE31: =+BC31-BD31 -> 0 | BF31: =+BA31+IFERROR(VLOOKUP($A31,'A0 BS 1240在建'!$1:$1048576,53,0),0) -> 0 | BG31: =+BB31+IFERROR(VLOOKUP($A31,'B0 2264預收'!$1:$1048576,53,0),0) -> 0 | BH31: =+BF31-BG31 -> 0 | BI31: =+BD31+IFERROR(+VLOOKUP($A31,'B0 2264預收'!$1:$1048576,54,0),0) -> 0 | BJ31: =+BH31-BI31 -> 0 | BK31: =+BF31+IFERROR(VLOOKUP($A31,'A0 BS 1240在建'!$1:$1048576,57,0),0) -> 0 | BL31: =+BG31+IFERROR(VLOOKUP($A31,'B0 2264預收'!$1:$1048576,57,0),0) -> 0 | BM31: =+BK31-BL31 -> 0 | BN31: =+BI31+IFERROR(+VLOOKUP($A31,'B0 2264預收'!$1:$1048576,58,0),0) -> 0 | BO31: =+BM31-BN31 -> 0 | BP31: =+BK31+IFERROR(VLOOKUP($A31,'A0 BS 1240在建'!$1:$1048576,61,0),0) -> 0 | BQ31: =+BL31+IFERROR(VLOOKUP($A31,'B0 2264預收'!$1:$1048576,61,0),0) -> 0 | BR31: =+BP31-BQ31 -> 0 | BS31: =+BN31+IFERROR(+VLOOKUP($A31,'B0 2264預收'!$1:$1048576,62,0),0) -> 0 | BT31: =+BR31-BS31 -> 0 | BU31: =+IFERROR(VLOOKUP($A31,'A0 BS 1240在建'!$1:$1048576,77,0),0) -> 0 | BV31: =+IFERROR(VLOOKUP($A31,'B0 2264預收'!$1:$1048576,77,0),0) -> 0 | BW31: =+BU31-BV31 -> 0 | BX31: =+IFERROR(+VLOOKUP($A31,'B0 2264預收'!$1:$1048576,78,0),0) -> 0 | BY31: =+BW31-BX31 -> 0 | BZ31: =IFERROR(+VLOOKUP($A31,'A0 BS 1240在建'!$1:$1048576,85,0),0) -> 0 | CA31: =IFERROR(+VLOOKUP($A31,'B0 2264預收'!$1:$1048576,85,0),0) -> 0 | CB31: =+BZ31-CA31 -> 0 | CC31: =+IFERROR(+VLOOKUP($A31,'B0 2264預收'!$1:$1048576,86,0),0) -> 0 | CD31: =+CB31-CC31 -> 0 | CE31: =+IFERROR(VLOOKUP($A31,'A0 BS 1240在建'!$1:$1048576,93,0),0) -> 0 | CF31: =+IFERROR(VLOOKUP($A31,'B0 2264預收'!$1:$1048576,93,0),0) -> 0 | CG31: =+CE31-CF31 -> 0 | CH31: =+IFERROR(+VLOOKUP($A31,'B0 2264預收'!$1:$1048576,94,0),0) -> 0 | CI31: =+CG31-CH31 -> 0 | CJ31: =IFERROR(+VLOOKUP($A31,'A0 BS 1240在建'!$1:$1048576,101,0),0) -> 0 | CK31: =IFERROR(+VLOOKUP($A31,'B0 2264預收'!$1:$1048576,101,0),0) -> 0 | CL31: =+CJ31-CK31 -> 0 | CM31: =+IFERROR(+VLOOKUP($A31,'B0 2264預收'!$1:$1048576,102,0),0) -> 0 | CN31: =+CL31-CM31 -> 0 | CP31: =+J31-E31 -> 0 | CQ31: =-E31 -> 0 | CR31: =+J31 -> 0 | CU31: =+BR31-J31 -> 0 | CW31: =+CU31 -> 0 | CY31: =IF(AND(BR31>0, J31>0), BR31-J31, "") | CZ31: =IF(AND(BR31<0,J31>0),-J31," ") | DA31: =IF(AND(BR31>0,J31<0),BR31," ") | DB31: =IF(AND(L31=0,BR31<0),-BR31," ") | DC31: =SUM(CY31:DB31) -> 0 | DD31: =IF(AND(BR31<0, J31<0), (BR31-J31)*-1, "") | DE31: =IF(AND(BR31<0,J31>0),-BR31," ") | DF31: =IF(AND(BR31>0,J31<0),-J31*-1," ") | DG31: =IF(AND(L31<0,BR31=0),-L31*-1," ") | DH31: =SUM(DD31:DG31) -> 0
