Workbook

Sheet 工作表1
C1: poc | M1: 非POC
C2: 內案(POC) | H2: 外案(POC) | M2: 非POC之內案(雜項)C/99992、C/9999B | R2: 非POC之內案(備標)對象為公司業務部 C/99993、C/9999D
A3: No. | B3: 交易性質 | C3: 借/貸 | D3: 會科代號 | E3: 會科名稱 | F3: 金額 | G3: 備註 | H3: 借/貸 | I3: 會科代號 | J3: 會科名稱 | K3: 金額 | L3: 備註 | M3: 借/貸 | N3: 會科代號 | O3: 會科名稱 | P3: 金額 | Q3: 備註 | R3: 借/貸 | S3: 會科代號 | T3: 會科名稱 | U3: 金額 | V3: 備註
A4: 1 | B4: BIM費用入帳 | C4: Dr. | D4: 62xxxxxx | E4: 辦公室費用 | F4: =$E$82 | H4: Dr. | I4: 62xxxxxx | J4: 辦公室費用 | K4: =$E$82 | M4: Dr. | N4: 62xxxxxx | O4: 辦公室費用 | P4: =$E$82 | R4: Dr. | S4: 62xxxxxx | T4: 辦公室費用 | U4: =$E$82
C5: Dr. | D5: 12640000 | E5: 進項稅額 | F5: =F4*5% | H5: Dr. | I5: 12640000 | J5: 進項稅額 | K5: =K4*5% | M5: Dr. | N5: 12640000 | O5: 進項稅額 | P5: =P4*5% | R5: Dr. | S5: 12640000 | T5: 進項稅額 | U5: =U4*5%
C6: Cr. | D6: 21430000 | E6: 應付帳款 | F6: =-(F4+F5) | H6: Cr. | I6: 21430000 | J6: 應付帳款 | K6: =-(K4+K5) | M6: Cr. | N6: 21430000 | O6: 應付帳款 | P6: =-(P4+P5) | R6: Cr. | S6: 21430000 | T6: 應付帳款 | U6: =-(U4+U5)
A8: 2 | B8: BIM費用轉列成本 | C8: Dr. | D8: 63xxxxxx | E8: 工程費用 | F8: =-F9 | H8: Dr. | I8: 63xxxxxx | J8: 工程費用 | K8: =-K9 | M8: Dr. | N8: 55/56xxxxxx | O8: 專案成本 | P8: =-SUM(P9:P10) | Q8: (原作法:成本由管理費用分攤而來) | R8: Dr. | S8: 55/56xxxxxx | T8: 專案成本 | U8: =-SUM(U9:U10) | V8: (原作法:成本由管理費用分攤而來)
C9: Cr. | D9: 62xxxxxx | E9: 辦公室費用 | F9: =-F4 | H9: Cr. | I9: 62xxxxxx | J9: 辦公室費用 | K9: =-K4 | M9: Cr. | N9: 62109999 | O9: 人事分攤 | P9: -80 | R9: Cr. | S9: 62109999 | T9: 人事費用-分攤 | U9: -80
M10: Cr. | N10: 62350099 | O10: 電腦out charge | P10: -20 | R10: Cr. | S10: 62350099 | T10: 電腦費用-Out Charge | U10: -20
B12: ELIA內部沖銷 | R12: Dr. | S12: 62109999 | T12: 人事費用-分攤 | U12: =-U9 | V12: 備標沖銷
R13: Cr. | S13: 55/56xxxxxx | T13: 專案成本 | U13: =-U12 | V13: 55110099承攬工程成本-人事費
R14: Dr. | S14: 62350099 | T14: 電腦費用-Out Charge | U14: =-U10 | V14: 備標沖銷
R15: Cr. | S15: 55/56xxxxxx | T15: 專案成本 | U15: =-U14 | V15: 55110098承攬工程成本-非人事
A16: 3 | B16: BIM月底結轉在建 | C16: Dr. | D16: 12400000 | E16: 在建工程 | F16: =-F17 | H16: Dr. | I16: 12400000 | J16: 在建工程 | K16: =-K17
B17: (CJ88) | C17: Cr. | D17: 63810030 | E17: 工程費用轉在建工程 | F17: =-F8 | H17: Cr. | I17: 63810030 | J17: 工程費用轉在建工程 | K17: =-K8
A20: 4 | B20: BIM完工百分比 | C20: Dr. | D20: 55110000 | E20: 承攬工程成本 | F20: =F8 | H20: Dr. | I20: 55110000 | J20: 承攬工程成本 | K20: =K8
B21: 損益認列 | C21: Dr. | D21: 12470000 | E21: 在建損益-承攬案 | F21: =-F22-F20 | H21: Dr. | I21: 12470000 | J21: 在建損益-承攬案 | K21: =-K22-K20
C22: Cr. | D22: 45110000 | E22: 承攬工程收入 | F22: =-F20/(1-$E$80) | H22: Cr. | I22: 45110000 | J22: 承攬工程收入 | K22: =-K20/(1-$E$80)
B24: ELIA內部沖銷 | C24: Dr. | D24: 45110000 | E24: 承攬工程收入 | F24: =-F22
B25: TBU無分錄 | C25: Cr. | D25: 12470000 | E25: 在建損益-承攬案 | F25: =-F21
B26: 屬單邊沖銷 | C26: Cr. | D26: 55110000 | E26: 承攬工程成本 | F26: =-F20
C28: 此資產對全公司來說是「跟自己賺的錢」,不存在
A29: 5 | B29: 虧損專案 | C29: Dr. | D29: 55110006 | E29: 成本-負債準備 | F29: =$E$81 | H29: Dr. | I29: 55110006 | J29: 成本-負債準備 | K29: =$E$81
C30: Cr. | D30: 25600020 | E30: 負債準備 | F30: =-F29 | H30: Cr. | I30: 25600020 | J30: 負債準備 | K30: =-K29
A33: 6 | B33: BIM開立業主發票 | C33: Dr. | D33: 11430000 | E33: 公司內部往來-TO & BIM | F33: =$E$83 | G33: (B/S往來視為AR應收帳款) | H33: Dr. | I33: 11430000 | J33: 應收帳款 | K33: =-SUM(K34:K35) | L33: (真實應收) | M33: Dr. | N33: 11430000 | O33: 公司內部往來-TO & BIM | P33: =$E$83 | Q33: (B/S往來視為AR應收帳款) | R33: Dr. | S33: 11430000 | T33: 公司內部往來-TO & BIM | U33: =$E$83 | V33: (B/S往來視為AR應收帳款)
B34: BIM認列收入 | C34: Cr. | D34: 22640000 | E34: 預收工程款 | F34: =-F33 | H34: Cr. | I34: 22640000 | J34: 預收工程款 | K34: =-$E83 | M34: Cr. | N34: 46110050 | O34: 勞務收入-內部計價 | P34: =-P33 | R34: Cr. | S34: 46110050 | T34: 勞務收入-內部計價 | U34: =-U33
C35: Cr. | D35: 22140000 | E35: 銷項稅額 | H35: Cr. | I35: 22140000 | J35: 銷項稅額 | K35: =K34*0.05
B37: TBU認列成本 | C37: Dr. | D37: 63670100 | E37: 工程工務所費用-其他費用 | F37: =$E$83 | M37: Dr. | N37: 63670100 | O37: 工程工務所費用-其他費用 | P37: =$E$83 | R37: Dr. | S37: 62370030 | T37: 勞務費-其他 | U37: =$E$83
C38: Cr. | D38: 12872012 | E38: 公司內部往來-TO & BIM | F38: =-F37 | M38: Cr. | N38: 12872012 | O38: 公司內部往來-TO & BIM | P38: =-P37 | R38: Cr. | S38: 12872012 | T38: 公司內部往來-TO & BIM | U38: =-U37
B40: ELIA內部沖銷 | C40: Dr. | D40: 22640000 | E40: 預收工程款 | F40: =-F34 | M40: Dr. | N40: 46110050 | O40: 勞務收入-內部計價 | P40: =-P34 | R40: Dr. | S40: 46110050 | T40: 勞務收入-內部計價 | U40: =-U34
C41: Cr. | D41: 55110095 | E41: 承攬工程成本-其他 | F41: =-F40 | M41: Cr. | N41: 55110095 | O41: 承攬工程成本-其他 | P41: =-P40 | R41: Cr. | S41: 62370099 | T41: 勞務費-收回投標費 | U41: =-U40
A44: 7 | B44: BIM支付AP | C44: Dr. | D44: 21430000 | E44: 應付帳款 | F44: =-F6 | H44: Dr. | I44: 21430000 | J44: 應付帳款 | K44: =-K6 | M44: Dr. | N44: 21430000 | O44: 應付帳款 | P44: =-P6 | R44: Dr. | S44: 21430000 | T44: 應付帳款 | U44: =-U6
C45: Cr. | D45: 1103xxxx | E45: 銀行存款 | F45: =-F44 | H45: Cr. | I45: 1103xxxx | J45: 銀行存款 | K45: =-K44 | M45: Cr. | N45: 1103xxxx | O45: 銀行存款 | P45: =-P44 | R45: Cr. | S45: 1103xxxx | T45: 銀行存款 | U45: =-U44
A47: 8 | B47: BIM收取AR | C47: Dr. | D47: 1103xxxx | E47: 銀行存款 | H47: Dr. | I47: 1103xxxx | J47: 銀行存款 | K47: =-K48
C48: Cr. | D48: 11430000 | E48: 應收帳款 | H48: Cr. | I48: 11430000 | J48: 應收帳款 | K48: =-K33
A52: 期末總結 | B52: B/S | C52: 12400000 | D52: 在建工程 | E52: =SUMIF($D$4:$D$10,$C52,$F$4:$F$10)+SUMIF($D$16:$D$22,$C52,$F$16:$F$22)+SUMIF($D$33:$D$35,$C52,$F$33:$F$35)+SUMIF($D$44:$D$48,$C52,$F$44:$F$48)+SUMIF($D$29:$D$30,$C52,$F$29:$F$30) | F52: =SUM(E52:E54) | G52: =IF(F52>0,"應收建造合約款","應付建造合約款") | H52: 12400000 | I52: 在建工程 | J52: =SUMIF($I$4:$I$10,$H52,$K$4:$K$10)+SUMIF($I$16:$I$22,$H52,$K$16:$K$22)+SUMIF($I$33:$I$35,$H52,$K$33:$K$35)+SUMIF($I$44:$I$48,$H52,$K$44:$K$48)+SUMIF($I$29:$I$30,$H52,$K$29:$K$30) | K52: =SUM(J52:J54) | L52: =IF(K52>0,"應收建造合約款","應付建造合約款") | M52: 12400000 | N52: 在建工程 | O52: =SUMIF($N$4:$N$10,$M52,$P$4:$P$10)+SUMIF($N$16:$N$22,$M52,$P$16:$P$22)+SUMIF($N$33:$N$35,$M52,$P$33:$P$35)+SUMIF($N$44:$N$48,$M52,$P$44:$P$48)+SUMIF($N$29:$N$30,$M52,$P$29:$P$30) | P52: =SUM(O52:O54) | Q52: =IF(P52>0,"應收建造合約款","應付建造合約款") | R52: 12400000 | S52: 在建工程 | T52: =SUMIF($S$4:$S$10,$R52,$U$4:$U$10)+SUMIF($S$16:$S$22,$R52,$U$16:$U$22)+SUMIF($S$33:$S$35,$R52,$U$33:$U$35)+SUMIF($S$44:$S$48,$R52,$U$44:$U$48)+SUMIF($S$29:$S$30,$R52,$U$29:$U$30) | U52: =SUM(T52:T54) | V52: =IF(U52>0,"應收建造合約款","應付建造合約款")
C53: 12470000 | D53: 在建損益-承攬案 | E53: =SUMIF($D$4:$D$10,$C53,$F$4:$F$10)+SUMIF($D$16:$D$22,$C53,$F$16:$F$22)+SUMIF($D$33:$D$35,$C53,$F$33:$F$35)+SUMIF($D$44:$D$48,$C53,$F$44:$F$48)+SUMIF($D$29:$D$30,$C53,$F$29:$F$30) | H53: 12470000 | I53: 在建損益-承攬案 | J53: =SUMIF($I$4:$I$10,$H53,$K$4:$K$10)+SUMIF($I$16:$I$22,$H53,$K$16:$K$22)+SUMIF($I$33:$I$35,$H53,$K$33:$K$35)+SUMIF($I$44:$I$48,$H53,$K$44:$K$48)+SUMIF($I$29:$I$30,$H53,$K$29:$K$30) | M53: 12470000 | N53: 在建損益-承攬案 | O53: =SUMIF($N$4:$N$10,$M53,$P$4:$P$10)+SUMIF($N$16:$N$22,$M53,$P$16:$P$22)+SUMIF($N$33:$N$35,$M53,$P$33:$P$35)+SUMIF($N$44:$N$48,$M53,$P$44:$P$48)+SUMIF($N$29:$N$30,$M53,$P$29:$P$30) | R53: 12470000 | S53: 在建損益-承攬案 | T53: =SUMIF($S$4:$S$10,$R53,$U$4:$U$10)+SUMIF($S$16:$S$22,$R53,$U$16:$U$22)+SUMIF($S$33:$S$35,$R53,$U$33:$U$35)+SUMIF($S$44:$S$48,$R53,$U$44:$U$48)+SUMIF($S$29:$S$30,$R53,$U$29:$U$30)
C54: 22640000 | D54: 預收工程款 | E54: =SUMIF($D$4:$D$10,$C54,$F$4:$F$10)+SUMIF($D$16:$D$22,$C54,$F$16:$F$22)+SUMIF($D$33:$D$35,$C54,$F$33:$F$35)+SUMIF($D$44:$D$48,$C54,$F$44:$F$48)+SUMIF($D$29:$D$30,$C54,$F$29:$F$30) | H54: 22640000 | I54: 預收工程款 | J54: =SUMIF($I$4:$I$10,$H54,$K$4:$K$10)+SUMIF($I$16:$I$22,$H54,$K$16:$K$22)+SUMIF($I$33:$I$35,$H54,$K$33:$K$35)+SUMIF($I$44:$I$48,$H54,$K$44:$K$48)+SUMIF($I$29:$I$30,$H54,$K$29:$K$30) | M54: 22640000 | N54: 預收工程款 | O54: =SUMIF($N$4:$N$10,$M54,$P$4:$P$10)+SUMIF($N$16:$N$22,$M54,$P$16:$P$22)+SUMIF($N$33:$N$35,$M54,$P$33:$P$35)+SUMIF($N$44:$N$48,$M54,$P$44:$P$48)+SUMIF($N$29:$N$30,$M54,$P$29:$P$30) | R54: 22640000 | S54: 預收工程款 | T54: =SUMIF($S$4:$S$10,$R54,$U$4:$U$10)+SUMIF($S$16:$S$22,$R54,$U$16:$U$22)+SUMIF($S$33:$S$35,$R54,$U$33:$U$35)+SUMIF($S$44:$S$48,$R54,$U$44:$U$48)+SUMIF($S$29:$S$30,$R54,$U$29:$U$30)
C55: 1103xxxx | D55: 銀行存款 | E55: =SUMIF($D$4:$D$10,$C55,$F$4:$F$10)+SUMIF($D$16:$D$22,$C55,$F$16:$F$22)+SUMIF($D$33:$D$35,$C55,$F$33:$F$35)+SUMIF($D$44:$D$48,$C55,$F$44:$F$48)+SUMIF($D$29:$D$30,$C55,$F$29:$F$30) | F55: =E55 | G55: 銀行存款 | H55: 1103xxxx | I55: 銀行存款 | J55: =SUMIF($I$4:$I$10,$H55,$K$4:$K$10)+SUMIF($I$16:$I$22,$H55,$K$16:$K$22)+SUMIF($I$33:$I$35,$H55,$K$33:$K$35)+SUMIF($I$44:$I$48,$H55,$K$44:$K$48)+SUMIF($I$29:$I$30,$H55,$K$29:$K$30) | K55: =J55 | L55: 銀行存款 | M55: 1103xxxx | N55: 銀行存款 | O55: =SUMIF($N$4:$N$10,$M55,$P$4:$P$10)+SUMIF($N$16:$N$22,$M55,$P$16:$P$22)+SUMIF($N$33:$N$35,$M55,$P$33:$P$35)+SUMIF($N$44:$N$48,$M55,$P$44:$P$48)+SUMIF($N$29:$N$30,$M55,$P$29:$P$30) | P55: =O55 | Q55: 銀行存款 | R55: 1103xxxx | S55: 銀行存款 | T55: =SUMIF($S$4:$S$10,$R55,$U$4:$U$10)+SUMIF($S$16:$S$22,$R55,$U$16:$U$22)+SUMIF($S$33:$S$35,$R55,$U$33:$U$35)+SUMIF($S$44:$S$48,$R55,$U$44:$U$48)+SUMIF($S$29:$S$30,$R55,$U$29:$U$30) | U55: =T55 | V55: 銀行存款
C56: 11430000 | D56: 應收帳款 | E56: =SUMIF($D$4:$D$10,$C56,$F$4:$F$10)+SUMIF($D$16:$D$22,$C56,$F$16:$F$22)+SUMIF($D$33:$D$35,$C56,$F$33:$F$35)+SUMIF($D$44:$D$48,$C56,$F$44:$F$48)+SUMIF($D$29:$D$30,$C56,$F$29:$F$30) | F56: =E56 | G56: 應收帳款 | H56: 11430000 | I56: 應收帳款 | J56: =SUMIF($I$4:$I$10,$H56,$K$4:$K$10)+SUMIF($I$16:$I$22,$H56,$K$16:$K$22)+SUMIF($I$33:$I$35,$H56,$K$33:$K$35)+SUMIF($I$44:$I$48,$H56,$K$44:$K$48)+SUMIF($I$29:$I$30,$H56,$K$29:$K$30) | K56: =J56 | L56: 應收帳款 | M56: 11430000 | N56: 應收帳款 | O56: =SUMIF($N$4:$N$10,$M56,$P$4:$P$10)+SUMIF($N$16:$N$22,$M56,$P$16:$P$22)+SUMIF($N$33:$N$35,$M56,$P$33:$P$35)+SUMIF($N$44:$N$48,$M56,$P$44:$P$48)+SUMIF($N$29:$N$30,$M56,$P$29:$P$30) | P56: =O56 | Q56: 應收帳款 | R56: 11430000 | S56: 應收帳款 | T56: =SUMIF($S$4:$S$10,$R56,$U$4:$U$10)+SUMIF($S$16:$S$22,$R56,$U$16:$U$22)+SUMIF($S$33:$S$35,$R56,$U$33:$U$35)+SUMIF($S$44:$S$48,$R56,$U$44:$U$48)+SUMIF($S$29:$S$30,$R56,$U$29:$U$30) | U56: =T56 | V56: 應收帳款
C57: 21430000 | D57: 應付帳款 | E57: =SUMIF($D$4:$D$10,$C57,$F$4:$F$10)+SUMIF($D$16:$D$22,$C57,$F$16:$F$22)+SUMIF($D$33:$D$35,$C57,$F$33:$F$35)+SUMIF($D$44:$D$48,$C57,$F$44:$F$48)+SUMIF($D$29:$D$30,$C57,$F$29:$F$30) | F57: =E57 | G57: 應付帳款 | H57: 21430000 | I57: 應付帳款 | J57: =SUMIF($I$4:$I$10,$H57,$K$4:$K$10)+SUMIF($I$16:$I$22,$H57,$K$16:$K$22)+SUMIF($I$33:$I$35,$H57,$K$33:$K$35)+SUMIF($I$44:$I$48,$H57,$K$44:$K$48)+SUMIF($I$29:$I$30,$H57,$K$29:$K$30) | K57: =J57 | L57: 應付帳款 | M57: 21430000 | N57: 應付帳款 | O57: =SUMIF($N$4:$N$10,$M57,$P$4:$P$10)+SUMIF($N$16:$N$22,$M57,$P$16:$P$22)+SUMIF($N$33:$N$35,$M57,$P$33:$P$35)+SUMIF($N$44:$N$48,$M57,$P$44:$P$48)+SUMIF($N$29:$N$30,$M57,$P$29:$P$30) | P57: =O57 | Q57: 應付帳款 | R57: 21430000 | S57: 應付帳款 | T57: =SUMIF($S$4:$S$10,$R57,$U$4:$U$10)+SUMIF($S$16:$S$22,$R57,$U$16:$U$22)+SUMIF($S$33:$S$35,$R57,$U$33:$U$35)+SUMIF($S$44:$S$48,$R57,$U$44:$U$48)+SUMIF($S$29:$S$30,$R57,$U$29:$U$30) | U57: =T57 | V57: 應付帳款
C58: 25600020 | D58: 負債準備 | E58: =SUMIF($D$4:$D$10,$C58,$F$4:$F$10)+SUMIF($D$16:$D$22,$C58,$F$16:$F$22)+SUMIF($D$33:$D$35,$C58,$F$33:$F$35)+SUMIF($D$44:$D$48,$C58,$F$44:$F$48)+SUMIF($D$29:$D$30,$C58,$F$29:$F$30) | F58: =E58 | G58: 負債準備 | H58: 25600020 | I58: 負債準備 | J58: =SUMIF($I$4:$I$10,$H58,$K$4:$K$10)+SUMIF($I$16:$I$22,$H58,$K$16:$K$22)+SUMIF($I$33:$I$35,$H58,$K$33:$K$35)+SUMIF($I$44:$I$48,$H58,$K$44:$K$48)+SUMIF($I$29:$I$30,$H58,$K$29:$K$30) | K58: =J58 | L58: 負債準備
C59: 12640000 | D59: 進項稅額 | E59: =SUMIF($D$4:$D$10,$C59,$F$4:$F$10)+SUMIF($D$16:$D$22,$C59,$F$16:$F$22)+SUMIF($D$33:$D$35,$C59,$F$33:$F$35)+SUMIF($D$44:$D$48,$C59,$F$44:$F$48)+SUMIF($D$29:$D$30,$C59,$F$29:$F$30) | F59: =E59 | G59: 進項稅額 | H59: 12640000 | I59: 進項稅額 | J59: =SUMIF($I$4:$I$10,$H59,$K$4:$K$10)+SUMIF($I$16:$I$22,$H59,$K$16:$K$22)+SUMIF($I$33:$I$35,$H59,$K$33:$K$35)+SUMIF($I$44:$I$48,$H59,$K$44:$K$48)+SUMIF($I$29:$I$30,$H59,$K$29:$K$30) | K59: =J59 | L59: 進項稅額 | M59: 12640000 | N59: 進項稅額 | O59: =SUMIF($N$4:$N$10,$M59,$P$4:$P$10)+SUMIF($N$16:$N$22,$M59,$P$16:$P$22)+SUMIF($N$33:$N$35,$M59,$P$33:$P$35)+SUMIF($N$44:$N$48,$M59,$P$44:$P$48)+SUMIF($N$29:$N$30,$M59,$P$29:$P$30) | P59: =O59 | Q59: 進項稅額 | R59: 12640000 | S59: 進項稅額 | T59: =SUMIF($S$4:$S$10,$R59,$U$4:$U$10)+SUMIF($S$16:$S$22,$R59,$U$16:$U$22)+SUMIF($S$33:$S$35,$R59,$U$33:$U$35)+SUMIF($S$44:$S$48,$R59,$U$44:$U$48)+SUMIF($S$29:$S$30,$R59,$U$29:$U$30) | U59: =T59 | V59: 進項稅額
C60: 22140000 | D60: 銷項稅額 | E60: =SUMIF($D$4:$D$10,$C60,$F$4:$F$10)+SUMIF($D$16:$D$22,$C60,$F$16:$F$22)+SUMIF($D$33:$D$35,$C60,$F$33:$F$35)+SUMIF($D$44:$D$48,$C60,$F$44:$F$48)+SUMIF($D$29:$D$30,$C60,$F$29:$F$30) | F60: =E60 | G60: 銷項稅額 | H60: 22140000 | I60: 銷項稅額 | J60: =SUMIF($I$4:$I$10,$H60,$K$4:$K$10)+SUMIF($I$16:$I$22,$H60,$K$16:$K$22)+SUMIF($I$33:$I$35,$H60,$K$33:$K$35)+SUMIF($I$44:$I$48,$H60,$K$44:$K$48)+SUMIF($I$29:$I$30,$H60,$K$29:$K$30) | K60: =J60 | L60: 銷項稅額 | M60: 22140000 | N60: 銷項稅額 | O60: =SUMIF($N$4:$N$10,$M60,$P$4:$P$10)+SUMIF($N$16:$N$22,$M60,$P$16:$P$22)+SUMIF($N$33:$N$35,$M60,$P$33:$P$35)+SUMIF($N$44:$N$48,$M60,$P$44:$P$48)+SUMIF($N$29:$N$30,$M60,$P$29:$P$30) | P60: =O60 | Q60: 銷項稅額 | R60: 22140000 | S60: 銷項稅額 | T60: =SUMIF($S$4:$S$10,$R60,$U$4:$U$10)+SUMIF($S$16:$S$22,$R60,$U$16:$U$22)+SUMIF($S$33:$S$35,$R60,$U$33:$U$35)+SUMIF($S$44:$S$48,$R60,$U$44:$U$48)+SUMIF($S$29:$S$30,$R60,$U$29:$U$30) | U60: =T60 | V60: 銷項稅額
B61: P/L | C61: 45110000 | D61: 承攬工程收入 | E61: =SUMIF($D$4:$D$10,$C61,$F$4:$F$10)+SUMIF($D$16:$D$22,$C61,$F$16:$F$22)+SUMIF($D$33:$D$35,$C61,$F$33:$F$35)+SUMIF($D$44:$D$48,$C61,$F$44:$F$48)+SUMIF($D$29:$D$30,$C61,$F$29:$F$30) | F61: =SUM(E61:E71) | G61: 本期損益 | H61: 45110000 | I61: 承攬工程收入 | J61: =SUMIF($I$4:$I$10,$H61,$K$4:$K$10)+SUMIF($I$16:$I$22,$H61,$K$16:$K$22)+SUMIF($I$33:$I$35,$H61,$K$33:$K$35)+SUMIF($I$44:$I$48,$H61,$K$44:$K$48)+SUMIF($I$29:$I$30,$H61,$K$29:$K$30) | K61: =SUM(J61:J71) | L61: 本期損益 | M61: 45110000 | N61: 承攬工程收入 | O61: =SUMIF($N$4:$N$10,$M61,$P$4:$P$10)+SUMIF($N$16:$N$22,$M61,$P$16:$P$22)+SUMIF($N$33:$N$35,$M61,$P$33:$P$35)+SUMIF($N$44:$N$48,$M61,$P$44:$P$48)+SUMIF($N$29:$N$30,$M61,$P$29:$P$30) | P61: =SUM(O61:O71) | Q61: 本期損益 | R61: 45110000 | S61: 承攬工程收入 | T61: =SUMIF($S$4:$S$10,$R61,$U$4:$U$10)+SUMIF($S$16:$S$22,$R61,$U$16:$U$22)+SUMIF($S$33:$S$35,$R61,$U$33:$U$35)+SUMIF($S$44:$S$48,$R61,$U$44:$U$48)+SUMIF($S$29:$S$30,$R61,$U$29:$U$30) | U61: =SUM(T61:T71) | V61: 本期損益
C62: 55110000 | D62: 承攬工程成本 | E62: =SUMIF($D$4:$D$10,$C62,$F$4:$F$10)+SUMIF($D$16:$D$22,$C62,$F$16:$F$22)+SUMIF($D$33:$D$35,$C62,$F$33:$F$35)+SUMIF($D$44:$D$48,$C62,$F$44:$F$48)+SUMIF($D$29:$D$30,$C62,$F$29:$F$30) | H62: 55110000 | I62: 承攬工程成本 | J62: =SUMIF($I$4:$I$10,$H62,$K$4:$K$10)+SUMIF($I$16:$I$22,$H62,$K$16:$K$22)+SUMIF($I$33:$I$35,$H62,$K$33:$K$35)+SUMIF($I$44:$I$48,$H62,$K$44:$K$48)+SUMIF($I$29:$I$30,$H62,$K$29:$K$30) | M62: 55110000 | N62: 承攬工程成本 | O62: =SUMIF($N$4:$N$10,$M62,$P$4:$P$10)+SUMIF($N$16:$N$22,$M62,$P$16:$P$22)+SUMIF($N$33:$N$35,$M62,$P$33:$P$35)+SUMIF($N$44:$N$48,$M62,$P$44:$P$48)+SUMIF($N$29:$N$30,$M62,$P$29:$P$30) | R62: 55110000 | S62: 承攬工程成本 | T62: =SUMIF($S$4:$S$10,$R62,$U$4:$U$10)+SUMIF($S$16:$S$22,$R62,$U$16:$U$22)+SUMIF($S$33:$S$35,$R62,$U$33:$U$35)+SUMIF($S$44:$S$48,$R62,$U$44:$U$48)+SUMIF($S$29:$S$30,$R62,$U$29:$U$30)
C63: 55110006 | D63: 成本-負債準備 | E63: =SUMIF($D$4:$D$10,$C63,$F$4:$F$10)+SUMIF($D$16:$D$22,$C63,$F$16:$F$22)+SUMIF($D$33:$D$35,$C63,$F$33:$F$35)+SUMIF($D$44:$D$48,$C63,$F$44:$F$48)+SUMIF($D$29:$D$30,$C63,$F$29:$F$30) | H63: 55110006 | I63: 成本-負債準備 | J63: =SUMIF($I$4:$I$10,$H63,$K$4:$K$10)+SUMIF($I$16:$I$22,$H63,$K$16:$K$22)+SUMIF($I$33:$I$35,$H63,$K$33:$K$35)+SUMIF($I$44:$I$48,$H63,$K$44:$K$48)+SUMIF($I$29:$I$30,$H63,$K$29:$K$30) | M63: 55/56xxxxxx | N63: 專案成本 | O63: =SUMIF($N$4:$N$10,$M63,$P$4:$P$10)+SUMIF($N$16:$N$22,$M63,$P$16:$P$22)+SUMIF($N$33:$N$35,$M63,$P$33:$P$35)+SUMIF($N$44:$N$48,$M63,$P$44:$P$48)+SUMIF($N$29:$N$30,$M63,$P$29:$P$30) | R63: 55/56xxxxxx | S63: 專案成本 | T63: =SUMIF($S$4:$S$10,$R63,$U$4:$U$10)+SUMIF($S$16:$S$22,$R63,$U$16:$U$22)+SUMIF($S$33:$S$35,$R63,$U$33:$U$35)+SUMIF($S$44:$S$48,$R63,$U$44:$U$48)+SUMIF($S$29:$S$30,$R63,$U$29:$U$30)
J64: =SUMIF($I$4:$I$10,$H64,$K$4:$K$10)+SUMIF($I$16:$I$22,$H64,$K$16:$K$22)+SUMIF($I$33:$I$35,$H64,$K$33:$K$35)+SUMIF($I$44:$I$48,$H64,$K$44:$K$48)+SUMIF($I$29:$I$30,$H64,$K$29:$K$30) | M64: 55110098 | N64: 承攬工程成本-非人事 | O64: =SUMIF($N$4:$N$10,$M64,$P$4:$P$10)+SUMIF($N$16:$N$22,$M64,$P$16:$P$22)+SUMIF($N$33:$N$35,$M64,$P$33:$P$35)+SUMIF($N$44:$N$48,$M64,$P$44:$P$48)+SUMIF($N$29:$N$30,$M64,$P$29:$P$30) | R64: 55110098 | S64: 承攬工程成本-非人事 | T64: =SUMIF($S$4:$S$10,$R64,$U$4:$U$10)+SUMIF($S$16:$S$22,$R64,$U$16:$U$22)+SUMIF($S$33:$S$35,$R64,$U$33:$U$35)+SUMIF($S$44:$S$48,$R64,$U$44:$U$48)+SUMIF($S$29:$S$30,$R64,$U$29:$U$30)
C65: 62xxxxxx | D65: 辦公室費用 | E65: =SUMIF($D$4:$D$10,$C65,$F$4:$F$10)+SUMIF($D$16:$D$22,$C65,$F$16:$F$22)+SUMIF($D$33:$D$35,$C65,$F$33:$F$35)+SUMIF($D$44:$D$48,$C65,$F$44:$F$48)+SUMIF($D$29:$D$30,$C65,$F$29:$F$30) | H65: 62xxxxxx | I65: 辦公室費用 | J65: =SUMIF($I$4:$I$10,$H65,$K$4:$K$10)+SUMIF($I$16:$I$22,$H65,$K$16:$K$22)+SUMIF($I$33:$I$35,$H65,$K$33:$K$35)+SUMIF($I$44:$I$48,$H65,$K$44:$K$48)+SUMIF($I$29:$I$30,$H65,$K$29:$K$30) | M65: 46110050 | N65: 勞務收入-內部計價 | O65: =SUMIF($N$4:$N$10,$M65,$P$4:$P$10)+SUMIF($N$16:$N$22,$M65,$P$16:$P$22)+SUMIF($N$33:$N$35,$M65,$P$33:$P$35)+SUMIF($N$44:$N$48,$M65,$P$44:$P$48)+SUMIF($N$29:$N$30,$M65,$P$29:$P$30) | R65: 46110050 | S65: 勞務收入-內部計價 | T65: =SUMIF($S$4:$S$10,$R65,$U$4:$U$10)+SUMIF($S$16:$S$22,$R65,$U$16:$U$22)+SUMIF($S$33:$S$35,$R65,$U$33:$U$35)+SUMIF($S$44:$S$48,$R65,$U$44:$U$48)+SUMIF($S$29:$S$30,$R65,$U$29:$U$30)
E66: =SUMIF($D$4:$D$10,$C66,$F$4:$F$10)+SUMIF($D$16:$D$22,$C66,$F$16:$F$22)+SUMIF($D$33:$D$35,$C66,$F$33:$F$35)+SUMIF($D$44:$D$48,$C66,$F$44:$F$48)+SUMIF($D$29:$D$30,$C66,$F$29:$F$30) | J66: =SUMIF($I$4:$I$10,$H66,$K$4:$K$10)+SUMIF($I$16:$I$22,$H66,$K$16:$K$22)+SUMIF($I$33:$I$35,$H66,$K$33:$K$35)+SUMIF($I$44:$I$48,$H66,$K$44:$K$48)+SUMIF($I$29:$I$30,$H66,$K$29:$K$30) | M66: 62xxxxxx | N66: 辦公室費用 | O66: =SUMIF($N$4:$N$10,$M66,$P$4:$P$10)+SUMIF($N$16:$N$22,$M66,$P$16:$P$22)+SUMIF($N$33:$N$35,$M66,$P$33:$P$35)+SUMIF($N$44:$N$48,$M66,$P$44:$P$48)+SUMIF($N$29:$N$30,$M66,$P$29:$P$30) | R66: 62xxxxxx | S66: 辦公室費用 | T66: =SUMIF($S$4:$S$10,$R66,$U$4:$U$10)+SUMIF($S$16:$S$22,$R66,$U$16:$U$22)+SUMIF($S$33:$S$35,$R66,$U$33:$U$35)+SUMIF($S$44:$S$48,$R66,$U$44:$U$48)+SUMIF($S$29:$S$30,$R66,$U$29:$U$30)
J67: =SUMIF($I$4:$I$10,$H67,$K$4:$K$10)+SUMIF($I$16:$I$22,$H67,$K$16:$K$22)+SUMIF($I$33:$I$35,$H67,$K$33:$K$35)+SUMIF($I$44:$I$48,$H67,$K$44:$K$48)+SUMIF($I$29:$I$30,$H67,$K$29:$K$30) | M67: 62109999 | N67: 人事分攤 | O67: =SUMIF($N$4:$N$10,$M67,$P$4:$P$10)+SUMIF($N$16:$N$22,$M67,$P$16:$P$22)+SUMIF($N$33:$N$35,$M67,$P$33:$P$35)+SUMIF($N$44:$N$48,$M67,$P$44:$P$48)+SUMIF($N$29:$N$30,$M67,$P$29:$P$30) | R67: 62109999 | S67: 人事分攤 | T67: =SUMIF($S$4:$S$10,$R67,$U$4:$U$10)+SUMIF($S$16:$S$22,$R67,$U$16:$U$22)+SUMIF($S$33:$S$35,$R67,$U$33:$U$35)+SUMIF($S$44:$S$48,$R67,$U$44:$U$48)+SUMIF($S$29:$S$30,$R67,$U$29:$U$30)
J68: =SUMIF($I$4:$I$10,$H68,$K$4:$K$10)+SUMIF($I$16:$I$22,$H68,$K$16:$K$22)+SUMIF($I$33:$I$35,$H68,$K$33:$K$35)+SUMIF($I$44:$I$48,$H68,$K$44:$K$48)+SUMIF($I$29:$I$30,$H68,$K$29:$K$30) | M68: 62370099 | N68: 勞務費-收回投標費 | O68: =SUMIF($N$4:$N$10,$M68,$P$4:$P$10)+SUMIF($N$16:$N$22,$M68,$P$16:$P$22)+SUMIF($N$33:$N$35,$M68,$P$33:$P$35)+SUMIF($N$44:$N$48,$M68,$P$44:$P$48)+SUMIF($N$29:$N$30,$M68,$P$29:$P$30) | R68: 62370099 | S68: 勞務費-收回投標費 | T68: =SUMIF($S$4:$S$10,$R68,$U$4:$U$10)+SUMIF($S$16:$S$22,$R68,$U$16:$U$22)+SUMIF($S$33:$S$35,$R68,$U$33:$U$35)+SUMIF($S$44:$S$48,$R68,$U$44:$U$48)+SUMIF($S$29:$S$30,$R68,$U$29:$U$30)
E69: =SUMIF($D$4:$D$10,$C69,$F$4:$F$10)+SUMIF($D$16:$D$22,$C69,$F$16:$F$22)+SUMIF($D$33:$D$35,$C69,$F$33:$F$35)+SUMIF($D$44:$D$48,$C69,$F$44:$F$48)+SUMIF($D$29:$D$30,$C69,$F$29:$F$30) | J69: =SUMIF($I$4:$I$10,$H69,$K$4:$K$10)+SUMIF($I$16:$I$22,$H69,$K$16:$K$22)+SUMIF($I$33:$I$35,$H69,$K$33:$K$35)+SUMIF($I$44:$I$48,$H69,$K$44:$K$48)+SUMIF($I$29:$I$30,$H69,$K$29:$K$30) | M69: 62350099 | N69: 電腦out charge | O69: =SUMIF($N$4:$N$10,$M69,$P$4:$P$10)+SUMIF($N$16:$N$22,$M69,$P$16:$P$22)+SUMIF($N$33:$N$35,$M69,$P$33:$P$35)+SUMIF($N$44:$N$48,$M69,$P$44:$P$48)+SUMIF($N$29:$N$30,$M69,$P$29:$P$30) | R69: 62350099 | S69: 電腦out charge | T69: =SUMIF($S$4:$S$10,$R69,$U$4:$U$10)+SUMIF($S$16:$S$22,$R69,$U$16:$U$22)+SUMIF($S$33:$S$35,$R69,$U$33:$U$35)+SUMIF($S$44:$S$48,$R69,$U$44:$U$48)+SUMIF($S$29:$S$30,$R69,$U$29:$U$30)
C70: 63xxxxxx | D70: 工程費用 | E70: =SUMIF($D$4:$D$10,$C70,$F$4:$F$10)+SUMIF($D$16:$D$22,$C70,$F$16:$F$22)+SUMIF($D$33:$D$35,$C70,$F$33:$F$35)+SUMIF($D$44:$D$48,$C70,$F$44:$F$48)+SUMIF($D$29:$D$30,$C70,$F$29:$F$30) | H70: 63xxxxxx | I70: 工程費用 | J70: =SUMIF($I$4:$I$10,$H70,$K$4:$K$10)+SUMIF($I$16:$I$22,$H70,$K$16:$K$22)+SUMIF($I$33:$I$35,$H70,$K$33:$K$35)+SUMIF($I$44:$I$48,$H70,$K$44:$K$48)+SUMIF($I$29:$I$30,$H70,$K$29:$K$30) | M70: 63xxxxxx | N70: 工程費用 | O70: =SUMIF($N$4:$N$10,$M70,$P$4:$P$10)+SUMIF($N$16:$N$22,$M70,$P$16:$P$22)+SUMIF($N$33:$N$35,$M70,$P$33:$P$35)+SUMIF($N$44:$N$48,$M70,$P$44:$P$48)+SUMIF($N$29:$N$30,$M70,$P$29:$P$30) | R70: 63xxxxxx | S70: 工程費用 | T70: =SUMIF($S$4:$S$10,$R70,$U$4:$U$10)+SUMIF($S$16:$S$22,$R70,$U$16:$U$22)+SUMIF($S$33:$S$35,$R70,$U$33:$U$35)+SUMIF($S$44:$S$48,$R70,$U$44:$U$48)+SUMIF($S$29:$S$30,$R70,$U$29:$U$30)
C71: 63810030 | D71: 工程費用轉在建工程 | E71: =SUMIF($D$4:$D$10,$C71,$F$4:$F$10)+SUMIF($D$16:$D$22,$C71,$F$16:$F$22)+SUMIF($D$33:$D$35,$C71,$F$33:$F$35)+SUMIF($D$44:$D$48,$C71,$F$44:$F$48)+SUMIF($D$29:$D$30,$C71,$F$29:$F$30) | H71: 63810030 | I71: 工程費用轉在建工程 | J71: =SUMIF($I$4:$I$10,$H71,$K$4:$K$10)+SUMIF($I$16:$I$22,$H71,$K$16:$K$22)+SUMIF($I$33:$I$35,$H71,$K$33:$K$35)+SUMIF($I$44:$I$48,$H71,$K$44:$K$48)+SUMIF($I$29:$I$30,$H71,$K$29:$K$30) | M71: 63810030 | N71: 工程費用轉在建工程 | O71: =SUMIF($N$4:$N$10,$M71,$P$4:$P$10)+SUMIF($N$16:$N$22,$M71,$P$16:$P$22)+SUMIF($N$33:$N$35,$M71,$P$33:$P$35)+SUMIF($N$44:$N$48,$M71,$P$44:$P$48)+SUMIF($N$29:$N$30,$M71,$P$29:$P$30) | R71: 63810030 | S71: 工程費用轉在建工程 | T71: =SUMIF($S$4:$S$10,$R71,$U$4:$U$10)+SUMIF($S$16:$S$22,$R71,$U$16:$U$22)+SUMIF($S$33:$S$35,$R71,$U$33:$U$35)+SUMIF($S$44:$S$48,$R71,$U$44:$U$48)+SUMIF($S$29:$S$30,$R71,$U$29:$U$30)
D72: check | E72: =SUM(E52:E71) | F72: =SUM(F52:F71) | J72: =SUM(J52:J71) | K72: =SUM(K52:K71) | O72: =SUM(O52:O71) | P72: =SUM(P52:P71) | T72: =SUM(T52:T71) | U72: =SUM(U52:U71)
C76: 假設:
D77: 合約總價 | E77: 1000
D78: 預估完工總成本 | E78: 950
D79: 預估毛利 | E79: =E77-E78
D80: 預估毛利率 | E80: =E79/E77
D81: 本月提列虧損準備(虧損專案) | E81: 10
D82: 本月投入成本 | E82: 100
D83: 本月開立發票(未稅) | E83: 120
D85: 完工百分比 | E85: =E82/E78

Sheet 檢核
A1: A. 每筆分錄借貸差（應為0） | G1: 輔助：主表每列（非BIM列記為空）
A2: 分錄 | B2: 內案POC | C2: 外案POC | D2: 雜項 | E2: 備標
A3: 1 費用入帳（第4-6列） | B3: =ROUND(SUM(工作表1!F4:F6),6) | C3: =ROUND(SUM(工作表1!K4:K6),6) | D3: =ROUND(SUM(工作表1!P4:P6),6) | E3: =ROUND(SUM(工作表1!U4:U6),6) | H3: 內案POC類別 | I3: 內案POC金額 | J3: 內案POC未入總結 | K3: 外案POC類別 | L3: 外案POC金額 | M3: 外案POC未入總結 | N3: 雜項類別 | O3: 雜項金額 | P3: 雜項未入總結 | Q3: 備標類別 | R3: 備標金額 | S3: 備標未入總結
A4: 2 費用轉列成本（第8-10列） | B4: =ROUND(SUM(工作表1!F8:F10),6) | C4: =ROUND(SUM(工作表1!K8:K10),6) | D4: =ROUND(SUM(工作表1!P8:P10),6) | E4: =ROUND(SUM(工作表1!U8:U10),6) | H4: =IF(工作表1!D4="","",LEFT(工作表1!D4,1)) | I4: =IF(ISNUMBER(工作表1!F4),工作表1!F4,0) | J4: =IF(工作表1!D4="",0,IF(COUNTIF(工作表1!$C$52:$C$71,工作表1!D4)>0,0,1)) | K4: =IF(工作表1!I4="","",LEFT(工作表1!I4,1)) | L4: =IF(ISNUMBER(工作表1!K4),工作表1!K4,0) | M4: =IF(工作表1!I4="",0,IF(COUNTIF(工作表1!$H$52:$H$71,工作表1!I4)>0,0,1)) | N4: =IF(工作表1!N4="","",LEFT(工作表1!N4,1)) | O4: =IF(ISNUMBER(工作表1!P4),工作表1!P4,0) | P4: =IF(工作表1!N4="",0,IF(COUNTIF(工作表1!$M$52:$M$71,工作表1!N4)>0,0,1)) | Q4: =IF(工作表1!S4="","",LEFT(工作表1!S4,1)) | R4: =IF(ISNUMBER(工作表1!U4),工作表1!U4,0) | S4: =IF(工作表1!S4="",0,IF(COUNTIF(工作表1!$R$52:$R$71,工作表1!S4)>0,0,1))
A5: 2 ELIA(備標)（第12-15列） | B5: =ROUND(SUM(工作表1!F12:F15),6) | C5: =ROUND(SUM(工作表1!K12:K15),6) | D5: =ROUND(SUM(工作表1!P12:P15),6) | E5: =ROUND(SUM(工作表1!U12:U15),6) | H5: =IF(工作表1!D5="","",LEFT(工作表1!D5,1)) | I5: =IF(ISNUMBER(工作表1!F5),工作表1!F5,0) | J5: =IF(工作表1!D5="",0,IF(COUNTIF(工作表1!$C$52:$C$71,工作表1!D5)>0,0,1)) | K5: =IF(工作表1!I5="","",LEFT(工作表1!I5,1)) | L5: =IF(ISNUMBER(工作表1!K5),工作表1!K5,0) | M5: =IF(工作表1!I5="",0,IF(COUNTIF(工作表1!$H$52:$H$71,工作表1!I5)>0,0,1)) | N5: =IF(工作表1!N5="","",LEFT(工作表1!N5,1)) | O5: =IF(ISNUMBER(工作表1!P5),工作表1!P5,0) | P5: =IF(工作表1!N5="",0,IF(COUNTIF(工作表1!$M$52:$M$71,工作表1!N5)>0,0,1)) | Q5: =IF(工作表1!S5="","",LEFT(工作表1!S5,1)) | R5: =IF(ISNUMBER(工作表1!U5),工作表1!U5,0) | S5: =IF(工作表1!S5="",0,IF(COUNTIF(工作表1!$R$52:$R$71,工作表1!S5)>0,0,1))
A6: 3 月底結轉在建（第16-17列） | B6: =ROUND(SUM(工作表1!F16:F17),6) | C6: =ROUND(SUM(工作表1!K16:K17),6) | D6: =ROUND(SUM(工作表1!P16:P17),6) | E6: =ROUND(SUM(工作表1!U16:U17),6) | H6: =IF(工作表1!D6="","",LEFT(工作表1!D6,1)) | I6: =IF(ISNUMBER(工作表1!F6),工作表1!F6,0) | J6: =IF(工作表1!D6="",0,IF(COUNTIF(工作表1!$C$52:$C$71,工作表1!D6)>0,0,1)) | K6: =IF(工作表1!I6="","",LEFT(工作表1!I6,1)) | L6: =IF(ISNUMBER(工作表1!K6),工作表1!K6,0) | M6: =IF(工作表1!I6="",0,IF(COUNTIF(工作表1!$H$52:$H$71,工作表1!I6)>0,0,1)) | N6: =IF(工作表1!N6="","",LEFT(工作表1!N6,1)) | O6: =IF(ISNUMBER(工作表1!P6),工作表1!P6,0) | P6: =IF(工作表1!N6="",0,IF(COUNTIF(工作表1!$M$52:$M$71,工作表1!N6)>0,0,1)) | Q6: =IF(工作表1!S6="","",LEFT(工作表1!S6,1)) | R6: =IF(ISNUMBER(工作表1!U6),工作表1!U6,0) | S6: =IF(工作表1!S6="",0,IF(COUNTIF(工作表1!$R$52:$R$71,工作表1!S6)>0,0,1))
A7: 4 完工百分比認列（第20-22列） | B7: =ROUND(SUM(工作表1!F20:F22),6) | C7: =ROUND(SUM(工作表1!K20:K22),6) | D7: =ROUND(SUM(工作表1!P20:P22),6) | E7: =ROUND(SUM(工作表1!U20:U22),6) | H7: =IF(工作表1!D7="","",LEFT(工作表1!D7,1)) | I7: =IF(ISNUMBER(工作表1!F7),工作表1!F7,0) | J7: =IF(工作表1!D7="",0,IF(COUNTIF(工作表1!$C$52:$C$71,工作表1!D7)>0,0,1)) | K7: =IF(工作表1!I7="","",LEFT(工作表1!I7,1)) | L7: =IF(ISNUMBER(工作表1!K7),工作表1!K7,0) | M7: =IF(工作表1!I7="",0,IF(COUNTIF(工作表1!$H$52:$H$71,工作表1!I7)>0,0,1)) | N7: =IF(工作表1!N7="","",LEFT(工作表1!N7,1)) | O7: =IF(ISNUMBER(工作表1!P7),工作表1!P7,0) | P7: =IF(工作表1!N7="",0,IF(COUNTIF(工作表1!$M$52:$M$71,工作表1!N7)>0,0,1)) | Q7: =IF(工作表1!S7="","",LEFT(工作表1!S7,1)) | R7: =IF(ISNUMBER(工作表1!U7),工作表1!U7,0) | S7: =IF(工作表1!S7="",0,IF(COUNTIF(工作表1!$R$52:$R$71,工作表1!S7)>0,0,1))
A8: 4 ELIA（第24-26列） | B8: =ROUND(SUM(工作表1!F24:F26),6) | C8: =ROUND(SUM(工作表1!K24:K26),6) | D8: =ROUND(SUM(工作表1!P24:P26),6) | E8: =ROUND(SUM(工作表1!U24:U26),6) | H8: =IF(工作表1!D8="","",LEFT(工作表1!D8,1)) | I8: =IF(ISNUMBER(工作表1!F8),工作表1!F8,0) | J8: =IF(工作表1!D8="",0,IF(COUNTIF(工作表1!$C$52:$C$71,工作表1!D8)>0,0,1)) | K8: =IF(工作表1!I8="","",LEFT(工作表1!I8,1)) | L8: =IF(ISNUMBER(工作表1!K8),工作表1!K8,0) | M8: =IF(工作表1!I8="",0,IF(COUNTIF(工作表1!$H$52:$H$71,工作表1!I8)>0,0,1)) | N8: =IF(工作表1!N8="","",LEFT(工作表1!N8,1)) | O8: =IF(ISNUMBER(工作表1!P8),工作表1!P8,0) | P8: =IF(工作表1!N8="",0,IF(COUNTIF(工作表1!$M$52:$M$71,工作表1!N8)>0,0,1)) | Q8: =IF(工作表1!S8="","",LEFT(工作表1!S8,1)) | R8: =IF(ISNUMBER(工作表1!U8),工作表1!U8,0) | S8: =IF(工作表1!S8="",0,IF(COUNTIF(工作表1!$R$52:$R$71,工作表1!S8)>0,0,1))
A9: 5 虧損專案（負債準備）（第29-30列） | B9: =ROUND(SUM(工作表1!F29:F30),6) | C9: =ROUND(SUM(工作表1!K29:K30),6) | D9: =ROUND(SUM(工作表1!P29:P30),6) | E9: =ROUND(SUM(工作表1!U29:U30),6) | H9: =IF(工作表1!D9="","",LEFT(工作表1!D9,1)) | I9: =IF(ISNUMBER(工作表1!F9),工作表1!F9,0) | J9: =IF(工作表1!D9="",0,IF(COUNTIF(工作表1!$C$52:$C$71,工作表1!D9)>0,0,1)) | K9: =IF(工作表1!I9="","",LEFT(工作表1!I9,1)) | L9: =IF(ISNUMBER(工作表1!K9),工作表1!K9,0) | M9: =IF(工作表1!I9="",0,IF(COUNTIF(工作表1!$H$52:$H$71,工作表1!I9)>0,0,1)) | N9: =IF(工作表1!N9="","",LEFT(工作表1!N9,1)) | O9: =IF(ISNUMBER(工作表1!P9),工作表1!P9,0) | P9: =IF(工作表1!N9="",0,IF(COUNTIF(工作表1!$M$52:$M$71,工作表1!N9)>0,0,1)) | Q9: =IF(工作表1!S9="","",LEFT(工作表1!S9,1)) | R9: =IF(ISNUMBER(工作表1!U9),工作表1!U9,0) | S9: =IF(工作表1!S9="",0,IF(COUNTIF(工作表1!$R$52:$R$71,工作表1!S9)>0,0,1))
A10: 6 開立發票（第33-35列） | B10: =ROUND(SUM(工作表1!F33:F35),6) | C10: =ROUND(SUM(工作表1!K33:K35),6) | D10: =ROUND(SUM(工作表1!P33:P35),6) | E10: =ROUND(SUM(工作表1!U33:U35),6) | H10: =IF(工作表1!D10="","",LEFT(工作表1!D10,1)) | I10: =IF(ISNUMBER(工作表1!F10),工作表1!F10,0) | J10: =IF(工作表1!D10="",0,IF(COUNTIF(工作表1!$C$52:$C$71,工作表1!D10)>0,0,1)) | K10: =IF(工作表1!I10="","",LEFT(工作表1!I10,1)) | L10: =IF(ISNUMBER(工作表1!K10),工作表1!K10,0) | M10: =IF(工作表1!I10="",0,IF(COUNTIF(工作表1!$H$52:$H$71,工作表1!I10)>0,0,1)) | N10: =IF(工作表1!N10="","",LEFT(工作表1!N10,1)) | O10: =IF(ISNUMBER(工作表1!P10),工作表1!P10,0) | P10: =IF(工作表1!N10="",0,IF(COUNTIF(工作表1!$M$52:$M$71,工作表1!N10)>0,0,1)) | Q10: =IF(工作表1!S10="","",LEFT(工作表1!S10,1)) | R10: =IF(ISNUMBER(工作表1!U10),工作表1!U10,0) | S10: =IF(工作表1!S10="",0,IF(COUNTIF(工作表1!$R$52:$R$71,工作表1!S10)>0,0,1))
A11: 6 TBU認列成本（第37-38列） | B11: =ROUND(SUM(工作表1!F37:F38),6) | C11: =ROUND(SUM(工作表1!K37:K38),6) | D11: =ROUND(SUM(工作表1!P37:P38),6) | E11: =ROUND(SUM(工作表1!U37:U38),6) | I11: 0 | J11: 0 | L11: 0 | M11: 0 | O11: 0 | P11: 0 | R11: 0 | S11: 0
A12: 6 ELIA（第40-41列） | B12: =ROUND(SUM(工作表1!F40:F41),6) | C12: =ROUND(SUM(工作表1!K40:K41),6) | D12: =ROUND(SUM(工作表1!P40:P41),6) | E12: =ROUND(SUM(工作表1!U40:U41),6) | I12: 0 | J12: 0 | L12: 0 | M12: 0 | O12: 0 | P12: 0 | R12: 0 | S12: 0
A13: 7 支付AP（第44-45列） | B13: =ROUND(SUM(工作表1!F44:F45),6) | C13: =ROUND(SUM(工作表1!K44:K45),6) | D13: =ROUND(SUM(工作表1!P44:P45),6) | E13: =ROUND(SUM(工作表1!U44:U45),6) | I13: 0 | J13: 0 | L13: 0 | M13: 0 | O13: 0 | P13: 0 | R13: 0 | S13: 0
A14: 8 收取AR（第47-48列） | B14: =ROUND(SUM(工作表1!F47:F48),6) | C14: =ROUND(SUM(工作表1!K47:K48),6) | D14: =ROUND(SUM(工作表1!P47:P48),6) | E14: =ROUND(SUM(工作表1!U47:U48),6) | I14: 0 | J14: 0 | L14: 0 | M14: 0 | O14: 0 | P14: 0 | R14: 0 | S14: 0
A15: A 結果 | B15: =IF(SUMPRODUCT(ABS(B3:B14))<0.000001,"OK","不平") | C15: =IF(SUMPRODUCT(ABS(C3:C14))<0.000001,"OK","不平") | D15: =IF(SUMPRODUCT(ABS(D3:D14))<0.000001,"OK","不平") | E15: =IF(SUMPRODUCT(ABS(E3:E14))<0.000001,"OK","不平") | I15: 0 | J15: 0 | L15: 0 | M15: 0 | O15: 0 | P15: 0 | R15: 0 | S15: 0
A16: B. 期末總結 vs BIM分錄直接加總（只計BIM列；代號首碼1/2=B/S，4/5/6=P/L） | H16: =IF(工作表1!D16="","",LEFT(工作表1!D16,1)) | I16: =IF(ISNUMBER(工作表1!F16),工作表1!F16,0) | J16: =IF(工作表1!D16="",0,IF(COUNTIF(工作表1!$C$52:$C$71,工作表1!D16)>0,0,1)) | K16: =IF(工作表1!I16="","",LEFT(工作表1!I16,1)) | L16: =IF(ISNUMBER(工作表1!K16),工作表1!K16,0) | M16: =IF(工作表1!I16="",0,IF(COUNTIF(工作表1!$H$52:$H$71,工作表1!I16)>0,0,1)) | N16: =IF(工作表1!N16="","",LEFT(工作表1!N16,1)) | O16: =IF(ISNUMBER(工作表1!P16),工作表1!P16,0) | P16: =IF(工作表1!N16="",0,IF(COUNTIF(工作表1!$M$52:$M$71,工作表1!N16)>0,0,1)) | Q16: =IF(工作表1!S16="","",LEFT(工作表1!S16,1)) | R16: =IF(ISNUMBER(工作表1!U16),工作表1!U16,0) | S16: =IF(工作表1!S16="",0,IF(COUNTIF(工作表1!$R$52:$R$71,工作表1!S16)>0,0,1))
A17: 項目 | B17: 內案POC | C17: 外案POC | D17: 雜項 | E17: 備標 | H17: =IF(工作表1!D17="","",LEFT(工作表1!D17,1)) | I17: =IF(ISNUMBER(工作表1!F17),工作表1!F17,0) | J17: =IF(工作表1!D17="",0,IF(COUNTIF(工作表1!$C$52:$C$71,工作表1!D17)>0,0,1)) | K17: =IF(工作表1!I17="","",LEFT(工作表1!I17,1)) | L17: =IF(ISNUMBER(工作表1!K17),工作表1!K17,0) | M17: =IF(工作表1!I17="",0,IF(COUNTIF(工作表1!$H$52:$H$71,工作表1!I17)>0,0,1)) | N17: =IF(工作表1!N17="","",LEFT(工作表1!N17,1)) | O17: =IF(ISNUMBER(工作表1!P17),工作表1!P17,0) | P17: =IF(工作表1!N17="",0,IF(COUNTIF(工作表1!$M$52:$M$71,工作表1!N17)>0,0,1)) | Q17: =IF(工作表1!S17="","",LEFT(工作表1!S17,1)) | R17: =IF(ISNUMBER(工作表1!U17),工作表1!U17,0) | S17: =IF(工作表1!S17="",0,IF(COUNTIF(工作表1!$R$52:$R$71,工作表1!S17)>0,0,1))
A18: B/S 分錄加總 | B18: =SUMIF($H$4:$H$47,"1",$I$4:$I$47)+SUMIF($H$4:$H$47,"2",$I$4:$I$47) | C18: =SUMIF($K$4:$K$47,"1",$L$4:$L$47)+SUMIF($K$4:$K$47,"2",$L$4:$L$47) | D18: =SUMIF($N$4:$N$47,"1",$O$4:$O$47)+SUMIF($N$4:$N$47,"2",$O$4:$O$47) | E18: =SUMIF($Q$4:$Q$47,"1",$R$4:$R$47)+SUMIF($Q$4:$Q$47,"2",$R$4:$R$47) | H18: =IF(工作表1!D18="","",LEFT(工作表1!D18,1)) | I18: =IF(ISNUMBER(工作表1!F18),工作表1!F18,0) | J18: =IF(工作表1!D18="",0,IF(COUNTIF(工作表1!$C$52:$C$71,工作表1!D18)>0,0,1)) | K18: =IF(工作表1!I18="","",LEFT(工作表1!I18,1)) | L18: =IF(ISNUMBER(工作表1!K18),工作表1!K18,0) | M18: =IF(工作表1!I18="",0,IF(COUNTIF(工作表1!$H$52:$H$71,工作表1!I18)>0,0,1)) | N18: =IF(工作表1!N18="","",LEFT(工作表1!N18,1)) | O18: =IF(ISNUMBER(工作表1!P18),工作表1!P18,0) | P18: =IF(工作表1!N18="",0,IF(COUNTIF(工作表1!$M$52:$M$71,工作表1!N18)>0,0,1)) | Q18: =IF(工作表1!S18="","",LEFT(工作表1!S18,1)) | R18: =IF(ISNUMBER(工作表1!U18),工作表1!U18,0) | S18: =IF(工作表1!S18="",0,IF(COUNTIF(工作表1!$R$52:$R$71,工作表1!S18)>0,0,1))
A19: B/S 期末總結(總計欄52+55:60) | B19: =工作表1!F52+SUM(工作表1!F55:F60) | C19: =工作表1!K52+SUM(工作表1!K55:K60) | D19: =工作表1!P52+SUM(工作表1!P55:P60) | E19: =工作表1!U52+SUM(工作表1!U55:U60) | H19: =IF(工作表1!D19="","",LEFT(工作表1!D19,1)) | I19: =IF(ISNUMBER(工作表1!F19),工作表1!F19,0) | J19: =IF(工作表1!D19="",0,IF(COUNTIF(工作表1!$C$52:$C$71,工作表1!D19)>0,0,1)) | K19: =IF(工作表1!I19="","",LEFT(工作表1!I19,1)) | L19: =IF(ISNUMBER(工作表1!K19),工作表1!K19,0) | M19: =IF(工作表1!I19="",0,IF(COUNTIF(工作表1!$H$52:$H$71,工作表1!I19)>0,0,1)) | N19: =IF(工作表1!N19="","",LEFT(工作表1!N19,1)) | O19: =IF(ISNUMBER(工作表1!P19),工作表1!P19,0) | P19: =IF(工作表1!N19="",0,IF(COUNTIF(工作表1!$M$52:$M$71,工作表1!N19)>0,0,1)) | Q19: =IF(工作表1!S19="","",LEFT(工作表1!S19,1)) | R19: =IF(ISNUMBER(工作表1!U19),工作表1!U19,0) | S19: =IF(工作表1!S19="",0,IF(COUNTIF(工作表1!$R$52:$R$71,工作表1!S19)>0,0,1))
A20: P/L 分錄加總 | B20: =SUMIF($H$4:$H$47,"4",$I$4:$I$47)+SUMIF($H$4:$H$47,"5",$I$4:$I$47)+SUMIF($H$4:$H$47,"6",$I$4:$I$47) | C20: =SUMIF($K$4:$K$47,"4",$L$4:$L$47)+SUMIF($K$4:$K$47,"5",$L$4:$L$47)+SUMIF($K$4:$K$47,"6",$L$4:$L$47) | D20: =SUMIF($N$4:$N$47,"4",$O$4:$O$47)+SUMIF($N$4:$N$47,"5",$O$4:$O$47)+SUMIF($N$4:$N$47,"6",$O$4:$O$47) | E20: =SUMIF($Q$4:$Q$47,"4",$R$4:$R$47)+SUMIF($Q$4:$Q$47,"5",$R$4:$R$47)+SUMIF($Q$4:$Q$47,"6",$R$4:$R$47) | H20: =IF(工作表1!D20="","",LEFT(工作表1!D20,1)) | I20: =IF(ISNUMBER(工作表1!F20),工作表1!F20,0) | J20: =IF(工作表1!D20="",0,IF(COUNTIF(工作表1!$C$52:$C$71,工作表1!D20)>0,0,1)) | K20: =IF(工作表1!I20="","",LEFT(工作表1!I20,1)) | L20: =IF(ISNUMBER(工作表1!K20),工作表1!K20,0) | M20: =IF(工作表1!I20="",0,IF(COUNTIF(工作表1!$H$52:$H$71,工作表1!I20)>0,0,1)) | N20: =IF(工作表1!N20="","",LEFT(工作表1!N20,1)) | O20: =IF(ISNUMBER(工作表1!P20),工作表1!P20,0) | P20: =IF(工作表1!N20="",0,IF(COUNTIF(工作表1!$M$52:$M$71,工作表1!N20)>0,0,1)) | Q20: =IF(工作表1!S20="","",LEFT(工作表1!S20,1)) | R20: =IF(ISNUMBER(工作表1!U20),工作表1!U20,0) | S20: =IF(工作表1!S20="",0,IF(COUNTIF(工作表1!$R$52:$R$71,工作表1!S20)>0,0,1))
A21: P/L 期末總結(總計欄61) | B21: =工作表1!F61 | C21: =工作表1!K61 | D21: =工作表1!P61 | E21: =工作表1!U61 | H21: =IF(工作表1!D21="","",LEFT(工作表1!D21,1)) | I21: =IF(ISNUMBER(工作表1!F21),工作表1!F21,0) | J21: =IF(工作表1!D21="",0,IF(COUNTIF(工作表1!$C$52:$C$71,工作表1!D21)>0,0,1)) | K21: =IF(工作表1!I21="","",LEFT(工作表1!I21,1)) | L21: =IF(ISNUMBER(工作表1!K21),工作表1!K21,0) | M21: =IF(工作表1!I21="",0,IF(COUNTIF(工作表1!$H$52:$H$71,工作表1!I21)>0,0,1)) | N21: =IF(工作表1!N21="","",LEFT(工作表1!N21,1)) | O21: =IF(ISNUMBER(工作表1!P21),工作表1!P21,0) | P21: =IF(工作表1!N21="",0,IF(COUNTIF(工作表1!$M$52:$M$71,工作表1!N21)>0,0,1)) | Q21: =IF(工作表1!S21="","",LEFT(工作表1!S21,1)) | R21: =IF(ISNUMBER(工作表1!U21),工作表1!U21,0) | S21: =IF(工作表1!S21="",0,IF(COUNTIF(工作表1!$R$52:$R$71,工作表1!S21)>0,0,1))
A22: B/S 差異 | B22: =B19-B18 | C22: =C19-C18 | D22: =D19-D18 | E22: =E19-E18 | H22: =IF(工作表1!D22="","",LEFT(工作表1!D22,1)) | I22: =IF(ISNUMBER(工作表1!F22),工作表1!F22,0) | J22: =IF(工作表1!D22="",0,IF(COUNTIF(工作表1!$C$52:$C$71,工作表1!D22)>0,0,1)) | K22: =IF(工作表1!I22="","",LEFT(工作表1!I22,1)) | L22: =IF(ISNUMBER(工作表1!K22),工作表1!K22,0) | M22: =IF(工作表1!I22="",0,IF(COUNTIF(工作表1!$H$52:$H$71,工作表1!I22)>0,0,1)) | N22: =IF(工作表1!N22="","",LEFT(工作表1!N22,1)) | O22: =IF(ISNUMBER(工作表1!P22),工作表1!P22,0) | P22: =IF(工作表1!N22="",0,IF(COUNTIF(工作表1!$M$52:$M$71,工作表1!N22)>0,0,1)) | Q22: =IF(工作表1!S22="","",LEFT(工作表1!S22,1)) | R22: =IF(ISNUMBER(工作表1!U22),工作表1!U22,0) | S22: =IF(工作表1!S22="",0,IF(COUNTIF(工作表1!$R$52:$R$71,工作表1!S22)>0,0,1))
A23: P/L 差異 | B23: =B21-B20 | C23: =C21-C20 | D23: =D21-D20 | E23: =E21-E20 | I23: 0 | J23: 0 | L23: 0 | M23: 0 | O23: 0 | P23: 0 | R23: 0 | S23: 0
A24: B/S+P/L(應為0) | B24: =B19+B21 | C24: =C19+C21 | D24: =D19+D21 | E24: =E19+E21 | I24: 0 | J24: 0 | L24: 0 | M24: 0 | O24: 0 | P24: 0 | R24: 0 | S24: 0
A25: B 結果 | B25: =IF(AND(ABS(B22)<0.000001,ABS(B23)<0.000001,ABS(B24)<0.000001),"OK","不符") | C25: =IF(AND(ABS(C22)<0.000001,ABS(C23)<0.000001,ABS(C24)<0.000001),"OK","不符") | D25: =IF(AND(ABS(D22)<0.000001,ABS(D23)<0.000001,ABS(D24)<0.000001),"OK","不符") | E25: =IF(AND(ABS(E22)<0.000001,ABS(E23)<0.000001,ABS(E24)<0.000001),"OK","不符") | I25: 0 | J25: 0 | L25: 0 | M25: 0 | O25: 0 | P25: 0 | R25: 0 | S25: 0
A26: C. BIM分錄科目未列入期末總結的行數 | B26: =SUM($J$4:$J$47) | C26: =SUM($M$4:$M$47) | D26: =SUM($P$4:$P$47) | E26: =SUM($S$4:$S$47) | I26: 0 | J26: 0 | L26: 0 | M26: 0 | O26: 0 | P26: 0 | R26: 0 | S26: 0
A27: C 結果 | B27: =IF(B26=0,"OK","有漏列") | C27: =IF(C26=0,"OK","有漏列") | D27: =IF(D26=0,"OK","有漏列") | E27: =IF(E26=0,"OK","有漏列") | I27: 0 | J27: 0 | L27: 0 | M27: 0 | O27: 0 | P27: 0 | R27: 0 | S27: 0
I28: 0 | J28: 0 | L28: 0 | M28: 0 | O28: 0 | P28: 0 | R28: 0 | S28: 0
H29: =IF(工作表1!D29="","",LEFT(工作表1!D29,1)) | I29: =IF(ISNUMBER(工作表1!F29),工作表1!F29,0) | J29: =IF(工作表1!D29="",0,IF(COUNTIF(工作表1!$C$52:$C$71,工作表1!D29)>0,0,1)) | K29: =IF(工作表1!I29="","",LEFT(工作表1!I29,1)) | L29: =IF(ISNUMBER(工作表1!K29),工作表1!K29,0) | M29: =IF(工作表1!I29="",0,IF(COUNTIF(工作表1!$H$52:$H$71,工作表1!I29)>0,0,1)) | N29: =IF(工作表1!N29="","",LEFT(工作表1!N29,1)) | O29: =IF(ISNUMBER(工作表1!P29),工作表1!P29,0) | P29: =IF(工作表1!N29="",0,IF(COUNTIF(工作表1!$M$52:$M$71,工作表1!N29)>0,0,1)) | Q29: =IF(工作表1!S29="","",LEFT(工作表1!S29,1)) | R29: =IF(ISNUMBER(工作表1!U29),工作表1!U29,0) | S29: =IF(工作表1!S29="",0,IF(COUNTIF(工作表1!$R$52:$R$71,工作表1!S29)>0,0,1))
H30: =IF(工作表1!D30="","",LEFT(工作表1!D30,1)) | I30: =IF(ISNUMBER(工作表1!F30),工作表1!F30,0) | J30: =IF(工作表1!D30="",0,IF(COUNTIF(工作表1!$C$52:$C$71,工作表1!D30)>0,0,1)) | K30: =IF(工作表1!I30="","",LEFT(工作表1!I30,1)) | L30: =IF(ISNUMBER(工作表1!K30),工作表1!K30,0) | M30: =IF(工作表1!I30="",0,IF(COUNTIF(工作表1!$H$52:$H$71,工作表1!I30)>0,0,1)) | N30: =IF(工作表1!N30="","",LEFT(工作表1!N30,1)) | O30: =IF(ISNUMBER(工作表1!P30),工作表1!P30,0) | P30: =IF(工作表1!N30="",0,IF(COUNTIF(工作表1!$M$52:$M$71,工作表1!N30)>0,0,1)) | Q30: =IF(工作表1!S30="","",LEFT(工作表1!S30,1)) | R30: =IF(ISNUMBER(工作表1!U30),工作表1!U30,0) | S30: =IF(工作表1!S30="",0,IF(COUNTIF(工作表1!$R$52:$R$71,工作表1!S30)>0,0,1))
H31: =IF(工作表1!D33="","",LEFT(工作表1!D33,1)) | I31: =IF(ISNUMBER(工作表1!F33),工作表1!F33,0) | J31: =IF(工作表1!D33="",0,IF(COUNTIF(工作表1!$C$52:$C$71,工作表1!D33)>0,0,1)) | K31: =IF(工作表1!I33="","",LEFT(工作表1!I33,1)) | L31: =IF(ISNUMBER(工作表1!K33),工作表1!K33,0) | M31: =IF(工作表1!I33="",0,IF(COUNTIF(工作表1!$H$52:$H$71,工作表1!I33)>0,0,1)) | N31: =IF(工作表1!N33="","",LEFT(工作表1!N33,1)) | O31: =IF(ISNUMBER(工作表1!P33),工作表1!P33,0) | P31: =IF(工作表1!N33="",0,IF(COUNTIF(工作表1!$M$52:$M$71,工作表1!N33)>0,0,1)) | Q31: =IF(工作表1!S33="","",LEFT(工作表1!S33,1)) | R31: =IF(ISNUMBER(工作表1!U33),工作表1!U33,0) | S31: =IF(工作表1!S33="",0,IF(COUNTIF(工作表1!$R$52:$R$71,工作表1!S33)>0,0,1))
H32: =IF(工作表1!D34="","",LEFT(工作表1!D34,1)) | I32: =IF(ISNUMBER(工作表1!F34),工作表1!F34,0) | J32: =IF(工作表1!D34="",0,IF(COUNTIF(工作表1!$C$52:$C$71,工作表1!D34)>0,0,1)) | K32: =IF(工作表1!I34="","",LEFT(工作表1!I34,1)) | L32: =IF(ISNUMBER(工作表1!K34),工作表1!K34,0) | M32: =IF(工作表1!I34="",0,IF(COUNTIF(工作表1!$H$52:$H$71,工作表1!I34)>0,0,1)) | N32: =IF(工作表1!N34="","",LEFT(工作表1!N34,1)) | O32: =IF(ISNUMBER(工作表1!P34),工作表1!P34,0) | P32: =IF(工作表1!N34="",0,IF(COUNTIF(工作表1!$M$52:$M$71,工作表1!N34)>0,0,1)) | Q32: =IF(工作表1!S34="","",LEFT(工作表1!S34,1)) | R32: =IF(ISNUMBER(工作表1!U34),工作表1!U34,0) | S32: =IF(工作表1!S34="",0,IF(COUNTIF(工作表1!$R$52:$R$71,工作表1!S34)>0,0,1))
H33: =IF(工作表1!D35="","",LEFT(工作表1!D35,1)) | I33: =IF(ISNUMBER(工作表1!F35),工作表1!F35,0) | J33: =IF(工作表1!D35="",0,IF(COUNTIF(工作表1!$C$52:$C$71,工作表1!D35)>0,0,1)) | K33: =IF(工作表1!I35="","",LEFT(工作表1!I35,1)) | L33: =IF(ISNUMBER(工作表1!K35),工作表1!K35,0) | M33: =IF(工作表1!I35="",0,IF(COUNTIF(工作表1!$H$52:$H$71,工作表1!I35)>0,0,1)) | N33: =IF(工作表1!N35="","",LEFT(工作表1!N35,1)) | O33: =IF(ISNUMBER(工作表1!P35),工作表1!P35,0) | P33: =IF(工作表1!N35="",0,IF(COUNTIF(工作表1!$M$52:$M$71,工作表1!N35)>0,0,1)) | Q33: =IF(工作表1!S35="","",LEFT(工作表1!S35,1)) | R33: =IF(ISNUMBER(工作表1!U35),工作表1!U35,0) | S33: =IF(工作表1!S35="",0,IF(COUNTIF(工作表1!$R$52:$R$71,工作表1!S35)>0,0,1))
I34: 0 | J34: 0 | L34: 0 | M34: 0 | O34: 0 | P34: 0 | R34: 0 | S34: 0
I35: 0 | J35: 0 | L35: 0 | M35: 0 | O35: 0 | P35: 0 | R35: 0 | S35: 0
I36: 0 | J36: 0 | L36: 0 | M36: 0 | O36: 0 | P36: 0 | R36: 0 | S36: 0
I37: 0 | J37: 0 | L37: 0 | M37: 0 | O37: 0 | P37: 0 | R37: 0 | S37: 0
I38: 0 | J38: 0 | L38: 0 | M38: 0 | O38: 0 | P38: 0 | R38: 0 | S38: 0
I39: 0 | J39: 0 | L39: 0 | M39: 0 | O39: 0 | P39: 0 | R39: 0 | S39: 0
I40: 0 | J40: 0 | L40: 0 | M40: 0 | O40: 0 | P40: 0 | R40: 0 | S40: 0
I41: 0 | J41: 0 | L41: 0 | M41: 0 | O41: 0 | P41: 0 | R41: 0 | S41: 0
H42: =IF(工作表1!D44="","",LEFT(工作表1!D44,1)) | I42: =IF(ISNUMBER(工作表1!F44),工作表1!F44,0) | J42: =IF(工作表1!D44="",0,IF(COUNTIF(工作表1!$C$52:$C$71,工作表1!D44)>0,0,1)) | K42: =IF(工作表1!I44="","",LEFT(工作表1!I44,1)) | L42: =IF(ISNUMBER(工作表1!K44),工作表1!K44,0) | M42: =IF(工作表1!I44="",0,IF(COUNTIF(工作表1!$H$52:$H$71,工作表1!I44)>0,0,1)) | N42: =IF(工作表1!N44="","",LEFT(工作表1!N44,1)) | O42: =IF(ISNUMBER(工作表1!P44),工作表1!P44,0) | P42: =IF(工作表1!N44="",0,IF(COUNTIF(工作表1!$M$52:$M$71,工作表1!N44)>0,0,1)) | Q42: =IF(工作表1!S44="","",LEFT(工作表1!S44,1)) | R42: =IF(ISNUMBER(工作表1!U44),工作表1!U44,0) | S42: =IF(工作表1!S44="",0,IF(COUNTIF(工作表1!$R$52:$R$71,工作表1!S44)>0,0,1))
H43: =IF(工作表1!D45="","",LEFT(工作表1!D45,1)) | I43: =IF(ISNUMBER(工作表1!F45),工作表1!F45,0) | J43: =IF(工作表1!D45="",0,IF(COUNTIF(工作表1!$C$52:$C$71,工作表1!D45)>0,0,1)) | K43: =IF(工作表1!I45="","",LEFT(工作表1!I45,1)) | L43: =IF(ISNUMBER(工作表1!K45),工作表1!K45,0) | M43: =IF(工作表1!I45="",0,IF(COUNTIF(工作表1!$H$52:$H$71,工作表1!I45)>0,0,1)) | N43: =IF(工作表1!N45="","",LEFT(工作表1!N45,1)) | O43: =IF(ISNUMBER(工作表1!P45),工作表1!P45,0) | P43: =IF(工作表1!N45="",0,IF(COUNTIF(工作表1!$M$52:$M$71,工作表1!N45)>0,0,1)) | Q43: =IF(工作表1!S45="","",LEFT(工作表1!S45,1)) | R43: =IF(ISNUMBER(工作表1!U45),工作表1!U45,0) | S43: =IF(工作表1!S45="",0,IF(COUNTIF(工作表1!$R$52:$R$71,工作表1!S45)>0,0,1))
H44: =IF(工作表1!D46="","",LEFT(工作表1!D46,1)) | I44: =IF(ISNUMBER(工作表1!F46),工作表1!F46,0) | J44: =IF(工作表1!D46="",0,IF(COUNTIF(工作表1!$C$52:$C$71,工作表1!D46)>0,0,1)) | K44: =IF(工作表1!I46="","",LEFT(工作表1!I46,1)) | L44: =IF(ISNUMBER(工作表1!K46),工作表1!K46,0) | M44: =IF(工作表1!I46="",0,IF(COUNTIF(工作表1!$H$52:$H$71,工作表1!I46)>0,0,1)) | N44: =IF(工作表1!N46="","",LEFT(工作表1!N46,1)) | O44: =IF(ISNUMBER(工作表1!P46),工作表1!P46,0) | P44: =IF(工作表1!N46="",0,IF(COUNTIF(工作表1!$M$52:$M$71,工作表1!N46)>0,0,1)) | Q44: =IF(工作表1!S46="","",LEFT(工作表1!S46,1)) | R44: =IF(ISNUMBER(工作表1!U46),工作表1!U46,0) | S44: =IF(工作表1!S46="",0,IF(COUNTIF(工作表1!$R$52:$R$71,工作表1!S46)>0,0,1))
H45: =IF(工作表1!D47="","",LEFT(工作表1!D47,1)) | I45: =IF(ISNUMBER(工作表1!F47),工作表1!F47,0) | J45: =IF(工作表1!D47="",0,IF(COUNTIF(工作表1!$C$52:$C$71,工作表1!D47)>0,0,1)) | K45: =IF(工作表1!I47="","",LEFT(工作表1!I47,1)) | L45: =IF(ISNUMBER(工作表1!K47),工作表1!K47,0) | M45: =IF(工作表1!I47="",0,IF(COUNTIF(工作表1!$H$52:$H$71,工作表1!I47)>0,0,1)) | N45: =IF(工作表1!N47="","",LEFT(工作表1!N47,1)) | O45: =IF(ISNUMBER(工作表1!P47),工作表1!P47,0) | P45: =IF(工作表1!N47="",0,IF(COUNTIF(工作表1!$M$52:$M$71,工作表1!N47)>0,0,1)) | Q45: =IF(工作表1!S47="","",LEFT(工作表1!S47,1)) | R45: =IF(ISNUMBER(工作表1!U47),工作表1!U47,0) | S45: =IF(工作表1!S47="",0,IF(COUNTIF(工作表1!$R$52:$R$71,工作表1!S47)>0,0,1))
H46: =IF(工作表1!D48="","",LEFT(工作表1!D48,1)) | I46: =IF(ISNUMBER(工作表1!F48),工作表1!F48,0) | J46: =IF(工作表1!D48="",0,IF(COUNTIF(工作表1!$C$52:$C$71,工作表1!D48)>0,0,1)) | K46: =IF(工作表1!I48="","",LEFT(工作表1!I48,1)) | L46: =IF(ISNUMBER(工作表1!K48),工作表1!K48,0) | M46: =IF(工作表1!I48="",0,IF(COUNTIF(工作表1!$H$52:$H$71,工作表1!I48)>0,0,1)) | N46: =IF(工作表1!N48="","",LEFT(工作表1!N48,1)) | O46: =IF(ISNUMBER(工作表1!P48),工作表1!P48,0) | P46: =IF(工作表1!N48="",0,IF(COUNTIF(工作表1!$M$52:$M$71,工作表1!N48)>0,0,1)) | Q46: =IF(工作表1!S48="","",LEFT(工作表1!S48,1)) | R46: =IF(ISNUMBER(工作表1!U48),工作表1!U48,0) | S46: =IF(工作表1!S48="",0,IF(COUNTIF(工作表1!$R$52:$R$71,工作表1!S48)>0,0,1))
I47: 0 | J47: 0 | L47: 0 | M47: 0 | O47: 0 | P47: 0 | R47: 0 | S47: 0
